Workbook
Name SERVER: #REF!
Name SERVER: #REF!
Name SERVER: #REF!
Name SERVER: #REF!
Name SERVER: #REF!
Name SERVER: #REF!
Name SERVER: #REF!
Name SERVER: #REF!
Name SERVER: #REF!
Name SERVER: #REF!
Name SERVER: #REF!
Name SERVER: #REF!
Name SERVER: #REF!
Name SERVER: #REF!
Name SERVER: #REF!
Name SERVER: '[1]2017 Forecast'!$E$19
Name spec: #REF!
Name spec: #REF!
Name spec: #REF!
Name spec: #REF!
Name spec: #REF!
Name spec: #REF!
Name spec: #REF!
Name spec: #REF!
Name spec: [2]Montreal!#REF!
Name spec: #REF!
Name spec: #REF!
Name spec: #REF!
Name spec: #REF!
Name spec: #REF!
Name spec: #REF!
Name spec: #REF!
Name spec: [2]Montreal!#REF!
Name TM1REBUILDOPTION: 1

Sheet RDG Weekly
D2: =CONCATENATE("Riviera Dining Group - Profit & Loss",) -> Riviera Dining Group - Profit & Loss | AK2: Weekly Budget | AU2: Month to Date
D3: =CONCATENATE(E3," ",F3) -> #REF! | E3: Week | F3: =+#REF! -> #REF! | X3: =+#REF! -> #REF!
B4: ACT. | C4: eUD. | D4: =CONCATENATE(E4," ",F4) -> #REF! | E4: Week | F4: =+F3+1 -> #REF! | X4: =+X3+1 -> #REF!
B5: ACT. | C5: BUD. | D5: =CONCATENATE(E5," ",F5) -> #REF! | E5: Week | F5: =+F4+1 -> #REF! | X5: =+X4+1 -> #REF!
B6: ACT. | C6: BUD. | D6: =CONCATENATE(E6," ",F6) -> #REF! | E6: Week | F6: =+F5+1 -> #REF! | X6: =+X5+1 -> #REF!
B7: ACT. | C7: BUD. | D7: =CONCATENATE(E7," ",F7) -> #REF! | E7: Week | F7: =+F6+1 -> #REF! | X7: =+X6+1 -> #REF!
B8: ACT. | C8: BUD.
B9: =VLOOKUP($D9,'[3]REF #'!$C:$E,2,FALSE) -> #REF! | C9: =VLOOKUP($D9,'[3]REF #'!$C:$E,3,FALSE) -> #REF! | D9: =+#REF! -> #REF! | F9: MTD | X9: YTD | AK9: =+D3 -> #REF! | AM9: =+D4 -> #REF! | AO9: =+D5 -> #REF! | AQ9: =+D6 -> #REF! | AU9: =+D3 -> #REF! | AY9: =+D4 -> #REF! | BC9: =+D5 -> #REF!
F11: MILA 3F | I11: MILA 2F | M11: AVA | Q11: CASA NEOS | X11: MILA | AB11: MILA MM | AE11: AVA | AG11: BAOLI | AK11: BUDGET | AM11: BUDGET | AO11: BUDGET | AQ11: BUDGET | AU11: 2023 | AW11: BUDGET | AY11: 2023 | BA11: BUDGET | BC11: 2023 | BE11: BUDGET
B13: Total Sales | D13: Net Sales | F13: =SUMIFS(#REF!,#REF!,$B$13) -> #REF! | G13: =IFERROR(F13/F13,0) -> 0 | I13: =SUMIFS(#REF!,#REF!,$B$13) -> #REF! | K13: =IFERROR(I13/I13,0) -> 0 | M13: =SUMIFS(#REF!,#REF!,$B$13) -> #REF! | O13: =IFERROR(M13/M13,0) -> 0 | Q13: =SUMIFS(#REF!,#REF!,$B$13) -> #REF! | S13: =IFERROR(Q13/Q13,0) -> 0 | X13: =SUMIFS(#REF!,#REF!,'RDG Weekly'!Q13) -> #REF! | Z13: =IFERROR(X13/X13,0) -> 0 | AB13: =SUMIFS(#REF!,#REF!,'RDG Weekly'!Q13) -> #REF! | AD13: =IFERROR(AB13/AB13,0) -> 0 | AE13: =SUMIFS(#REF!,#REF!,'RDG Weekly'!Q13) -> #REF! | AF13: =IFERROR(AE13/AE13,0) -> 0 | AG13: =SUMIFS(#REF!,#REF!,'RDG Weekly'!Q13) -> #REF! | AH13: =IFERROR(AG13/AG13,0) -> 0 | AK13: =VLOOKUP(D3,#REF!,2,FALSE) -> #REF! | AL13: =IFERROR(AK13/AK13,0) -> 0 | AM13: =VLOOKUP(D4,#REF!,2,FALSE) -> #REF! | AN13: =IFERROR(AM13/AM13,0) -> 0 | AO13: =VLOOKUP(D5,#REF!,2,FALSE) -> #REF! | AP13: =IFERROR(AO13/AO13,0) -> 0 | AQ13: =VLOOKUP(D6,#REF!,2,FALSE) -> #REF! | AR13: =IFERROR(AQ13/AQ13,0) -> 0 | AU13: =SUMIFS($F$13:$F$34,$D$13:$D$34,D13) -> #REF! | AV13: =IFERROR(AU13/AU13,0) -> 0 | AW13: =+AK13 -> #REF! | AX13: =IFERROR(AW13/AW13,0) -> 0 | AY13: =SUMIFS($I$13:$I$34,$D$13:$D$34,D13)+SUMIFS($AU$13:$AU$34,$D$13:$D$34,D13) -> #REF! | AZ13: =IFERROR(AY13/AY13,0) -> 0 | BA13: =SUMIFS($AM$13:$AM$34,$D$13:$D$34,D13)+SUMIFS($AW$13:$AW$34,$D$13:$D$34,D13) -> #REF! | BB13: =IFERROR(BA13/BA13,0) -> 0 | BC13: =SUMIFS($M$13:$M$34,$D$13:$D$34,D13)+SUMIFS($AY$13:$AY$34,$D$13:$D$34,D13) -> #REF! | BD13: =IFERROR(BC13/BC13,0) -> 0 | BE13: =SUMIFS($AO$13:$AO$34,$D$13:$D$34,D13)+SUMIFS($BA$13:$BA$34,$D$13:$D$34,D13) -> #REF! | BF13: =IFERROR(BE13/BE13,0) -> 0
B14: Total Food Cost | D14: Cost of Goods Sold | F14: =SUMIFS(#REF!,#REF!,'RDG Weekly'!$B$14)+SUMIFS(#REF!,#REF!,'RDG Weekly'!$B$15)+SUMIFS(#REF!,#REF!,'RDG Weekly'!$B$16) -> #REF! | G14: =IFERROR(F14/F13,0) -> 0 | I14: =SUMIFS(#REF!,#REF!,'RDG Weekly'!$B$14)+SUMIFS(#REF!,#REF!,'RDG Weekly'!$B$15)+SUMIFS(#REF!,#REF!,'RDG Weekly'!$B$16) -> #REF! | K14: =IFERROR(I14/I13,0) -> 0 | M14: =SUMIFS(#REF!,#REF!,'RDG Weekly'!$B$14)+SUMIFS(#REF!,#REF!,'RDG Weekly'!$B$15)+SUMIFS(#REF!,#REF!,'RDG Weekly'!$B$16) -> #REF! | O14: =IFERROR(M14/M13,0) -> 0 | Q14: =SUMIFS(#REF!,#REF!,'RDG Weekly'!$B$14)+SUMIFS(#REF!,#REF!,'RDG Weekly'!$B$15)+SUMIFS(#REF!,#REF!,'RDG Weekly'!$B$16) -> #REF! | S14: =IFERROR(Q14/Q13,0) -> 0 | X14: =SUMIFS(#REF!,#REF!,'RDG Weekly'!Q14)+SUMIFS(#REF!,#REF!,'RDG Weekly'!Q15)+SUMIFS(#REF!,#REF!,'RDG Weekly'!Q16) -> #REF! | Z14: =IFERROR(X14/X13,0) -> 0 | AB14: =SUMIFS(#REF!,#REF!,'RDG Weekly'!Q14)+SUMIFS(#REF!,#REF!,'RDG Weekly'!Q15)+SUMIFS(#REF!,#REF!,'RDG Weekly'!Q16) -> #REF! | AD14: =IFERROR(AB14/AB13,0) -> 0 | AE14: =SUMIFS(#REF!,#REF!,'RDG Weekly'!Q14)+SUMIFS(#REF!,#REF!,'RDG Weekly'!Q15)+SUMIFS(#REF!,#REF!,'RDG Weekly'!Q16) -> #REF! | AF14: =IFERROR(AE14/AE13,0) -> 0 | AG14: =SUMIFS(#REF!,#REF!,'RDG Weekly'!Q14)+SUMIFS(#REF!,#REF!,'RDG Weekly'!Q15)+SUMIFS(#REF!,#REF!,'RDG Weekly'!Q16) -> #REF! | AH14: =IFERROR(AG14/AG13,0) -> 0 | AK14: =+#REF! -> #REF! | AL14: =IFERROR(AK14/AK13,0) -> 0 | AM14: =+#REF! -> #REF! | AN14: =IFERROR(AM14/AM13,0) -> 0 | AO14: =+#REF! -> #REF! | AP14: =IFERROR(AO14/AO13,0) -> 0 | AQ14: =+AP14*AQ13 -> #REF! | AR14: =IFERROR(AQ14/AQ13,0) -> 0 | AU14: =SUMIFS($F$13:$F$34,$D$13:$D$34,D14) -> #REF! | AV14: =IFERROR(AU14/AU13,0) -> 0 | AW14: =+AK14 -> #REF! | AX14: =IFERROR(AW14/AW13,0) -> 0 | AY14: =SUMIFS($I$13:$I$34,$D$13:$D$34,D14)+SUMIFS($AU$13:$AU$34,$D$13:$D$34,D14) -> #REF! | AZ14: =IFERROR(AY14/AY13,0) -> 0 | BA14: =SUMIFS($AM$13:$AM$34,$D$13:$D$34,D14)+SUMIFS($AW$13:$AW$34,$D$13:$D$34,D14) -> #REF! | BB14: =IFERROR(BA14/BA13,0) -> 0 | BC14: =SUMIFS($M$13:$M$34,$D$13:$D$34,D14)+SUMIFS($AY$13:$AY$34,$D$13:$D$34,D14) -> #REF! | BD14: =IFERROR(BC14/BC13,0) -> 0 | BE14: =SUMIFS($AO$13:$AO$34,$D$13:$D$34,D14)+SUMIFS($BA$13:$BA$34,$D$13:$D$34,D14) -> #REF! | BF14: =IFERROR(BE14/BE13,0) -> 0
B15: 5080 - Purchase N/A Beverages
B16: Total LBW Cost | D16: Gross Profit | F16: =F13-F14 -> #REF! | G16: =IFERROR(F16/F13,0) -> 0 | I16: =I13-I14 -> #REF! | K16: =IFERROR(I16/I13,0) -> 0 | M16: =M13-M14 -> #REF! | O16: =IFERROR(M16/M13,0) -> 0 | Q16: =Q13-Q14 -> #REF! | S16: =IFERROR(Q16/Q13,0) -> 0 | X16: =X13-X14 -> #REF! | Z16: =IFERROR(X16/X13,0) -> 0 | AB16: =AB13-AB14 -> #REF! | AD16: =IFERROR(AB16/AB13,0) -> 0 | AE16: =AE13-AE14 -> #REF! | AF16: =IFERROR(AE16/AE13,0) -> 0 | AG16: =AG13-AG14 -> #REF! | AH16: =IFERROR(AG16/AG13,0) -> 0 | AK16: =AK13-AK14 -> #REF! | AL16: =IFERROR(AK16/AK13,0) -> 0 | AM16: =AM13-AM14 -> #REF! | AN16: =IFERROR(AM16/AM13,0) -> 0 | AO16: =AO13-AO14 -> #REF! | AP16: =IFERROR(AO16/AO13,0) -> 0 | AQ16: =AQ13-AQ14 -> #REF! | AR16: =IFERROR(AQ16/AQ13,0) -> 0 | AU16: =AU13-AU14 -> #REF! | AV16: =IFERROR(AU16/AU13,0) -> 0 | AW16: =AW13-AW14 -> #REF! | AX16: =IFERROR(AW16/AW13,0) -> 0 | AY16: =AY13-AY14 -> #REF! | AZ16: =IFERROR(AY16/AY13,0) -> 0 | BA16: =BA13-BA14 -> #REF! | BB16: =IFERROR(BA16/BA13,0) -> 0 | BC16: =BC13-BC14 -> #REF! | BD16: =IFERROR(BC16/BC13,0) -> 0 | BE16: =BE13-BE14 -> #REF! | BF16: =IFERROR(BE16/BE13,0) -> 0
B18: Total Payroll Expenses | C18: Total Salaries and Wages | D18: Cost of Labor | F18: =+SUMIFS(#REF!,#REF!,'RDG Weekly'!B18)+SUMIFS(#REF!,#REF!,'RDG Weekly'!C18)+SUMIFS(#REF!,#REF!,'RDG Weekly'!C22)+SUMIFS(#REF!,#REF!,'RDG Weekly'!C23) -> #REF! | G18: =IFERROR(F18/F13,0) -> 0 | I18: =+SUMIFS(#REF!,#REF!,'RDG Weekly'!B18)+SUMIFS(#REF!,#REF!,'RDG Weekly'!C18)+SUMIFS(#REF!,#REF!,'RDG Weekly'!C22)+SUMIFS(#REF!,#REF!,'RDG Weekly'!C23) -> #REF! | K18: =IFERROR(I18/I13,0) -> 0 | M18: =+SUMIFS(#REF!,#REF!,'RDG Weekly'!B18)+SUMIFS(#REF!,#REF!,'RDG Weekly'!C18)+SUMIFS(#REF!,#REF!,'RDG Weekly'!C22)+SUMIFS(#REF!,#REF!,'RDG Weekly'!C23) -> #REF! | O18: =IFERROR(M18/M13,0) -> 0 | Q18: =+SUMIFS(#REF!,#REF!,'RDG Weekly'!B18)+SUMIFS(#REF!,#REF!,'RDG Weekly'!C18)+SUMIFS(#REF!,#REF!,'RDG Weekly'!C22)+SUMIFS(#REF!,#REF!,'RDG Weekly'!C23) -> #REF! | S18: =IFERROR(Q18/Q13,0) -> 0 | X18: =+SUMIFS(#REF!,#REF!,'RDG Weekly'!Q18)+SUMIFS(#REF!,#REF!,'RDG Weekly'!S18)+SUMIFS(#REF!,#REF!,'RDG Weekly'!S22)+SUMIFS(#REF!,#REF!,'RDG Weekly'!S23) -> #REF! | Z18: =IFERROR(X18/X13,0) -> 0 | AB18: =+SUMIFS(#REF!,#REF!,'RDG Weekly'!Q18)+SUMIFS(#REF!,#REF!,'RDG Weekly'!S18)+SUMIFS(#REF!,#REF!,'RDG Weekly'!S22)+SUMIFS(#REF!,#REF!,'RDG Weekly'!S23) -> #REF! | AD18: =IFERROR(AB18/AB13,0) -> 0 | AE18: =+SUMIFS(#REF!,#REF!,'RDG Weekly'!Q18)+SUMIFS(#REF!,#REF!,'RDG Weekly'!S18)+SUMIFS(#REF!,#REF!,'RDG Weekly'!S22)+SUMIFS(#REF!,#REF!,'RDG Weekly'!S23) -> #REF! | AF18: =IFERROR(AE18/AE13,0) -> 0 | AG18: =+SUMIFS(#REF!,#REF!,'RDG Weekly'!Q18)+SUMIFS(#REF!,#REF!,'RDG Weekly'!S18)+SUMIFS(#REF!,#REF!,'RDG Weekly'!S22)+SUMIFS(#REF!,#REF!,'RDG Weekly'!S23) -> #REF! | AH18: =IFERROR(AG18/AG13,0) -> 0 | AK18: =+#REF! -> #REF! | AL18: =IFERROR(AK18/AK13,0) -> 0 | AM18: =+AK18 -> #REF! | AN18: =IFERROR(AM18/AM13,0) -> 0 | AO18: =+AM18 -> #REF! | AP18: =IFERROR(AO18/AO13,0) -> 0 | AQ18: =+AO18 -> #REF! | AR18: =IFERROR(AQ18/AQ13,0) -> 0 | AU18: =SUMIFS($F$13:$F$34,$D$13:$D$34,D18) -> #REF! | AV18: =IFERROR(AU18/AU13,0) -> 0 | AW18: =+AK18 -> #REF! | AX18: =IFERROR(AW18/AW13,0) -> 0 | AY18: =SUMIFS($I$13:$I$34,$D$13:$D$34,D18)+SUMIFS($AU$13:$AU$34,$D$13:$D$34,D18) -> #REF! | AZ18: =IFERROR(AY18/AY13,0) -> 0 | BA18: =SUMIFS($AM$13:$AM$34,$D$13:$D$34,D18)+SUMIFS($AW$13:$AW$34,$D$13:$D$34,D18) -> #REF! | BB18: =IFERROR(BA18/BA13,0) -> 0 | BC18: =SUMIFS($M$13:$M$34,$D$13:$D$34,D18)+SUMIFS($AY$13:$AY$34,$D$13:$D$34,D18) -> #REF! | BD18: =IFERROR(BC18/BC13,0) -> 0 | BE18: =SUMIFS($AO$13:$AO$34,$D$13:$D$34,D18)+SUMIFS($BA$13:$BA$34,$D$13:$D$34,D18) -> #REF! | BF18: =IFERROR(BE18/BE13,0) -> 0
D19: FOH - Hourly | F19: =+SUMIFS(#REF!,#REF!,'RDG Weekly'!B18)-F20 -> #REF! | G19: =+F19/$F$13 -> #REF! | I19: =+SUMIFS(#REF!,#REF!,'RDG Weekly'!B18)-I20 -> #REF! | K19: =+I19/$I$13 -> #REF! | M19: =+SUMIFS(#REF!,#REF!,'RDG Weekly'!B18)-M20 -> #REF! | O19: =+M19/$M$13 -> #REF! | Q19: =+SUMIFS(#REF!,#REF!,'RDG Weekly'!B18)-Q20 -> #REF! | S19: =+Q19/$M$13 -> #REF! | X19: =+SUMIFS(#REF!,#REF!,'RDG Weekly'!Q18)-X20 -> #REF! | Z19: =+X19/$F$13 -> #REF! | AB19: =+SUMIFS(#REF!,#REF!,'RDG Weekly'!Q18)-AB20 -> #REF! | AD19: =+AB19/$I$13 -> #REF! | AE19: =+SUMIFS(#REF!,#REF!,'RDG Weekly'!Q18)-AE20 -> #REF! | AF19: =+AE19/$M$13 -> #REF! | AG19: =+SUMIFS(#REF!,#REF!,'RDG Weekly'!Q18)-AG20 -> #REF! | AH19: =+AG19/$M$13 -> #REF! | AK19: =+#REF! -> #REF! | AL19: =+AK19/$AK$13 -> #REF! | AM19: =+AK19 -> #REF! | AN19: =+AM19/$AM$13 -> #REF! | AO19: =+AM19 -> #REF! | AP19: =+AO19/$AO$13 -> #REF! | AQ19: =+AO19 -> #REF! | AR19: =+AQ19/$AQ$13 -> #REF! | AU19: =SUMIFS($F$13:$F$34,$D$13:$D$34,D19) -> #REF! | AV19: =+AU19/$AU$13 -> #REF! | AW19: =+AK19 -> #REF! | AX19: =+AW19/$AW$13 -> #REF! | AY19: =SUMIFS($I$13:$I$34,$D$13:$D$34,D19)+SUMIFS($AU$13:$AU$34,$D$13:$D$34,D19) -> #REF! | AZ19: =+AY19/$AY$13 -> #REF! | BA19: =SUMIFS($AM$13:$AM$34,$D$13:$D$34,D19)+SUMIFS($AW$13:$AW$34,$D$13:$D$34,D19) -> #REF! | BB19: =+BA19/$BA$13 -> #REF! | BC19: =SUMIFS($M$13:$M$34,$D$13:$D$34,D19)+SUMIFS($AY$13:$AY$34,$D$13:$D$34,D19) -> #REF! | BD19: =+BC19/$BC$13 -> #REF! | BE19: =SUMIFS($AO$13:$AO$34,$D$13:$D$34,D19)+SUMIFS($BA$13:$BA$34,$D$13:$D$34,D19) -> #REF! | BF19: =+BE19/$BE$13 -> #REF!
D20: BOH - Hourly | G20: =+F20/$F$13 -> #REF! | I20: =+SUMIFS(#REF!,#REF!,'RDG Weekly'!B223)+SUMIFS(#REF!,#REF!,'RDG Weekly'!B224)+SUMIFS(#REF!,#REF!,'RDG Weekly'!B225)+SUMIFS(#REF!,#REF!,'RDG Weekly'!B226)+SUMIFS(#REF!,#REF!,'RDG Weekly'!B227)+SUMIFS(#REF!,#REF!,'RDG Weekly'!B228)+SUMIFS(#REF!,#REF!,'RDG Weekly'!B229)+SUMIFS(#REF!,#REF!,'RDG Weekly'!B230) -> #REF! | K20: =+I20/$I$13 -> #REF! | M20: =+SUMIFS(#REF!,#REF!,'RDG Weekly'!B223)+SUMIFS(#REF!,#REF!,'RDG Weekly'!B224)+SUMIFS(#REF!,#REF!,'RDG Weekly'!B225)+SUMIFS(#REF!,#REF!,'RDG Weekly'!B226)+SUMIFS(#REF!,#REF!,'RDG Weekly'!B227)+SUMIFS(#REF!,#REF!,'RDG Weekly'!B228)+SUMIFS(#REF!,#REF!,'RDG Weekly'!B229)+SUMIFS(#REF!,#REF!,'RDG Weekly'!B230) -> #REF! | O20: =+M20/$M$13 -> #REF! | Q20: =+SUMIFS(#REF!,#REF!,'RDG Weekly'!B223)+SUMIFS(#REF!,#REF!,'RDG Weekly'!B224)+SUMIFS(#REF!,#REF!,'RDG Weekly'!B225)+SUMIFS(#REF!,#REF!,'RDG Weekly'!B226)+SUMIFS(#REF!,#REF!,'RDG Weekly'!B227)+SUMIFS(#REF!,#REF!,'RDG Weekly'!B228)+SUMIFS(#REF!,#REF!,'RDG Weekly'!B229)+SUMIFS(#REF!,#REF!,'RDG Weekly'!B230) -> #REF! | S20: =+Q20/$M$13 -> #REF! | X20: =+SUMIFS(#REF!,#REF!,'RDG Weekly'!Q48)+SUMIFS(#REF!,#REF!,'RDG Weekly'!Q49)+SUMIFS(#REF!,#REF!,'RDG Weekly'!Q50)+SUMIFS(#REF!,#REF!,'RDG Weekly'!Q51)+SUMIFS(#REF!,#REF!,'RDG Weekly'!Q52)+SUMIFS(#REF!,#REF!,'RDG Weekly'!Q53)+SUMIFS(#REF!,#REF!,'RDG Weekly'!Q54)+SUMIFS(#REF!,#REF!,'RDG Weekly'!Q55) -> #REF! | Z20: =+X20/$F$13 -> #REF! | AB20: =+SUMIFS(#REF!,#REF!,'RDG Weekly'!Q48)+SUMIFS(#REF!,#REF!,'RDG Weekly'!Q49)+SUMIFS(#REF!,#REF!,'RDG Weekly'!Q50)+SUMIFS(#REF!,#REF!,'RDG Weekly'!Q51)+SUMIFS(#REF!,#REF!,'RDG Weekly'!Q52)+SUMIFS(#REF!,#REF!,'RDG Weekly'!Q53)+SUMIFS(#REF!,#REF!,'RDG Weekly'!Q54)+SUMIFS(#REF!,#REF!,'RDG Weekly'!Q55) -> #REF! | AD20: =+AB20/$I$13 -> #REF! | AE20: =+SUMIFS(#REF!,#REF!,'RDG Weekly'!Q48)+SUMIFS(#REF!,#REF!,'RDG Weekly'!Q49)+SUMIFS(#REF!,#REF!,'RDG Weekly'!Q50)+SUMIFS(#REF!,#REF!,'RDG Weekly'!Q51)+SUMIFS(#REF!,#REF!,'RDG Weekly'!Q52)+SUMIFS(#REF!,#REF!,'RDG Weekly'!Q53)+SUMIFS(#REF!,#REF!,'RDG Weekly'!Q54)+SUMIFS(#REF!,#REF!,'RDG Weekly'!Q55) -> #REF! | AF20: =+AE20/$M$13 -> #REF! | AG20: =+SUMIFS(#REF!,#REF!,'RDG Weekly'!Q48)+SUMIFS(#REF!,#REF!,'RDG Weekly'!Q49)+SUMIFS(#REF!,#REF!,'RDG Weekly'!Q50)+SUMIFS(#REF!,#REF!,'RDG Weekly'!Q51)+SUMIFS(#REF!,#REF!,'RDG Weekly'!Q52)+SUMIFS(#REF!,#REF!,'RDG Weekly'!Q53)+SUMIFS(#REF!,#REF!,'RDG Weekly'!Q54)+SUMIFS(#REF!,#REF!,'RDG Weekly'!Q55) -> #REF! | AH20: =+AG20/$M$13 -> #REF! | AK20: =+#REF! -> #REF! | AL20: =+AK20/$AK$13 -> #REF! | AM20: =+AK20 -> #REF! | AN20: =+AM20/$AM$13 -> #REF! | AO20: =+AM20 -> #REF! | AP20: =+AO20/$AO$13 -> #REF! | AQ20: =+AO20 -> #REF! | AR20: =+AQ20/$AQ$13 -> #REF! | AU20: =SUMIFS($F$13:$F$34,$D$13:$D$34,D20) -> 0 | AV20: =+AU20/$AU$13 -> #REF! | AW20: =+AK20 -> #REF! | AX20: =+AW20/$AW$13 -> #REF! | AY20: =SUMIFS($I$13:$I$34,$D$13:$D$34,D20)+SUMIFS($AU$13:$AU$34,$D$13:$D$34,D20) -> #REF! | AZ20: =+AY20/$AY$13 -> #REF! | BA20: =SUMIFS($AM$13:$AM$34,$D$13:$D$34,D20)+SUMIFS($AW$13:$AW$34,$D$13:$D$34,D20) -> #REF! | BB20: =+BA20/$BA$13 -> #REF! | BC20: =SUMIFS($M$13:$M$34,$D$13:$D$34,D20)+SUMIFS($AY$13:$AY$34,$D$13:$D$34,D20) -> #REF! | BD20: =+BC20/$BC$13 -> #REF! | BE20: =SUMIFS($AO$13:$AO$34,$D$13:$D$34,D20)+SUMIFS($BA$13:$BA$34,$D$13:$D$34,D20) -> #REF! | BF20: =+BE20/$BE$13 -> #REF!
D21: Management | F21: =+SUMIFS(#REF!,#REF!,'RDG Weekly'!C18) -> #REF! | G21: =+F21/$F$13 -> #REF! | I21: =+SUMIFS(#REF!,#REF!,'RDG Weekly'!C18) -> #REF! | K21: =+I21/$I$13 -> #REF! | M21: =+SUMIFS(#REF!,#REF!,'RDG Weekly'!C18) -> #REF! | O21: =+M21/$M$13 -> #REF! | Q21: =+SUMIFS(#REF!,#REF!,'RDG Weekly'!C18) -> #REF! | S21: =+Q21/$M$13 -> #REF! | X21: =+SUMIFS(#REF!,#REF!,'RDG Weekly'!S18) -> #REF! | Z21: =+X21/$F$13 -> #REF! | AB21: =+SUMIFS(#REF!,#REF!,'RDG Weekly'!S18) -> #REF! | AD21: =+AB21/$I$13 -> #REF! | AE21: =+SUMIFS(#REF!,#REF!,'RDG Weekly'!S18) -> #REF! | AF21: =+AE21/$M$13 -> #REF! | AG21: =+SUMIFS(#REF!,#REF!,'RDG Weekly'!S18) -> #REF! | AH21: =+AG21/$M$13 -> #REF! | AK21: =+#REF! -> #REF! | AL21: =+AK21/$AK$13 -> #REF! | AM21: =+AK21 -> #REF! | AN21: =+AM21/$AM$13 -> #REF! | AO21: =+AM21 -> #REF! | AP21: =+AO21/$AO$13 -> #REF! | AQ21: =+AO21 -> #REF! | AR21: =+AQ21/$AQ$13 -> #REF! | AU21: =SUMIFS($F$13:$F$34,$D$13:$D$34,D21) -> #REF! | AV21: =+AU21/$AU$13 -> #REF! | AW21: =+AK21 -> #REF! | AX21: =+AW21/$AW$13 -> #REF! | AY21: =SUMIFS($I$13:$I$34,$D$13:$D$34,D21)+SUMIFS($AU$13:$AU$34,$D$13:$D$34,D21) -> #REF! | AZ21: =+AY21/$AY$13 -> #REF! | BA21: =SUMIFS($AM$13:$AM$34,$D$13:$D$34,D21)+SUMIFS($AW$13:$AW$34,$D$13:$D$34,D21) -> #REF! | BB21: =+BA21/$BA$13 -> #REF! | BC21: =SUMIFS($M$13:$M$34,$D$13:$D$34,D21)+SUMIFS($AY$13:$AY$34,$D$13:$D$34,D21) -> #REF! | BD21: =+BC21/$BC$13 -> #REF! | BE21: =SUMIFS($AO$13:$AO$34,$D$13:$D$34,D21)+SUMIFS($BA$13:$BA$34,$D$13:$D$34,D21) -> #REF! | BF21: =+BE21/$BE$13 -> #REF!
B22: Total Occupancy | C22: Total Payroll Taxes | D22: Occupancy | F22: =+SUMIFS(#REF!,#REF!,'RDG Weekly'!B22) -> #REF! | G22: =IFERROR(F22/F13,0) -> 0 | I22: =+SUMIFS(#REF!,#REF!,'RDG Weekly'!B22) -> #REF! | K22: =IFERROR(I22/I13,0) -> 0 | M22: =+SUMIFS(#REF!,#REF!,'RDG Weekly'!B22) -> #REF! | O22: =IFERROR(M22/M13,0) -> 0 | Q22: =+SUMIFS(#REF!,#REF!,'RDG Weekly'!B22) -> #REF! | S22: =IFERROR(Q22/Q13,0) -> 0 | X22: =+SUMIFS(#REF!,#REF!,'RDG Weekly'!Q22) -> #REF! | Z22: =IFERROR(X22/X13,0) -> 0 | AB22: =+SUMIFS(#REF!,#REF!,'RDG Weekly'!Q22) -> #REF! | AD22: =IFERROR(AB22/AB13,0) -> 0 | AE22: =+SUMIFS(#REF!,#REF!,'RDG Weekly'!Q22) -> #REF! | AF22: =IFERROR(AE22/AE13,0) -> 0 | AG22: =+SUMIFS(#REF!,#REF!,'RDG Weekly'!Q22) -> #REF! | AH22: =IFERROR(AG22/AG13,0) -> 0 | AK22: =+#REF! -> #REF! | AL22: =IFERROR(AK22/AK13,0) -> 0 | AM22: =+AK22 -> #REF! | AN22: =IFERROR(AM22/AM13,0) -> 0 | AO22: =+AM22 -> #REF! | AP22: =IFERROR(AO22/AO13,0) -> 0 | AQ22: =+AO22 -> #REF! | AR22: =IFERROR(AQ22/AQ13,0) -> 0 | AU22: =SUMIFS($F$13:$F$34,$D$13:$D$34,D22) -> #REF! | AV22: =IFERROR(AU22/AU13,0) -> 0 | AW22: =+AK22 -> #REF! | AX22: =IFERROR(AW22/AW13,0) -> 0 | AY22: =SUMIFS($I$13:$I$34,$D$13:$D$34,D22)+SUMIFS($AU$13:$AU$34,$D$13:$D$34,D22) -> #REF! | AZ22: =IFERROR(AY22/AY13,0) -> 0 | BA22: =SUMIFS($AM$13:$AM$34,$D$13:$D$34,D22)+SUMIFS($AW$13:$AW$34,$D$13:$D$34,D22) -> #REF! | BB22: =IFERROR(BA22/BA13,0) -> 0 | BC22: =SUMIFS($M$13:$M$34,$D$13:$D$34,D22)+SUMIFS($AY$13:$AY$34,$D$13:$D$34,D22) -> #REF! | BD22: =IFERROR(BC22/BC13,0) -> 0 | BE22: =SUMIFS($AO$13:$AO$34,$D$13:$D$34,D22)+SUMIFS($BA$13:$BA$34,$D$13:$D$34,D22) -> #REF! | BF22: =IFERROR(BE22/BE13,0) -> 0
B23: Total Direct Operating Expenses | C23: 5970 - Group Health Insurance | D23: Operating Expenses | F23: =+SUMIFS(#REF!,#REF!,'RDG Weekly'!B23) -> #REF! | G23: =IFERROR(F23/F13,0) -> 0 | I23: =+SUMIFS(#REF!,#REF!,'RDG Weekly'!B23) -> #REF! | K23: =IFERROR(I23/I13,0) -> 0 | M23: =+SUMIFS(#REF!,#REF!,'RDG Weekly'!B23) -> #REF! | O23: =IFERROR(M23/M13,0) -> 0 | Q23: =+SUMIFS(#REF!,#REF!,'RDG Weekly'!B23) -> #REF! | S23: =IFERROR(Q23/Q13,0) -> 0 | X23: =+SUMIFS(#REF!,#REF!,'RDG Weekly'!Q23) -> #REF! | Z23: =IFERROR(X23/X13,0) -> 0 | AB23: =+SUMIFS(#REF!,#REF!,'RDG Weekly'!Q23) -> #REF! | AD23: =IFERROR(AB23/AB13,0) -> 0 | AE23: =+SUMIFS(#REF!,#REF!,'RDG Weekly'!Q23) -> #REF! | AF23: =IFERROR(AE23/AE13,0) -> 0 | AG23: =+SUMIFS(#REF!,#REF!,'RDG Weekly'!Q23) -> #REF! | AH23: =IFERROR(AG23/AG13,0) -> 0 | AK23: =+#REF! -> #REF! | AL23: =IFERROR(AK23/AK13,0) -> 0 | AM23: =+AK23 -> #REF! | AN23: =IFERROR(AM23/AM13,0) -> 0 | AO23: =+AM23 -> #REF! | AP23: =IFERROR(AO23/AO13,0) -> 0 | AQ23: =+AO23 -> #REF! | AR23: =IFERROR(AQ23/AQ13,0) -> 0 | AU23: =SUMIFS($F$13:$F$34,$D$13:$D$34,D23) -> #REF! | AV23: =IFERROR(AU23/AU13,0) -> 0 | AW23: =+AK23 -> #REF! | AX23: =IFERROR(AW23/AW13,0) -> 0 | AY23: =SUMIFS($I$13:$I$34,$D$13:$D$34,D23)+SUMIFS($AU$13:$AU$34,$D$13:$D$34,D23) -> #REF! | AZ23: =IFERROR(AY23/AY13,0) -> 0 | BA23: =SUMIFS($AM$13:$AM$34,$D$13:$D$34,D23)+SUMIFS($AW$13:$AW$34,$D$13:$D$34,D23) -> #REF! | BB23: =IFERROR(BA23/BA13,0) -> 0 | BC23: =SUMIFS($M$13:$M$34,$D$13:$D$34,D23)+SUMIFS($AY$13:$AY$34,$D$13:$D$34,D23) -> #REF! | BD23: =IFERROR(BC23/BC13,0) -> 0 | BE23: =SUMIFS($AO$13:$AO$34,$D$13:$D$34,D23)+SUMIFS($BA$13:$BA$34,$D$13:$D$34,D23) -> #REF! | BF23: =IFERROR(BE23/BE13,0) -> 0
B24: Total General and Administrative | D24: General & Administrative | F24: =+SUMIFS(#REF!,#REF!,'RDG Weekly'!B24) -> #REF! | G24: =IFERROR(F24/F13,0) -> 0 | I24: =+SUMIFS(#REF!,#REF!,'RDG Weekly'!B24) -> #REF! | K24: =IFERROR(I24/I13,0) -> 0 | M24: =+SUMIFS(#REF!,#REF!,'RDG Weekly'!B24) -> #REF! | O24: =IFERROR(M24/M13,0) -> 0 | Q24: =+SUMIFS(#REF!,#REF!,'RDG Weekly'!B24) -> #REF! | S24: =IFERROR(Q24/Q13,0) -> 0 | X24: =+SUMIFS(#REF!,#REF!,'RDG Weekly'!Q24) -> #REF! | Z24: =IFERROR(X24/X13,0) -> 0 | AB24: =+SUMIFS(#REF!,#REF!,'RDG Weekly'!Q24) -> #REF! | AD24: =IFERROR(AB24/AB13,0) -> 0 | AE24: =+SUMIFS(#REF!,#REF!,'RDG Weekly'!Q24) -> #REF! | AF24: =IFERROR(AE24/AE13,0) -> 0 | AG24: =+SUMIFS(#REF!,#REF!,'RDG Weekly'!Q24) -> #REF! | AH24: =IFERROR(AG24/AG13,0) -> 0 | AK24: =+#REF! -> #REF! | AL24: =IFERROR(AK24/AK13,0) -> 0 | AM24: =+AK24 -> #REF! | AN24: =IFERROR(AM24/AM13,0) -> 0 | AO24: =+AM24 -> #REF! | AP24: =IFERROR(AO24/AO13,0) -> 0 | AQ24: =+AO24 -> #REF! | AR24: =IFERROR(AQ24/AQ13,0) -> 0 | AU24: =SUMIFS($F$13:$F$34,$D$13:$D$34,D24) -> #REF! | AV24: =IFERROR(AU24/AU13,0) -> 0 | AW24: =+AK24 -> #REF! | AX24: =IFERROR(AW24/AW13,0) -> 0 | AY24: =SUMIFS($I$13:$I$34,$D$13:$D$34,D24)+SUMIFS($AU$13:$AU$34,$D$13:$D$34,D24) -> #REF! | AZ24: =IFERROR(AY24/AY13,0) -> 0 | BA24: =SUMIFS($AM$13:$AM$34,$D$13:$D$34,D24)+SUMIFS($AW$13:$AW$34,$D$13:$D$34,D24) -> #REF! | BB24: =IFERROR(BA24/BA13,0) -> 0 | BC24: =SUMIFS($M$13:$M$34,$D$13:$D$34,D24)+SUMIFS($AY$13:$AY$34,$D$13:$D$34,D24) -> #REF! | BD24: =IFERROR(BC24/BC13,0) -> 0 | BE24: =SUMIFS($AO$13:$AO$34,$D$13:$D$34,D24)+SUMIFS($BA$13:$BA$34,$D$13:$D$34,D24) -> #REF! | BF24: =IFERROR(BE24/BE13,0) -> 0
B25: Total Utilities | D25: Utilities | F25: =+SUMIFS(#REF!,#REF!,'RDG Weekly'!B25) -> #REF! | G25: =IFERROR(F25/F13,0) -> 0 | I25: =+SUMIFS(#REF!,#REF!,'RDG Weekly'!B25) -> #REF! | K25: =IFERROR(I25/I13,0) -> 0 | M25: =+SUMIFS(#REF!,#REF!,'RDG Weekly'!B25) -> #REF! | O25: =IFERROR(M25/M13,0) -> 0 | Q25: =+SUMIFS(#REF!,#REF!,'RDG Weekly'!B25) -> #REF! | S25: =IFERROR(Q25/Q13,0) -> 0 | X25: =+SUMIFS(#REF!,#REF!,'RDG Weekly'!Q25) -> #REF! | Z25: =IFERROR(X25/X13,0) -> 0 | AB25: =+SUMIFS(#REF!,#REF!,'RDG Weekly'!Q25) -> #REF! | AD25: =IFERROR(AB25/AB13,0) -> 0 | AE25: =+SUMIFS(#REF!,#REF!,'RDG Weekly'!Q25) -> #REF! | AF25: =IFERROR(AE25/AE13,0) -> 0 | AG25: =+SUMIFS(#REF!,#REF!,'RDG Weekly'!Q25) -> #REF! | AH25: =IFERROR(AG25/AG13,0) -> 0 | AK25: =+#REF! -> #REF! | AL25: =IFERROR(AK25/AK13,0) -> 0 | AM25: =+AK25 -> #REF! | AN25: =IFERROR(AM25/AM13,0) -> 0 | AO25: =+AM25 -> #REF! | AP25: =IFERROR(AO25/AO13,0) -> 0 | AQ25: =+AO25 -> #REF! | AR25: =IFERROR(AQ25/AQ13,0) -> 0 | AU25: =SUMIFS($F$13:$F$34,$D$13:$D$34,D25) -> #REF! | AV25: =IFERROR(AU25/AU13,0) -> 0 | AW25: =+AK25 -> #REF! | AX25: =IFERROR(AW25/AW13,0) -> 0 | AY25: =SUMIFS($I$13:$I$34,$D$13:$D$34,D25)+SUMIFS($AU$13:$AU$34,$D$13:$D$34,D25) -> #REF! | AZ25: =IFERROR(AY25/AY13,0) -> 0 | BA25: =SUMIFS($AM$13:$AM$34,$D$13:$D$34,D25)+SUMIFS($AW$13:$AW$34,$D$13:$D$34,D25) -> #REF! | BB25: =IFERROR(BA25/BA13,0) -> 0 | BC25: =SUMIFS($M$13:$M$34,$D$13:$D$34,D25)+SUMIFS($AY$13:$AY$34,$D$13:$D$34,D25) -> #REF! | BD25: =IFERROR(BC25/BC13,0) -> 0 | BE25: =SUMIFS($AO$13:$AO$34,$D$13:$D$34,D25)+SUMIFS($BA$13:$BA$34,$D$13:$D$34,D25) -> #REF! | BF25: =IFERROR(BE25/BE13,0) -> 0
B26: Total Other (Income) Expenses | D26: Other Income | F26: =+SUMIFS(#REF!,#REF!,'RDG Weekly'!B26) -> #REF! | G26: =IFERROR(F26/F13,0) -> 0 | I26: =+SUMIFS(#REF!,#REF!,'RDG Weekly'!B26) -> #REF! | K26: =IFERROR(I26/I13,0) -> 0 | M26: =+SUMIFS(#REF!,#REF!,'RDG Weekly'!B26) -> #REF! | O26: =IFERROR(M26/M13,0) -> 0 | Q26: =+SUMIFS(#REF!,#REF!,'RDG Weekly'!B26) -> #REF! | S26: =IFERROR(Q26/Q13,0) -> 0 | X26: =+SUMIFS(#REF!,#REF!,'RDG Weekly'!Q26) -> #REF! | Z26: =IFERROR(X26/X13,0) -> 0 | AB26: =+SUMIFS(#REF!,#REF!,'RDG Weekly'!Q26) -> #REF! | AD26: =IFERROR(AB26/AB13,0) -> 0 | AE26: =+SUMIFS(#REF!,#REF!,'RDG Weekly'!Q26) -> #REF! | AF26: =IFERROR(AE26/AE13,0) -> 0 | AG26: =+SUMIFS(#REF!,#REF!,'RDG Weekly'!Q26) -> #REF! | AH26: =IFERROR(AG26/AG13,0) -> 0 | AK26: =+#REF! -> #REF! | AL26: =IFERROR(AK26/AK13,0) -> 0 | AM26: =+AK26 -> #REF! | AN26: =IFERROR(AM26/AM13,0) -> 0 | AO26: =+AM26 -> #REF! | AP26: =IFERROR(AO26/AO13,0) -> 0 | AQ26: =+AO26 -> #REF! | AR26: =IFERROR(AQ26/AQ13,0) -> 0 | AU26: =SUMIFS($F$13:$F$34,$D$13:$D$34,D26) -> #REF! | AV26: =IFERROR(AU26/AU13,0) -> 0 | AW26: =+AK26 -> #REF! | AX26: =IFERROR(AW26/AW13,0) -> 0 | AY26: =SUMIFS($I$13:$I$34,$D$13:$D$34,D26)+SUMIFS($AU$13:$AU$34,$D$13:$D$34,D26) -> #REF! | AZ26: =IFERROR(AY26/AY13,0) -> 0 | BA26: =SUMIFS($AM$13:$AM$34,$D$13:$D$34,D26)+SUMIFS($AW$13:$AW$34,$D$13:$D$34,D26) -> #REF! | BB26: =IFERROR(BA26/BA13,0) -> 0 | BC26: =SUMIFS($M$13:$M$34,$D$13:$D$34,D26)+SUMIFS($AY$13:$AY$34,$D$13:$D$34,D26) -> #REF! | BD26: =IFERROR(BC26/BC13,0) -> 0 | BE26: =SUMIFS($AO$13:$AO$34,$D$13:$D$34,D26)+SUMIFS($BA$13:$BA$34,$D$13:$D$34,D26) -> #REF! | BF26: =IFERROR(BE26/BE13,0) -> 0
D28: Total Operating Expenses | F28: =SUM(F22:F26,F18) -> #REF! | G28: =IFERROR(F28/F13,0) -> 0 | I28: =SUM(I22:I26,I18) -> #REF! | K28: =IFERROR(I28/I13,0) -> 0 | M28: =SUM(M22:M26,M18) -> #REF! | O28: =IFERROR(M28/M13,0) -> 0 | Q28: =SUM(Q22:Q26,Q18) -> #REF! | S28: =IFERROR(Q28/Q13,0) -> 0 | X28: =SUM(X22:X26,X18) -> #REF! | Z28: =IFERROR(X28/X13,0) -> 0 | AB28: =SUM(AB22:AB26,AB18) -> #REF! | AD28: =IFERROR(AB28/AB13,0) -> 0 | AE28: =SUM(AE22:AE26,AE18) -> #REF! | AF28: =IFERROR(AE28/AE13,0) -> 0 | AG28: =SUM(AG22:AG26,AG18) -> #REF! | AH28: =IFERROR(AG28/AG13,0) -> 0 | AK28: =SUM(AK22:AK26,AK18) -> #REF! | AL28: =IFERROR(AK28/AK13,0) -> 0 | AM28: =SUM(AM22:AM26,AM18) -> #REF! | AN28: =IFERROR(AM28/AM13,0) -> 0 | AO28: =SUM(AO22:AO26,AO18) -> #REF! | AP28: =IFERROR(AO28/AO13,0) -> 0 | AQ28: =SUM(AQ22:AQ26,AQ18) -> #REF! | AR28: =IFERROR(AQ28/AQ13,0) -> 0 | AU28: =SUM(AU22:AU26,AU18) -> #REF! | AV28: =IFERROR(AU28/AU13,0) -> 0 | AW28: =SUM(AW22:AW26,AW18) -> #REF! | AX28: =IFERROR(AW28/AW13,0) -> 0 | AY28: =SUM(AY22:AY26,AY18) -> #REF! | AZ28: =IFERROR(AY28/AY13,0) -> 0 | BA28: =SUM(BA22:BA26,BA18) -> #REF! | BB28: =IFERROR(BA28/BA13,0) -> 0 | BC28: =SUM(BC22:BC26,BC18) -> #REF! | BD28: =IFERROR(BC28/BC13,0) -> 0 | BE28: =SUM(BE22:BE26,BE18) -> #REF! | BF28: =IFERROR(BE28/BE13,0) -> 0
D30: Net Operating Income | F30: =F16-F28 -> #REF! | G30: =IFERROR(F30/F13,0) -> 0 | I30: =I16-I28 -> #REF! | K30: =IFERROR(I30/I13,0) -> 0 | M30: =M16-M28 -> #REF! | O30: =IFERROR(M30/M13,0) -> 0 | Q30: =Q16-Q28 -> #REF! | S30: =IFERROR(Q30/Q13,0) -> 0 | X30: =X16-X28 -> #REF! | Z30: =IFERROR(X30/X13,0) -> 0 | AB30: =AB16-AB28 -> #REF! | AD30: =IFERROR(AB30/AB13,0) -> 0 | AE30: =AE16-AE28 -> #REF! | AF30: =IFERROR(AE30/AE13,0) -> 0 | AG30: =AG16-AG28 -> #REF! | AH30: =IFERROR(AG30/AG13,0) -> 0 | AK30: =AK16-AK28 -> #REF! | AL30: =IFERROR(AK30/AK13,0) -> 0 | AM30: =AM16-AM28 -> #REF! | AN30: =IFERROR(AM30/AM13,0) -> 0 | AO30: =AO16-AO28 -> #REF! | AP30: =IFERROR(AO30/AO13,0) -> 0 | AQ30: =AQ16-AQ28 -> #REF! | AR30: =IFERROR(AQ30/AQ13,0) -> 0 | AU30: =AU16-AU28 -> #REF! | AV30: =IFERROR(AU30/AU13,0) -> 0 | AW30: =AW16-AW28 -> #REF! | AX30: =IFERROR(AW30/AW13,0) -> 0 | AY30: =AY16-AY28 -> #REF! | AZ30: =IFERROR(AY30/AY13,0) -> 0 | BA30: =BA16-BA28 -> #REF! | BB30: =IFERROR(BA30/BA13,0) -> 0 | BC30: =BC16-BC28 -> #REF! | BD30: =IFERROR(BC30/BC13,0) -> 0 | BE30: =BE16-BE28 -> #REF! | BF30: =IFERROR(BE30/BE13,0) -> 0
B32: Total Corporate Overhead | D32: Other G&A | F32: =+SUMIFS(#REF!,#REF!,'RDG Weekly'!B32)-SUMIFS(#REF!,#REF!,'RDG Weekly'!B33) -> #REF! | G32: =IFERROR(F32/F13,0) -> 0 | I32: =+SUMIFS(#REF!,#REF!,'RDG Weekly'!B32) -> #REF! | K32: =IFERROR(I32/I13,0) -> 0 | M32: =+SUMIFS(#REF!,#REF!,'RDG Weekly'!B32) -> #REF! | O32: =IFERROR(M32/M13,0) -> 0 | Q32: =+SUMIFS(#REF!,#REF!,'RDG Weekly'!B32) -> #REF! | S32: =IFERROR(Q32/Q13,0) -> 0 | X32: =+SUMIFS(#REF!,#REF!,'RDG Weekly'!Q32)-SUMIFS(#REF!,#REF!,'RDG Weekly'!Q33) -> #REF! | Z32: =IFERROR(X32/X13,0) -> 0 | AB32: =+SUMIFS(#REF!,#REF!,'RDG Weekly'!Q32) -> #REF! | AD32: =IFERROR(AB32/AB13,0) -> 0 | AE32: =+SUMIFS(#REF!,#REF!,'RDG Weekly'!Q32) -> #REF! | AF32: =IFERROR(AE32/AE13,0) -> 0 | AG32: =+SUMIFS(#REF!,#REF!,'RDG Weekly'!Q32) -> #REF! | AH32: =IFERROR(AG32/AG13,0) -> 0 | AK32: =+#REF! -> #REF! | AL32: =IFERROR(AK32/AK13,0) -> 0 | AM32: =+AK32 -> #REF! | AN32: =IFERROR(AM32/AM13,0) -> 0 | AO32: =+AM32 -> #REF! | AP32: =IFERROR(AO32/AO13,0) -> 0 | AQ32: =+AO32 -> #REF! | AR32: =IFERROR(AQ32/AQ13,0) -> 0 | AU32: =SUMIFS($F$13:$F$34,$D$13:$D$34,D32) -> #REF! | AV32: =IFERROR(AU32/AU13,0) -> 0 | AW32: =+AK32 -> #REF! | AX32: =IFERROR(AW32/AW13,0) -> 0 | AY32: =SUMIFS($I$13:$I$34,$D$13:$D$34,D32)+SUMIFS($AU$13:$AU$34,$D$13:$D$34,D32) -> #REF! | AZ32: =IFERROR(AY32/AY13,0) -> 0 | BA32: =SUMIFS($AM$13:$AM$34,$D$13:$D$34,D32)+SUMIFS($AW$13:$AW$34,$D$13:$D$34,D32) -> #REF! | BB32: =IFERROR(BA32/BA13,0) -> 0 | BC32: =SUMIFS($M$13:$M$34,$D$13:$D$34,D32)+SUMIFS($AY$13:$AY$34,$D$13:$D$34,D32) -> #REF! | BD32: =IFERROR(BC32/BC13,0) -> 0 | BE32: =+AO32+BA32 -> #REF! | BF32: =IFERROR(BE32/BE13,0) -> 0
B33: 9205 - Depreciation Expense
B34: Total New Location | D34: EBITDA | F34: =F30-F32 -> #REF! | G34: =IFERROR(F34/F13,0) -> 0 | I34: =I30-I32 -> #REF! | K34: =IFERROR(I34/I13,0) -> 0 | M34: =M30-M32 -> #REF! | O34: =IFERROR(M34/M13,0) -> 0 | Q34: =Q30-Q32 -> #REF! | S34: =IFERROR(Q34/Q13,0) -> 0 | X34: =X30-X32 -> #REF! | Z34: =IFERROR(X34/X13,0) -> 0 | AB34: =AB30-AB32 -> #REF! | AD34: =IFERROR(AB34/AB13,0) -> 0 | AE34: =AE30-AE32 -> #REF! | AF34: =IFERROR(AE34/AE13,0) -> 0 | AG34: =AG30-AG32 -> #REF! | AH34: =IFERROR(AG34/AG13,0) -> 0 | AK34: =AK30-AK32 -> #REF! | AL34: =IFERROR(AK34/AK13,0) -> 0 | AM34: =AM30-AM32 -> #REF! | AN34: =IFERROR(AM34/AM13,0) -> 0 | AO34: =AO30-AO32 -> #REF! | AP34: =IFERROR(AO34/AO13,0) -> 0 | AQ34: =AQ30-AQ32 -> #REF! | AR34: =IFERROR(AQ34/AQ13,0) -> 0 | AU34: =AU30-AU32 -> #REF! | AV34: =IFERROR(AU34/AU13,0) -> 0 | AW34: =AW30-AW32 -> #REF! | AX34: =IFERROR(AW34/AW13,0) -> 0 | AY34: =AY30-AY32 -> #REF! | AZ34: =IFERROR(AY34/AY13,0) -> 0 | BA34: =BA30-BA32 -> #REF! | BB34: =IFERROR(BA34/BA13,0) -> 0 | BC34: =BC30-BC32 -> #REF! | BD34: =IFERROR(BC34/BC13,0) -> 0 | BE34: =BE30-BE32 -> #REF! | BF34: =IFERROR(BE34/BE13,0) -> 0
B35: 9010 - Interest Expense
D36: Key Performing Indicators | F36: =+F11 -> MILA 3F | I36: =+I11 -> MILA 2F | M36: =+M11 -> AVA | Q36: =+Q11 -> CASA NEOS | X36: =+X11 -> MILA | AB36: =+AB11 -> MILA MM | AE36: =+AE11 -> AVA | AG36: =+AG11 -> BAOLI
D38: Food Cost % | F38: =+SUMIFS(#REF!,#REF!,'RDG Weekly'!$B$213)/+SUMIFS(#REF!,#REF!,'RDG Weekly'!$B$212) -> #REF! | I38: =+SUMIFS(#REF!,#REF!,#REF!)/+SUMIFS(#REF!,#REF!,#REF!) -> #REF! | M38: =+SUMIFS(#REF!,#REF!,#REF!)/+SUMIFS(#REF!,#REF!,#REF!) -> #REF! | Q38: =+SUMIFS(#REF!,#REF!,#REF!)/+SUMIFS(#REF!,#REF!,#REF!) -> #REF! | X38: =+SUMIFS(#REF!,#REF!,'RDG Weekly'!$B$213)/+SUMIFS(#REF!,#REF!,'RDG Weekly'!$B$212) -> #REF! | AB38: =+SUMIFS(#REF!,#REF!,#REF!)/+SUMIFS(#REF!,#REF!,#REF!) -> #REF! | AE38: =+SUMIFS(#REF!,#REF!,#REF!)/+SUMIFS(#REF!,#REF!,#REF!) -> #REF! | AG38: =+SUMIFS(#REF!,#REF!,#REF!)/+SUMIFS(#REF!,#REF!,#REF!) -> #REF!
D39: Liqour % | F39: =+(SUMIFS(#REF!,#REF!,'RDG Weekly'!$C$215)+SUMIFS(#REF!,#REF!,'RDG Weekly'!$C$218))/+SUMIFS(#REF!,#REF!,'RDG Weekly'!$C$214) -> #REF! | I39: =+(SUMIFS(#REF!,#REF!,#REF!)+SUMIFS(#REF!,#REF!,#REF!))/+SUMIFS(#REF!,#REF!,#REF!) -> #REF! | M39: =+(SUMIFS(#REF!,#REF!,#REF!)+SUMIFS(#REF!,#REF!,#REF!))/+SUMIFS(#REF!,#REF!,#REF!) -> #REF! | Q39: =+(SUMIFS(#REF!,#REF!,#REF!)+SUMIFS(#REF!,#REF!,#REF!))/+SUMIFS(#REF!,#REF!,#REF!) -> #REF! | X39: =+(SUMIFS(#REF!,#REF!,'RDG Weekly'!$C$215)+SUMIFS(#REF!,#REF!,'RDG Weekly'!$C$218))/+SUMIFS(#REF!,#REF!,'RDG Weekly'!$C$214) -> #REF! | AB39: =+(SUMIFS(#REF!,#REF!,#REF!)+SUMIFS(#REF!,#REF!,#REF!))/+SUMIFS(#REF!,#REF!,#REF!) -> #REF! | AE39: =+(SUMIFS(#REF!,#REF!,#REF!)+SUMIFS(#REF!,#REF!,#REF!))/+SUMIFS(#REF!,#REF!,#REF!) -> #REF! | AG39: =+(SUMIFS(#REF!,#REF!,#REF!)+SUMIFS(#REF!,#REF!,#REF!))/+SUMIFS(#REF!,#REF!,#REF!) -> #REF!
D40: Wine % | F40: =+(SUMIFS(#REF!,#REF!,'RDG Weekly'!$B$219)++SUMIFS(#REF!,#REF!,'RDG Weekly'!$B$220)+SUMIFS(#REF!,#REF!,'RDG Weekly'!$B$221))/(+SUMIFS(#REF!,#REF!,'RDG Weekly'!$B$214)+SUMIFS(#REF!,#REF!,'RDG Weekly'!$B$215)+SUMIFS(#REF!,#REF!,'RDG Weekly'!$B$218)) -> #REF! | I40: =+(SUMIFS(#REF!,#REF!,#REF!)++SUMIFS(#REF!,#REF!,#REF!)+SUMIFS(#REF!,#REF!,#REF!))/(+SUMIFS(#REF!,#REF!,#REF!)+SUMIFS(#REF!,#REF!,#REF!)+SUMIFS(#REF!,#REF!,#REF!)) -> #REF! | M40: =+(SUMIFS(#REF!,#REF!,#REF!)++SUMIFS(#REF!,#REF!,#REF!)+SUMIFS(#REF!,#REF!,#REF!))/(+SUMIFS(#REF!,#REF!,#REF!)+SUMIFS(#REF!,#REF!,#REF!)+SUMIFS(#REF!,#REF!,#REF!)) -> #REF! | Q40: =+(SUMIFS(#REF!,#REF!,#REF!)++SUMIFS(#REF!,#REF!,#REF!)+SUMIFS(#REF!,#REF!,#REF!))/(+SUMIFS(#REF!,#REF!,#REF!)+SUMIFS(#REF!,#REF!,#REF!)+SUMIFS(#REF!,#REF!,#REF!)) -> #REF! | X40: =+(SUMIFS(#REF!,#REF!,'RDG Weekly'!$B$219)++SUMIFS(#REF!,#REF!,'RDG Weekly'!$B$220)+SUMIFS(#REF!,#REF!,'RDG Weekly'!$B$221))/(+SUMIFS(#REF!,#REF!,'RDG Weekly'!$B$214)+SUMIFS(#REF!,#REF!,'RDG Weekly'!$B$215)+SUMIFS(#REF!,#REF!,'RDG Weekly'!$B$218)) -> #REF! | AB40: =+(SUMIFS(#REF!,#REF!,#REF!)++SUMIFS(#REF!,#REF!,#REF!)+SUMIFS(#REF!,#REF!,#REF!))/(+SUMIFS(#REF!,#REF!,#REF!)+SUMIFS(#REF!,#REF!,#REF!)+SUMIFS(#REF!,#REF!,#REF!)) -> #REF! | AE40: =+(SUMIFS(#REF!,#REF!,#REF!)++SUMIFS(#REF!,#REF!,#REF!)+SUMIFS(#REF!,#REF!,#REF!))/(+SUMIFS(#REF!,#REF!,#REF!)+SUMIFS(#REF!,#REF!,#REF!)+SUMIFS(#REF!,#REF!,#REF!)) -> #REF! | AG40: =+(SUMIFS(#REF!,#REF!,#REF!)++SUMIFS(#REF!,#REF!,#REF!)+SUMIFS(#REF!,#REF!,#REF!))/(+SUMIFS(#REF!,#REF!,#REF!)+SUMIFS(#REF!,#REF!,#REF!)+SUMIFS(#REF!,#REF!,#REF!)) -> #REF!
D42: BOH Labour Cost % | F42: =F20/+SUMIFS(#REF!,#REF!,#REF!) -> #REF! | I42: =I20/+SUMIFS(#REF!,#REF!,B212) -> #REF! | M42: =M20/+SUMIFS(#REF!,#REF!,B212) -> #REF! | Q42: =Q20/+SUMIFS(#REF!,#REF!,B212) -> #REF! | X42: =X20/+SUMIFS(#REF!,#REF!,#REF!) -> #REF! | AB42: =AB20/+SUMIFS(#REF!,#REF!,Q37) -> #REF! | AE42: =AE20/+SUMIFS(#REF!,#REF!,Q37) -> #REF! | AG42: =AG20/+SUMIFS(#REF!,#REF!,Q37) -> #REF!
D44: Commentary
D46: Cost of Goods Sold | F46: Food cost upside in wk 5 with the buyout, liqour cost was steady with minimal variance of 6 btls which were rail product. Champ consumption during Brunch is till relativly high
D47: Cost of Labour | F47: BOH Casa Neo's chefs impacting MILA budget, along with RDG re-billing (Marketing/IT)
D48: Occupancy | F48: Turnover rent is higher due to higher sales vs budget
D49: Operating Expenses | F49: Tight spending for whole month of July, 38k upside within restaurant supplies (new napkins) that was realized within P5 accounts.
D50: General & Administrative | F50: Overage driven by storage fee 5k (no budget) & General liability insurance. (15k)
D51: Utilities
D56: RDG Ownership | F56: 0.88166667 | X56: 0.88166667
D57: EBITDA by Ownership | F57: =F34*F56 -> #REF! | X57: =X34*X56 -> #REF!
D60: Covers | F60: =VLOOKUP(F11,#REF!,4,FALSE) -> #REF! | I60: =VLOOKUP(I11,#REF!,4,FALSE) -> #REF! | M60: =VLOOKUP(M11,#REF!,4,FALSE) -> #REF! | Q60: =VLOOKUP(Q11,#REF!,4,FALSE) -> #REF! | X60: =VLOOKUP(X11,#REF!,4,FALSE) -> #REF! | AB60: =VLOOKUP(AB11,#REF!,4,FALSE) -> #REF! | AE60: =VLOOKUP(AE11,#REF!,4,FALSE) -> #REF! | AG60: =VLOOKUP(AG11,#REF!,4,FALSE) -> #REF!
D61: ASPH | F61: =+F13/F60 -> #REF! | I61: =+I13/I60 -> #REF! | M61: =+M13/M60 -> #REF! | Q61: =+Q13/Q60 -> #REF! | X61: =+X13/X60 -> #REF! | AB61: =+AB13/AB60 -> #REF! | AE61: =+AE13/AE60 -> #REF! | AG61: =+AG13/AG60 -> #REF!
D76: =CONCATENATE("MILA Lounge - Profit & Loss",) -> MILA Lounge - Profit & Loss | AK76: Weekly Budget | AU76: Month to Date
C78: BUD.
D81: MILA II - P6 | F81: =+F9 -> MTD | X81: =+X9 -> YTD | AK81: =+AK9 -> #REF! | AM81: =+AM9 -> #REF! | AO81: =+AO9 -> #REF! | AQ81: =+AQ9 -> #REF! | AU81: =+AU9 -> #REF! | AY81: =+AY9 -> #REF! | BC81: =+BC9 -> #REF!
F83: =+F11 -> MILA 3F | I83: =+I11 -> MILA 2F | M83: =+M11 -> AVA | Q83: =+Q11 -> CASA NEOS | X83: =+X11 -> MILA | AB83: =+AB11 -> MILA MM | AE83: =+AE11 -> AVA | AG83: =+AG11 -> BAOLI | AK83: BUDGET | AM83: BUDGET | AO83: BUDGET | AQ83: BUDGET | AU83: 2023 | AW83: BUDGET | AY83: 2023 | BA83: BUDGET | BC83: 2023 | BE83: BUDGET
D85: Net Sales | F85: =SUMIFS(#REF!,#REF!,'RDG Weekly'!B13) -> #REF! | G85: =IFERROR(F85/F85,0) -> 0 | I85: =SUMIFS(#REF!,#REF!,'RDG Weekly'!B13) -> #REF! | K85: =IFERROR(I85/I85,0) -> 0 | M85: =SUMIFS(#REF!,#REF!,'RDG Weekly'!B13) -> #REF! | O85: =IFERROR(M85/M85,0) -> 0 | Q85: =SUMIFS(#REF!,#REF!,'RDG Weekly'!B13) -> #REF! | S85: =IFERROR(Q85/Q85,0) -> 0 | X85: =SUMIFS(#REF!,#REF!,'RDG Weekly'!Q13) -> #REF! | Z85: =IFERROR(X85/X85,0) -> 0 | AB85: =SUMIFS(#REF!,#REF!,'RDG Weekly'!Q13) -> #REF! | AD85: =IFERROR(AB85/AB85,0) -> 0 | AE85: =SUMIFS(#REF!,#REF!,'RDG Weekly'!Q13) -> #REF! | AF85: =IFERROR(AE85/AE85,0) -> 0 | AG85: =SUMIFS(#REF!,#REF!,'RDG Weekly'!Q13) -> #REF! | AH85: =IFERROR(AG85/AG85,0) -> 0 | AK85: =+#REF!/#REF! -> #REF! | AL85: =IFERROR(AK85/AK85,0) -> 0 | AM85: =+AK85 -> #REF! | AN85: =IFERROR(AM85/AM85,0) -> 0 | AO85: =+AM85 -> #REF! | AP85: =IFERROR(AO85/AO85,0) -> 0 | AQ85: =+AO85 -> #REF! | AR85: =IFERROR(AQ85/AQ85,0) -> 0 | AU85: =SUMIFS($F$85:$F$106,$D$85:$D$106,D85) -> #REF! | AV85: =IFERROR(AU85/AU85,0) -> 0 | AW85: =+AK85 -> #REF! | AX85: =IFERROR(AW85/AW85,0) -> 0 | AY85: =SUMIFS($I$85:$I$106,$D$85:$D$106,D85)+SUMIFS($AU$85:$AU$106,$D$85:$D$106,D85) -> #REF! | AZ85: =IFERROR(AY85/AY85,0) -> 0 | BA85: =SUMIFS($AM$85:$AM$106,$D$85:$D$106,D85)+SUMIFS($AW$85:$AW$106,$D$85:$D$106,D85) -> #REF! | BB85: =IFERROR(BA85/BA85,0) -> 0 | BC85: =SUMIFS($M$85:$M$106,$D$85:$D$106,D85)+SUMIFS($AY$85:$AY$106,$D$85:$D$106,D85) -> #REF! | BD85: =IFERROR(BC85/BC85,0) -> 0 | BE85: =SUMIFS($AO$85:$AO$106,$D$85:$D$106,D85)+SUMIFS($BA$85:$BA$106,$D$85:$D$106,D85) -> #REF! | BF85: =IFERROR(BE85/BE85,0) -> 0
D86: Cost of Goods Sold | F86: =SUMIFS(#REF!,#REF!,'RDG Weekly'!B14)+SUMIFS(#REF!,#REF!,'RDG Weekly'!B15)+SUMIFS(#REF!,#REF!,'RDG Weekly'!B16) -> #REF! | G86: =IFERROR(F86/F85,0) -> 0 | I86: =SUMIFS(#REF!,#REF!,'RDG Weekly'!B14)+SUMIFS(#REF!,#REF!,'RDG Weekly'!B15)+SUMIFS(#REF!,#REF!,'RDG Weekly'!B16) -> #REF! | K86: =IFERROR(I86/I85,0) -> 0 | M86: =SUMIFS(#REF!,#REF!,'RDG Weekly'!B14)+SUMIFS(#REF!,#REF!,'RDG Weekly'!B15)+SUMIFS(#REF!,#REF!,'RDG Weekly'!B16) -> #REF! | O86: =IFERROR(M86/M85,0) -> 0 | Q86: =SUMIFS(#REF!,#REF!,'RDG Weekly'!B14)+SUMIFS(#REF!,#REF!,'RDG Weekly'!B15)+SUMIFS(#REF!,#REF!,'RDG Weekly'!B16) -> #REF! | S86: =IFERROR(Q86/Q85,0) -> 0 | X86: =SUMIFS(#REF!,#REF!,'RDG Weekly'!Q14)+SUMIFS(#REF!,#REF!,'RDG Weekly'!Q15)+SUMIFS(#REF!,#REF!,'RDG Weekly'!Q16) -> #REF! | Z86: =IFERROR(X86/X85,0) -> 0 | AB86: =SUMIFS(#REF!,#REF!,'RDG Weekly'!Q14)+SUMIFS(#REF!,#REF!,'RDG Weekly'!Q15)+SUMIFS(#REF!,#REF!,'RDG Weekly'!Q16) -> #REF! | AD86: =IFERROR(AB86/AB85,0) -> 0 | AE86: =SUMIFS(#REF!,#REF!,'RDG Weekly'!Q14)+SUMIFS(#REF!,#REF!,'RDG Weekly'!Q15)+SUMIFS(#REF!,#REF!,'RDG Weekly'!Q16) -> #REF! | AF86: =IFERROR(AE86/AE85,0) -> 0 | AG86: =SUMIFS(#REF!,#REF!,'RDG Weekly'!Q14)+SUMIFS(#REF!,#REF!,'RDG Weekly'!Q15)+SUMIFS(#REF!,#REF!,'RDG Weekly'!Q16) -> #REF! | AH86: =IFERROR(AG86/AG85,0) -> 0 | AK86: =+AK85*#REF! -> #REF! | AL86: =IFERROR(AK86/AK85,0) -> 0 | AM86: =+AM85*#REF! -> #REF! | AN86: =IFERROR(AM86/AM85,0) -> 0 | AO86: =+AO85*#REF! -> #REF! | AP86: =IFERROR(AO86/AO85,0) -> 0 | AQ86: =+AQ85*#REF! -> #REF! | AR86: =IFERROR(AQ86/AQ85,0) -> 0 | AU86: =SUMIFS($F$85:$F$106,$D$85:$D$106,D86) -> #REF! | AV86: =IFERROR(AU86/AU85,0) -> 0 | AW86: =+AK86 -> #REF! | AX86: =IFERROR(AW86/AW85,0) -> 0 | AY86: =SUMIFS($I$85:$I$106,$D$85:$D$106,D86)+SUMIFS($AU$85:$AU$106,$D$85:$D$106,D86) -> #REF! | AZ86: =IFERROR(AY86/AY85,0) -> 0 | BA86: =SUMIFS($AM$85:$AM$106,$D$85:$D$106,D86)+SUMIFS($AW$85:$AW$106,$D$85:$D$106,D86) -> #REF! | BB86: =IFERROR(BA86/BA85,0) -> 0 | BC86: =SUMIFS($M$85:$M$106,$D$85:$D$106,D86)+SUMIFS($AY$85:$AY$106,$D$85:$D$106,D86) -> #REF! | BD86: =IFERROR(BC86/BC85,0) -> 0 | BE86: =SUMIFS($AO$85:$AO$106,$D$85:$D$106,D86)+SUMIFS($BA$85:$BA$106,$D$85:$D$106,D86) -> #REF! | BF86: =IFERROR(BE86/BE85,0) -> 0
D88: Gross Profit | F88: =F85-F86 -> #REF! | G88: =IFERROR(F88/F85,0) -> 0 | I88: =I85-I86 -> #REF! | K88: =IFERROR(I88/I85,0) -> 0 | M88: =M85-M86 -> #REF! | O88: =IFERROR(M88/M85,0) -> 0 | Q88: =Q85-Q86 -> #REF! | S88: =IFERROR(Q88/Q85,0) -> 0 | X88: =X85-X86 -> #REF! | Z88: =IFERROR(X88/X85,0) -> 0 | AB88: =AB85-AB86 -> #REF! | AD88: =IFERROR(AB88/AB85,0) -> 0 | AE88: =AE85-AE86 -> #REF! | AF88: =IFERROR(AE88/AE85,0) -> 0 | AG88: =AG85-AG86 -> #REF! | AH88: =IFERROR(AG88/AG85,0) -> 0 | AK88: =AK85-AK86 -> #REF! | AL88: =IFERROR(AK88/AK85,0) -> 0 | AM88: =AM85-AM86 -> #REF! | AN88: =IFERROR(AM88/AM85,0) -> 0 | AO88: =AO85-AO86 -> #REF! | AP88: =IFERROR(AO88/AO85,0) -> 0 | AQ88: =AQ85-AQ86 -> #REF! | AR88: =IFERROR(AQ88/AQ85,0) -> 0 | AU88: =AU85-AU86 -> #REF! | AV88: =IFERROR(AU88/AU85,0) -> 0 | AW88: =AW85-AW86 -> #REF! | AX88: =IFERROR(AW88/AW85,0) -> 0 | AY88: =AY85-AY86 -> #REF! | AZ88: =IFERROR(AY88/AY85,0) -> 0 | BA88: =BA85-BA86 -> #REF! | BB88: =IFERROR(BA88/BA85,0) -> 0 | BC88: =BC85-BC86 -> #REF! | BD88: =IFERROR(BC88/BC85,0) -> 0 | BE88: =BE85-BE86 -> #REF! | BF88: =IFERROR(BE88/BE85,0) -> 0
D90: Cost of Labor | F90: =+SUMIFS(#REF!,#REF!,'RDG Weekly'!B18)+SUMIFS(#REF!,#REF!,'RDG Weekly'!C18)+SUMIFS(#REF!,#REF!,'RDG Weekly'!C22)+SUMIFS(#REF!,#REF!,'RDG Weekly'!C23) -> #REF! | G90: =IFERROR(F90/F85,0) -> 0 | I90: =+SUMIFS(#REF!,#REF!,'RDG Weekly'!B18)+SUMIFS(#REF!,#REF!,'RDG Weekly'!C18)+SUMIFS(#REF!,#REF!,'RDG Weekly'!C22)+SUMIFS(#REF!,#REF!,'RDG Weekly'!C23) -> #REF! | K90: =IFERROR(I90/I85,0) -> 0 | M90: =+SUMIFS(#REF!,#REF!,'RDG Weekly'!B18)+SUMIFS(#REF!,#REF!,'RDG Weekly'!C18)+SUMIFS(#REF!,#REF!,'RDG Weekly'!C22)+SUMIFS(#REF!,#REF!,'RDG Weekly'!C23) -> #REF! | O90: =IFERROR(M90/M85,0) -> 0 | Q90: =+SUMIFS(#REF!,#REF!,'RDG Weekly'!B18)+SUMIFS(#REF!,#REF!,'RDG Weekly'!C18)+SUMIFS(#REF!,#REF!,'RDG Weekly'!C22)+SUMIFS(#REF!,#REF!,'RDG Weekly'!C23) -> #REF! | S90: =IFERROR(Q90/Q85,0) -> 0 | X90: =+SUMIFS(#REF!,#REF!,'RDG Weekly'!Q18)+SUMIFS(#REF!,#REF!,'RDG Weekly'!S18)+SUMIFS(#REF!,#REF!,'RDG Weekly'!S22)+SUMIFS(#REF!,#REF!,'RDG Weekly'!S23) -> #REF! | Z90: =IFERROR(X90/X85,0) -> 0 | AB90: =+SUMIFS(#REF!,#REF!,'RDG Weekly'!Q18)+SUMIFS(#REF!,#REF!,'RDG Weekly'!S18)+SUMIFS(#REF!,#REF!,'RDG Weekly'!S22)+SUMIFS(#REF!,#REF!,'RDG Weekly'!S23) -> #REF! | AD90: =IFERROR(AB90/AB85,0) -> 0 | AE90: =+SUMIFS(#REF!,#REF!,'RDG Weekly'!Q18)+SUMIFS(#REF!,#REF!,'RDG Weekly'!S18)+SUMIFS(#REF!,#REF!,'RDG Weekly'!S22)+SUMIFS(#REF!,#REF!,'RDG Weekly'!S23) -> #REF! | AF90: =IFERROR(AE90/AE85,0) -> 0 | AG90: =+SUMIFS(#REF!,#REF!,'RDG Weekly'!Q18)+SUMIFS(#REF!,#REF!,'RDG Weekly'!S18)+SUMIFS(#REF!,#REF!,'RDG Weekly'!S22)+SUMIFS(#REF!,#REF!,'RDG Weekly'!S23) -> #REF! | AH90: =IFERROR(AG90/AG85,0) -> 0 | AK90: =+#REF!/#REF! -> #REF! | AL90: =IFERROR(AK90/AK85,0) -> 0 | AM90: =+AK90 -> #REF! | AN90: =IFERROR(AM90/AM85,0) -> 0 | AO90: =+AM90 -> #REF! | AP90: =IFERROR(AO90/AO85,0) -> 0 | AQ90: =+AO90 -> #REF! | AR90: =IFERROR(AQ90/AQ85,0) -> 0 | AU90: =SUMIFS($F$85:$F$106,$D$85:$D$106,D90) -> #REF! | AV90: =IFERROR(AU90/AU85,0) -> 0 | AW90: =+AK90 -> #REF! | AX90: =IFERROR(AW90/AW85,0) -> 0 | AY90: =SUMIFS($I$85:$I$106,$D$85:$D$106,D90)+SUMIFS($AU$85:$AU$106,$D$85:$D$106,D90) -> #REF! | AZ90: =IFERROR(AY90/AY85,0) -> 0 | BA90: =SUMIFS($AM$85:$AM$106,$D$85:$D$106,D90)+SUMIFS($AW$85:$AW$106,$D$85:$D$106,D90) -> #REF! | BB90: =IFERROR(BA90/BA85,0) -> 0 | BC90: =SUMIFS($M$85:$M$106,$D$85:$D$106,D90)+SUMIFS($AY$85:$AY$106,$D$85:$D$106,D90) -> #REF! | BD90: =IFERROR(BC90/BC85,0) -> 0 | BE90: =SUMIFS($AO$85:$AO$106,$D$85:$D$106,D90)+SUMIFS($BA$85:$BA$106,$D$85:$D$106,D90) -> #REF! | BF90: =IFERROR(BE90/BE85,0) -> 0
D91: FOH - Hourly | F91: =+SUMIFS(#REF!,#REF!,'RDG Weekly'!B18)-F92 -> #REF! | G91: =+F91/$F$85 -> #REF! | I91: =+SUMIFS(#REF!,#REF!,'RDG Weekly'!B18)-I92 -> #REF! | K91: =+I91/$I$85 -> #REF! | M91: =+SUMIFS(#REF!,#REF!,'RDG Weekly'!B18)-M92 -> #REF! | O91: =+M91/$M$85 -> #REF! | Q91: =+SUMIFS(#REF!,#REF!,'RDG Weekly'!B18)-Q92 -> #REF! | S91: =IFERROR(+Q91/$Q$85,0) -> 0 | X91: =+SUMIFS(#REF!,#REF!,'RDG Weekly'!Q18)-X92 -> #REF! | Z91: =+X91/$F$85 -> #REF! | AB91: =+SUMIFS(#REF!,#REF!,'RDG Weekly'!Q18)-AB92 -> #REF! | AD91: =+AB91/$I$85 -> #REF! | AE91: =+SUMIFS(#REF!,#REF!,'RDG Weekly'!Q18)-AE92 -> #REF! | AF91: =+AE91/$M$85 -> #REF! | AG91: =+SUMIFS(#REF!,#REF!,'RDG Weekly'!Q18)-AG92 -> #REF! | AH91: =IFERROR(+AG91/$Q$85,0) -> 0 | AK91: =+#REF!/5 -> #REF! | AL91: =+AK91/$AK$85 -> #REF! | AM91: =+AK91 -> #REF! | AN91: =+AM91/$AM$85 -> #REF! | AO91: =+AM91 -> #REF! | AP91: =+AO91/$AO$85 -> #REF! | AQ91: =+AO91 -> #REF! | AR91: =+AQ91/$AQ$85 -> #REF! | AU91: =SUMIFS($F$85:$F$106,$D$85:$D$106,D91) -> #REF! | AV91: =+AU91/$AU$85 -> #REF! | AW91: =+AK91 -> #REF! | AX91: =+AW91/$AW$85 -> #REF! | AY91: =SUMIFS($I$85:$I$106,$D$85:$D$106,D91)+SUMIFS($AU$85:$AU$106,$D$85:$D$106,D91) -> #REF! | AZ91: =+AY91/$AY$85 -> #REF! | BA91: =SUMIFS($AM$85:$AM$106,$D$85:$D$106,D91)+SUMIFS($AW$85:$AW$106,$D$85:$D$106,D91) -> #REF! | BB91: =+BA91/$BA$85 -> #REF! | BC91: =SUMIFS($M$85:$M$106,$D$85:$D$106,D91)+SUMIFS($AY$85:$AY$106,$D$85:$D$106,D91) -> #REF! | BD91: =+BC91/$BC$85 -> #REF! | BE91: =SUMIFS($AO$85:$AO$106,$D$85:$D$106,D91)+SUMIFS($BA$85:$BA$106,$D$85:$D$106,D91) -> #REF! | BF91: =+BE91/$BE$85 -> #REF!
D92: BOH - Hourly | F92: =+SUMIFS(#REF!,#REF!,'RDG Weekly'!B223)+SUMIFS(#REF!,#REF!,'RDG Weekly'!B224)+SUMIFS(#REF!,#REF!,'RDG Weekly'!B225)+SUMIFS(#REF!,#REF!,'RDG Weekly'!B226)+SUMIFS(#REF!,#REF!,'RDG Weekly'!B227)+SUMIFS(#REF!,#REF!,'RDG Weekly'!B228)+SUMIFS(#REF!,#REF!,'RDG Weekly'!B229)+SUMIFS(#REF!,#REF!,'RDG Weekly'!B230) -> #REF! | G92: =+F92/$F$85 -> #REF! | I92: =+SUMIFS(#REF!,#REF!,'RDG Weekly'!B223)+SUMIFS(#REF!,#REF!,'RDG Weekly'!B224)+SUMIFS(#REF!,#REF!,'RDG Weekly'!B225)+SUMIFS(#REF!,#REF!,'RDG Weekly'!B226)+SUMIFS(#REF!,#REF!,'RDG Weekly'!B227)+SUMIFS(#REF!,#REF!,'RDG Weekly'!B228)+SUMIFS(#REF!,#REF!,'RDG Weekly'!B229)+SUMIFS(#REF!,#REF!,'RDG Weekly'!B230) -> #REF! | K92: =+I92/$I$85 -> #REF! | M92: =+SUMIFS(#REF!,#REF!,'RDG Weekly'!B223)+SUMIFS(#REF!,#REF!,'RDG Weekly'!B224)+SUMIFS(#REF!,#REF!,'RDG Weekly'!B225)+SUMIFS(#REF!,#REF!,'RDG Weekly'!B226)+SUMIFS(#REF!,#REF!,'RDG Weekly'!B227)+SUMIFS(#REF!,#REF!,'RDG Weekly'!B228)+SUMIFS(#REF!,#REF!,'RDG Weekly'!B229)+SUMIFS(#REF!,#REF!,'RDG Weekly'!B230) -> #REF! | O92: =+M92/$M$85 -> #REF! | Q92: =+SUMIFS(#REF!,#REF!,'RDG Weekly'!B223)+SUMIFS(#REF!,#REF!,'RDG Weekly'!B224)+SUMIFS(#REF!,#REF!,'RDG Weekly'!B225)+SUMIFS(#REF!,#REF!,'RDG Weekly'!B226)+SUMIFS(#REF!,#REF!,'RDG Weekly'!B227)+SUMIFS(#REF!,#REF!,'RDG Weekly'!B228)+SUMIFS(#REF!,#REF!,'RDG Weekly'!B229)+SUMIFS(#REF!,#REF!,'RDG Weekly'!B230) -> #REF! | S92: =IFERROR(+Q92/$Q$85,0) -> 0 | X92: =+SUMIFS(#REF!,#REF!,'RDG Weekly'!Q48)+SUMIFS(#REF!,#REF!,'RDG Weekly'!Q49)+SUMIFS(#REF!,#REF!,'RDG Weekly'!Q50)+SUMIFS(#REF!,#REF!,'RDG Weekly'!Q51)+SUMIFS(#REF!,#REF!,'RDG Weekly'!Q52)+SUMIFS(#REF!,#REF!,'RDG Weekly'!Q53)+SUMIFS(#REF!,#REF!,'RDG Weekly'!Q54)+SUMIFS(#REF!,#REF!,'RDG Weekly'!Q55) -> #REF! | Z92: =+X92/$F$85 -> #REF! | AB92: =+SUMIFS(#REF!,#REF!,'RDG Weekly'!Q48)+SUMIFS(#REF!,#REF!,'RDG Weekly'!Q49)+SUMIFS(#REF!,#REF!,'RDG Weekly'!Q50)+SUMIFS(#REF!,#REF!,'RDG Weekly'!Q51)+SUMIFS(#REF!,#REF!,'RDG Weekly'!Q52)+SUMIFS(#REF!,#REF!,'RDG Weekly'!Q53)+SUMIFS(#REF!,#REF!,'RDG Weekly'!Q54)+SUMIFS(#REF!,#REF!,'RDG Weekly'!Q55) -> #REF! | AD92: =+AB92/$I$85 -> #REF! | AE92: =+SUMIFS(#REF!,#REF!,'RDG Weekly'!Q48)+SUMIFS(#REF!,#REF!,'RDG Weekly'!Q49)+SUMIFS(#REF!,#REF!,'RDG Weekly'!Q50)+SUMIFS(#REF!,#REF!,'RDG Weekly'!Q51)+SUMIFS(#REF!,#REF!,'RDG Weekly'!Q52)+SUMIFS(#REF!,#REF!,'RDG Weekly'!Q53)+SUMIFS(#REF!,#REF!,'RDG Weekly'!Q54)+SUMIFS(#REF!,#REF!,'RDG Weekly'!Q55) -> #REF! | AF92: =+AE92/$M$85 -> #REF! | AG92: =+SUMIFS(#REF!,#REF!,'RDG Weekly'!Q48)+SUMIFS(#REF!,#REF!,'RDG Weekly'!Q49)+SUMIFS(#REF!,#REF!,'RDG Weekly'!Q50)+SUMIFS(#REF!,#REF!,'RDG Weekly'!Q51)+SUMIFS(#REF!,#REF!,'RDG Weekly'!Q52)+SUMIFS(#REF!,#REF!,'RDG Weekly'!Q53)+SUMIFS(#REF!,#REF!,'RDG Weekly'!Q54)+SUMIFS(#REF!,#REF!,'RDG Weekly'!Q55) -> #REF! | AH92: =IFERROR(+AG92/$Q$85,0) -> 0 | AK92: =+#REF!/5 -> #REF! | AL92: =+AK92/$AK$85 -> #REF! | AM92: =+AK92 -> #REF! | AN92: =+AM92/$AM$85 -> #REF! | AO92: =+AM92 -> #REF! | AP92: =+AO92/$AO$85 -> #REF! | AQ92: =+AO92 -> #REF! | AR92: =+AQ92/$AQ$85 -> #REF! | AU92: =SUMIFS($F$85:$F$106,$D$85:$D$106,D92) -> #REF! | AV92: =+AU92/$AU$85 -> #REF! | AW92: =+AK92 -> #REF! | AX92: =+AW92/$AW$85 -> #REF! | AY92: =SUMIFS($I$85:$I$106,$D$85:$D$106,D92)+SUMIFS($AU$85:$AU$106,$D$85:$D$106,D92) -> #REF! | AZ92: =+AY92/$AY$85 -> #REF! | BA92: =SUMIFS($AM$85:$AM$106,$D$85:$D$106,D92)+SUMIFS($AW$85:$AW$106,$D$85:$D$106,D92) -> #REF! | BB92: =+BA92/$BA$85 -> #REF! | BC92: =SUMIFS($M$85:$M$106,$D$85:$D$106,D92)+SUMIFS($AY$85:$AY$106,$D$85:$D$106,D92) -> #REF! | BD92: =+BC92/$BC$85 -> #REF! | BE92: =SUMIFS($AO$85:$AO$106,$D$85:$D$106,D92)+SUMIFS($BA$85:$BA$106,$D$85:$D$106,D92) -> #REF! | BF92: =+BE92/$BE$85 -> #REF!
D93: Management | F93: =+SUMIFS(#REF!,#REF!,'RDG Weekly'!C18) -> #REF! | G93: =+F93/$F$85 -> #REF! | I93: =+SUMIFS(#REF!,#REF!,'RDG Weekly'!C18) -> #REF! | K93: =+I93/$I$85 -> #REF! | M93: =+SUMIFS(#REF!,#REF!,'RDG Weekly'!C18) -> #REF! | O93: =+M93/$M$85 -> #REF! | Q93: =+SUMIFS(#REF!,#REF!,'RDG Weekly'!C18) -> #REF! | S93: =IFERROR(+Q93/$Q$85,0) -> 0 | X93: =+SUMIFS(#REF!,#REF!,'RDG Weekly'!S18) -> #REF! | Z93: =+X93/$F$85 -> #REF! | AB93: =+SUMIFS(#REF!,#REF!,'RDG Weekly'!S18) -> #REF! | AD93: =+AB93/$I$85 -> #REF! | AE93: =+SUMIFS(#REF!,#REF!,'RDG Weekly'!S18) -> #REF! | AF93: =+AE93/$M$85 -> #REF! | AG93: =+SUMIFS(#REF!,#REF!,'RDG Weekly'!S18) -> #REF! | AH93: =IFERROR(+AG93/$Q$85,0) -> 0 | AK93: =+#REF!/5 -> #REF! | AL93: =+AK93/$AK$85 -> #REF! | AM93: =+AK93 -> #REF! | AN93: =+AM93/$AM$85 -> #REF! | AO93: =+AM93 -> #REF! | AP93: =+AO93/$AO$85 -> #REF! | AQ93: =+AO93 -> #REF! | AR93: =+AQ93/$AQ$85 -> #REF! | AU93: =SUMIFS($F$85:$F$106,$D$85:$D$106,D93) -> #REF! | AV93: =+AU93/$AU$85 -> #REF! | AW93: =+AK93 -> #REF! | AX93: =+AW93/$AW$85 -> #REF! | AY93: =SUMIFS($I$85:$I$106,$D$85:$D$106,D93)+SUMIFS($AU$85:$AU$106,$D$85:$D$106,D93) -> #REF! | AZ93: =+AY93/$AY$85 -> #REF! | BA93: =SUMIFS($AM$85:$AM$106,$D$85:$D$106,D93)+SUMIFS($AW$85:$AW$106,$D$85:$D$106,D93) -> #REF! | BB93: =+BA93/$BA$85 -> #REF! | BC93: =SUMIFS($M$85:$M$106,$D$85:$D$106,D93)+SUMIFS($AY$85:$AY$106,$D$85:$D$106,D93) -> #REF! | BD93: =+BC93/$BC$85 -> #REF! | BE93: =SUMIFS($AO$85:$AO$106,$D$85:$D$106,D93)+SUMIFS($BA$85:$BA$106,$D$85:$D$106,D93) -> #REF! | BF93: =+BE93/$BE$85 -> #REF!
D94: Occupancy | F94: =+SUMIFS(#REF!,#REF!,'RDG Weekly'!B22) -> #REF! | G94: =IFERROR(F94/F85,0) -> 0 | I94: =+SUMIFS(#REF!,#REF!,'RDG Weekly'!B22) -> #REF! | K94: =IFERROR(I94/I85,0) -> 0 | M94: =+SUMIFS(#REF!,#REF!,'RDG Weekly'!B22) -> #REF! | O94: =IFERROR(M94/M85,0) -> 0 | Q94: =+SUMIFS(#REF!,#REF!,'RDG Weekly'!B22) -> #REF! | S94: =IFERROR(Q94/Q85,0) -> 0 | X94: =+SUMIFS(#REF!,#REF!,'RDG Weekly'!Q22) -> #REF! | Z94: =IFERROR(X94/X85,0) -> 0 | AB94: =+SUMIFS(#REF!,#REF!,'RDG Weekly'!Q22) -> #REF! | AD94: =IFERROR(AB94/AB85,0) -> 0 | AE94: =+SUMIFS(#REF!,#REF!,'RDG Weekly'!Q22) -> #REF! | AF94: =IFERROR(AE94/AE85,0) -> 0 | AG94: =+SUMIFS(#REF!,#REF!,'RDG Weekly'!Q22) -> #REF! | AH94: =IFERROR(AG94/AG85,0) -> 0 | AK94: =+#REF!/#REF! -> #REF! | AL94: =IFERROR(AK94/AK85,0) -> 0 | AM94: =+AK94 -> #REF! | AN94: =IFERROR(AM94/AM85,0) -> 0 | AO94: =+AM94 -> #REF! | AP94: =IFERROR(AO94/AO85,0) -> 0 | AQ94: =+AO94 -> #REF! | AR94: =IFERROR(AQ94/AQ85,0) -> 0 | AU94: =SUMIFS($F$85:$F$106,$D$85:$D$106,D94) -> #REF! | AV94: =IFERROR(AU94/AU85,0) -> 0 | AW94: =+AK94 -> #REF! | AX94: =IFERROR(AW94/AW85,0) -> 0 | AY94: =SUMIFS($I$85:$I$106,$D$85:$D$106,D94)+SUMIFS($AU$85:$AU$106,$D$85:$D$106,D94) -> #REF! | AZ94: =IFERROR(AY94/AY85,0) -> 0 | BA94: =SUMIFS($AM$85:$AM$106,$D$85:$D$106,D94)+SUMIFS($AW$85:$AW$106,$D$85:$D$106,D94) -> #REF! | BB94: =IFERROR(BA94/BA85,0) -> 0 | BC94: =SUMIFS($M$85:$M$106,$D$85:$D$106,D94)+SUMIFS($AY$85:$AY$106,$D$85:$D$106,D94) -> #REF! | BD94: =IFERROR(BC94/BC85,0) -> 0 | BE94: =SUMIFS($AO$85:$AO$106,$D$85:$D$106,D94)+SUMIFS($BA$85:$BA$106,$D$85:$D$106,D94) -> #REF! | BF94: =IFERROR(BE94/BE85,0) -> 0
D95: Operating Expenses | F95: =+SUMIFS(#REF!,#REF!,'RDG Weekly'!B23) -> #REF! | G95: =IFERROR(F95/F85,0) -> 0 | I95: =+SUMIFS(#REF!,#REF!,'RDG Weekly'!B23) -> #REF! | K95: =IFERROR(I95/I85,0) -> 0 | M95: =+SUMIFS(#REF!,#REF!,'RDG Weekly'!B23) -> #REF! | O95: =IFERROR(M95/M85,0) -> 0 | Q95: =+SUMIFS(#REF!,#REF!,'RDG Weekly'!B23) -> #REF! | S95: =IFERROR(Q95/Q85,0) -> 0 | X95: =+SUMIFS(#REF!,#REF!,'RDG Weekly'!Q23) -> #REF! | Z95: =IFERROR(X95/X85,0) -> 0 | AB95: =+SUMIFS(#REF!,#REF!,'RDG Weekly'!Q23) -> #REF! | AD95: =IFERROR(AB95/AB85,0) -> 0 | AE95: =+SUMIFS(#REF!,#REF!,'RDG Weekly'!Q23) -> #REF! | AF95: =IFERROR(AE95/AE85,0) -> 0 | AG95: =+SUMIFS(#REF!,#REF!,'RDG Weekly'!Q23) -> #REF! | AH95: =IFERROR(AG95/AG85,0) -> 0 | AK95: =+#REF!/#REF! -> #REF! | AL95: =IFERROR(AK95/AK85,0) -> 0 | AM95: =+AK95 -> #REF! | AN95: =IFERROR(AM95/AM85,0) -> 0 | AO95: =+AM95 -> #REF! | AP95: =IFERROR(AO95/AO85,0) -> 0 | AQ95: =+AO95 -> #REF! | AR95: =IFERROR(AQ95/AQ85,0) -> 0 | AU95: =SUMIFS($F$85:$F$106,$D$85:$D$106,D95) -> #REF! | AV95: =IFERROR(AU95/AU85,0) -> 0 | AW95: =+AK95 -> #REF! | AX95: =IFERROR(AW95/AW85,0) -> 0 | AY95: =SUMIFS($I$85:$I$106,$D$85:$D$106,D95)+SUMIFS($AU$85:$AU$106,$D$85:$D$106,D95) -> #REF! | AZ95: =IFERROR(AY95/AY85,0) -> 0 | BA95: =SUMIFS($AM$85:$AM$106,$D$85:$D$106,D95)+SUMIFS($AW$85:$AW$106,$D$85:$D$106,D95) -> #REF! | BB95: =IFERROR(BA95/BA85,0) -> 0 | BC95: =SUMIFS($M$85:$M$106,$D$85:$D$106,D95)+SUMIFS($AY$85:$AY$106,$D$85:$D$106,D95) -> #REF! | BD95: =IFERROR(BC95/BC85,0) -> 0 | BE95: =SUMIFS($AO$85:$AO$106,$D$85:$D$106,D95)+SUMIFS($BA$85:$BA$106,$D$85:$D$106,D95) -> #REF! | BF95: =IFERROR(BE95/BE85,0) -> 0
D96: General & Administrative | F96: =+SUMIFS(#REF!,#REF!,'RDG Weekly'!B24) -> #REF! | G96: =IFERROR(F96/F85,0) -> 0 | I96: =+SUMIFS(#REF!,#REF!,'RDG Weekly'!B24) -> #REF! | K96: =IFERROR(I96/I85,0) -> 0 | M96: =+SUMIFS(#REF!,#REF!,'RDG Weekly'!B24) -> #REF! | O96: =IFERROR(M96/M85,0) -> 0 | Q96: =+SUMIFS(#REF!,#REF!,'RDG Weekly'!B24) -> #REF! | S96: =IFERROR(Q96/Q85,0) -> 0 | X96: =+SUMIFS(#REF!,#REF!,'RDG Weekly'!Q24) -> #REF! | Z96: =IFERROR(X96/X85,0) -> 0 | AB96: =+SUMIFS(#REF!,#REF!,'RDG Weekly'!Q24) -> #REF! | AD96: =IFERROR(AB96/AB85,0) -> 0 | AE96: =+SUMIFS(#REF!,#REF!,'RDG Weekly'!Q24) -> #REF! | AF96: =IFERROR(AE96/AE85,0) -> 0 | AG96: =+SUMIFS(#REF!,#REF!,'RDG Weekly'!Q24) -> #REF! | AH96: =IFERROR(AG96/AG85,0) -> 0 | AK96: =+#REF!/#REF! -> #REF! | AL96: =IFERROR(AK96/AK85,0) -> 0 | AM96: =+AK96 -> #REF! | AN96: =IFERROR(AM96/AM85,0) -> 0 | AO96: =+AM96 -> #REF! | AP96: =IFERROR(AO96/AO85,0) -> 0 | AQ96: =+AO96 -> #REF! | AR96: =IFERROR(AQ96/AQ85,0) -> 0 | AU96: =SUMIFS($F$85:$F$106,$D$85:$D$106,D96) -> #REF! | AV96: =IFERROR(AU96/AU85,0) -> 0 | AW96: =+AK96 -> #REF! | AX96: =IFERROR(AW96/AW85,0) -> 0 | AY96: =SUMIFS($I$85:$I$106,$D$85:$D$106,D96)+SUMIFS($AU$85:$AU$106,$D$85:$D$106,D96) -> #REF! | AZ96: =IFERROR(AY96/AY85,0) -> 0 | BA96: =SUMIFS($AM$85:$AM$106,$D$85:$D$106,D96)+SUMIFS($AW$85:$AW$106,$D$85:$D$106,D96) -> #REF! | BB96: =IFERROR(BA96/BA85,0) -> 0 | BC96: =SUMIFS($M$85:$M$106,$D$85:$D$106,D96)+SUMIFS($AY$85:$AY$106,$D$85:$D$106,D96) -> #REF! | BD96: =IFERROR(BC96/BC85,0) -> 0 | BE96: =SUMIFS($AO$85:$AO$106,$D$85:$D$106,D96)+SUMIFS($BA$85:$BA$106,$D$85:$D$106,D96) -> #REF! | BF96: =IFERROR(BE96/BE85,0) -> 0
D97: Utilities | F97: =+SUMIFS(#REF!,#REF!,'RDG Weekly'!B25) -> #REF! | G97: =IFERROR(F97/F85,0) -> 0 | I97: =+SUMIFS(#REF!,#REF!,'RDG Weekly'!B25) -> #REF! | K97: =IFERROR(I97/I85,0) -> 0 | M97: =+SUMIFS(#REF!,#REF!,'RDG Weekly'!B25) -> #REF! | O97: =IFERROR(M97/M85,0) -> 0 | Q97: =+SUMIFS(#REF!,#REF!,'RDG Weekly'!B25) -> #REF! | S97: =IFERROR(Q97/Q85,0) -> 0 | X97: =+SUMIFS(#REF!,#REF!,'RDG Weekly'!Q25) -> #REF! | Z97: =IFERROR(X97/X85,0) -> 0 | AB97: =+SUMIFS(#REF!,#REF!,'RDG Weekly'!Q25) -> #REF! | AD97: =IFERROR(AB97/AB85,0) -> 0 | AE97: =+SUMIFS(#REF!,#REF!,'RDG Weekly'!Q25) -> #REF! | AF97: =IFERROR(AE97/AE85,0) -> 0 | AG97: =+SUMIFS(#REF!,#REF!,'RDG Weekly'!Q25) -> #REF! | AH97: =IFERROR(AG97/AG85,0) -> 0 | AK97: =+#REF!/#REF! -> #REF! | AL97: =IFERROR(AK97/AK85,0) -> 0 | AM97: =+AK97 -> #REF! | AN97: =IFERROR(AM97/AM85,0) -> 0 | AO97: =+AM97 -> #REF! | AP97: =IFERROR(AO97/AO85,0) -> 0 | AQ97: =+AO97 -> #REF! | AR97: =IFERROR(AQ97/AQ85,0) -> 0 | AU97: =SUMIFS($F$85:$F$106,$D$85:$D$106,D97) -> #REF! | AV97: =IFERROR(AU97/AU85,0) -> 0 | AW97: =+AK97 -> #REF! | AX97: =IFERROR(AW97/AW85,0) -> 0 | AY97: =SUMIFS($I$85:$I$106,$D$85:$D$106,D97)+SUMIFS($AU$85:$AU$106,$D$85:$D$106,D97) -> #REF! | AZ97: =IFERROR(AY97/AY85,0) -> 0 | BA97: =SUMIFS($AM$85:$AM$106,$D$85:$D$106,D97)+SUMIFS($AW$85:$AW$106,$D$85:$D$106,D97) -> #REF! | BB97: =IFERROR(BA97/BA85,0) -> 0 | BC97: =SUMIFS($M$85:$M$106,$D$85:$D$106,D97)+SUMIFS($AY$85:$AY$106,$D$85:$D$106,D97) -> #REF! | BD97: =IFERROR(BC97/BC85,0) -> 0 | BE97: =SUMIFS($AO$85:$AO$106,$D$85:$D$106,D97)+SUMIFS($BA$85:$BA$106,$D$85:$D$106,D97) -> #REF! | BF97: =IFERROR(BE97/BE85,0) -> 0
D98: Other Income | F98: =+SUMIFS(#REF!,#REF!,'RDG Weekly'!B26) -> #REF! | G98: =IFERROR(F98/F85,0) -> 0 | I98: =+SUMIFS(#REF!,#REF!,'RDG Weekly'!B26) -> #REF! | K98: =IFERROR(I98/I85,0) -> 0 | M98: =+SUMIFS(#REF!,#REF!,'RDG Weekly'!B26) -> #REF! | O98: =IFERROR(M98/M85,0) -> 0 | Q98: =+SUMIFS(#REF!,#REF!,'RDG Weekly'!B26) -> #REF! | S98: =IFERROR(Q98/Q85,0) -> 0 | X98: =+SUMIFS(#REF!,#REF!,'RDG Weekly'!Q26) -> #REF! | Z98: =IFERROR(X98/X85,0) -> 0 | AB98: =+SUMIFS(#REF!,#REF!,'RDG Weekly'!Q26) -> #REF! | AD98: =IFERROR(AB98/AB85,0) -> 0 | AE98: =+SUMIFS(#REF!,#REF!,'RDG Weekly'!Q26) -> #REF! | AF98: =IFERROR(AE98/AE85,0) -> 0 | AG98: =+SUMIFS(#REF!,#REF!,'RDG Weekly'!Q26) -> #REF! | AH98: =IFERROR(AG98/AG85,0) -> 0 | AK98: =+#REF!/#REF! -> #REF! | AL98: =IFERROR(AK98/AK85,0) -> 0 | AM98: =+AK98 -> #REF! | AN98: =IFERROR(AM98/AM85,0) -> 0 | AO98: =+AM98 -> #REF! | AP98: =IFERROR(AO98/AO85,0) -> 0 | AQ98: =+AO98 -> #REF! | AR98: =IFERROR(AQ98/AQ85,0) -> 0 | AU98: =SUMIFS($F$85:$F$106,$D$85:$D$106,D98) -> #REF! | AV98: =IFERROR(AU98/AU85,0) -> 0 | AW98: =+AK98 -> #REF! | AX98: =IFERROR(AW98/AW85,0) -> 0 | AY98: =SUMIFS($I$85:$I$106,$D$85:$D$106,D98)+SUMIFS($AU$85:$AU$106,$D$85:$D$106,D98) -> #REF! | AZ98: =IFERROR(AY98/AY85,0) -> 0 | BA98: =SUMIFS($AM$85:$AM$106,$D$85:$D$106,D98)+SUMIFS($AW$85:$AW$106,$D$85:$D$106,D98) -> #REF! | BB98: =IFERROR(BA98/BA85,0) -> 0 | BC98: =SUMIFS($M$85:$M$106,$D$85:$D$106,D98)+SUMIFS($AY$85:$AY$106,$D$85:$D$106,D98) -> #REF! | BD98: =IFERROR(BC98/BC85,0) -> 0 | BE98: =SUMIFS($AO$85:$AO$106,$D$85:$D$106,D98)+SUMIFS($BA$85:$BA$106,$D$85:$D$106,D98) -> #REF! | BF98: =IFERROR(BE98/BE85,0) -> 0
D100: Total Operating Expenses | F100: =SUM(F94:F98,F90) -> #REF! | G100: =IFERROR(F100/F85,0) -> 0 | I100: =SUM(I94:I98,I90) -> #REF! | K100: =IFERROR(I100/I85,0) -> 0 | M100: =SUM(M94:M98,M90) -> #REF! | O100: =IFERROR(M100/M85,0) -> 0 | Q100: =SUM(Q94:Q98,Q90) -> #REF! | S100: =IFERROR(Q100/Q85,0) -> 0 | X100: =SUM(X94:X98,X90) -> #REF! | Z100: =IFERROR(X100/X85,0) -> 0 | AB100: =SUM(AB94:AB98,AB90) -> #REF! | AD100: =IFERROR(AB100/AB85,0) -> 0 | AE100: =SUM(AE94:AE98,AE90) -> #REF! | AF100: =IFERROR(AE100/AE85,0) -> 0 | AG100: =SUM(AG94:AG98,AG90) -> #REF! | AH100: =IFERROR(AG100/AG85,0) -> 0 | AK100: =SUM(AK94:AK98,AK90) -> #REF! | AL100: =IFERROR(AK100/AK85,0) -> 0 | AM100: =SUM(AM94:AM98,AM90) -> #REF! | AN100: =IFERROR(AM100/AM85,0) -> 0 | AO100: =SUM(AO94:AO98,AO90) -> #REF! | AP100: =IFERROR(AO100/AO85,0) -> 0 | AQ100: =SUM(AQ94:AQ98,AQ90) -> #REF! | AR100: =IFERROR(AQ100/AQ85,0) -> 0 | AU100: =SUM(AU94:AU98,AU90) -> #REF! | AV100: =IFERROR(AU100/AU85,0) -> 0 | AW100: =SUM(AW94:AW98,AW90) -> #REF! | AX100: =IFERROR(AW100/AW85,0) -> 0 | AY100: =SUM(AY94:AY98,AY90) -> #REF! | AZ100: =IFERROR(AY100/AY85,0) -> 0 | BA100: =SUM(BA94:BA98,BA90) -> #REF! | BB100: =IFERROR(BA100/BA85,0) -> 0 | BC100: =SUM(BC94:BC98,BC90) -> #REF! | BD100: =IFERROR(BC100/BC85,0) -> 0 | BE100: =SUM(BE94:BE98,BE90) -> #REF! | BF100: =IFERROR(BE100/BE85,0) -> 0
D102: Net Operating Income | F102: =F88-F100 -> #REF! | G102: =IFERROR(F102/F85,0) -> 0 | I102: =I88-I100 -> #REF! | K102: =IFERROR(I102/I85,0) -> 0 | M102: =M88-M100 -> #REF! | O102: =IFERROR(M102/M85,0) -> 0 | Q102: =Q88-Q100 -> #REF! | S102: =IFERROR(Q102/Q85,0) -> 0 | X102: =X88-X100 -> #REF! | Z102: =IFERROR(X102/X85,0) -> 0 | AB102: =AB88-AB100 -> #REF! | AD102: =IFERROR(AB102/AB85,0) -> 0 | AE102: =AE88-AE100 -> #REF! | AF102: =IFERROR(AE102/AE85,0) -> 0 | AG102: =AG88-AG100 -> #REF! | AH102: =IFERROR(AG102/AG85,0) -> 0 | AK102: =AK88-AK100 -> #REF! | AL102: =IFERROR(AK102/AK85,0) -> 0 | AM102: =AM88-AM100 -> #REF! | AN102: =IFERROR(AM102/AM85,0) -> 0 | AO102: =AO88-AO100 -> #REF! | AP102: =IFERROR(AO102/AO85,0) -> 0 | AQ102: =AQ88-AQ100 -> #REF! | AR102: =IFERROR(AQ102/AQ85,0) -> 0 | AU102: =AU88-AU100 -> #REF! | AV102: =IFERROR(AU102/AU85,0) -> 0 | AW102: =AW88-AW100 -> #REF! | AX102: =IFERROR(AW102/AW85,0) -> 0 | AY102: =AY88-AY100 -> #REF! | AZ102: =IFERROR(AY102/AY85,0) -> 0 | BA102: =BA88-BA100 -> #REF! | BB102: =IFERROR(BA102/BA85,0) -> 0 | BC102: =BC88-BC100 -> #REF! | BD102: =IFERROR(BC102/BC85,0) -> 0 | BE102: =BE88-BE100 -> #REF! | BF102: =IFERROR(BE102/BE85,0) -> 0
D104: Other G&A | F104: =+SUMIFS(#REF!,#REF!,'RDG Weekly'!B32)-SUMIFS(#REF!,#REF!,'RDG Weekly'!B33) -> #REF! | G104: =IFERROR(F104/F85,0) -> 0 | I104: =+SUMIFS(#REF!,#REF!,'RDG Weekly'!B32) -> #REF! | K104: =IFERROR(I104/I85,0) -> 0 | M104: =+SUMIFS(#REF!,#REF!,'RDG Weekly'!B32) -> #REF! | O104: =IFERROR(M104/M85,0) -> 0 | Q104: =+SUMIFS(#REF!,#REF!,'RDG Weekly'!B32) -> #REF! | S104: =IFERROR(Q104/Q85,0) -> 0 | X104: =+SUMIFS(#REF!,#REF!,'RDG Weekly'!Q32)-SUMIFS(#REF!,#REF!,'RDG Weekly'!Q33) -> #REF! | Z104: =IFERROR(X104/X85,0) -> 0 | AB104: =+SUMIFS(#REF!,#REF!,'RDG Weekly'!Q32) -> #REF! | AD104: =IFERROR(AB104/AB85,0) -> 0 | AE104: =+SUMIFS(#REF!,#REF!,'RDG Weekly'!Q32) -> #REF! | AF104: =IFERROR(AE104/AE85,0) -> 0 | AG104: =+SUMIFS(#REF!,#REF!,'RDG Weekly'!Q32) -> #REF! | AH104: =IFERROR(AG104/AG85,0) -> 0 | AK104: =+#REF!/#REF! -> #REF! | AL104: =IFERROR(AK104/AK85,0) -> 0 | AM104: =+AK104 -> #REF! | AN104: =IFERROR(AM104/AM85,0) -> 0 | AO104: =+AM104 -> #REF! | AP104: =IFERROR(AO104/AO85,0) -> 0 | AQ104: =+AO104 -> #REF! | AR104: =IFERROR(AQ104/AQ85,0) -> 0 | AU104: =SUMIFS($F$85:$F$106,$D$85:$D$106,D104) -> #REF! | AV104: =IFERROR(AU104/AU85,0) -> 0 | AW104: =+AK104 -> #REF! | AX104: =IFERROR(AW104/AW85,0) -> 0 | AY104: =SUMIFS($I$85:$I$106,$D$85:$D$106,D104)+SUMIFS($AU$85:$AU$106,$D$85:$D$106,D104) -> #REF! | AZ104: =IFERROR(AY104/AY85,0) -> 0 | BA104: =SUMIFS($AM$85:$AM$106,$D$85:$D$106,D104)+SUMIFS($AW$85:$AW$106,$D$85:$D$106,D104) -> #REF! | BB104: =IFERROR(BA104/BA85,0) -> 0 | BC104: =SUMIFS($M$85:$M$106,$D$85:$D$106,D104)+SUMIFS($AY$85:$AY$106,$D$85:$D$106,D104) -> #REF! | BD104: =IFERROR(BC104/BC85,0) -> 0 | BE104: =SUMIFS($AO$85:$AO$106,$D$85:$D$106,D104)+SUMIFS($BA$85:$BA$106,$D$85:$D$106,D104) -> #REF! | BF104: =IFERROR(BE104/BE85,0) -> 0
D106: EBITDA | F106: =F102-F104 -> #REF! | G106: =IFERROR(F106/F85,0) -> 0 | I106: =I102-I104 -> #REF! | K106: =IFERROR(I106/I85,0) -> 0 | M106: =M102-M104 -> #REF! | O106: =IFERROR(M106/M85,0) -> 0 | Q106: =Q102-Q104 -> #REF! | S106: =IFERROR(Q106/Q85,0) -> 0 | X106: =X102-X104 -> #REF! | Z106: =IFERROR(X106/X85,0) -> 0 | AB106: =AB102-AB104 -> #REF! | AD106: =IFERROR(AB106/AB85,0) -> 0 | AE106: =AE102-AE104 -> #REF! | AF106: =IFERROR(AE106/AE85,0) -> 0 | AG106: =AG102-AG104 -> #REF! | AH106: =IFERROR(AG106/AG85,0) -> 0 | AK106: =AK102-AK104 -> #REF! | AL106: =IFERROR(AK106/AK85,0) -> 0 | AM106: =AM102-AM104 -> #REF! | AN106: =IFERROR(AM106/AM85,0) -> 0 | AO106: =AO102-AO104 -> #REF! | AP106: =IFERROR(AO106/AO85,0) -> 0 | AQ106: =AQ102-AQ104 -> #REF! | AR106: =IFERROR(AQ106/AQ85,0) -> 0 | AU106: =AU102-AU104 -> #REF! | AV106: =IFERROR(AU106/AU85,0) -> 0 | AW106: =AW102-AW104 -> #REF! | AX106: =IFERROR(AW106/AW85,0) -> 0 | AY106: =AY102-AY104 -> #REF! | AZ106: =IFERROR(AY106/AY85,0) -> 0 | BA106: =BA102-BA104 -> #REF! | BB106: =IFERROR(BA106/BA85,0) -> 0 | BC106: =BC102-BC104 -> #REF! | BD106: =IFERROR(BC106/BC85,0) -> 0 | BE106: =BE102-BE104 -> #REF! | BF106: =IFERROR(BE106/BE85,0) -> 0
D108: Key Performing Indicators | F108: =+F83 -> MILA 3F | I108: =+I83 -> MILA 2F | M108: =+M83 -> AVA | Q108: =+Q83 -> CASA NEOS | X108: =+X83 -> MILA | AB108: =+AB83 -> MILA MM | AE108: =+AE83 -> AVA | AG108: =+AG83 -> BAOLI
D110: Food Cost % | F110: =+SUMIFS(#REF!,#REF!,'RDG Weekly'!$B$213)/+SUMIFS(#REF!,#REF!,'RDG Weekly'!$B$212) -> #REF! | I110: =+SUMIFS(#REF!,#REF!,#REF!)/+SUMIFS(#REF!,#REF!,#REF!) -> #REF! | M110: =+SUMIFS(#REF!,#REF!,#REF!)/+SUMIFS(#REF!,#REF!,#REF!) -> #REF! | Q110: =+SUMIFS(#REF!,#REF!,#REF!)/+SUMIFS(#REF!,#REF!,#REF!) -> #REF! | X110: =+SUMIFS(#REF!,#REF!,'RDG Weekly'!$B$213)/+SUMIFS(#REF!,#REF!,'RDG Weekly'!$B$212) -> #REF! | AB110: =+SUMIFS(#REF!,#REF!,#REF!)/+SUMIFS(#REF!,#REF!,#REF!) -> #REF! | AE110: =+SUMIFS(#REF!,#REF!,#REF!)/+SUMIFS(#REF!,#REF!,#REF!) -> #REF! | AG110: =+SUMIFS(#REF!,#REF!,#REF!)/+SUMIFS(#REF!,#REF!,#REF!) -> #REF!
D111: Liqour % | F111: =+(SUMIFS(#REF!,#REF!,'RDG Weekly'!$C$215)+SUMIFS(#REF!,#REF!,'RDG Weekly'!$C$218))/+SUMIFS(#REF!,#REF!,'RDG Weekly'!$C$214) -> #REF! | I111: =+(SUMIFS(#REF!,#REF!,#REF!)+SUMIFS(#REF!,#REF!,#REF!))/+SUMIFS(#REF!,#REF!,#REF!) -> #REF! | M111: =+(SUMIFS(#REF!,#REF!,#REF!)+SUMIFS(#REF!,#REF!,#REF!))/+SUMIFS(#REF!,#REF!,#REF!) -> #REF! | Q111: =+(SUMIFS(#REF!,#REF!,#REF!)+SUMIFS(#REF!,#REF!,#REF!))/+SUMIFS(#REF!,#REF!,#REF!) -> #REF! | X111: =+(SUMIFS(#REF!,#REF!,'RDG Weekly'!$C$215)+SUMIFS(#REF!,#REF!,'RDG Weekly'!$C$218))/+SUMIFS(#REF!,#REF!,'RDG Weekly'!$C$214) -> #REF! | AB111: =+(SUMIFS(#REF!,#REF!,#REF!)+SUMIFS(#REF!,#REF!,#REF!))/+SUMIFS(#REF!,#REF!,#REF!) -> #REF! | AE111: =+(SUMIFS(#REF!,#REF!,#REF!)+SUMIFS(#REF!,#REF!,#REF!))/+SUMIFS(#REF!,#REF!,#REF!) -> #REF! | AG111: =+(SUMIFS(#REF!,#REF!,#REF!)+SUMIFS(#REF!,#REF!,#REF!))/+SUMIFS(#REF!,#REF!,#REF!) -> #REF!
D112: Wine % | F112: =+(SUMIFS(#REF!,#REF!,'RDG Weekly'!$B$219)++SUMIFS(#REF!,#REF!,'RDG Weekly'!$B$220)+SUMIFS(#REF!,#REF!,'RDG Weekly'!$B$221))/(+SUMIFS(#REF!,#REF!,'RDG Weekly'!$B$214)+SUMIFS(#REF!,#REF!,'RDG Weekly'!$B$215)+SUMIFS(#REF!,#REF!,'RDG Weekly'!$B$218)) -> #REF! | I112: =+(SUMIFS(#REF!,#REF!,#REF!)++SUMIFS(#REF!,#REF!,#REF!)+SUMIFS(#REF!,#REF!,#REF!))/(+SUMIFS(#REF!,#REF!,#REF!)+SUMIFS(#REF!,#REF!,#REF!)+SUMIFS(#REF!,#REF!,#REF!)) -> #REF! | M112: =+(SUMIFS(#REF!,#REF!,#REF!)++SUMIFS(#REF!,#REF!,#REF!)+SUMIFS(#REF!,#REF!,#REF!))/(+SUMIFS(#REF!,#REF!,#REF!)+SUMIFS(#REF!,#REF!,#REF!)+SUMIFS(#REF!,#REF!,#REF!)) -> #REF! | Q112: =+(SUMIFS(#REF!,#REF!,#REF!)++SUMIFS(#REF!,#REF!,#REF!)+SUMIFS(#REF!,#REF!,#REF!))/(+SUMIFS(#REF!,#REF!,#REF!)+SUMIFS(#REF!,#REF!,#REF!)+SUMIFS(#REF!,#REF!,#REF!)) -> #REF! | X112: =+(SUMIFS(#REF!,#REF!,'RDG Weekly'!$B$219)++SUMIFS(#REF!,#REF!,'RDG Weekly'!$B$220)+SUMIFS(#REF!,#REF!,'RDG Weekly'!$B$221))/(+SUMIFS(#REF!,#REF!,'RDG Weekly'!$B$214)+SUMIFS(#REF!,#REF!,'RDG Weekly'!$B$215)+SUMIFS(#REF!,#REF!,'RDG Weekly'!$B$218)) -> #REF! | AB112: =+(SUMIFS(#REF!,#REF!,#REF!)++SUMIFS(#REF!,#REF!,#REF!)+SUMIFS(#REF!,#REF!,#REF!))/(+SUMIFS(#REF!,#REF!,#REF!)+SUMIFS(#REF!,#REF!,#REF!)+SUMIFS(#REF!,#REF!,#REF!)) -> #REF! | AE112: =+(SUMIFS(#REF!,#REF!,#REF!)++SUMIFS(#REF!,#REF!,#REF!)+SUMIFS(#REF!,#REF!,#REF!))/(+SUMIFS(#REF!,#REF!,#REF!)+SUMIFS(#REF!,#REF!,#REF!)+SUMIFS(#REF!,#REF!,#REF!)) -> #REF! | AG112: =+(SUMIFS(#REF!,#REF!,#REF!)++SUMIFS(#REF!,#REF!,#REF!)+SUMIFS(#REF!,#REF!,#REF!))/(+SUMIFS(#REF!,#REF!,#REF!)+SUMIFS(#REF!,#REF!,#REF!)+SUMIFS(#REF!,#REF!,#REF!)) -> #REF!
D114: Commentary
D116: Cost of Goods Sold
D117: Cost of Labour | F117: Further reduction of labour with relative good sales is for wk 22.
D118: Occupancy | F118: Turnover rent is higher due to higher sales vs budget
D119: Operating Expenses | F119: Slow purchasing week despite a 10k purchase for branded coasters & menu covers
D120: General & Administrative | F120: No areas to flag at the moment
D121: Utilities
D141: MILA Combined - Profit & Loss | AK141: Weekly Budget | AU141: Month to Date
D146: MILA COMBINED - P6 | F146: =+F81 -> MTD | X146: =+X81 -> YTD | AK146: =+AK81 -> #REF! | AM146: =+AM81 -> #REF! | AO146: =+AO81 -> #REF! | AQ146: =+AQ81 -> #REF! | AU146: =+AU81 -> #REF! | AY146: =+AY81 -> #REF! | BC146: =+BC81 -> #REF!
F148: =+F83 -> MILA 3F | I148: =+I83 -> MILA 2F | M148: =+M83 -> AVA | Q148: =+Q83 -> CASA NEOS | X148: =+X83 -> MILA | AB148: =+AB83 -> MILA MM | AE148: =+AE83 -> AVA | AG148: =+AG83 -> BAOLI | AK148: BUDGET | AM148: BUDGET | AO148: BUDGET | AQ148: BUDGET | AU148: 2023 | AW148: BUDGET | AY148: 2023 | BA148: BUDGET | BC148: 2023 | BE148: BUDGET
D150: Net Sales | F150: =+F13+F85 -> #REF! | G150: =IFERROR(F150/F150,0) -> 0 | I150: =+I13+I85 -> #REF! | K150: =IFERROR(I150/I150,0) -> 0 | M150: =+M13+M85 -> #REF! | O150: =IFERROR(M150/M150,0) -> 0 | Q150: =+Q13+Q85 -> #REF! | S150: =IFERROR(Q150/Q150,0) -> 0 | X150: =+X13+X85 -> #REF! | Z150: =IFERROR(X150/X150,0) -> 0 | AB150: =+AB13+AB85 -> #REF! | AD150: =IFERROR(AB150/AB150,0) -> 0 | AE150: =+AE13+AE85 -> #REF! | AF150: =IFERROR(AE150/AE150,0) -> 0 | AG150: =+AG13+AG85 -> #REF! | AH150: =IFERROR(AG150/AG150,0) -> 0 | AK150: =+AK13+AK85 -> #REF! | AL150: =IFERROR(AK150/AK150,0) -> 0 | AM150: =+AM13+AM85 -> #REF! | AN150: =IFERROR(AM150/AM150,0) -> 0 | AO150: =+AO13+AO85 -> #REF! | AP150: =IFERROR(AO150/AO150,0) -> 0 | AQ150: =+AQ13+AQ85 -> #REF! | AR150: =IFERROR(AQ150/AQ150,0) -> 0 | AU150: =SUMIFS($F$150:$F$171,$D$150:$D$171,D150) -> #REF! | AV150: =IFERROR(AU150/AU150,0) -> 0 | AW150: =SUMIFS($AK$150:$AK$171,$D$150:$D$171,D150) -> #REF! | AX150: =IFERROR(AW150/AW150,0) -> 0 | AY150: =SUMIFS($I$150:$I$171,$D$150:$D$171,D150)+SUMIFS($AU$150:$AU$171,$D$150:$D$171,D150) -> #REF! | AZ150: =IFERROR(AY150/AY150,0) -> 0 | BA150: =SUMIFS($AM$150:$AM$171,$D$150:$D$171,D150)+SUMIFS($AW$150:$AW$171,$D$150:$D$171,D150) -> #REF! | BB150: =IFERROR(BA150/BA150,0) -> 0 | BC150: =SUMIFS($M$150:$M$171,$D$150:$D$171,#REF!)+SUMIFS($AY$150:$AY$171,$D$150:$D$171,#REF!) -> 0 | BD150: =IFERROR(BC150/BC150,0) -> 0 | BE150: =SUMIFS($AO$150:$AO$171,$D$150:$D$171,#REF!)+SUMIFS($BA$150:$BA$171,$D$150:$D$171,#REF!) -> 0 | BF150: =IFERROR(BE150/BE150,0) -> 0
D151: Cost of Goods Sold | F151: =+F14+F86 -> #REF! | G151: =IFERROR(F151/F150,0) -> 0 | I151: =+I14+I86 -> #REF! | K151: =IFERROR(I151/I150,0) -> 0 | M151: =+M14+M86 -> #REF! | O151: =IFERROR(M151/M150,0) -> 0 | Q151: =+Q14+Q86 -> #REF! | S151: =IFERROR(Q151/Q150,0) -> 0 | X151: =+X14+X86 -> #REF! | Z151: =IFERROR(X151/X150,0) -> 0 | AB151: =+AB14+AB86 -> #REF! | AD151: =IFERROR(AB151/AB150,0) -> 0 | AE151: =+AE14+AE86 -> #REF! | AF151: =IFERROR(AE151/AE150,0) -> 0 | AG151: =+AG14+AG86 -> #REF! | AH151: =IFERROR(AG151/AG150,0) -> 0 | AK151: =+AK14+AK86 -> #REF! | AL151: =IFERROR(AK151/AK150,0) -> 0 | AM151: =+AM14+AM86 -> #REF! | AN151: =IFERROR(AM151/AM150,0) -> 0 | AO151: =+AO14+AO86 -> #REF! | AP151: =IFERROR(AO151/AO150,0) -> 0 | AQ151: =+AQ14+AQ86 -> #REF! | AR151: =IFERROR(AQ151/AQ150,0) -> 0 | AU151: =SUMIFS($F$150:$F$171,$D$150:$D$171,D151) -> #REF! | AV151: =IFERROR(AU151/AU150,0) -> 0 | AW151: =SUMIFS($AK$150:$AK$171,$D$150:$D$171,D151) -> #REF! | AX151: =IFERROR(AW151/AW150,0) -> 0 | AY151: =SUMIFS($I$150:$I$171,$D$150:$D$171,D151)+SUMIFS($AU$150:$AU$171,$D$150:$D$171,D151) -> #REF! | AZ151: =IFERROR(AY151/AY150,0) -> 0 | BA151: =SUMIFS($AM$150:$AM$171,$D$150:$D$171,D151)+SUMIFS($AW$150:$AW$171,$D$150:$D$171,D151) -> #REF! | BB151: =IFERROR(BA151/BA150,0) -> 0 | BC151: =SUMIFS($M$150:$M$171,$D$150:$D$171,#REF!)+SUMIFS($AY$150:$AY$171,$D$150:$D$171,#REF!) -> 0 | BD151: =IFERROR(BC151/BC150,0) -> 0 | BE151: =SUMIFS($AO$150:$AO$171,$D$150:$D$171,#REF!)+SUMIFS($BA$150:$BA$171,$D$150:$D$171,#REF!) -> 0 | BF151: =IFERROR(BE151/BE150,0) -> 0
D153: Gross Profit | F153: =F150-F151 -> #REF! | G153: =IFERROR(F153/F150,0) -> 0 | I153: =I150-I151 -> #REF! | K153: =IFERROR(I153/I150,0) -> 0 | M153: =M150-M151 -> #REF! | O153: =IFERROR(M153/M150,0) -> 0 | Q153: =Q150-Q151 -> #REF! | S153: =IFERROR(Q153/Q150,0) -> 0 | X153: =X150-X151 -> #REF! | Z153: =IFERROR(X153/X150,0) -> 0 | AB153: =AB150-AB151 -> #REF! | AD153: =IFERROR(AB153/AB150,0) -> 0 | AE153: =AE150-AE151 -> #REF! | AF153: =IFERROR(AE153/AE150,0) -> 0 | AG153: =AG150-AG151 -> #REF! | AH153: =IFERROR(AG153/AG150,0) -> 0 | AK153: =AK150-AK151 -> #REF! | AL153: =IFERROR(AK153/AK150,0) -> 0 | AM153: =AM150-AM151 -> #REF! | AN153: =IFERROR(AM153/AM150,0) -> 0 | AO153: =AO150-AO151 -> #REF! | AP153: =IFERROR(AO153/AO150,0) -> 0 | AQ153: =AQ150-AQ151 -> #REF! | AR153: =IFERROR(AQ153/AQ150,0) -> 0 | AU153: =AU150-AU151 -> #REF! | AV153: =IFERROR(AU153/AU150,0) -> 0 | AW153: =AW150-AW151 -> #REF! | AX153: =IFERROR(AW153/AW150,0) -> 0 | AY153: =AY150-AY151 -> #REF! | AZ153: =IFERROR(AY153/AY150,0) -> 0 | BA153: =BA150-BA151 -> #REF! | BB153: =IFERROR(BA153/BA150,0) -> 0 | BC153: =BC150-BC151 -> 0 | BD153: =IFERROR(BC153/BC150,0) -> 0 | BE153: =BE150-BE151 -> 0 | BF153: =IFERROR(BE153/BE150,0) -> 0
D155: Cost of Labor | F155: =+F18+F90 -> #REF! | G155: =IFERROR(F155/F150,0) -> 0 | I155: =+I18+I90 -> #REF! | K155: =IFERROR(I155/I150,0) -> 0 | M155: =+M18+M90 -> #REF! | O155: =IFERROR(M155/M150,0) -> 0 | Q155: =+Q18+Q90 -> #REF! | S155: =IFERROR(Q155/Q150,0) -> 0 | X155: =+X18+X90 -> #REF! | Z155: =IFERROR(X155/X150,0) -> 0 | AB155: =+AB18+AB90 -> #REF! | AD155: =IFERROR(AB155/AB150,0) -> 0 | AE155: =+AE18+AE90 -> #REF! | AF155: =IFERROR(AE155/AE150,0) -> 0 | AG155: =+AG18+AG90 -> #REF! | AH155: =IFERROR(AG155/AG150,0) -> 0 | AK155: =+AK18+AK90 -> #REF! | AL155: =IFERROR(AK155/AK150,0) -> 0 | AM155: =+AM18+AM90 -> #REF! | AN155: =IFERROR(AM155/AM150,0) -> 0 | AO155: =+AO18+AO90 -> #REF! | AP155: =IFERROR(AO155/AO150,0) -> 0 | AQ155: =+AQ18+AQ90 -> #REF! | AR155: =IFERROR(AQ155/AQ150,0) -> 0 | AU155: =SUMIFS($F$150:$F$171,$D$150:$D$171,D155) -> #REF! | AV155: =IFERROR(AU155/AU150,0) -> 0 | AW155: =SUMIFS($AK$150:$AK$171,$D$150:$D$171,D155) -> #REF! | AX155: =IFERROR(AW155/AW150,0) -> 0 | AY155: =SUMIFS($I$150:$I$171,$D$150:$D$171,D155)+SUMIFS($AU$150:$AU$171,$D$150:$D$171,D155) -> #REF! | AZ155: =IFERROR(AY155/AY150,0) -> 0 | BA155: =SUMIFS($AM$150:$AM$171,$D$150:$D$171,D155)+SUMIFS($AW$150:$AW$171,$D$150:$D$171,D155) -> #REF! | BB155: =IFERROR(BA155/BA150,0) -> 0 | BC155: =SUMIFS($M$150:$M$171,$D$150:$D$171,#REF!)+SUMIFS($AY$150:$AY$171,$D$150:$D$171,#REF!) -> 0 | BD155: =IFERROR(BC155/BC150,0) -> 0 | BE155: =SUMIFS($AO$150:$AO$171,$D$150:$D$171,#REF!)+SUMIFS($BA$150:$BA$171,$D$150:$D$171,#REF!) -> 0 | BF155: =IFERROR(BE155/BE150,0) -> 0
D156: FOH - Hourly | F156: =+F19+F91 -> #REF! | G156: =+F156/$F$150 -> #REF! | I156: =+I19+I91 -> #REF! | K156: =+I156/$I$150 -> #REF! | M156: =+M19+M91 -> #REF! | O156: =+M156/$M$150 -> #REF! | Q156: =+Q19+Q91 -> #REF! | S156: =+Q156/$Q$150 -> #REF! | X156: =+X19+X91 -> #REF! | Z156: =+X156/$F$150 -> #REF! | AB156: =+AB19+AB91 -> #REF! | AD156: =+AB156/$I$150 -> #REF! | AE156: =+AE19+AE91 -> #REF! | AF156: =+AE156/$M$150 -> #REF! | AG156: =+AG19+AG91 -> #REF! | AH156: =+AG156/$Q$150 -> #REF! | AK156: =+AK19+AK91 -> #REF! | AL156: =+AK156/$AK$150 -> #REF! | AM156: =+AM19+AM91 -> #REF! | AN156: =+AM156/$AM$150 -> #REF! | AO156: =+AO19+AO91 -> #REF! | AP156: =+AO156/$AO$150 -> #REF! | AQ156: =+AQ19+AQ91 -> #REF! | AR156: =+AQ156/$AQ$150 -> #REF! | AU156: =SUMIFS($F$150:$F$171,$D$150:$D$171,D156) -> #REF! | AV156: =+AU156/$AU$150 -> #REF! | AW156: =SUMIFS($AK$150:$AK$171,$D$150:$D$171,D156) -> #REF! | AX156: =+AW156/$AW$150 -> #REF! | AY156: =SUMIFS($I$150:$I$171,$D$150:$D$171,D156)+SUMIFS($AU$150:$AU$171,$D$150:$D$171,D156) -> #REF! | AZ156: =+AY156/$AY$150 -> #REF! | BA156: =SUMIFS($AM$150:$AM$171,$D$150:$D$171,D156)+SUMIFS($AW$150:$AW$171,$D$150:$D$171,D156) -> #REF! | BB156: =+BA156/$BA$150 -> #REF! | BC156: =SUMIFS($M$150:$M$171,$D$150:$D$171,#REF!)+SUMIFS($AY$150:$AY$171,$D$150:$D$171,#REF!) -> 0 | BD156: =+BC156/$BC$150 -> #DIV/0! | BE156: =SUMIFS($AO$150:$AO$171,$D$150:$D$171,#REF!)+SUMIFS($BA$150:$BA$171,$D$150:$D$171,#REF!) -> 0 | BF156: =+BE156/$BE$150 -> #DIV/0!
D157: BOH - Hourly | F157: =+F20+F92 -> #REF! | G157: =+F157/$F$150 -> #REF! | I157: =+I20+I92 -> #REF! | K157: =+I157/$I$150 -> #REF! | M157: =+M20+M92 -> #REF! | O157: =+M157/$M$150 -> #REF! | Q157: =+Q20+Q92 -> #REF! | S157: =+Q157/$Q$150 -> #REF! | X157: =+X20+X92 -> #REF! | Z157: =+X157/$F$150 -> #REF! | AB157: =+AB20+AB92 -> #REF! | AD157: =+AB157/$I$150 -> #REF! | AE157: =+AE20+AE92 -> #REF! | AF157: =+AE157/$M$150 -> #REF! | AG157: =+AG20+AG92 -> #REF! | AH157: =+AG157/$Q$150 -> #REF! | AK157: =+AK20+AK92 -> #REF! | AL157: =+AK157/$AK$150 -> #REF! | AM157: =+AM20+AM92 -> #REF! | AN157: =+AM157/$AM$150 -> #REF! | AO157: =+AO20+AO92 -> #REF! | AP157: =+AO157/$AO$150 -> #REF! | AQ157: =+AQ20+AQ92 -> #REF! | AR157: =+AQ157/$AQ$150 -> #REF! | AU157: =SUMIFS($F$150:$F$171,$D$150:$D$171,D157) -> #REF! | AV157: =+AU157/$AU$150 -> #REF! | AW157: =SUMIFS($AK$150:$AK$171,$D$150:$D$171,D157) -> #REF! | AX157: =+AW157/$AW$150 -> #REF! | AY157: =SUMIFS($I$150:$I$171,$D$150:$D$171,D157)+SUMIFS($AU$150:$AU$171,$D$150:$D$171,D157) -> #REF! | AZ157: =+AY157/$AY$150 -> #REF! | BA157: =SUMIFS($AM$150:$AM$171,$D$150:$D$171,D157)+SUMIFS($AW$150:$AW$171,$D$150:$D$171,D157) -> #REF! | BB157: =+BA157/$BA$150 -> #REF! | BC157: =SUMIFS($M$150:$M$171,$D$150:$D$171,#REF!)+SUMIFS($AY$150:$AY$171,$D$150:$D$171,#REF!) -> 0 | BD157: =+BC157/$BC$150 -> #DIV/0! | BE157: =SUMIFS($AO$150:$AO$171,$D$150:$D$171,#REF!)+SUMIFS($BA$150:$BA$171,$D$150:$D$171,#REF!) -> 0 | BF157: =+BE157/$BE$150 -> #DIV/0!
D158: Management | F158: =+F21+F93 -> #REF! | G158: =+F158/$F$150 -> #REF! | I158: =+I21+I93 -> #REF! | K158: =+I158/$I$150 -> #REF! | M158: =+M21+M93 -> #REF! | O158: =+M158/$M$150 -> #REF! | Q158: =+Q21+Q93 -> #REF! | S158: =+Q158/$Q$150 -> #REF! | X158: =+X21+X93 -> #REF! | Z158: =+X158/$F$150 -> #REF! | AB158: =+AB21+AB93 -> #REF! | AD158: =+AB158/$I$150 -> #REF! | AE158: =+AE21+AE93 -> #REF! | AF158: =+AE158/$M$150 -> #REF! | AG158: =+AG21+AG93 -> #REF! | AH158: =+AG158/$Q$150 -> #REF! | AK158: =+AK21+AK93 -> #REF! | AL158: =+AK158/$AK$150 -> #REF! | AM158: =+AM21+AM93 -> #REF! | AN158: =+AM158/$AM$150 -> #REF! | AO158: =+AO21+AO93 -> #REF! | AP158: =+AO158/$AO$150 -> #REF! | AQ158: =+AQ21+AQ93 -> #REF! | AR158: =+AQ158/$AQ$150 -> #REF! | AU158: =SUMIFS($F$150:$F$171,$D$150:$D$171,D158) -> #REF! | AV158: =+AU158/$AU$150 -> #REF! | AW158: =SUMIFS($AK$150:$AK$171,$D$150:$D$171,D158) -> #REF! | AX158: =+AW158/$AW$150 -> #REF! | AY158: =SUMIFS($I$150:$I$171,$D$150:$D$171,D158)+SUMIFS($AU$150:$AU$171,$D$150:$D$171,D158) -> #REF! | AZ158: =+AY158/$AY$150 -> #REF! | BA158: =SUMIFS($AM$150:$AM$171,$D$150:$D$171,D158)+SUMIFS($AW$150:$AW$171,$D$150:$D$171,D158) -> #REF! | BB158: =+BA158/$BA$150 -> #REF! | BC158: =SUMIFS($M$150:$M$171,$D$150:$D$171,#REF!)+SUMIFS($AY$150:$AY$171,$D$150:$D$171,#REF!) -> 0 | BD158: =+BC158/$BC$150 -> #DIV/0! | BE158: =SUMIFS($AO$150:$AO$171,$D$150:$D$171,#REF!)+SUMIFS($BA$150:$BA$171,$D$150:$D$171,#REF!) -> 0 | BF158: =+BE158/$BE$150 -> #DIV/0!
D159: Occupancy | F159: =+F22+F94 -> #REF! | G159: =IFERROR(F159/F150,0) -> 0 | I159: =+I22+I94 -> #REF! | K159: =IFERROR(I159/I150,0) -> 0 | M159: =+M22+M94 -> #REF! | O159: =IFERROR(M159/M150,0) -> 0 | Q159: =+Q22+Q94 -> #REF! | S159: =IFERROR(Q159/Q150,0) -> 0 | X159: =+X22+X94 -> #REF! | Z159: =IFERROR(X159/X150,0) -> 0 | AB159: =+AB22+AB94 -> #REF! | AD159: =IFERROR(AB159/AB150,0) -> 0 | AE159: =+AE22+AE94 -> #REF! | AF159: =IFERROR(AE159/AE150,0) -> 0 | AG159: =+AG22+AG94 -> #REF! | AH159: =IFERROR(AG159/AG150,0) -> 0 | AK159: =+AK22+AK94 -> #REF! | AL159: =IFERROR(AK159/AK150,0) -> 0 | AM159: =+AM22+AM94 -> #REF! | AN159: =IFERROR(AM159/AM150,0) -> 0 | AO159: =+AO22+AO94 -> #REF! | AP159: =IFERROR(AO159/AO150,0) -> 0 | AQ159: =+AQ22+AQ94 -> #REF! | AR159: =IFERROR(AQ159/AQ150,0) -> 0 | AU159: =SUMIFS($F$150:$F$171,$D$150:$D$171,D159) -> #REF! | AV159: =IFERROR(AU159/AU150,0) -> 0 | AW159: =SUMIFS($AK$150:$AK$171,$D$150:$D$171,D159) -> #REF! | AX159: =IFERROR(AW159/AW150,0) -> 0 | AY159: =SUMIFS($I$150:$I$171,$D$150:$D$171,D159)+SUMIFS($AU$150:$AU$171,$D$150:$D$171,D159) -> #REF! | AZ159: =IFERROR(AY159/AY150,0) -> 0 | BA159: =SUMIFS($AM$150:$AM$171,$D$150:$D$171,D159)+SUMIFS($AW$150:$AW$171,$D$150:$D$171,D159) -> #REF! | BB159: =IFERROR(BA159/BA150,0) -> 0 | BC159: =SUMIFS($M$150:$M$171,$D$150:$D$171,#REF!)+SUMIFS($AY$150:$AY$171,$D$150:$D$171,#REF!) -> 0 | BD159: =IFERROR(BC159/BC150,0) -> 0 | BE159: =SUMIFS($AO$150:$AO$171,$D$150:$D$171,#REF!)+SUMIFS($BA$150:$BA$171,$D$150:$D$171,#REF!) -> 0 | BF159: =IFERROR(BE159/BE150,0) -> 0
D160: Operating Expenses | F160: =+F23+F95 -> #REF! | G160: =IFERROR(F160/F150,0) -> 0 | I160: =+I23+I95 -> #REF! | K160: =IFERROR(I160/I150,0) -> 0 | M160: =+M23+M95 -> #REF! | O160: =IFERROR(M160/M150,0) -> 0 | Q160: =+Q23+Q95 -> #REF! | S160: =IFERROR(Q160/Q150,0) -> 0 | X160: =+X23+X95 -> #REF! | Z160: =IFERROR(X160/X150,0) -> 0 | AB160: =+AB23+AB95 -> #REF! | AD160: =IFERROR(AB160/AB150,0) -> 0 | AE160: =+AE23+AE95 -> #REF! | AF160: =IFERROR(AE160/AE150,0) -> 0 | AG160: =+AG23+AG95 -> #REF! | AH160: =IFERROR(AG160/AG150,0) -> 0 | AK160: =+AK23+AK95 -> #REF! | AL160: =IFERROR(AK160/AK150,0) -> 0 | AM160: =+AM23+AM95 -> #REF! | AN160: =IFERROR(AM160/AM150,0) -> 0 | AO160: =+AO23+AO95 -> #REF! | AP160: =IFERROR(AO160/AO150,0) -> 0 | AQ160: =+AQ23+AQ95 -> #REF! | AR160: =IFERROR(AQ160/AQ150,0) -> 0 | AU160: =SUMIFS($F$150:$F$171,$D$150:$D$171,D160) -> #REF! | AV160: =IFERROR(AU160/AU150,0) -> 0 | AW160: =SUMIFS($AK$150:$AK$171,$D$150:$D$171,D160) -> #REF! | AX160: =IFERROR(AW160/AW150,0) -> 0 | AY160: =SUMIFS($I$150:$I$171,$D$150:$D$171,D160)+SUMIFS($AU$150:$AU$171,$D$150:$D$171,D160) -> #REF! | AZ160: =IFERROR(AY160/AY150,0) -> 0 | BA160: =SUMIFS($AM$150:$AM$171,$D$150:$D$171,D160)+SUMIFS($AW$150:$AW$171,$D$150:$D$171,D160) -> #REF! | BB160: =IFERROR(BA160/BA150,0) -> 0 | BC160: =SUMIFS($M$150:$M$171,$D$150:$D$171,#REF!)+SUMIFS($AY$150:$AY$171,$D$150:$D$171,#REF!) -> 0 | BD160: =IFERROR(BC160/BC150,0) -> 0 | BE160: =SUMIFS($AO$150:$AO$171,$D$150:$D$171,#REF!)+SUMIFS($BA$150:$BA$171,$D$150:$D$171,#REF!) -> 0 | BF160: =IFERROR(BE160/BE150,0) -> 0
D161: General & Administrative | F161: =+F24+F96 -> #REF! | G161: =IFERROR(F161/F150,0) -> 0 | I161: =+I24+I96 -> #REF! | K161: =IFERROR(I161/I150,0) -> 0 | M161: =+M24+M96 -> #REF! | O161: =IFERROR(M161/M150,0) -> 0 | Q161: =+Q24+Q96 -> #REF! | S161: =IFERROR(Q161/Q150,0) -> 0 | X161: =+X24+X96 -> #REF! | Z161: =IFERROR(X161/X150,0) -> 0 | AB161: =+AB24+AB96 -> #REF! | AD161: =IFERROR(AB161/AB150,0) -> 0 | AE161: =+AE24+AE96 -> #REF! | AF161: =IFERROR(AE161/AE150,0) -> 0 | AG161: =+AG24+AG96 -> #REF! | AH161: =IFERROR(AG161/AG150,0) -> 0 | AK161: =+AK24+AK96 -> #REF! | AL161: =IFERROR(AK161/AK150,0) -> 0 | AM161: =+AM24+AM96 -> #REF! | AN161: =IFERROR(AM161/AM150,0) -> 0 | AO161: =+AO24+AO96 -> #REF! | AP161: =IFERROR(AO161/AO150,0) -> 0 | AQ161: =+AQ24+AQ96 -> #REF! | AR161: =IFERROR(AQ161/AQ150,0) -> 0 | AU161: =SUMIFS($F$150:$F$171,$D$150:$D$171,D161) -> #REF! | AV161: =IFERROR(AU161/AU150,0) -> 0 | AW161: =SUMIFS($AK$150:$AK$171,$D$150:$D$171,D161) -> #REF! | AX161: =IFERROR(AW161/AW150,0) -> 0 | AY161: =SUMIFS($I$150:$I$171,$D$150:$D$171,D161)+SUMIFS($AU$150:$AU$171,$D$150:$D$171,D161) -> #REF! | AZ161: =IFERROR(AY161/AY150,0) -> 0 | BA161: =SUMIFS($AM$150:$AM$171,$D$150:$D$171,D161)+SUMIFS($AW$150:$AW$171,$D$150:$D$171,D161) -> #REF! | BB161: =IFERROR(BA161/BA150,0) -> 0 | BC161: =SUMIFS($M$150:$M$171,$D$150:$D$171,#REF!)+SUMIFS($AY$150:$AY$171,$D$150:$D$171,#REF!) -> 0 | BD161: =IFERROR(BC161/BC150,0) -> 0 | BE161: =SUMIFS($AO$150:$AO$171,$D$150:$D$171,#REF!)+SUMIFS($BA$150:$BA$171,$D$150:$D$171,#REF!) -> 0 | BF161: =IFERROR(BE161/BE150,0) -> 0
D162: Utilities | F162: =+F25+F97 -> #REF! | G162: =IFERROR(F162/F150,0) -> 0 | I162: =+I25+I97 -> #REF! | K162: =IFERROR(I162/I150,0) -> 0 | M162: =+M25+M97 -> #REF! | O162: =IFERROR(M162/M150,0) -> 0 | Q162: =+Q25+Q97 -> #REF! | S162: =IFERROR(Q162/Q150,0) -> 0 | X162: =+X25+X97 -> #REF! | Z162: =IFERROR(X162/X150,0) -> 0 | AB162: =+AB25+AB97 -> #REF! | AD162: =IFERROR(AB162/AB150,0) -> 0 | AE162: =+AE25+AE97 -> #REF! | AF162: =IFERROR(AE162/AE150,0) -> 0 | AG162: =+AG25+AG97 -> #REF! | AH162: =IFERROR(AG162/AG150,0) -> 0 | AK162: =+AK25+AK97 -> #REF! | AL162: =IFERROR(AK162/AK150,0) -> 0 | AM162: =+AM25+AM97 -> #REF! | AN162: =IFERROR(AM162/AM150,0) -> 0 | AO162: =+AO25+AO97 -> #REF! | AP162: =IFERROR(AO162/AO150,0) -> 0 | AQ162: =+AQ25+AQ97 -> #REF! | AR162: =IFERROR(AQ162/AQ150,0) -> 0 | AU162: =SUMIFS($F$150:$F$171,$D$150:$D$171,D162) -> #REF! | AV162: =IFERROR(AU162/AU150,0) -> 0 | AW162: =SUMIFS($AK$150:$AK$171,$D$150:$D$171,D162) -> #REF! | AX162: =IFERROR(AW162/AW150,0) -> 0 | AY162: =SUMIFS($I$150:$I$171,$D$150:$D$171,D162)+SUMIFS($AU$150:$AU$171,$D$150:$D$171,D162) -> #REF! | AZ162: =IFERROR(AY162/AY150,0) -> 0 | BA162: =SUMIFS($AM$150:$AM$171,$D$150:$D$171,D162)+SUMIFS($AW$150:$AW$171,$D$150:$D$171,D162) -> #REF! | BB162: =IFERROR(BA162/BA150,0) -> 0 | BC162: =SUMIFS($M$150:$M$171,$D$150:$D$171,#REF!)+SUMIFS($AY$150:$AY$171,$D$150:$D$171,#REF!) -> 0 | BD162: =IFERROR(BC162/BC150,0) -> 0 | BE162: =SUMIFS($AO$150:$AO$171,$D$150:$D$171,#REF!)+SUMIFS($BA$150:$BA$171,$D$150:$D$171,#REF!) -> 0 | BF162: =IFERROR(BE162/BE150,0) -> 0
D163: Other Income | F163: =+F26+F98 -> #REF! | G163: =IFERROR(F163/F150,0) -> 0 | I163: =+I26+I98 -> #REF! | K163: =IFERROR(I163/I150,0) -> 0 | M163: =+M26+M98 -> #REF! | O163: =IFERROR(M163/M150,0) -> 0 | Q163: =+Q26+Q98 -> #REF! | S163: =IFERROR(Q163/Q150,0) -> 0 | X163: =+X26+X98 -> #REF! | Z163: =IFERROR(X163/X150,0) -> 0 | AB163: =+AB26+AB98 -> #REF! | AD163: =IFERROR(AB163/AB150,0) -> 0 | AE163: =+AE26+AE98 -> #REF! | AF163: =IFERROR(AE163/AE150,0) -> 0 | AG163: =+AG26+AG98 -> #REF! | AH163: =IFERROR(AG163/AG150,0) -> 0 | AK163: =+AK26+AK98 -> #REF! | AL163: =IFERROR(AK163/AK150,0) -> 0 | AM163: =+AM26+AM98 -> #REF! | AN163: =IFERROR(AM163/AM150,0) -> 0 | AO163: =+AO26+AO98 -> #REF! | AP163: =IFERROR(AO163/AO150,0) -> 0 | AQ163: =+AQ26+AQ98 -> #REF! | AR163: =IFERROR(AQ163/AQ150,0) -> 0 | AU163: =SUMIFS($F$150:$F$171,$D$150:$D$171,D163) -> #REF! | AV163: =IFERROR(AU163/AU150,0) -> 0 | AW163: =SUMIFS($AK$150:$AK$171,$D$150:$D$171,D163) -> #REF! | AX163: =IFERROR(AW163/AW150,0) -> 0 | AY163: =SUMIFS($I$150:$I$171,$D$150:$D$171,D163)+SUMIFS($AU$150:$AU$171,$D$150:$D$171,D163) -> #REF! | AZ163: =IFERROR(AY163/AY150,0) -> 0 | BA163: =SUMIFS($AM$150:$AM$171,$D$150:$D$171,D163)+SUMIFS($AW$150:$AW$171,$D$150:$D$171,D163) -> #REF! | BB163: =IFERROR(BA163/BA150,0) -> 0 | BC163: =SUMIFS($M$150:$M$171,$D$150:$D$171,#REF!)+SUMIFS($AY$150:$AY$171,$D$150:$D$171,#REF!) -> 0 | BD163: =IFERROR(BC163/BC150,0) -> 0 | BE163: =SUMIFS($AO$150:$AO$171,$D$150:$D$171,#REF!)+SUMIFS($BA$150:$BA$171,$D$150:$D$171,#REF!) -> 0 | BF163: =IFERROR(BE163/BE150,0) -> 0
D165: Total Operating Expenses | F165: =SUM(F159:F163,F155) -> #REF! | G165: =IFERROR(F165/F150,0) -> 0 | I165: =SUM(I159:I163,I155) -> #REF! | K165: =IFERROR(I165/I150,0) -> 0 | M165: =SUM(M159:M163,M155) -> #REF! | O165: =IFERROR(M165/M150,0) -> 0 | Q165: =SUM(Q159:Q163,Q155) -> #REF! | S165: =IFERROR(Q165/Q150,0) -> 0 | X165: =SUM(X159:X163,X155) -> #REF! | Z165: =IFERROR(X165/X150,0) -> 0 | AB165: =SUM(AB159:AB163,AB155) -> #REF! | AD165: =IFERROR(AB165/AB150,0) -> 0 | AE165: =SUM(AE159:AE163,AE155) -> #REF! | AF165: =IFERROR(AE165/AE150,0) -> 0 | AG165: =SUM(AG159:AG163,AG155) -> #REF! | AH165: =IFERROR(AG165/AG150,0) -> 0 | AK165: =SUM(AK159:AK163,AK155) -> #REF! | AL165: =IFERROR(AK165/AK150,0) -> 0 | AM165: =SUM(AM159:AM163,AM155) -> #REF! | AN165: =IFERROR(AM165/AM150,0) -> 0 | AO165: =SUM(AO159:AO163,AO155) -> #REF! | AP165: =IFERROR(AO165/AO150,0) -> 0 | AQ165: =SUM(AQ159:AQ163,AQ155) -> #REF! | AR165: =IFERROR(AQ165/AQ150,0) -> 0 | AU165: =SUM(AU159:AU163,AU155) -> #REF! | AV165: =IFERROR(AU165/AU150,0) -> 0 | AW165: =SUM(AW159:AW163,AW155) -> #REF! | AX165: =IFERROR(AW165/AW150,0) -> 0 | AY165: =SUM(AY159:AY163,AY155) -> #REF! | AZ165: =IFERROR(AY165/AY150,0) -> 0 | BA165: =SUM(BA159:BA163,BA155) -> #REF! | BB165: =IFERROR(BA165/BA150,0) -> 0 | BC165: =SUM(BC159:BC163,BC155) -> 0 | BD165: =IFERROR(BC165/BC150,0) -> 0 | BE165: =SUM(BE159:BE163,BE155) -> 0 | BF165: =IFERROR(BE165/BE150,0) -> 0
D167: Net Operating Income | F167: =F153-F165 -> #REF! | G167: =IFERROR(F167/F150,0) -> 0 | I167: =I153-I165 -> #REF! | K167: =IFERROR(I167/I150,0) -> 0 | M167: =M153-M165 -> #REF! | O167: =IFERROR(M167/M150,0) -> 0 | Q167: =Q153-Q165 -> #REF! | S167: =IFERROR(Q167/Q150,0) -> 0 | X167: =X153-X165 -> #REF! | Z167: =IFERROR(X167/X150,0) -> 0 | AB167: =AB153-AB165 -> #REF! | AD167: =IFERROR(AB167/AB150,0) -> 0 | AE167: =AE153-AE165 -> #REF! | AF167: =IFERROR(AE167/AE150,0) -> 0 | AG167: =AG153-AG165 -> #REF! | AH167: =IFERROR(AG167/AG150,0) -> 0 | AK167: =AK153-AK165 -> #REF! | AL167: =IFERROR(AK167/AK150,0) -> 0 | AM167: =AM153-AM165 -> #REF! | AN167: =IFERROR(AM167/AM150,0) -> 0 | AO167: =AO153-AO165 -> #REF! | AP167: =IFERROR(AO167/AO150,0) -> 0 | AQ167: =AQ153-AQ165 -> #REF! | AR167: =IFERROR(AQ167/AQ150,0) -> 0 | AU167: =AU153-AU165 -> #REF! | AV167: =IFERROR(AU167/AU150,0) -> 0 | AW167: =AW153-AW165 -> #REF! | AX167: =IFERROR(AW167/AW150,0) -> 0 | AY167: =AY153-AY165 -> #REF! | AZ167: =IFERROR(AY167/AY150,0) -> 0 | BA167: =BA153-BA165 -> #REF! | BB167: =IFERROR(BA167/BA150,0) -> 0 | BC167: =BC153-BC165 -> 0 | BD167: =IFERROR(BC167/BC150,0) -> 0 | BE167: =BE153-BE165 -> 0 | BF167: =IFERROR(BE167/BE150,0) -> 0
D169: Other G&A | F169: =+F32+F104 -> #REF! | G169: =IFERROR(F169/F150,0) -> 0 | I169: =+I32+I104 -> #REF! | K169: =IFERROR(I169/I150,0) -> 0 | M169: =+M32+M104 -> #REF! | O169: =IFERROR(M169/M150,0) -> 0 | Q169: =+Q32+Q104 -> #REF! | S169: =IFERROR(Q169/Q150,0) -> 0 | X169: =+X32+X104 -> #REF! | Z169: =IFERROR(X169/X150,0) -> 0 | AB169: =+AB32+AB104 -> #REF! | AD169: =IFERROR(AB169/AB150,0) -> 0 | AE169: =+AE32+AE104 -> #REF! | AF169: =IFERROR(AE169/AE150,0) -> 0 | AG169: =+AG32+AG104 -> #REF! | AH169: =IFERROR(AG169/AG150,0) -> 0 | AK169: =+AK32+AK104 -> #REF! | AL169: =IFERROR(AK169/AK150,0) -> 0 | AM169: =+AM104+AM32 -> #REF! | AN169: =IFERROR(AM169/AM150,0) -> 0 | AO169: =+AO104+AO32 -> #REF! | AP169: =IFERROR(AO169/AO150,0) -> 0 | AQ169: =+AQ104+AQ32 -> #REF! | AR169: =IFERROR(AQ169/AQ150,0) -> 0 | AU169: =SUMIFS($F$150:$F$171,$D$150:$D$171,D169) -> #REF! | AV169: =IFERROR(AU169/AU150,0) -> 0 | AW169: =SUMIFS($AK$150:$AK$171,$D$150:$D$171,D169) -> #REF! | AX169: =IFERROR(AW169/AW150,0) -> 0 | AY169: =SUMIFS($I$150:$I$171,$D$150:$D$171,D169)+SUMIFS($AU$150:$AU$171,$D$150:$D$171,D169) -> #REF! | AZ169: =IFERROR(AY169/AY150,0) -> 0 | BA169: =SUMIFS($AM$150:$AM$171,$D$150:$D$171,D169)+SUMIFS($AW$150:$AW$171,$D$150:$D$171,D169) -> #REF! | BB169: =IFERROR(BA169/BA150,0) -> 0 | BC169: =SUMIFS($M$150:$M$171,$D$150:$D$171,#REF!)+SUMIFS($AY$150:$AY$171,$D$150:$D$171,#REF!) -> 0 | BD169: =IFERROR(BC169/BC150,0) -> 0 | BE169: =SUMIFS($AO$150:$AO$171,$D$150:$D$171,#REF!)+SUMIFS($BA$150:$BA$171,$D$150:$D$171,#REF!) -> 0 | BF169: =IFERROR(BE169/BE150,0) -> 0
D171: EBITDA | F171: =F167-F169 -> #REF! | G171: =IFERROR(F171/F150,0) -> 0 | I171: =I167-I169 -> #REF! | K171: =IFERROR(I171/I150,0) -> 0 | M171: =M167-M169 -> #REF! | O171: =IFERROR(M171/M150,0) -> 0 | Q171: =Q167-Q169 -> #REF! | S171: =IFERROR(Q171/Q150,0) -> 0 | X171: =X167-X169 -> #REF! | Z171: =IFERROR(X171/X150,0) -> 0 | AB171: =AB167-AB169 -> #REF! | AD171: =IFERROR(AB171/AB150,0) -> 0 | AE171: =AE167-AE169 -> #REF! | AF171: =IFERROR(AE171/AE150,0) -> 0 | AG171: =AG167-AG169 -> #REF! | AH171: =IFERROR(AG171/AG150,0) -> 0 | AK171: =AK167-AK169 -> #REF! | AL171: =IFERROR(AK171/AK150,0) -> 0 | AM171: =AM167-AM169 -> #REF! | AN171: =IFERROR(AM171/AM150,0) -> 0 | AO171: =AO167-AO169 -> #REF! | AP171: =IFERROR(AO171/AO150,0) -> 0 | AQ171: =AQ167-AQ169 -> #REF! | AR171: =IFERROR(AQ171/AQ150,0) -> 0 | AU171: =AU167-AU169 -> #REF! | AV171: =IFERROR(AU171/AU150,0) -> 0 | AW171: =AW167-AW169 -> #REF! | AX171: =IFERROR(AW171/AW150,0) -> 0 | AY171: =AY167-AY169 -> #REF! | AZ171: =IFERROR(AY171/AY150,0) -> 0 | BA171: =BA167-BA169 -> #REF! | BB171: =IFERROR(BA171/BA150,0) -> 0 | BC171: =BC167-BC169 -> 0 | BD171: =IFERROR(BC171/BC150,0) -> 0 | BE171: =BE167-BE169 -> 0 | BF171: =IFERROR(BE171/BE150,0) -> 0
AQ183: Sales | AR183: COGS | AS183: WAGES | AT183: OPEX | AU183: Other G&A | AV183: EBIDTA
D191: =CONCATENATE("Riviera Dining Group - Profit & Loss",) -> Riviera Dining Group - Profit & Loss
C193: =VLOOKUP($D$193,#REF!,2,FALSE) -> #REF! | D193: P10 | F193: MTD | S193: YTD
F195: SALES | G195: COGS | I195: WAGES | K195: OPEX | M195: Other G&A | O195: EBITDA | S195: SALES | T195: COGS | V195: WAGES | X195: OPEX | Z195: Other G&A | AB195: EBITDA
D196: MILA 3F | F196: =SUMIFS(#REF!,#REF!,$B$13) -> #REF! | G196: =SUMIFS(#REF!,#REF!,'RDG Weekly'!$B$14)+SUMIFS(#REF!,#REF!,'RDG Weekly'!$B$15)+SUMIFS(#REF!,#REF!,'RDG Weekly'!$B$16) -> #REF! | H196: =IFERROR(G196/$F$196,0) -> 0 | I196: =+SUMIFS(#REF!,#REF!,'RDG Weekly'!$B$18) +SUMIFS(#REF!,#REF!,'RDG Weekly'!$C$18) +SUMIFS(#REF!,#REF!,'RDG Weekly'!$C$22) +SUMIFS(#REF!,#REF!,'RDG Weekly'!$C$23) -> #REF! | J196: =IFERROR(I196/$F$196,0) -> 0 | K196: =+SUMIFS(#REF!,#REF!,'RDG Weekly'!$B$22) +SUMIFS(#REF!,#REF!,'RDG Weekly'!$B$23) +SUMIFS(#REF!,#REF!,'RDG Weekly'!$B$24) +SUMIFS(#REF!,#REF!,'RDG Weekly'!$B$25) +SUMIFS(#REF!,#REF!,'RDG Weekly'!$B$26) -> #REF! | L196: =IFERROR(K196/$F$196,0) -> 0 | M196: =+SUMIFS(#REF!,#REF!,'RDG Weekly'!$B$32) -SUMIFS(#REF!,#REF!,'RDG Weekly'!$B$35)-SUMIFS(#REF!,#REF!,'RDG Weekly'!$B$33) -> #REF! | N196: =IFERROR(M196/$F$196,0) -> 0 | O196: =F196-G196-I196-K196-M196 -> #REF! | P196: =IFERROR(O196/$F$196,0) -> 0 | S196: =SUMIFS(#REF!,#REF!,$B$13) -> #REF! | T196: =SUMIFS(#REF!,#REF!,'RDG Weekly'!$B$14)+SUMIFS(#REF!,#REF!,'RDG Weekly'!$B$15)+SUMIFS(#REF!,#REF!,'RDG Weekly'!$B$16) -> #REF! | U196: =IFERROR(T196/$S196,0) -> 0 | V196: =+SUMIFS(#REF!,#REF!,'RDG Weekly'!$B$18) +SUMIFS(#REF!,#REF!,'RDG Weekly'!$C$18) +SUMIFS(#REF!,#REF!,'RDG Weekly'!$C$22) +SUMIFS(#REF!,#REF!,'RDG Weekly'!$C$23) -> #REF! | W196: =IFERROR(V196/$S196,0) -> 0 | X196: =+SUMIFS(#REF!,#REF!,'RDG Weekly'!$B$22) +SUMIFS(#REF!,#REF!,'RDG Weekly'!$B$23) +SUMIFS(#REF!,#REF!,'RDG Weekly'!$B$24) +SUMIFS(#REF!,#REF!,'RDG Weekly'!$B$25) +SUMIFS(#REF!,#REF!,'RDG Weekly'!$B$26) -> #REF! | Y196: =IFERROR(X196/$S196,0) -> 0 | Z196: =+SUMIFS(#REF!,#REF!,'RDG Weekly'!$B$32) -SUMIFS(#REF!,#REF!,'RDG Weekly'!$B$35)-SUMIFS(#REF!,#REF!,'RDG Weekly'!$B$33) -> #REF! | AA196: =IFERROR(Z196/$S196,0) -> 0 | AB196: =S196-T196-V196-X196-Z196 -> #REF! | AC196: =IFERROR(AB196/$S196,0) -> 0
D197: Budget | F197: =HLOOKUP($D$193,#REF!,2,FALSE) -> #REF! | G197: =HLOOKUP($D$193,#REF!,3,FALSE) -> #REF! | H197: =IFERROR(G197/$F$197,0) -> 0 | I197: =HLOOKUP($D$193,#REF!,7,FALSE) -> #REF! | J197: =IFERROR(I197/$F$197,0) -> 0 | K197: =HLOOKUP($D$193,#REF!,8,FALSE)+HLOOKUP($D$193,#REF!,9,FALSE)+HLOOKUP($D$193,#REF!,10,FALSE)+HLOOKUP($D$193,#REF!,11,FALSE)+HLOOKUP($D$193,#REF!,12,FALSE) -> #REF! | L197: =IFERROR(K197/$F$197,0) -> 0 | M197: =HLOOKUP($D$193,#REF!,18,FALSE) -> #REF! | N197: =IFERROR(M197/$F$197,0) -> 0 | O197: =F197-G197-I197-K197-M197 -> #REF! | P197: =IFERROR(O197/$F$197,0) -> 0 | S197: =SUMIF(#REF!,"actual",#REF!) -> #REF! | T197: =SUMIF(#REF!,"actual",#REF!) -> #REF! | U197: =IFERROR(T197/$S197,0) -> 0 | V197: =SUMIF(#REF!,"actual",#REF!) -> #REF! | W197: =IFERROR(V197/$S197,0) -> 0 | X197: =SUMIF(#REF!,"actual",#REF!)+SUMIF(#REF!,"actual",#REF!)+SUMIF(#REF!,"actual",#REF!)+SUMIF(#REF!,"actual",#REF!)+SUMIF(#REF!,"actual",#REF!) -> #REF! | Y197: =IFERROR(X197/$S197,0) -> 0 | Z197: =SUMIF(#REF!,"actual",#REF!) -> #REF! | AA197: =IFERROR(Z197/$S197,0) -> 0 | AB197: =S197-T197-V197-X197-Z197 -> #REF! | AC197: =IFERROR(AB197/$S197,0) -> 0
...

Sheet Reconciliation
B2: Week # | C2: Week 34
B3: Period | C3: {=_xlfn._xlws.FILTER(Table3[Period],Table3[Week '#]=Reconciliation!$C$2,"")} -> P8
B6: Week # | C6: Consolidated $ | D6: Actual - 2026 | E6: Variance
B7: {=_xlfn.UNIQUE(_xlfn._xlws.FILTER(CHOOSE({1,2},Table6[Week '#],SUMPRODUCT((Table6[Week '#]=Reconciliation!$C$2)*(Table6[Net sales]))),Table6[Week '#]=Reconciliation!$C$2,""))} -> Week 34 | C7: 2000757.3 | D7: =SUMIF('Actual - 2026'!$A$5:$A$56,$C$2,'Actual - 2026'!$K$5:$K$56)+SUMIF('Actual - 2026'!$A$5:$A$56,$C$2,'Actual - 2026'!$W$5:$W$56)+SUMIF('Actual - 2026'!$A$5:$A$56,$C$2,'Actual - 2026'!$AI$5:$AI$56)+SUMIF('Actual - 2026'!$A$5:$A$56,$C$2,'Actual - 2026'!$AR$5:$AR$56)+SUMIF('Actual - 2026'!$A$5:$A$56,$C$2,'Actual - 2026'!$BA$5:$BA$56)+SUMIF('Actual - 2026'!$A$5:$A$56,$C$2,'Actual - 2026'!$BM$5:$BM$56)+SUMIF('Actual - 2026'!$A$5:$A$56,$C$2,'Actual - 2026'!$BV$5:$BV$56) -> 1995361.8 | E7: =C7-D7 -> 5395.52
B8: Non-Grat Svc Charges | E8: {=SUMPRODUCT((Table4[Week '#]=Reconciliation!$C$2)*(Table4[Non-Grat Service $]))} -> 5552.87
B9: Total | E9: =E7-E8 -> -157.35
B13: Week # | C13: Day of Week | D13: Consolidated $
B14: {=_xlfn._xlws.FILTER(CHOOSE({1,2,3},Table6[Week '#],Table6[Day of Week],Table6[Net sales]),Table6[Week '#]=Reconciliation!$C$2,"")} -> Week 34 | C14: Monday | D14: 99798.77
B15: Week 34 | C15: Tuesday | D15: 170377.19
B16: Week 34 | C16: Wednesday | D16: 179832.09
B17: Week 34 | C17: Thursday | D17: 295283.89
B18: Week 34 | C18: Friday | D18: 440631.69
B19: Week 34 | C19: Saturday | D19: 511041.9
B20: Week 34 | C20: Sunday | D20: 303791.78
B21: Total | D21: =SUM(D14:D20) -> 2000757.3

Sheet Reference Tab
B3: DATE TABLE | H3: TOTAL SALES | P3: NON-GRATUITY SERVICE CHARGE
B5: Period | C5: Week # | D5: Start Date | E5: End Date | F5: Period 1 | H5: yyyyMMdd | I5: Net sales | J5: Total orders | K5: Total guests | L5: Date | M5: Day of Week | N5: Week # | P5: Period | Q5: Week # | R5: Start Date | S5: End Date | T5: Non-Grat Service $
B6: P1 | C6: Week 1 | D6: 46020 | E6: =Table3[[#This Row],[Start Date]]+6 -> 46026 | F6: Period 1 | H6: 20251229 | I6: 395375.12 | J6: 1227 | K6: 2791 | L6: =DATE(LEFT(H6,4),MID(H6,5,2),RIGHT(H6,2)) -> 46020 | M6: =TEXT(L6,"DDDD") -> Monday | N6: {=_xlfn._xlws.FILTER(Table3[Week '#],(Table3[Start Date]<=Table6[[#This Row],[Date]])*(Table3[End Date]>=Table6[[#This Row],[Date]]),"")} -> Week 1 | P6: P1 | Q6: Week 1 | R6: 46020 | S6: 46026 | T6: 4667.91
B7: P1 | C7: Week 2 | D7: =+E6+1 -> 46027 | E7: =Table3[[#This Row],[Start Date]]+6 -> 46033 | F7: Period 1 | H7: 20251230 | I7: 677868.52 | J7: 2060 | K7: 5012 | L7: =DATE(LEFT(H7,4),MID(H7,5,2),RIGHT(H7,2)) -> 46021 | M7: =TEXT(L7,"DDDD") -> Tuesday | N7: {=_xlfn._xlws.FILTER(Table3[Week '#],(Table3[Start Date]<=Table6[[#This Row],[Date]])*(Table3[End Date]>=Table6[[#This Row],[Date]]),"")} -> Week 1 | P7: P1 | Q7: Week 2 | R7: 46027 | S7: 46033 | T7: 27138.13
B8: P1 | C8: Week 3 | D8: =+E7+1 -> 46034 | E8: =Table3[[#This Row],[Start Date]]+6 -> 46040 | F8: Period 1 | H8: 20251231 | I8: 1515268 | J8: 1850 | K8: 4252 | L8: =DATE(LEFT(H8,4),MID(H8,5,2),RIGHT(H8,2)) -> 46022 | M8: =TEXT(L8,"DDDD") -> Wednesday | N8: {=_xlfn._xlws.FILTER(Table3[Week '#],(Table3[Start Date]<=Table6[[#This Row],[Date]])*(Table3[End Date]>=Table6[[#This Row],[Date]]),"")} -> Week 1 | P8: P1 | Q8: Week 3 | R8: 46034 | S8: 46040 | T8: 25872
B9: P1 | C9: Week 4 | D9: =+E8+1 -> 46041 | E9: =Table3[[#This Row],[Start Date]]+6 -> 46047 | F9: Period 2 | H9: 20260101 | I9: 398848.39 | J9: 1285 | K9: 3192 | L9: =DATE(LEFT(H9,4),MID(H9,5,2),RIGHT(H9,2)) -> 46023 | M9: =TEXT(L9,"DDDD") -> Thursday | N9: {=_xlfn._xlws.FILTER(Table3[Week '#],(Table3[Start Date]<=Table6[[#This Row],[Date]])*(Table3[End Date]>=Table6[[#This Row],[Date]]),"")} -> Week 1 | P9: P1 | Q9: Week 4 | R9: 46041 | S9: 46047 | T9: 19485.47
B10: P2 | C10: Week 5 | D10: =+E9+1 -> 46048 | E10: =Table3[[#This Row],[Start Date]]+6 -> 46054 | F10: Period 2 | H10: 20260102 | I10: 514278.04 | J10: 1768 | K10: 4087 | L10: =DATE(LEFT(H10,4),MID(H10,5,2),RIGHT(H10,2)) -> 46024 | M10: =TEXT(L10,"DDDD") -> Friday | N10: {=_xlfn._xlws.FILTER(Table3[Week '#],(Table3[Start Date]<=Table6[[#This Row],[Date]])*(Table3[End Date]>=Table6[[#This Row],[Date]]),"")} -> Week 1 | P10: P2 | Q10: Week 5 | R10: 46048 | S10: 46054 | T10: 25498.07
B11: P2 | C11: Week 6 | D11: =+E10+1 -> 46055 | E11: =Table3[[#This Row],[Start Date]]+6 -> 46061 | F11: Period 2 | H11: 20260103 | I11: 756008.97 | J11: 2673 | K11: 7579 | L11: =DATE(LEFT(H11,4),MID(H11,5,2),RIGHT(H11,2)) -> 46025 | M11: =TEXT(L11,"DDDD") -> Saturday | N11: {=_xlfn._xlws.FILTER(Table3[Week '#],(Table3[Start Date]<=Table6[[#This Row],[Date]])*(Table3[End Date]>=Table6[[#This Row],[Date]]),"")} -> Week 1 | P11: P2 | Q11: Week 6 | R11: 46055 | S11: 46061 | T11: 17785.49
B12: P2 | C12: Week 7 | D12: =+E11+1 -> 46062 | E12: =Table3[[#This Row],[Start Date]]+6 -> 46068 | F12: Period 2 | H12: 20260104 | I12: 421022.34 | J12: 1406 | K12: 3316 | L12: =DATE(LEFT(H12,4),MID(H12,5,2),RIGHT(H12,2)) -> 46026 | M12: =TEXT(L12,"DDDD") -> Sunday | N12: {=_xlfn._xlws.FILTER(Table3[Week '#],(Table3[Start Date]<=Table6[[#This Row],[Date]])*(Table3[End Date]>=Table6[[#This Row],[Date]]),"")} -> Week 1 | P12: P2 | Q12: Week 7 | R12: 46062 | S12: 46068 | T12: 19543.79
B13: P2 | C13: Week 8 | D13: =+E12+1 -> 46069 | E13: =Table3[[#This Row],[Start Date]]+6 -> 46075 | F13: Period 3 | H13: 20260105 | I13: 180439.84 | J13: 460 | K13: 1088 | L13: =DATE(LEFT(H13,4),MID(H13,5,2),RIGHT(H13,2)) -> 46027 | M13: =TEXT(L13,"DDDD") -> Monday | N13: {=_xlfn._xlws.FILTER(Table3[Week '#],(Table3[Start Date]<=Table6[[#This Row],[Date]])*(Table3[End Date]>=Table6[[#This Row],[Date]]),"")} -> Week 2 | P13: P2 | Q13: Week 8 | R13: 46069 | S13: 46075 | T13: 14781.81
B14: P3 | C14: Week 9 | D14: =+E13+1 -> 46076 | E14: =Table3[[#This Row],[Start Date]]+6 -> 46082 | F14: Period 3 | H14: 20260106 | I14: 148250.4 | J14: 627 | K14: 1271 | L14: =DATE(LEFT(H14,4),MID(H14,5,2),RIGHT(H14,2)) -> 46028 | M14: =TEXT(L14,"DDDD") -> Tuesday | N14: {=_xlfn._xlws.FILTER(Table3[Week '#],(Table3[Start Date]<=Table6[[#This Row],[Date]])*(Table3[End Date]>=Table6[[#This Row],[Date]]),"")} -> Week 2 | P14: P3 | Q14: Week 9 | R14: 46076 | S14: 46082 | T14: 37196.71
B15: P3 | C15: Week 10 | D15: =+E14+1 -> 46083 | E15: =Table3[[#This Row],[Start Date]]+6 -> 46089 | F15: Period 3 | H15: 20260107 | I15: 304728.96 | J15: 403 | K15: 1357 | L15: =DATE(LEFT(H15,4),MID(H15,5,2),RIGHT(H15,2)) -> 46029 | M15: =TEXT(L15,"DDDD") -> Wednesday | N15: {=_xlfn._xlws.FILTER(Table3[Week '#],(Table3[Start Date]<=Table6[[#This Row],[Date]])*(Table3[End Date]>=Table6[[#This Row],[Date]]),"")} -> Week 2 | P15: P3 | Q15: Week 10 | R15: 46083 | S15: 46089 | T15: 18728.15
B16: P3 | C16: Week 11 | D16: =+E15+1 -> 46090 | E16: =Table3[[#This Row],[Start Date]]+6 -> 46096 | F16: Period 3 | H16: 20260108 | I16: 276687.96 | J16: 1008 | K16: 2498 | L16: =DATE(LEFT(H16,4),MID(H16,5,2),RIGHT(H16,2)) -> 46030 | M16: =TEXT(L16,"DDDD") -> Thursday | N16: {=_xlfn._xlws.FILTER(Table3[Week '#],(Table3[Start Date]<=Table6[[#This Row],[Date]])*(Table3[End Date]>=Table6[[#This Row],[Date]]),"")} -> Week 2 | P16: P3 | Q16: Week 11 | R16: 46090 | S16: 46096 | T16: 54236.2
B17: P3 | C17: Week 12 | D17: =+E16+1 -> 46097 | E17: =Table3[[#This Row],[Start Date]]+6 -> 46103 | F17: Period 3 | H17: 20260109 | I17: 446916.64 | J17: 1702 | K17: 4372 | L17: =DATE(LEFT(H17,4),MID(H17,5,2),RIGHT(H17,2)) -> 46031 | M17: =TEXT(L17,"DDDD") -> Friday | N17: {=_xlfn._xlws.FILTER(Table3[Week '#],(Table3[Start Date]<=Table6[[#This Row],[Date]])*(Table3[End Date]>=Table6[[#This Row],[Date]]),"")} -> Week 2 | P17: P3 | Q17: Week 12 | R17: 46097 | S17: 46103 | T17: 23589.84
B18: P3 | C18: Week 13 | D18: =+E17+1 -> 46104 | E18: =Table3[[#This Row],[Start Date]]+6 -> 46110 | F18: Period 4 | H18: 20260110 | I18: 796057.2 | J18: 2249 | K18: 5255 | L18: =DATE(LEFT(H18,4),MID(H18,5,2),RIGHT(H18,2)) -> 46032 | M18: =TEXT(L18,"DDDD") -> Saturday | N18: {=_xlfn._xlws.FILTER(Table3[Week '#],(Table3[Start Date]<=Table6[[#This Row],[Date]])*(Table3[End Date]>=Table6[[#This Row],[Date]]),"")} -> Week 2 | P18: P3 | Q18: Week 13 | R18: 46104 | S18: 46110 | T18: 13744.82
... B39: P8 | C39: Week 34 | D39: =+E38+1 -> 46251 | E39: =Table3[[#This Row],[Start Date]]+6 -> 46257 | F39: Period 9 | H39: 20260131 | I39: 646873.68 | J39: 2238 | K39: 5396 | L39: =DATE(LEFT(H39,4),MID(H39,5,2),RIGHT(H39,2)) -> 46053 | M39: =TEXT(L39,"DDDD") -> Saturday | N39: {=_xlfn._xlws.FILTER(Table3[Week '#],(Table3[Start Date]<=Table6[[#This Row],[Date]])*(Table3[End Date]>=Table6[[#This Row],[Date]]),"")} -> Week 5 | P39: P8 | Q39: Week 34 | R39: 46251 | S39: 46257 | T39: 5552.87
B40: P9 | C40: Week 35 | D40: =+E39+1 -> 46258 | E40: =Table3[[#This Row],[Start Date]]+6 -> 46264 | F40: Period 9 | H40: 20260201 | I40: 408520.4 | J40: 1293 | K40: 3259 | L40: =DATE(LEFT(H40,4),MID(H40,5,2),RIGHT(H40,2)) -> 46054 | M40: =TEXT(L40,"DDDD") -> Sunday | N40: {=_xlfn._xlws.FILTER(Table3[Week '#],(Table3[Start Date]<=Table6[[#This Row],[Date]])*(Table3[End Date]>=Table6[[#This Row],[Date]]),"")} -> Week 5 | P40: P9 | Q40: Week 35 | R40: 46258 | S40: 46264
B41: P9 | C41: Week 36 | D41: =+E40+1 -> 46265 | E41: =Table3[[#This Row],[Start Date]]+6 -> 46271 | F41: Period 9 | H41: 20260202 | I41: 138461.05 | J41: 365 | K41: 894 | L41: =DATE(LEFT(H41,4),MID(H41,5,2),RIGHT(H41,2)) -> 46055 | M41: =TEXT(L41,"DDDD") -> Monday | N41: {=_xlfn._xlws.FILTER(Table3[Week '#],(Table3[Start Date]<=Table6[[#This Row],[Date]])*(Table3[End Date]>=Table6[[#This Row],[Date]]),"")} -> Week 6 | P41: P9 | Q41: Week 36 | R41: 46265 | S41: 46271
B42: P9 | C42: Week 37 | D42: =+E41+1 -> 46272 | E42: =Table3[[#This Row],[Start Date]]+6 -> 46278 | F42: Period 9 | H42: 20260203 | I42: 265419.65 | J42: 462 | K42: 1539 | L42: =DATE(LEFT(H42,4),MID(H42,5,2),RIGHT(H42,2)) -> 46056 | M42: =TEXT(L42,"DDDD") -> Tuesday | N42: {=_xlfn._xlws.FILTER(Table3[Week '#],(Table3[Start Date]<=Table6[[#This Row],[Date]])*(Table3[End Date]>=Table6[[#This Row],[Date]]),"")} -> Week 6 | P42: P9 | Q42: Week 37 | R42: 46272 | S42: 46278
B43: P9 | C43: Week 38 | D43: =+E42+1 -> 46279 | E43: =Table3[[#This Row],[Start Date]]+6 -> 46285 | F43: Period 9 | H43: 20260204 | I43: 343983.63 | J43: 966 | K43: 2316 | L43: =DATE(LEFT(H43,4),MID(H43,5,2),RIGHT(H43,2)) -> 46057 | M43: =TEXT(L43,"DDDD") -> Wednesday | N43: {=_xlfn._xlws.FILTER(Table3[Week '#],(Table3[Start Date]<=Table6[[#This Row],[Date]])*(Table3[End Date]>=Table6[[#This Row],[Date]]),"")} -> Week 6 | P43: P9 | Q43: Week 38 | R43: 46279 | S43: 46285
B44: P9 | C44: Week 39 | D44: =+E43+1 -> 46286 | E44: =Table3[[#This Row],[Start Date]]+6 -> 46292 | F44: Period 10 | H44: 20260205 | I44: 368173.01 | J44: 1248 | K44: 2747 | L44: =DATE(LEFT(H44,4),MID(H44,5,2),RIGHT(H44,2)) -> 46058 | M44: =TEXT(L44,"DDDD") -> Thursday | N44: {=_xlfn._xlws.FILTER(Table3[Week '#],(Table3[Start Date]<=Table6[[#This Row],[Date]])*(Table3[End Date]>=Table6[[#This Row],[Date]]),"")} -> Week 6 | P44: P9 | Q44: Week 39 | R44: 46286 | S44: 46292
B45: P10 | C45: Week 40 | D45: =+E44+1 -> 46293 | E45: =Table3[[#This Row],[Start Date]]+6 -> 46299 | F45: Period 10 | H45: 20260206 | I45: 525992.3 | J45: 2066 | K45: 4463 | L45: =DATE(LEFT(H45,4),MID(H45,5,2),RIGHT(H45,2)) -> 46059 | M45: =TEXT(L45,"DDDD") -> Friday | N45: {=_xlfn._xlws.FILTER(Table3[Week '#],(Table3[Start Date]<=Table6[[#This Row],[Date]])*(Table3[End Date]>=Table6[[#This Row],[Date]]),"")} -> Week 6 | P45: P10 | Q45: Week 40 | R45: 46293 | S45: 46299
B46: P10 | C46: Week 41 | D46: =+E45+1 -> 46300 | E46: =Table3[[#This Row],[Start Date]]+6 -> 46306 | F46: Period 10 | H46: 20260207 | I46: 677501.44 | J46: 2435 | K46: 5769 | L46: =DATE(LEFT(H46,4),MID(H46,5,2),RIGHT(H46,2)) -> 46060 | M46: =TEXT(L46,"DDDD") -> Saturday | N46: {=_xlfn._xlws.FILTER(Table3[Week '#],(Table3[Start Date]<=Table6[[#This Row],[Date]])*(Table3[End Date]>=Table6[[#This Row],[Date]]),"")} -> Week 6 | P46: P10 | Q46: Week 41 | R46: 46300 | S46: 46306
B47: P10 | C47: Week 42 | D47: =+E46+1 -> 46307 | E47: =Table3[[#This Row],[Start Date]]+6 -> 46313 | F47: Period 10 | H47: 20260208 | I47: 348128.73 | J47: 1160 | K47: 2781 | L47: =DATE(LEFT(H47,4),MID(H47,5,2),RIGHT(H47,2)) -> 46061 | M47: =TEXT(L47,"DDDD") -> Sunday | N47: {=_xlfn._xlws.FILTER(Table3[Week '#],(Table3[Start Date]<=Table6[[#This Row],[Date]])*(Table3[End Date]>=Table6[[#This Row],[Date]]),"")} -> Week 6 | P47: P10 | Q47: Week 42 | R47: 46307 | S47: 46313
B48: P10 | C48: Week 43 | D48: =+E47+1 -> 46314 | E48: =Table3[[#This Row],[Start Date]]+6 -> 46320 | F48: Period 11 | H48: 20260209 | I48: 176290.38 | J48: 463 | K48: 1284 | L48: =DATE(LEFT(H48,4),MID(H48,5,2),RIGHT(H48,2)) -> 46062 | M48: =TEXT(L48,"DDDD") -> Monday | N48: {=_xlfn._xlws.FILTER(Table3[Week '#],(Table3[Start Date]<=Table6[[#This Row],[Date]])*(Table3[End Date]>=Table6[[#This Row],[Date]]),"")} -> Week 7 | P48: P10 | Q48: Week 43 | R48: 46314 | S48: 46320
B49: P11 | C49: Week 44 | D49: =+E48+1 -> 46321 | E49: =Table3[[#This Row],[Start Date]]+6 -> 46327 | F49: Period 11 | H49: 20260210 | I49: 231050.9 | J49: 520 | K49: 1444 | L49: =DATE(LEFT(H49,4),MID(H49,5,2),RIGHT(H49,2)) -> 46063 | M49: =TEXT(L49,"DDDD") -> Tuesday | N49: {=_xlfn._xlws.FILTER(Table3[Week '#],(Table3[Start Date]<=Table6[[#This Row],[Date]])*(Table3[End Date]>=Table6[[#This Row],[Date]]),"")} -> Week 7 | P49: P11 | Q49: Week 44 | R49: 46321 | S49: 46327
B50: P11 | C50: Week 45 | D50: =+E49+1 -> 46328 | E50: =Table3[[#This Row],[Start Date]]+6 -> 46334 | F50: Period 11 | H50: 20260211 | I50: 274089.49 | J50: 869 | K50: 2197 | L50: =DATE(LEFT(H50,4),MID(H50,5,2),RIGHT(H50,2)) -> 46064 | M50: =TEXT(L50,"DDDD") -> Wednesday | N50: {=_xlfn._xlws.FILTER(Table3[Week '#],(Table3[Start Date]<=Table6[[#This Row],[Date]])*(Table3[End Date]>=Table6[[#This Row],[Date]]),"")} -> Week 7 | P50: P11 | Q50: Week 45 | R50: 46328 | S50: 46334
B51: P11 | C51: Week 46 | D51: =+E50+1 -> 46335 | E51: =Table3[[#This Row],[Start Date]]+6 -> 46341 | F51: Period 11 | H51: 20260212 | I51: 386111.41 | J51: 1426 | K51: 3087 | L51: =DATE(LEFT(H51,4),MID(H51,5,2),RIGHT(H51,2)) -> 46065 | M51: =TEXT(L51,"DDDD") -> Thursday | N51: {=_xlfn._xlws.FILTER(Table3[Week '#],(Table3[Start Date]<=Table6[[#This Row],[Date]])*(Table3[End Date]>=Table6[[#This Row],[Date]]),"")} -> Week 7 | P51: P11 | Q51: Week 46 | R51: 46335 | S51: 46341
... B57: P12 | C57: Week 52 | D57: =+E56+1 -> 46377 | E57: =Table3[[#This Row],[Start Date]]+6 -> 46383 | F57: Period 12 | H57: 20260218 | I57: 285714.75 | J57: 947 | K57: 2256 | L57: =DATE(LEFT(H57,4),MID(H57,5,2),RIGHT(H57,2)) -> 46071 | M57: =TEXT(L57,"DDDD") -> Wednesday | N57: {=_xlfn._xlws.FILTER(Table3[Week '#],(Table3[Start Date]<=Table6[[#This Row],[Date]])*(Table3[End Date]>=Table6[[#This Row],[Date]]),"")} -> Week 8 | P57: P12 | Q57: Week 52 | R57: 46377 | S57: 46383
H58: 20260219 | I58: 401170.22 | J58: 1428 | K58: 3067 | L58: =DATE(LEFT(H58,4),MID(H58,5,2),RIGHT(H58,2)) -> 46072 | M58: =TEXT(L58,"DDDD") -> Thursday | N58: {=_xlfn._xlws.FILTER(Table3[Week '#],(Table3[Start Date]<=Table6[[#This Row],[Date]])*(Table3[End Date]>=Table6[[#This Row],[Date]]),"")} -> Week 8
H59: 20260220 | I59: 498937.45 | J59: 1826 | K59: 4178 | L59: =DATE(LEFT(H59,4),MID(H59,5,2),RIGHT(H59,2)) -> 46073 | M59: =TEXT(L59,"DDDD") -> Friday | N59: {=_xlfn._xlws.FILTER(Table3[Week '#],(Table3[Start Date]<=Table6[[#This Row],[Date]])*(Table3[End Date]>=Table6[[#This Row],[Date]]),"")} -> Week 8
H60: 20260221 | I60: 743869.34 | J60: 2360 | K60: 5659 | L60: =DATE(LEFT(H60,4),MID(H60,5,2),RIGHT(H60,2)) -> 46074 | M60: =TEXT(L60,"DDDD") -> Saturday | N60: {=_xlfn._xlws.FILTER(Table3[Week '#],(Table3[Start Date]<=Table6[[#This Row],[Date]])*(Table3[End Date]>=Table6[[#This Row],[Date]]),"")} -> Week 8
H61: 20260222 | I61: 582041.7 | J61: 1794 | K61: 4034 | L61: =DATE(LEFT(H61,4),MID(H61,5,2),RIGHT(H61,2)) -> 46075 | M61: =TEXT(L61,"DDDD") -> Sunday | N61: {=_xlfn._xlws.FILTER(Table3[Week '#],(Table3[Start Date]<=Table6[[#This Row],[Date]])*(Table3[End Date]>=Table6[[#This Row],[Date]]),"")} -> Week 8
H62: 20260223 | I62: 214497.37 | J62: 293 | K62: 873 | L62: =DATE(LEFT(H62,4),MID(H62,5,2),RIGHT(H62,2)) -> 46076 | M62: =TEXT(L62,"DDDD") -> Monday | N62: {=_xlfn._xlws.FILTER(Table3[Week '#],(Table3[Start Date]<=Table6[[#This Row],[Date]])*(Table3[End Date]>=Table6[[#This Row],[Date]]),"")} -> Week 9
H63: 20260224 | I63: 305144.39 | J63: 648 | K63: 1910 | L63: =DATE(LEFT(H63,4),MID(H63,5,2),RIGHT(H63,2)) -> 46077 | M63: =TEXT(L63,"DDDD") -> Tuesday | N63: {=_xlfn._xlws.FILTER(Table3[Week '#],(Table3[Start Date]<=Table6[[#This Row],[Date]])*(Table3[End Date]>=Table6[[#This Row],[Date]]),"")} -> Week 9
H64: 20260225 | I64: 378669.84 | J64: 956 | K64: 2761 | L64: =DATE(LEFT(H64,4),MID(H64,5,2),RIGHT(H64,2)) -> 46078 | M64: =TEXT(L64,"DDDD") -> Wednesday | N64: {=_xlfn._xlws.FILTER(Table3[Week '#],(Table3[Start Date]<=Table6[[#This Row],[Date]])*(Table3[End Date]>=Table6[[#This Row],[Date]]),"")} -> Week 9
H65: 20260226 | I65: 442314.83 | J65: 1283 | K65: 3479 | L65: =DATE(LEFT(H65,4),MID(H65,5,2),RIGHT(H65,2)) -> 46079 | M65: =TEXT(L65,"DDDD") -> Thursday | N65: {=_xlfn._xlws.FILTER(Table3[Week '#],(Table3[Start Date]<=Table6[[#This Row],[Date]])*(Table3[End Date]>=Table6[[#This Row],[Date]]),"")} -> Week 9
H66: 20260227 | I66: 571916.98 | J66: 1865 | K66: 4372 | L66: =DATE(LEFT(H66,4),MID(H66,5,2),RIGHT(H66,2)) -> 46080 | M66: =TEXT(L66,"DDDD") -> Friday | N66: {=_xlfn._xlws.FILTER(Table3[Week '#],(Table3[Start Date]<=Table6[[#This Row],[Date]])*(Table3[End Date]>=Table6[[#This Row],[Date]]),"")} -> Week 9
H67: 20260228 | I67: 783311.22 | J67: 2398 | K67: 5711 | L67: =DATE(LEFT(H67,4),MID(H67,5,2),RIGHT(H67,2)) -> 46081 | M67: =TEXT(L67,"DDDD") -> Saturday | N67: {=_xlfn._xlws.FILTER(Table3[Week '#],(Table3[Start Date]<=Table6[[#This Row],[Date]])*(Table3[End Date]>=Table6[[#This Row],[Date]]),"")} -> Week 9
H68: 20260301 | I68: 571775.35 | J68: 1717 | K68: 4672 | L68: =DATE(LEFT(H68,4),MID(H68,5,2),RIGHT(H68,2)) -> 46082 | M68: =TEXT(L68,"DDDD") -> Sunday | N68: {=_xlfn._xlws.FILTER(Table3[Week '#],(Table3[Start Date]<=Table6[[#This Row],[Date]])*(Table3[End Date]>=Table6[[#This Row],[Date]]),"")} -> Week 9
H69: 20260302 | I69: 173978.48 | J69: 470 | K69: 1142 | L69: =DATE(LEFT(H69,4),MID(H69,5,2),RIGHT(H69,2)) -> 46083 | M69: =TEXT(L69,"DDDD") -> Monday | N69: {=_xlfn._xlws.FILTER(Table3[Week '#],(Table3[Start Date]<=Table6[[#This Row],[Date]])*(Table3[End Date]>=Table6[[#This Row],[Date]]),"")} -> Week 10
... H243: 20260823 | I243: 303791.78 | J243: 1217 | K243: 2751 | L243: =DATE(LEFT(H243,4),MID(H243,5,2),RIGHT(H243,2)) -> 46257 | M243: =TEXT(L243,"DDDD") -> Sunday | N243: {=_xlfn._xlws.FILTER(Table3[Week '#],(Table3[Start Date]<=Table6[[#This Row],[Date]])*(Table3[End Date]>=Table6[[#This Row],[Date]]),"")} -> Week 34

Sheet Actual - 2026
A2: RDG OPS | E2: MILA 3F - 2026 | H2: MILA 3F - 2026 | K2: MILA 3F - 2026 | N2: MILA 2F - 2026 | Q2: MILA 2F - 2026 | T2: MILA 2F - 2026 | W2: MILA 2F - 2026 | Z2: AVA WP - 2026 | AC2: AVA WP - 2026 | AF2: AVA WP - 2026 | AI2: AVA WP - 2025 | AL2: CASA NEOS - 2026 | AO2: CASA NEOS - 2026 | AR2: CASA NEOS - 2026 | AU2: CLAUDIE - 2026 | AX2: CLAUDIE - 2026 | BA2: CLAUDIE - 2026 | BD2: AVA CG - 2026 | BG2: AVA CG - 2026 | BJ2: AVA CG - 2026 | BM2: AVA CG - 2026 | BP2: CASA NEOS LOUNGE - 2026 | BS2: CASA NEOS LOUNGE - 2026 | BV2: CASA NEOS LOUNGE - 2026 | BY2: AVA CG - 2025 | CB2: AVA CG - 2025 | CE2: AVA CG - 2025 | CH2: AVA CG - 2025
E3: Dinner | H3: Brunch | K3: Total | N3: Omakase | Q3: MM | T3: Lounge | W3: Total | Z3: Dinner | AC3: Brunch | AF3: MM | AI3: Total | AL3: Brunch | AO3: Dinner | AR3: Total | AU3: Brunch | AX3: Dinner | BA3: Total | BD3: Dinner | BG3: Brunch | BJ3: MM | BM3: Total | BP3: Lounge | BS3: MM | BV3: Total | BY3: Dinner | CB3: Brunch | CE3: MM | CH3: Total
E4: Sales | F4: Covers | G4: avg ck | H4: Sales | I4: Covers | J4: avg ck | K4: Total Sales | L4: Covers | M4: avg ck | N4: Sales | O4: Covers | P4: avg ck | Q4: Sales | R4: Covers | S4: avg ck | T4: Sales | U4: Covers | V4: avg ck | W4: Total Sales | X4: Covers | Y4: avg ck | Z4: Sales | AA4: Covers | AB4: avg ck | AC4: Sales | AD4: Covers | AE4: avg ck | AF4: Sales | AG4: Covers | AH4: avg ck | AI4: Total Sales | AJ4: Covers | AK4: avg ck | AL4: Sales | AM4: Covers | AN4: avg ck | AO4: Sales | AP4: Covers | AQ4: avg ck | AR4: Total Sales | AS4: Covers | AT4: avg ck | AU4: Sales | AV4: Covers | AW4: avg ck | AX4: Sales | AY4: Covers | AZ4: avg ck | BA4: Total Sales | BB4: Covers | BC4: avg ck | BD4: Sales | BE4: Covers | BF4: avg ck | BG4: Sales | BH4: Covers | BI4: avg ck | BJ4: Sales | BK4: Covers | BL4: avg ck | BM4: Total Sales | BN4: Covers | BO4: avg ck | BP4: Sales | BQ4: Covers | BR4: avg ck | BS4: Sales | BT4: Covers | BU4: avg ck | BV4: Total Sales | BW4: Covers | BX4: avg ck | BY4: Sales | BZ4: Covers | CA4: avg ck | CB4: Sales | CC4: Covers | CD4: avg ck | CE4: Sales | CF4: Covers | CG4: avg ck | CH4: Sales | CI4: Covers | CJ4: avg ck
A5: Week 1 | B5: P1 | C5: =VLOOKUP(A5,Dates!$B$2:$E$53,4,FALSE) -> 1 | D5: =IF(C5<='RDG Weekly Sales'!$F$1,TRUE,FALSE) -> TRUE | E5: =1102583.42-H5-694.45 -> 1054246.3 | F5: =6073-I5 -> 5640 | G5: =IFERROR(E5/F5,"") -> 186.9231 | H5: 47642.7 | I5: 433 | J5: =IFERROR(H5/I5,"") -> 110.02933 | K5: =E5+H5 -> 1101889 | L5: =F5+I5 -> 6073 | M5: =IFERROR(K5/L5,"") -> 181.44063 | N5: 37270 | O5: 94 | P5: =IFERROR(N5/O5,"") -> 396.48936 | Q5: =140722.92+33178 -> 173900.92 | R5: =127+138+2+79+88+130+118+2 -> 684 | S5: =IFERROR(Q5/R5,"") -> 254.24111 | T5: =519097.55+73494-362.61 -> 592228.94 | U5: =258+13+279+17+207+10+223+22+242+18+221+15 -> 1525 | V5: =IFERROR(T5/U5,"") -> 388.34685 | W5: =SUM(N5,Q5,T5) -> 803399.86 | X5: =SUM(O5,R5,U5) -> 2303 | Y5: =IFERROR(W5/X5,"") -> 348.84927 | Z5: =256579.58-AC5-361.6 -> 228189.62 | AA5: =2290-AD5 -> 1916 | AB5: =IFERROR(Z5/AA5,"") -> 119.09688 | AC5: 28028.36 | AD5: =180+194 -> 374 | AE5: =IFERROR(AC5/AD5,"") -> 74.942139 | AF5: =44840.44-521.92 -> 44318.52 | AG5: =57+26+52+69 -> 204 | AH5: =IFERROR(AF5/AG5,"") -> 217.24765 | AI5: =Z5+AF5+AC5 -> 300536.5 | AJ5: =AA5+AG5+AD5 -> 2494 | AK5: =IFERROR(AI5/AJ5,"") -> 120.50381 | AL5: 148498.5 | AM5: =529+573 -> 1102 | AN5: =IFERROR(AL5/AM5,"") -> 134.75363 | AO5: =1639708.27-2309.94-AL5 -> 1488899.8 | AP5: =6146-AM5 -> 5044 | AQ5: =IFERROR(AO5/AP5,"") -> 295.18236 | AR5: =AO5+AL5 -> 1637398.3 | AS5: =AP5+AM5 -> 6146 | AT5: =IFERROR(AR5/AS5,"") -> 266.41691 | AW5: =IFERROR(AU5/AV5,0) -> 0 | AX5: =574241.19-354.85-AU5 -> 573886.34 | AY5: 2831 | AZ5: =IFERROR(AX5/AY5,"") -> 202.71506 | BA5: =AX5+AU5 -> 573886.34 | BB5: =AY5+AV5 -> 2831 | BC5: =IFERROR(BA5/BB5,"") -> 202.71506 | BD5: =258336.81-104.4-BG5-BJ5 -> 245767.89 | BE5: =1726-BH5-BK5 -> 1553 | BF5: =IFERROR(BD5/BE5,"") -> 158.25363 | BG5: 12464.52 | BH5: =87+86 -> 173 | BI5: =IFERROR(BG5/BH5,"") -> 72.049249 | BL5: =IFERROR(BJ5/BK5,"") | BM5: =BD5+BJ5+BG5 -> 258232.41 | BN5: =BE5+BK5+BH5 -> 1726 | BO5: =IFERROR(BM5/BN5,"") -> 149.61322 | BP5: 0 | BQ5: 0 | BR5: =IFERROR(BP5/BQ5,"") | BS5: 0 | BT5: 0 | BU5: =IFERROR(BS5/BT5,"") | BV5: =+BP5+BS5 -> 0 | BW5: =BT5+BQ5 -> 0 | BX5: =IFERROR(BV5/BW5,"") | BY5: 0 | BZ5: 0 | CA5: =IFERROR(BY5/BZ5,"") | CB5: 0 | CC5: 0 | CD5: =IFERROR(CB5/CC5,"") | CG5: =IFERROR(CE5/CF5,"") | CH5: =BY5+CE5+CB5 -> 0 | CI5: =BZ5+CF5+CC5 -> 0 | CJ5: =IFERROR(CH5/CI5,"")
A6: Week 2 | B6: P1 | C6: =VLOOKUP(A6,Dates!$B$2:$E$53,4,FALSE) -> 2 | D6: =IF(C6<='RDG Weekly Sales'!$F$1,TRUE,FALSE) -> TRUE | E6: =880177.35-13716.72-H6-62000 -> 751094.63 | F6: =4397-I6 -> 4056 | G6: =IFERROR(E6/F6,"") -> 185.18112 | H6: 53366 | I6: 341 | J6: =IFERROR(H6/I6,"") -> 156.49853 | K6: =E6+H6 -> 804460.63 | L6: =F6+I6 -> 4397 | M6: =IFERROR(K6/L6,"") -> 182.9567 | N6: 18797 | O6: 66 | P6: =IFERROR(N6/O6,"") -> 284.80303 | Q6: =64479.17+45111 -> 109590.17 | R6: =2+45+104+114 -> 265 | S6: =IFERROR(Q6/R6,"") -> 413.54781 | T6: =201409.35+62707.18-9011.83+62000 -> 317104.7 | U6: =170+193+322+125 -> 810 | V6: =IFERROR(T6/U6,"") -> 391.48728 | W6: =SUM(N6,Q6,T6) -> 445491.87 | X6: =SUM(O6,R6,U6) -> 1141 | Y6: =IFERROR(W6/X6,"") -> 390.43985 | Z6: =192471.13-377.75-AC6 -> 166160.58 | AA6: =1965-AD6 -> 1577 | AB6: =IFERROR(Z6/AA6,"") -> 105.36498 | AC6: 25932.8 | AD6: =191+197 -> 388 | AE6: =IFERROR(AC6/AD6,"") -> 66.837113 | AF6: =25942.65-60.45 -> 25882.2 | AG6: =20+26+32+67+78 -> 223 | AH6: =IFERROR(AF6/AG6,"") -> 116.06368 | AI6: =Z6+AF6+AC6 -> 217975.58 | AJ6: =AA6+AG6+AD6 -> 2188 | AK6: =IFERROR(AI6/AJ6,"") -> 99.623208 | AL6: 158147.86 | AM6: =542+367 -> 909 | AN6: =IFERROR(AL6/AM6,"") -> 173.98004 | AO6: =679288.57-AL6-1727.5 -> 519413.21 | AP6: =3479-AM6 -> 2570 | AQ6: =IFERROR(AO6/AP6,"") -> 202.10631 | AR6: =AO6+AL6 -> 677561.07 | AS6: =AP6+AM6 -> 3479 | AT6: =IFERROR(AR6/AS6,"") -> 194.75742 | AW6: =IFERROR(AU6/AV6,0) -> 0 | AX6: =302340.95-AU6 -> 302340.95 | AY6: 1766 | AZ6: =IFERROR(AX6/AY6,"") -> 171.20099 | BA6: =AX6+AU6 -> 302340.95 | BB6: =AY6+AV6 -> 1766 | BC6: =IFERROR(BA6/BB6,"") -> 171.20099 | BD6: =198817.36-748.7-BG6 -> 184849.07 | BE6: =1562-BH6 -> 1396 | BF6: =IFERROR(BD6/BE6,"") -> 132.41337 | BG6: 13219.59 | BH6: =103+63 -> 166 | BI6: =IFERROR(BG6/BH6,"") -> 79.636084 | BL6: =IFERROR(BJ6/BK6,"") | BM6: =BD6+BJ6+BG6 -> 198068.66 | BN6: =BE6+BK6+BH6 -> 1562 | BO6: =IFERROR(BM6/BN6,"") -> 126.80452 | BP6: 0 | BQ6: 0 | BR6: =IFERROR(BP6/BQ6,"") | BS6: 0 | BT6: 0 | BU6: =IFERROR(BS6/BT6,"") | BV6: =+BP6+BS6 -> 0 | BW6: =BT6+BQ6 -> 0 | BX6: =IFERROR(BV6/BW6,"") | BY6: 0 | BZ6: 0 | CA6: =IFERROR(BY6/BZ6,"") | CB6: 0 | CC6: 0 | CD6: =IFERROR(CB6/CC6,"") | CG6: =IFERROR(CE6/CF6,"") | CH6: =BY6+CE6+CB6 -> 0 | CI6: =BZ6+CF6+CC6 -> 0 | CJ6: =IFERROR(CH6/CI6,"")
A7: Week 3 | B7: P1 | C7: =VLOOKUP(A7,Dates!$B$2:$E$53,4,FALSE) -> 3 | D7: =IF(C7<='RDG Weekly Sales'!$F$1,TRUE,FALSE) -> TRUE | E7: =928282.58-10682.07-H7 -> 850056.06 | F7: =4961-I7 -> 4497 | G7: =IFERROR(E7/F7,"") -> 189.02736 | H7: 67544.45 | I7: 464 | J7: =IFERROR(H7/I7,"") -> 145.56994 | K7: =E7+H7 -> 917600.51 | L7: =F7+I7 -> 4961 | M7: =IFERROR(K7/L7,"") -> 184.96281 | N7: 19544.75 | O7: 67 | P7: =IFERROR(N7/O7,"") -> 291.71269 | Q7: =87547.9+19112 -> 106659.9 | R7: =43+51+54+122+3+106+61 -> 440 | S7: =IFERROR(Q7/R7,"") -> 242.40886 | T7: =400126.75+36101.5 -> 436228.25 | U7: =60+98+217+256+15+247+15+122 -> 1030 | V7: =IFERROR(T7/U7,"") -> 423.52257 | W7: =SUM(N7,Q7,T7) -> 562432.9 | X7: =SUM(O7,R7,U7) -> 1537 | Y7: =IFERROR(W7/X7,"") -> 365.92902 | Z7: =205849.76-149.75-AC7 -> 179877.31 | AA7: =1930-AD7 -> 1557 | AB7: =IFERROR(Z7/AA7,"") -> 115.52814 | AC7: 25822.7 | AD7: =198+175 -> 373 | AE7: =IFERROR(AC7/AD7,"") -> 69.229759 | AF7: =36390.05-755.05 -> 35635 | AG7: 244 | AH7: =IFERROR(AF7/AG7,"") -> 146.04508 | AI7: =Z7+AF7+AC7 -> 241335.01 | AJ7: =AA7+AG7+AD7 -> 2174 | AK7: =IFERROR(AI7/AJ7,"") -> 111.00966 | AL7: 192827.35 | AM7: =726+381 -> 1107 | AN7: =IFERROR(AL7/AM7,"") -> 174.18911 | AO7: =748743.87-AL7-3171.55 -> 552744.97 | AP7: =4095-AM7 -> 2988 | AQ7: =IFERROR(AO7/AP7,"") -> 184.98828 | AR7: =AO7+AL7 -> 745572.32 | AS7: =AP7+AM7 -> 4095 | AT7: =IFERROR(AR7/AS7,"") -> 182.06894 | AW7: =IFERROR(AU7/AV7,0) -> 0 | AX7: =355272.03-1529.53-AU7 -> 353742.5 | AY7: 2057 | AZ7: =IFERROR(AX7/AY7,"") -> 171.9701 | BA7: =AX7+AU7 -> 353742.5 | BB7: =AY7+AV7 -> 2057 | BC7: =IFERROR(BA7/BB7,"") -> 171.9701 | BD7: =236324.62-533.55-BG7 -> 211945.97 | BE7: =2001-BH7 -> 1675 | BF7: =IFERROR(BD7/BE7,"") -> 126.53491 | BG7: 23845.1 | BH7: =208+118 -> 326 | BI7: =IFERROR(BG7/BH7,"") -> 73.144479 | BL7: =IFERROR(BJ7/BK7,"") | BM7: =BD7+BJ7+BG7 -> 235791.07 | BN7: =BE7+BK7+BH7 -> 2001 | BO7: =IFERROR(BM7/BN7,"") -> 117.83662 | BP7: 0 | BQ7: 0 | BR7: =IFERROR(BP7/BQ7,"") | BS7: 0 | BT7: 0 | BU7: =IFERROR(BS7/BT7,"") | BV7: =+BP7+BS7 -> 0 | BW7: =BT7+BQ7 -> 0 | BX7: =IFERROR(BV7/BW7,"") | BY7: 0 | BZ7: 0 | CA7: =IFERROR(BY7/BZ7,"") | CB7: 0 | CC7: 0 | CD7: =IFERROR(CB7/CC7,"") | CG7: =IFERROR(CE7/CF7,"") | CH7: =BY7+CE7+CB7 -> 0 | CI7: =BZ7+CF7+CC7 -> 0 | CJ7: =IFERROR(CH7/CI7,"")
A8: Week 4 | B8: P1 | C8: =VLOOKUP(A8,Dates!$B$2:$E$53,4,FALSE) -> 4 | D8: =IF(C8<='RDG Weekly Sales'!$F$1,TRUE,FALSE) -> TRUE | E8: =749054.32-H8-5728.22 -> 697530.35 | F8: =4463-I8 -> 4070 | G8: =IFERROR(E8/F8,"") -> 171.38338 | H8: 45795.75 | I8: =393 -> 393 | J8: =IFERROR(H8/I8,"") -> 116.52863 | K8: =E8+H8 -> 743326.1 | L8: =F8+I8 -> 4463 | M8: =IFERROR(K8/L8,"") -> 166.55301 | N8: 19994 | O8: 66 | P8: =IFERROR(N8/O8,"") -> 302.93939 | Q8: =81424.07+18061.5 -> 99485.57 | R8: =36+72+65+124+3+94 -> 394 | S8: =IFERROR(Q8/R8,"") -> 252.50145 | T8: =230113.95+37917.5-3194.02 -> 264837.43 | U8: =45+132+4+191+12+256+33+227+9 -> 909 | V8: =IFERROR(T8/U8,"") -> 291.35031 | W8: =SUM(N8,Q8,T8) -> 384317 | X8: =SUM(O8,R8,U8) -> 1369 | Y8: =IFERROR(W8/X8,"") -> 280.72827 | Z8: =197563.23-AC8-359.53 -> 185496.2 | AA8: =1817-AD8 -> 1629 | AB8: =IFERROR(Z8/AA8,"") -> 113.87121 | AC8: 11707.5 | AD8: =188 -> 188 | AE8: =IFERROR(AC8/AD8,"") -> 62.273936 | AF8: =43710.66-996.95 -> 42713.71 | AG8: =43+53+45+71 -> 212 | AH8: =IFERROR(AF8/AG8,"") -> 201.47976 | AI8: =Z8+AF8+AC8 -> 239917.41 | AJ8: =AA8+AG8+AD8 -> 2029 | AK8: =IFERROR(AI8/AJ8,"") -> 118.24416 | AL8: 142048.4 | AM8: =580+393 -> 973 | AN8: =IFERROR(AL8/AM8,"") -> 145.99013 | AO8: =727867.39-AL8-6332.27 -> 579486.72 | AP8: =3689-AM8 -> 2716 | AQ8: =IFERROR(AO8/AP8,"") -> 213.36035 | AR8: =AO8+AL8 -> 721535.12 | AS8: =AP8+AM8 -> 3689 | AT8: =IFERROR(AR8/AS8,"") -> 195.59098 | AW8: =IFERROR(AU8/AV8,0) -> 0 | AX8: =359346.45-2346.95-AU8 -> 356999.5 | AY8: 2001 | AZ8: =IFERROR(AX8/AY8,"") -> 178.41054 | BA8: =AX8+AU8 -> 356999.5 | BB8: =AY8+AV8 -> 2001 | BC8: =IFERROR(BA8/BB8,"") -> 178.41054 | BD8: =228875.32-BG8-527.53 -> 208987.07 | BE8: =1824-BH8 -> 1582 | BF8: =IFERROR(BD8/BE8,"") -> 132.10308 | BG8: 19360.72 | BH8: =152+90 -> 242 | BI8: =IFERROR(BG8/BH8,"") -> 80.002975 | BL8: =IFERROR(BJ8/BK8,"") | BM8: =BD8+BJ8+BG8 -> 228347.79 | BN8: =BE8+BK8+BH8 -> 1824 | BO8: =IFERROR(BM8/BN8,"") -> 125.19067 | BP8: 0 | BQ8: 0 | BR8: =IFERROR(BP8/BQ8,"") | BS8: 0 | BT8: 0 | BU8: =IFERROR(BS8/BT8,"") | BV8: =+BP8+BS8 -> 0 | BW8: =BT8+BQ8 -> 0 | BX8: =IFERROR(BV8/BW8,"") | BY8: 0 | BZ8: 0 | CA8: =IFERROR(BY8/BZ8,"") | CB8: 0 | CC8: 0 | CD8: =IFERROR(CB8/CC8,"") | CG8: =IFERROR(CE8/CF8,"") | CH8: =BY8+CE8+CB8 -> 0 | CI8: =BZ8+CF8+CC8 -> 0 | CJ8: =IFERROR(CH8/CI8,"")
A9: Week 5 | B9: P2 | C9: =VLOOKUP(A9,Dates!$B$2:$E$53,4,FALSE) -> 5 | D9: =IF(C9<='RDG Weekly Sales'!$F$1,TRUE,FALSE) -> TRUE | E9: =836326.2-H9-4662.7 -> 774111.65 | F9: =5072-I9 -> 4579 | G9: =IFERROR(E9/F9,"") -> 169.05692 | H9: 57551.85 | I9: 493 | J9: =IFERROR(H9/I9,"") -> 116.73803 | K9: =E9+H9 -> 831663.5 | L9: =F9+I9 -> 5072 | M9: =IFERROR(K9/L9,"") -> 163.97151 | N9: 28623 | O9: 85 | P9: =IFERROR(N9/O9,"") -> 336.74118 | Q9: =59528.9+33969.4 -> 93498.3 | R9: =50+72+92+88+143 -> 445 | S9: =IFERROR(Q9/R9,"") -> 210.10854 | T9: =200619.9+117516.48-6316.18 -> 311820.2 | U9: =95+167+210+15+196+234+16 -> 933 | V9: =IFERROR(T9/U9,"") -> 334.21243 | W9: =SUM(N9,Q9,T9) -> 433941.5 | X9: =SUM(O9,R9,U9) -> 1463 | Y9: =IFERROR(W9/X9,"") -> 296.61073 | Z9: =195857.3-1327.73-AC9 -> 173447.73 | AA9: =1745-AD9 -> 1467 | AB9: =IFERROR(Z9/AA9,"") -> 118.23294 | AC9: 21081.84 | AD9: =129+149 -> 278 | AE9: =IFERROR(AC9/AD9,"") -> 75.833957 | AF9: =36621-205.8 -> 36415.2 | AG9: =34+34+75+74 -> 217 | AH9: =IFERROR(AF9/AG9,"") -> 167.81198 | AI9: =Z9+AF9+AC9 -> 230944.77 | AJ9: =AA9+AG9+AD9 -> 1962 | AK9: =IFERROR(AI9/AJ9,"") -> 117.70885 | AL9: 139227.47 | AM9: =477+435 -> 912 | AN9: =IFERROR(AL9/AM9,"") -> 152.6617 | AO9: =700712.36-AL9-8191.18 -> 553293.71 | AP9: =3608-AM9 -> 2696 | AQ9: =IFERROR(AO9/AP9,"") -> 205.22764 | AR9: =AO9+AL9 -> 692521.18 | AS9: =AP9+AM9 -> 3608 | AT9: =IFERROR(AR9/AS9,"") -> 191.94046 | AW9: =IFERROR(AU9/AV9,0) -> 0 | AX9: =415269.59-3113.57-AU9 -> 412156.02 | AY9: 2192 | AZ9: =IFERROR(AX9/AY9,"") -> 188.02738 | BA9: =AX9+AU9 -> 412156.02 | BB9: =AY9+AV9 -> 2192 | BC9: =IFERROR(BA9/BB9,"") -> 188.02738 | BD9: =271809.13-1680.91-BG9 -> 199704.41 | BE9: =2367-BH9 -> 1681 | BF9: =IFERROR(BD9/BE9,"") -> 118.80096 | BG9: 70423.81 | BH9: =389+297 -> 686 | BI9: =IFERROR(BG9/BH9,"") -> 102.65862 | BL9: =IFERROR(BJ9/BK9,"") | BM9: =BD9+BJ9+BG9 -> 270128.22 | BN9: =BE9+BK9+BH9 -> 2367 | BO9: =IFERROR(BM9/BN9,"") -> 114.12261 | BP9: 0 | BQ9: 0 | BR9: =IFERROR(BP9/BQ9,"") | BS9: 0 | BT9: 0 | BU9: =IFERROR(BS9/BT9,"") | BV9: =+BP9+BS9 -> 0 | BW9: =BT9+BQ9 -> 0 | BX9: =IFERROR(BV9/BW9,"") | BY9: 0 | BZ9: 0 | CA9: =IFERROR(BY9/BZ9,"") | CB9: 0 | CC9: 0 | CD9: =IFERROR(CB9/CC9,"") | CG9: =IFERROR(CE9/CF9,"") | CH9: =BY9+CE9+CB9 -> 0 | CI9: =BZ9+CF9+CC9 -> 0 | CJ9: =IFERROR(CH9/CI9,"")
A10: Week 6 | B10: P2 | C10: =VLOOKUP(A10,Dates!$B$2:$E$53,4,FALSE) -> 6 | D10: =IF(C10<='RDG Weekly Sales'!$F$1,TRUE,FALSE) -> TRUE | E10: =731006.61-3761.5-H10 -> 687569.11 | F10: =4509-I10 -> 4155 | G10: =IFERROR(E10/F10,"") -> 165.47993 | H10: 39676 | I10: 354 | J10: =IFERROR(H10/I10,"") -> 112.0791 | K10: =E10+H10 -> 727245.11 | L10: =F10+I10 -> 4509 | M10: =IFERROR(K10/L10,"") -> 161.28745 | N10: 21827 | O10: 72 | P10: =IFERROR(N10/O10,"") -> 303.15278 | Q10: =54107+18849 -> 72956 | R10: =55+60+122+118+48+2 -> 405 | S10: =IFERROR(Q10/R10,"") -> 180.13827 | T10: =286154+37933-3156 -> 320931 | U10: =199+13+199+14+289+226+11+52 -> 1003 | V10: =IFERROR(T10/U10,"") -> 319.97109 | W10: =SUM(N10,Q10,T10) -> 415714 | X10: =SUM(O10,R10,U10) -> 1480 | Y10: =IFERROR(W10/X10,"") -> 280.88784 | Z10: =213194.1-716.27-AC10 -> 185434.58 | AA10: =1959-AD10 -> 1603 | AB10: =IFERROR(Z10/AA10,"") -> 115.67971 | AC10: 27043.25 | AD10: =182+174 -> 356 | AE10: =IFERROR(AC10/AD10,"") -> 75.964185 | AF10: =59727.82-1718.82 -> 58009 | AG10: =40+50+60+71+9 -> 230 | AH10: =IFERROR(AF10/AG10,"") -> 252.21304 | AI10: =Z10+AF10+AC10 -> 270486.83 | AJ10: =AA10+AG10+AD10 -> 2189 | AK10: =IFERROR(AI10/AJ10,"") -> 123.56639 | AL10: 123397.25 | AM10: =324+511 -> 835 | AN10: =IFERROR(AL10/AM10,"") -> 147.78114 | AO10: =608552.57-AL10-3344.5 -> 481810.82 | AP10: =3523-AM10 -> 2688 | AQ10: =IFERROR(AO10/AP10,"") -> 179.2451 | AR10: =AO10+AL10 -> 605208.07 | AS10: =AP10+AM10 -> 3523 | AT10: =IFERROR(AR10/AS10,"") -> 171.7877 | AU10: 0 | AV10: 0 | AW10: =IFERROR(AU10/AV10,0) -> 0 | AX10: =363175.5-3117.5-AU10 -> 360058 | AY10: 1720 | AZ10: =IFERROR(AX10/AY10,"") -> 209.33605 | BA10: =AX10+AU10 -> 360058 | BB10: =AY10+AV10 -> 1720 | BC10: =IFERROR(BA10/BB10,"") -> 209.33605 | BD10: =270813.62-1970.9-BG10 -> 202174.06 | BE10: =2180-BH10 -> 1552 | BF10: =IFERROR(BD10/BE10,"") -> 130.26679 | BG10: 66668.66 | BH10: =337+291 -> 628 | BI10: =IFERROR(BG10/BH10,"") -> 106.16029 | BL10: =IFERROR(BJ10/BK10,"") | BM10: =BD10+BJ10+BG10 -> 268842.72 | BN10: =BE10+BK10+BH10 -> 2180 | BO10: =IFERROR(BM10/BN10,"") -> 123.32235 | BP10: 0 | BQ10: 0 | BR10: =IFERROR(BP10/BQ10,"") | BS10: 0 | BT10: 0 | BU10: =IFERROR(BS10/BT10,"") | BV10: =+BP10+BS10 -> 0 | BW10: =BT10+BQ10 -> 0 | BX10: =IFERROR(BV10/BW10,"") | BY10: 0 | BZ10: 0 | CA10: =IFERROR(BY10/BZ10,"") | CB10: 0 | CC10: 0 | CD10: =IFERROR(CB10/CC10,"") | CG10: =IFERROR(CE10/CF10,"") | CH10: =BY10+CE10+CB10 -> 0 | CI10: =BZ10+CF10+CC10 -> 0 | CJ10: =IFERROR(CH10/CI10,"")
A11: Week 7 | B11: P2 | C11: =VLOOKUP(A11,Dates!$B$2:$E$53,4,FALSE) -> 7 | D11: =IF(C11<='RDG Weekly Sales'!$F$1,TRUE,FALSE) -> TRUE | E11: =879212.56-H11-11320.4 -> 792091.81 | F11: =4691-I11 -> 4250 | G11: =IFERROR(E11/F11,"") -> 186.37454 | H11: 75800.35 | I11: 441 | J11: =IFERROR(H11/I11,"") -> 171.88288 | K11: =E11+H11 -> 867892.16 | L11: =F11+I11 -> 4691 | M11: =IFERROR(K11/L11,"") -> 185.01219 | N11: 20641 | O11: 73 | P11: =IFERROR(N11/O11,"") -> 282.75342 | Q11: =82046.27+45619.75 -> 127666.02 | R11: =52+95+81+136+87+88+6 -> 545 | S11: =IFERROR(Q11/R11,"") -> 234.24958 | T11: =239340.23+35817-1843.15 -> 273314.08 | U11: =110+188+219+13+189+177 -> 896 | V11: =IFERROR(T11/U11,"") -> 305.03804 | W11: =SUM(N11,Q11,T11) -> 421621.1 | X11: =SUM(O11,R11,U11) -> 1514 | Y11: =IFERROR(W11/X11,"") -> 278.48157 | Z11: =267451.83-AC11-508 -> 233124.73 | AA11: =2450-AD11 -> 1983 | AB11: =IFERROR(Z11/AA11,"") -> 117.56164 | AC11: 33819.1 | AD11: =239+228 -> 467 | AE11: =IFERROR(AC11/AD11,"") -> 72.417773 | AF11: =37233.96-250 -> 36983.96 | AG11: =10+45+58+89 -> 202 | AH11: =IFERROR(AF11/AG11,"") -> 183.08891 | AI11: =Z11+AF11+AC11 -> 303927.79 | AJ11: =AA11+AG11+AD11 -> 2652 | AK11: =IFERROR(AI11/AJ11,"") -> 114.60324 | AL11: 188110.05 | AM11: =719+477 -> 1196 | AN11: =IFERROR(AL11/AM11,"") -> 157.28265 | AO11: =798739.68-AL11-3352.05 -> 607277.58 | AP11: =4313-AM11 -> 3117 | AQ11: =IFERROR(AO11/AP11,"") -> 194.82758 | AR11: =AO11+AL11 -> 795387.63 | AS11: =AP11+AM11 -> 4313 | AT11: =IFERROR(AR11/AS11,"") -> 184.41633 | AU11: 0 | AV11: 0 | AW11: =IFERROR(AU11/AV11,0) -> 0 | AX11: =436884.19-1395.99-AU11 -> 435488.2 | AY11: 2663 | AZ11: =IFERROR(AX11/AY11,"") -> 163.53293 | BA11: =AX11+AU11 -> 435488.2 | BB11: =AY11+AV11 -> 2663 | BC11: =IFERROR(BA11/BB11,"") -> 163.53293 | BD11: =297621.49-BG11-874.2 -> 238197.62 | BE11: =2450-BH11 -> 1744 | BF11: =IFERROR(BD11/BE11,"") -> 136.5812 | BG11: 58549.67 | BH11: =350+356 -> 706 | BI11: =IFERROR(BG11/BH11,"") -> 82.931544 | BL11: =IFERROR(BJ11/BK11,"") | BM11: =BD11+BJ11+BG11 -> 296747.29 | BN11: =BE11+BK11+BH11 -> 2450 | BO11: =IFERROR(BM11/BN11,"") -> 121.12134 | BP11: 0 | BQ11: 0 | BR11: =IFERROR(BP11/BQ11,"") | BS11: 0 | BT11: 0 | BU11: =IFERROR(BS11/BT11,"") | BV11: =+BP11+BS11 -> 0 | BW11: =BT11+BQ11 -> 0 | BX11: =IFERROR(BV11/BW11,"") | BY11: 0 | BZ11: 0 | CA11: =IFERROR(BY11/BZ11,"") | CB11: 0 | CC11: 0 | CD11: =IFERROR(CB11/CC11,"") | CG11: =IFERROR(CE11/CF11,"") | CH11: =BY11+CE11+CB11 -> 0 | CI11: =BZ11+CF11+CC11 -> 0 | CJ11: =IFERROR(CH11/CI11,"")
A12: Week 8 | B12: P2 | C12: =VLOOKUP(A12,Dates!$B$2:$E$53,4,FALSE) -> 8 | D12: =IF(C12<='RDG Weekly Sales'!$F$1,TRUE,FALSE) -> TRUE | E12: =810081.72-H12-5501.89 -> 747327.48 | F12: =4988-I12 -> 4576 | G12: =IFERROR(E12/F12,"") -> 163.31457 | H12: 57252.35 | I12: 412 | J12: =IFERROR(H12/I12,"") -> 138.96201 | K12: =E12+H12 -> 804579.83 | L12: =F12+I12 -> 4988 | M12: =IFERROR(K12/L12,"") -> 161.30309 | N12: 40327 | O12: 92 | P12: =IFERROR(N12/O12,"") -> 438.33696 | Q12: =32128+53555.36 -> 85683.36 | R12: 396 | S12: =IFERROR(Q12/R12,"") -> 216.37212 | T12: =230089.75+31935-2372.05 -> 259652.7 | U12: =893+14 -> 907 | V12: =IFERROR(T12/U12,"") -> 286.27641 | W12: =SUM(N12,Q12,T12) -> 385663.06 | X12: =SUM(O12,R12,U12) -> 1395 | Y12: =IFERROR(W12/X12,"") -> 276.46097 | Z12: =253108.52-AC12-516.22 -> 230509.81 | AA12: =2450-AD12 -> 2125 | AB12: =IFERROR(Z12/AA12,"") -> 108.4752 | AC12: 22082.49 | AD12: =169+156 -> 325 | AE12: =IFERROR(AC12/AD12,"") -> 67.946123 | AF12: =46891.5-860.8 -> 46030.7 | AG12: 160 | AH12: =IFERROR(AF12/AG12,"") -> 287.69187 | AI12: =Z12+AF12+AC12 -> 298623 | AJ12: =AA12+AG12+AD12 -> 2610 | AK12: =IFERROR(AI12/AJ12,"") -> 114.41494 | AL12: 184610.25 | AM12: =372+577 -> 949 | AN12: =IFERROR(AL12/AM12,"") -> 194.53135 | AO12: =785007.01-AL12-3688.91 -> 596707.85 | AP12: =4313-AM12 -> 3364 | AQ12: =IFERROR(AO12/AP12,"") -> 177.38045 | AR12: =AO12+AL12 -> 781318.1 | AS12: =AP12+AM12 -> 4313 | AT12: =IFERROR(AR12/AS12,"") -> 181.15421 | AU12: 0 | AV12: 0 | AW12: =IFERROR(AU12/AV12,0) -> 0 | AX12: =389129.54-1066.39-AU12 -> 388063.15 | AY12: 2134 | AZ12: =IFERROR(AX12/AY12,"") -> 181.84777 | BA12: =AX12+AU12 -> 388063.15 | BB12: =AY12+AV12 -> 2134 | BC12: =IFERROR(BA12/BB12,"") -> 181.84777 | BD12: =240615.98-BG12-775.55 -> 183373.6 | BE12: =2252-BH12 -> 1587 | BF12: =IFERROR(BD12/BE12,"") -> 115.54732 | BG12: 56466.83 | BH12: =290+375 -> 665 | BI12: =IFERROR(BG12/BH12,"") -> 84.912526 | BL12: =IFERROR(BJ12/BK12,"") | BM12: =BD12+BJ12+BG12 -> 239840.43 | BN12: =BE12+BK12+BH12 -> 2252 | BO12: =IFERROR(BM12/BN12,"") -> 106.50108 | BP12: 0 | BQ12: 0 | BR12: =IFERROR(BP12/BQ12,"") | BS12: 0 | BT12: 0 | BU12: =IFERROR(BS12/BT12,"") | BV12: =+BP12+BS12 -> 0 | BW12: =BT12+BQ12 -> 0 | BX12: =IFERROR(BV12/BW12,"") | BY12: 0 | BZ12: 0 | CA12: =IFERROR(BY12/BZ12,"") | CB12: 0 | CC12: 0 | CD12: =IFERROR(CB12/CC12,"") | CG12: =IFERROR(CE12/CF12,"") | CH12: =BY12+CE12+CB12 -> 0 | CI12: =BZ12+CF12+CC12 -> 0 | CJ12: =IFERROR(CH12/CI12,"")
A13: Week 9 | B13: P3 | C13: =VLOOKUP(A13,Dates!$B$2:$E$53,4,FALSE) -> 9 | D13: =IF(C13<='RDG Weekly Sales'!$F$1,TRUE,FALSE) -> TRUE | E13: =897319.85-H13-12670.85 -> 824772.95 | F13: =4689-I13 -> 4248 | G13: =IFERROR(E13/F13,"") -> 194.15559 | H13: 59876.05 | I13: 441 | J13: =IFERROR(H13/I13,"") -> 135.77336 | K13: =E13+H13 -> 884649 | L13: =F13+I13 -> 4689 | M13: =IFERROR(K13/L13,"") -> 188.66475 | N13: 21300.01 | O13: 80 | P13: =IFERROR(N13/O13,"") -> 266.25012 | Q13: =20846+131851.52 -> 152697.52 | R13: 374 | S13: =IFERROR(Q13/R13,"") -> 408.28214 | T13: =331755.8+61037-5693 -> 387099.8 | U13: 1307 | V13: =IFERROR(T13/U13,"") -> 296.17429 | W13: =SUM(N13,Q13,T13) -> 561097.33 | X13: =SUM(O13,R13,U13) -> 1761 | Y13: =IFERROR(W13/X13,"") -> 318.62426 | Z13: =211236.66-AC13-407.55 -> 186147.71 | AA13: =1942-AD13 -> 1576 | AB13: =IFERROR(Z13/AA13,"") -> 118.11403 | AC13: 24681.4 | AD13: =173+193 -> 366 | AE13: =IFERROR(AC13/AD13,"") -> 67.435519 | AF13: =33958.32-400.92 -> 33557.4 | AG13: 257 | AH13: =IFERROR(AF13/AG13,"") -> 130.57354 | AI13: =Z13+AF13+AC13 -> 244386.51 | AJ13: =AA13+AG13+AD13 -> 2199 | AK13: =IFERROR(AI13/AJ13,"") -> 111.13529 | AL13: 181622.75 | AM13: =508+545 -> 1053 | AN13: =IFERROR(AL13/AM13,"") -> 172.48124 | AO13: =871546.43-AL13-7188.15 -> 682735.53 | AP13: =4038-AM13 -> 2985 | AQ13: =IFERROR(AO13/AP13,"") -> 228.72212 | AR13: =AO13+AL13 -> 864358.28 | AS13: =AP13+AM13 -> 4038 | AT13: =IFERROR(AR13/AS13,"") -> 214.05604 | AU13: 0 | AV13: 0 | AW13: =IFERROR(AU13/AV13,0) -> 0 | AX13: =409160.4-2063.79-AU13 -> 407096.61 | AY13: 2231 | AZ13: =IFERROR(AX13/AY13,"") -> 182.47271 | BA13: =AX13+AU13 -> 407096.61 | BB13: =AY13+AV13 -> 2231 | BC13: =IFERROR(BA13/BB13,"") -> 182.47271 | BD13: =272112.51-BG13-1575.3 -> 216688.46 | BE13: =2415-BH13 -> 1666 | BF13: =IFERROR(BD13/BE13,"") -> 130.0651 | BG13: 53848.75 | BH13: =372+377 -> 749 | BI13: =IFERROR(BG13/BH13,"") -> 71.894192 | BL13: =IFERROR(BJ13/BK13,"") | BM13: =BD13+BJ13+BG13 -> 270537.21 | BN13: =BE13+BK13+BH13 -> 2415 | BO13: =IFERROR(BM13/BN13,"") -> 112.02369 | BP13: 0 | BQ13: 0 | BR13: =IFERROR(BP13/BQ13,"") | BS13: 0 | BT13: 0 | BU13: =IFERROR(BS13/BT13,"") | BV13: =+BP13+BS13 -> 0 | BW13: =BT13+BQ13 -> 0 | BX13: =IFERROR(BV13/BW13,"") | BY13: 0 | BZ13: 0 | CA13: =IFERROR(BY13/BZ13,"") | CB13: 0 | CC13: 0 | CD13: =IFERROR(CB13/CC13,"") | CG13: =IFERROR(CE13/CF13,"") | CH13: =BY13+CE13+CB13 -> 0 | CI13: =BZ13+CF13+CC13 -> 0 | CJ13: =IFERROR(CH13/CI13,"")
A14: Week 10 | B14: P3 | C14: =VLOOKUP(A14,Dates!$B$2:$E$53,4,FALSE) -> 10 | D14: =IF(C14<='RDG Weekly Sales'!$F$1,TRUE,FALSE) -> TRUE | E14: =856214.79-H14-4945.95 -> 803318.59 | F14: =5010-I14 -> 4610 | G14: =IFERROR(E14/F14,"") -> 174.25566 | H14: 47950.25 | I14: 400 | J14: =IFERROR(H14/I14,"") -> 119.87562 | K14: =E14+H14 -> 851268.84 | L14: =F14+I14 -> 5010 | M14: =IFERROR(K14/L14,"") -> 169.91394 | N14: 22609 | O14: 77 | P14: =IFERROR(N14/O14,"") -> 293.62338 | Q14: =24845+91647.3 -> 116492.3 | R14: 508 | S14: =IFERROR(Q14/R14,"") -> 229.31555 | T14: =253048.06+35529.29-3652 -> 284925.35 | U14: 983 | V14: =IFERROR(T14/U14,"") -> 289.85285 | W14: =SUM(N14,Q14,T14) -> 424026.65 | X14: =SUM(O14,R14,U14) -> 1568 | Y14: =IFERROR(W14/X14,"") -> 270.42516 | Z14: =204788.67-AC14-425.3 -> 180759.37 | AA14: =1912-AD14 -> 1553 | AB14: =IFERROR(Z14/AA14,"") -> 116.39367 | AC14: 23604 | AD14: =156+203 -> 359 | AE14: =IFERROR(AC14/AD14,"") -> 65.749304 | AF14: =39719.25-513.55 -> 39205.7 | AG14: 218 | AH14: =IFERROR(AF14/AG14,"") -> 179.84266 | AI14: =Z14+AF14+AC14 -> 243569.07 | AJ14: =AA14+AG14+AD14 -> 2130 | AK14: =IFERROR(AI14/AJ14,"") -> 114.35168 | AL14: 104062.6 | AM14: =850+660 -> 1510 | AN14: =IFERROR(AL14/AM14,"") -> 68.915629 | AO14: =653600.85-AL14-6803.25+340456 -> 883191 | AP14: =4355-AM14 -> 2845 | AQ14: =IFERROR(AO14/AP14,"") -> 310.4362 | AR14: =AO14+AL14 -> 987253.6 | AS14: =AP14+AM14 -> 4355 | AT14: =IFERROR(AR14/AS14,"") -> 226.69428 | AU14: 43462.3 | AV14: =61+72+105+40+90 -> 368 | AW14: =IFERROR(AU14/AV14,0) -> 118.10408 | AX14: =381769.9-1672.1-AU14 -> 336635.5 | AY14: =2513-AV14 -> 2145 | AZ14: =IFERROR(AX14/AY14,"") -> 156.93963 | BA14: =AX14+AU14 -> 380097.8 | BB14: =AY14+AV14 -> 2513 | BC14: =IFERROR(BA14/BB14,"") -> 151.25261 | BD14: =252697.66-BG14-716 -> 208268.04 | BE14: =2212-BH14 -> 1640 | BF14: =IFERROR(BD14/BE14,"") -> 126.99271 | BG14: 43713.62 | BH14: =329+243 -> 572 | BI14: =IFERROR(BG14/BH14,"") -> 76.422413 | BL14: =IFERROR(BJ14/BK14,"") | BM14: =BD14+BJ14+BG14 -> 251981.66 | BN14: =BE14+BK14+BH14 -> 2212 | BO14: =IFERROR(BM14/BN14,"") -> 113.91576 | BP14: =12484.52+70643+60327+8320+6611.84+79243 -> 237629.36 | BQ14: =192+153 -> 345 | BR14: =IFERROR(BP14/BQ14,"") -> 688.78075 | BS14: =9638+7366+2757+5607+1456+3115.36 -> 29939.36 | BT14: =120+74 -> 194 | BU14: =IFERROR(BS14/BT14,"") -> 154.3266 | BV14: =+BP14+BS14 -> 267568.72 | BW14: =BT14+BQ14 -> 539 | BX14: =IFERROR(BV14/BW14,"") -> 496.41692 | BY14: 0 | BZ14: 0 | CA14: =IFERROR(BY14/BZ14,"") | CB14: 0 | CC14: 0 | CD14: =IFERROR(CB14/CC14,"") | CG14: =IFERROR(CE14/CF14,"") | CH14: =BY14+CE14+CB14 -> 0 | CI14: =BZ14+CF14+CC14 -> 0 | CJ14: =IFERROR(CH14/CI14,"")
A15: Week 11 | B15: P3 | C15: =VLOOKUP(A15,Dates!$B$2:$E$53,4,FALSE) -> 11 | D15: =IF(C15<='RDG Weekly Sales'!$F$1,TRUE,FALSE) -> TRUE | E15: =863418.48-H15-13974.45 -> 792520.88 | F15: =4605-I15 -> 4159 | G15: =IFERROR(E15/F15,"") -> 190.55563 | H15: 56923.15 | I15: 446 | J15: =IFERROR(H15/I15,"") -> 127.63038 | K15: =E15+H15 -> 849444.03 | L15: =F15+I15 -> 4605 | M15: =IFERROR(K15/L15,"") -> 184.46124 | N15: 24784.01 | O15: 80 | P15: =IFERROR(N15/O15,"") -> 309.80012 | Q15: =14921+70010.2 -> 84931.2 | R15: 392 | S15: =IFERROR(Q15/R15,"") -> 216.66122 | T15: =176276.65+23263-1013.35 -> 198526.3 | U15: 769 | V15: =IFERROR(T15/U15,"") -> 258.16164 | W15: =SUM(N15,Q15,T15) -> 308241.51 | X15: =SUM(O15,R15,U15) -> 1241 | Y15: =IFERROR(W15/X15,"") -> 248.38156 | Z15: =199938.61-114.3-AC15 -> 184639.81 | AA15: =1874-AD15 -> 1608 | AB15: =IFERROR(Z15/AA15,"") -> 114.82575 | AC15: 15184.5 | AD15: =160+106 -> 266 | AE15: =IFERROR(AC15/AD15,"") -> 57.084586 | AF15: =27577.95-451.45 -> 27126.5 | AG15: 110 | AH15: =IFERROR(AF15/AG15,"") -> 246.60455 | AI15: =Z15+AF15+AC15 -> 226950.81 | AJ15: =AA15+AG15+AD15 -> 1984 | AK15: =IFERROR(AI15/AJ15,"") -> 114.39053 | AL15: =518482.09-376225.3 -> 142256.79 | AM15: =469+557 -> 1026 | AN15: =IFERROR(AL15/AM15,"") -> 138.65184 | AO15: =570034.64+17796.15-36856.93 -> 550973.86 | AP15: =4143-AM15 -> 3117 | AQ15: =IFERROR(AO15/AP15,"") -> 176.76415 | AR15: =AO15+AL15 -> 693230.65 | AS15: =AP15+AM15 -> 4143 | AT15: =IFERROR(AR15/AS15,"") -> 167.32577 | AU15: 39527.29 | AV15: =51+60+66+46+56 -> 279 | AW15: =IFERROR(AU15/AV15,0) -> 141.67487 | AX15: =348196.94-AU15-1092.94 -> 307576.71 | AY15: =2236-AV15 -> 1957 | AZ15: =IFERROR(AX15/AY15,"") -> 157.16746 | BA15: =AX15+AU15 -> 347104 | BB15: =AY15+AV15 -> 2236 | BC15: =IFERROR(BA15/BB15,"") -> 155.23435 | BD15: =239836.03-BG15-732.78 -> 193093.92 | BE15: =2151-BH15 -> 1525 | BF15: =IFERROR(BD15/BE15,"") -> 126.61896 | BG15: 46009.33 | BH15: =299+327 -> 626 | BI15: =IFERROR(BG15/BH15,"") -> 73.497332 | BL15: =IFERROR(BJ15/BK15,"") | BM15: =BD15+BJ15+BG15 -> 239103.25 | BN15: =BE15+BK15+BH15 -> 2151 | BO15: =IFERROR(BM15/BN15,"") -> 111.15911 | BP15: =228562.04+35471.68 -> 264033.72 | BQ15: 729 | BR15: =IFERROR(BP15/BQ15,"") -> 362.18617 | BS15: =12787.84+24339 -> 37126.84 | BT15: 221 | BU15: =IFERROR(BS15/BT15,"") -> 167.99475 | BV15: =+BP15+BS15 -> 301160.56 | BW15: =BT15+BQ15 -> 950 | BX15: =IFERROR(BV15/BW15,"") -> 317.01112 | BY15: 0 | BZ15: 0 | CA15: =IFERROR(BY15/BZ15,"") | CB15: 0 | CC15: 0 | CD15: =IFERROR(CB15/CC15,"") | CG15: =IFERROR(CE15/CF15,"") | CH15: =BY15+CE15+CB15 -> 0 | CI15: =BZ15+CF15+CC15 -> 0 | CJ15: =IFERROR(CH15/CI15,"")
A16: Week 12 | B16: P3 | C16: =VLOOKUP(A16,Dates!$B$2:$E$53,4,FALSE) -> 12 | D16: =IF(C16<='RDG Weekly Sales'!$F$1,TRUE,FALSE) -> TRUE | E16: =875753.37-H16-9224.61 -> 819512.76 | F16: =5026-I16 -> 4603 | G16: =IFERROR(E16/F16,"") -> 178.03884 | H16: 47016 | I16: 423 | J16: =IFERROR(H16/I16,"") -> 111.14894 | K16: =E16+H16 -> 866528.76 | L16: =F16+I16 -> 5026 | M16: =IFERROR(K16/L16,"") -> 172.40922 | N16: 22133.43 | O16: 66 | P16: =IFERROR(N16/O16,"") -> 335.355 | Q16: =12893+111200.5 -> 124093.5 | R16: 512 | S16: =IFERROR(Q16/R16,"") -> 242.37012 | T16: =278477.55+47950-3935 -> 322492.55 | U16: 1299 | V16: =IFERROR(T16/U16,"") -> 248.26216 | W16: =SUM(N16,Q16,T16) -> 468719.48 | X16: =SUM(O16,R16,U16) -> 1877 | Y16: =IFERROR(W16/X16,"") -> 249.71736 | Z16: =217501.6-AC16-77.65 -> 184170.95 | AA16: =2065-AD16 -> 1608 | AB16: =IFERROR(Z16/AA16,"") -> 114.53417 | AC16: 33253 | AD16: =208+249 -> 457 | AE16: =IFERROR(AC16/AD16,"") -> 72.763676 | AF16: =27235-419.78 -> 26815.22 | AG16: 144 | AH16: =IFERROR(AF16/AG16,"") -> 186.21681 | AI16: =Z16+AF16+AC16 -> 244239.17 | AJ16: =AA16+AG16+AD16 -> 2209 | AK16: =IFERROR(AI16/AJ16,"") -> 110.56549 | AL16: 236435.28 | AM16: =586+704 -> 1290 | AN16: =IFERROR(AL16/AM16,"") -> 183.28316 | AO16: =824962.45-AL16-2437.95 -> 586089.22 | AP16: =4496-AM16 -> 3206 | AQ16: =IFERROR(AO16/AP16,"") -> 182.81011 | AR16: =AO16+AL16 -> 822524.5 | AS16: =AP16+AM16 -> 4496 | AT16: =IFERROR(AR16/AS16,"") -> 182.94584 | AU16: 116260.76 | AV16: =41+35+65+74 -> 215 | AW16: =IFERROR(AU16/AV16,0) -> 540.74772 | AX16: =394989.6-AU16-4675 -> 274053.84 | AY16: =2070-AV16 -> 1855 | AZ16: =IFERROR(AX16/AY16,"") -> 147.73792 | BA16: =AX16+AU16 -> 390314.6 | BB16: =AY16+AV16 -> 2070 | BC16: =IFERROR(BA16/BB16,"") -> 188.55778 | BD16: =248999.92-BG16-1247.38 -> 200278.82 | BE16: =2241-BH16 -> 1682 | BF16: =IFERROR(BD16/BE16,"") -> 119.07183 | BG16: 47473.72 | BH16: =344+215 -> 559 | BI16: =IFERROR(BG16/BH16,"") -> 84.926154 | BL16: =IFERROR(BJ16/BK16,"") | BM16: =BD16+BJ16+BG16 -> 247752.54 | BN16: =BE16+BK16+BH16 -> 2241 | BO16: =IFERROR(BM16/BN16,"") -> 110.55446 | BP16: =292101.24-BS16-1692.22 -> 234905.5 | BQ16: 609 | BR16: =IFERROR(BP16/BQ16,"") -> 385.72332 | BS16: =11094.68+44408.84 -> 55503.52 | BT16: 367 | BU16: =IFERROR(BS16/BT16,"") -> 151.23575 | BV16: =+BP16+BS16 -> 290409.02 | BW16: =BT16+BQ16 -> 976 | BX16: =IFERROR(BV16/BW16,"") -> 297.55023 | BY16: 0 | BZ16: 0 | CA16: =IFERROR(BY16/BZ16,"") | CB16: 0 | CC16: 0 | CD16: =IFERROR(CB16/CC16,"") | CG16: =IFERROR(CE16/CF16,"") | CH16: =BY16+CE16+CB16 -> 0 | CI16: =BZ16+CF16+CC16 -> 0 | CJ16: =IFERROR(CH16/CI16,"")
A17: Week 13 | B17: P3 | C17: =VLOOKUP(A17,Dates!$B$2:$E$53,4,FALSE) -> 13 | D17: =IF(C17<='RDG Weekly Sales'!$F$1,TRUE,FALSE) -> TRUE | E17: =850297.27-H17-3649.75 -> 799812.52 | F17: =5162-I17 -> 4755 | G17: =IFERROR(E17/F17,"") -> 168.20453 | H17: 46835 | I17: 407 | J17: =IFERROR(H17/I17,"") -> 115.07371 | K17: =E17+H17 -> 846647.52 | L17: =F17+I17 -> 5162 | M17: =IFERROR(K17/L17,"") -> 164.0154 | N17: 27346.6 | O17: 88 | P17: =IFERROR(N17/O17,"") -> 310.75682 | Q17: =21012.5+62124.9 -> 83137.4 | R17: 414 | S17: =IFERROR(Q17/R17,"") -> 200.81498 | T17: =436150.36+41560-1568 -> 476142.36 | U17: 860 | V17: =IFERROR(T17/U17,"") -> 553.65391 | W17: =SUM(N17,Q17,T17) -> 586626.36 | X17: =SUM(O17,R17,U17) -> 1362 | Y17: =IFERROR(W17/X17,"") -> 430.70952 | Z17: =212722.9-AC17-755.45 -> 189692.44 | AA17: =1981-AD17 -> 1637 | AB17: =IFERROR(Z17/AA17,"") -> 115.87809 | AC17: 22275.01 | AD17: =160+184 -> 344 | AE17: =IFERROR(AC17/AD17,"") -> 64.752936 | AF17: =42188.62-1211.02 -> 40977.6 | AG17: 161 | AH17: =IFERROR(AF17/AG17,"") -> 254.51925 | AI17: =Z17+AF17+AC17 -> 252945.05 | AJ17: =AA17+AG17+AD17 -> 2142 | AK17: =IFERROR(AI17/AJ17,"") -> 118.08826 | AL17: 268953.8 | AM17: =667+732 -> 1399 | AN17: =IFERROR(AL17/AM17,"") -> 192.24718 | AO17: =1112400.79-AL17-2447 -> 840999.99 | AP17: =5194-AM17 -> 3795 | AQ17: =IFERROR(AO17/AP17,"") -> 221.60738 | AR17: =AO17+AL17 -> 1109953.8 | AS17: =AP17+AM17 -> 5194 | AT17: =IFERROR(AR17/AS17,"") -> 213.69923 | AU17: 41123.75 | AV17: =33+135+32+64+100 -> 364 | AW17: =IFERROR(AU17/AV17,0) -> 112.97734 | AX17: =366812.3-AU17-1375 -> 324313.55 | AY17: =2383-AV17 -> 2019 | AZ17: =IFERROR(AX17/AY17,"") -> 160.63078 | BA17: =AX17+AU17 -> 365437.3 | BB17: =AY17+AV17 -> 2383 | BC17: =IFERROR(BA17/BB17,"") -> 153.35178 | BD17: =234785.11-BG17-1115.7 -> 188857.05 | BE17: =2194-BH17 -> 1665 | BF17: =IFERROR(BD17/BE17,"") -> 113.42766 | BG17: 44812.36 | BH17: =262+267 -> 529 | BI17: =IFERROR(BG17/BH17,"") -> 84.711456 | BL17: =IFERROR(BJ17/BK17,"") | BM17: =BD17+BJ17+BG17 -> 233669.41 | BN17: =BE17+BK17+BH17 -> 2194 | BO17: =IFERROR(BM17/BN17,"") -> 106.50383 | BP17: =530604.56-BS17-1692.22 -> 436754.29 | BQ17: 933 | BR17: =IFERROR(BP17/BQ17,"") -> 468.11821 | BS17: =78606.05+13552 -> 92158.05 | BT17: 395 | BU17: =IFERROR(BS17/BT17,"") -> 233.31152 | BV17: =+BP17+BS17 -> 528912.34 | BW17: =BT17+BQ17 -> 1328 | BX17: =IFERROR(BV17/BW17,"") -> 398.27736 | BY17: 0 | BZ17: 0 | CA17: =IFERROR(BY17/BZ17,"") | CB17: 0 | CC17: 0 | CD17: =IFERROR(CB17/CC17,"") | CG17: =IFERROR(CE17/CF17,"") | CH17: =BY17+CE17+CB17 -> 0 | CI17: =BZ17+CF17+CC17 -> 0 | CJ17: =IFERROR(CH17/CI17,"")
A18: Week 14 | B18: P4 | C18: =VLOOKUP(A18,Dates!$B$2:$E$53,4,FALSE) -> 14 | D18: =IF(C18<='RDG Weekly Sales'!$F$1,TRUE,FALSE) -> TRUE | E18: =786333.87-H18-1808.78 -> 724988.19 | F18: =5180-I18 -> 4750 | G18: =IFERROR(E18/F18,"") -> 152.62909 | H18: 59536.9 | I18: 430 | J18: =IFERROR(H18/I18,"") -> 138.45791 | K18: =E18+H18 -> 784525.09 | L18: =F18+I18 -> 5180 | M18: =IFERROR(K18/L18,"") -> 151.45272 | N18: 27402.85 | O18: 81 | P18: =IFERROR(N18/O18,"") -> 338.30679 | Q18: =13735+27402 -> 41137 | R18: 413 | S18: =IFERROR(Q18/R18,"") -> 99.605327 | T18: =201751.57+28230-340.95 -> 229640.62 | U18: 706 | V18: =IFERROR(T18/U18,"") -> 325.27 | W18: =SUM(N18,Q18,T18) -> 298180.47 | X18: =SUM(O18,R18,U18) -> 1200 | Y18: =IFERROR(W18/X18,"") -> 248.48372 | Z18: =215990.05-AC18-147.15 -> 181775.9 | AA18: =2201-AD18 -> 1708 | AB18: =IFERROR(Z18/AA18,"") -> 106.42617 | AC18: 34067 | AD18: =318+175 -> 493 | AE18: =IFERROR(AC18/AD18,"") -> 69.10142 | AF18: 20300.09 | AG18: 134 | AH18: =IFERROR(AF18/AG18,"") -> 151.49321 | AI18: =Z18+AF18+AC18 -> 236142.99 | AJ18: =AA18+AG18+AD18 -> 2335 | AK18: =IFERROR(AI18/AJ18,"") -> 101.1319 | AL18: 164499.3 | AM18: =937+368 -> 1305 | AN18: =IFERROR(AL18/AM18,"") -> 126.0531 | AO18: =775942.93-AL18-2753.9 -> 608689.73 | AP18: =4518-AM18 -> 3213 | AQ18: =IFERROR(AO18/AP18,"") -> 189.44592 | AR18: =AO18+AL18 -> 773189.03 | AS18: =AP18+AM18 -> 4518 | AT18: =IFERROR(AR18/AS18,"") -> 171.13524 | AU18: 32633.31 | AV18: =54+69+56+112+114 -> 405 | AW18: =IFERROR(AU18/AV18,0) -> 80.576074 | AX18: =364492.51-AU18-288.09 -> 331571.11 | AY18: =2500-AV18 -> 2095 | AZ18: =IFERROR(AX18/AY18,"") -> 158.26783 | BA18: =AX18+AU18 -> 364204.42 | BB18: =AY18+AV18 -> 2500 | BC18: =IFERROR(BA18/BB18,"") -> 145.68177 | BD18: =224949.91-BG18-185.15 -> 160397.88 | BE18: =2157-BH18 -> 1419 | BF18: =IFERROR(BD18/BE18,"") -> 113.03586 | BG18: 64366.88 | BH18: =300+438 -> 738 | BI18: =IFERROR(BG18/BH18,"") -> 87.217995 | BL18: =IFERROR(BJ18/BK18,"") | BM18: =BD18+BJ18+BG18 -> 224764.76 | BN18: =BE18+BK18+BH18 -> 2157 | BO18: =IFERROR(BM18/BN18,"") -> 104.20248 | BP18: =242567.3-BS18-1235.05 -> 173704.95 | BQ18: 453 | BR18: =IFERROR(BP18/BQ18,"") -> 383.45464 | BS18: =8396+59231.3 -> 67627.3 | BT18: 255 | BU18: =IFERROR(BS18/BT18,"") -> 265.2051 | BV18: =+BP18+BS18 -> 241332.25 | BW18: =BT18+BQ18 -> 708 | BX18: =IFERROR(BV18/BW18,"") -> 340.86476 | BY18: 0 | BZ18: 0 | CA18: =IFERROR(BY18/BZ18,"") | CB18: 0 | CC18: 0 | CD18: =IFERROR(CB18/CC18,"") | CG18: =IFERROR(CE18/CF18,"") | CH18: =BY18+CE18+CB18 -> 0 | CI18: =BZ18+CF18+CC18 -> 0 | CJ18: =IFERROR(CH18/CI18,"")
A19: Week 15 | B19: P4 | C19: =VLOOKUP(A19,Dates!$B$2:$E$53,4,FALSE) -> 15 | D19: =IF(C19<='RDG Weekly Sales'!$F$1,TRUE,FALSE) -> TRUE | E19: =736996.96-H19-2726.15 -> 686335.86 | F19: =5056-I19 -> 4693 | G19: =IFERROR(E19/F19,"") -> 146.24672 | H19: 47934.95 | I19: 363 | J19: =IFERROR(H19/I19,"") -> 132.0522 | K19: =E19+H19 -> 734270.81 | L19: =F19+I19 -> 5056 | M19: =IFERROR(K19/L19,"") -> 145.22761 | N19: 28948.01 | O19: 90 | P19: =IFERROR(N19/O19,"") -> 321.64456 | Q19: =17148+63241.75 -> 80389.75 | R19: 382 | S19: =IFERROR(Q19/R19,"") -> 210.44437 | T19: =225439.1+31998-613.85 -> 256823.25 | U19: 792 | V19: =IFERROR(T19/U19,"") -> 324.27178 | W19: =SUM(N19,Q19,T19) -> 366161.01 | X19: =SUM(O19,R19,U19) -> 1264 | Y19: =IFERROR(W19/X19,"") -> 289.68434 | Z19: =215990.05-AC19-262.75 -> 194494.3 | AA19: =1969-AD19 -> 1604 | AB19: =IFERROR(Z19/AA19,"") -> 121.2558 | AC19: 21233 | AD19: =202+163 -> 365 | AE19: =IFERROR(AC19/AD19,"") -> 58.172603 | AF19: =46924.31-1027.93 -> 45896.38 | AG19: 210 | AH19: =IFERROR(AF19/AG19,"") -> 218.55419 | AI19: =Z19+AF19+AC19 -> 261623.68 | AJ19: =AA19+AG19+AD19 -> 2179 | AK19: =IFERROR(AI19/AJ19,"") -> 120.06594 | AL19: 172813.06 | AM19: =516+708 -> 1224 | AN19: =IFERROR(AL19/AM19,"") -> 141.18714 | AO19: =809251.06-AL19-5981.05 -> 630456.95 | AP19: =4485-AM19 -> 3261 | AQ19: =IFERROR(AO19/AP19,"") -> 193.3324 | AR19: =AO19+AL19 -> 803270.01 | AS19: =AP19+AM19 -> 4485 | AT19: =IFERROR(AR19/AS19,"") -> 179.10145 | AU19: 44764.14 | AV19: 345 | AW19: =IFERROR(AU19/AV19,0) -> 129.75113 | AX19: =337369.65-AU19-1103.54 -> 291501.97 | AY19: =2231-AV19 -> 1886 | AZ19: =IFERROR(AX19/AY19,"") -> 154.56096 | BA19: =AX19+AU19 -> 336266.11 | BB19: =AY19+AV19 -> 2231 | BC19: =IFERROR(BA19/BB19,"") -> 150.72439 | BD19: =216877.36-BG19-55.1 -> 175896.68 | BE19: =2046-BH19 -> 1501 | BF19: =IFERROR(BD19/BE19,"") -> 117.18633 | BG19: 40925.58 | BH19: =172+373 -> 545 | BI19: =IFERROR(BG19/BH19,"") -> 75.092807 | BL19: =IFERROR(BJ19/BK19,"") | BM19: =BD19+BJ19+BG19 -> 216822.26 | BN19: =BE19+BK19+BH19 -> 2046 | BO19: =IFERROR(BM19/BN19,"") -> 105.97373 | BP19: =226335.08-BS19-102.05 -> 176083.18 | BQ19: 460 | BR19: =IFERROR(BP19/BQ19,"") -> 382.78952 | BS19: =10243+39906.85 -> 50149.85 | BT19: 285 | BU19: =IFERROR(BS19/BT19,"") -> 175.96439 | BV19: =+BP19+BS19 -> 226233.03 | BW19: =BT19+BQ19 -> 745 | BX19: =IFERROR(BV19/BW19,"") -> 303.6685 | BY19: 0 | BZ19: 0 | CA19: =IFERROR(BY19/BZ19,"") | CB19: 0 | CC19: 0 | CD19: =IFERROR(CB19/CC19,"") | CG19: =IFERROR(CE19/CF19,"") | CH19: =BY19+CE19+CB19 -> 0 | CI19: =BZ19+CF19+CC19 -> 0 | CJ19: =IFERROR(CH19/CI19,"")
A20: Week 16 | B20: P4 | C20: =VLOOKUP(A20,Dates!$B$2:$E$53,4,FALSE) -> 16 | D20: =IF(C20<='RDG Weekly Sales'!$F$1,TRUE,FALSE) -> TRUE | E20: =838012.92-H20-7770.26 -> 783587.64 | F20: =4794-I20 -> 4377 | G20: =IFERROR(E20/F20,"") -> 179.02391 | H20: 46655.02 | I20: 417 | J20: =IFERROR(H20/I20,"") -> 111.88254 | K20: =E20+H20 -> 830242.66 | L20: =F20+I20 -> 4794 | M20: =IFERROR(K20/L20,"") -> 173.1837 | N20: 23710 | O20: 77 | P20: =IFERROR(N20/O20,"") -> 307.92208 | Q20: =19014+61582.4 -> 80596.4 | R20: 452 | S20: =IFERROR(Q20/R20,"") -> 178.31062 | T20: =270233.15+30035-4748.05 -> 295520.1 | U20: 888 | V20: =IFERROR(T20/U20,"") -> 332.79291 | W20: =SUM(N20,Q20,T20) -> 399826.5 | X20: =SUM(O20,R20,U20) -> 1417 | Y20: =IFERROR(W20/X20,"") -> 282.16408 | Z20: =225820.8-AC20-1714.35 -> 184733.12 | AA20: =2042-AD20 -> 1672 | AB20: =IFERROR(Z20/AA20,"") -> 110.48632 | AC20: =49373.33-10000 -> 39373.33 | AD20: =168+202 -> 370 | AE20: =IFERROR(AC20/AD20,"") -> 106.41441 | AF20: =33171.76-619.08 -> 32552.68 | AG20: 184 | AH20: =IFERROR(AF20/AG20,"") -> 176.91674 | AI20: =Z20+AF20+AC20 -> 256659.13 | AJ20: =AA20+AG20+AD20 -> 2226 | AK20: =IFERROR(AI20/AJ20,"") -> 115.3006 | AL20: 165091.05 | AM20: =412+764 -> 1176 | AN20: =IFERROR(AL20/AM20,"") -> 140.38355 | AO20: =733189.03-AL20-3906.12 -> 564191.86 | AP20: =4301-AM20 -> 3125 | AQ20: =IFERROR(AO20/AP20,"") -> 180.5414 | AR20: =AO20+AL20 -> 729282.91 | AS20: =AP20+AM20 -> 4301 | AT20: =IFERROR(AR20/AS20,"") -> 169.56124 | AU20: 45002.35 | AV20: =53+89+95+83+136 -> 456 | AW20: =IFERROR(AU20/AV20,0) -> 98.689364 | AX20: =337369.65-AU20-853.4 -> 291513.9 | AY20: =2202-AV20 -> 1746 | AZ20: =IFERROR(AX20/AY20,"") -> 166.961 | BA20: =AX20+AU20 -> 336516.25 | BB20: =AY20+AV20 -> 2202 | BC20: =IFERROR(BA20/BB20,"") -> 152.823 | BD20: =232124.53-BG20-1006.68 -> 175371.36 | BE20: =2126-BH20 -> 1489 | BF20: =IFERROR(BD20/BE20,"") -> 117.77794 | BG20: 55746.49 | BH20: =218+419 -> 637 | BI20: =IFERROR(BG20/BH20,"") -> 87.514113 | BL20: =IFERROR(BJ20/BK20,"") | BM20: =BD20+BJ20+BG20 -> 231117.85 | BN20: =BE20+BK20+BH20 -> 2126 | BO20: =IFERROR(BM20/BN20,"") -> 108.71018 | BP20: =225820.85-BS20 -> 178072.1 | BQ20: 413 | BR20: =IFERROR(BP20/BQ20,"") -> 431.16731 | BS20: =8501.5+39247.25 -> 47748.75 | BT20: 301 | BU20: =IFERROR(BS20/BT20,"") -> 158.63372 | BV20: =+BP20+BS20 -> 225820.85 | BW20: =BT20+BQ20 -> 714 | BX20: =IFERROR(BV20/BW20,"") -> 316.2757 | BY20: 0 | BZ20: 0 | CA20: =IFERROR(BY20/BZ20,"") | CB20: 0 | CC20: 0 | CD20: =IFERROR(CB20/CC20,"") | CG20: =IFERROR(CE20/CF20,"") | CH20: =BY20+CE20+CB20 -> 0 | CI20: =BZ20+CF20+CC20 -> 0 | CJ20: =IFERROR(CH20/CI20,"")
A21: Week 17 | B21: P4 | C21: =VLOOKUP(A21,Dates!$B$2:$E$53,4,FALSE) -> 17 | D21: =IF(C21<='RDG Weekly Sales'!$F$1,TRUE,FALSE) -> TRUE | E21: =786471.76-H21-10240.93 -> 725768.73 | F21: =4317-I21 -> 3868 | G21: =IFERROR(E21/F21,"") -> 187.63411 | H21: 50462.1 | I21: 449 | J21: =IFERROR(H21/I21,"") -> 112.38775 | K21: =E21+H21 -> 776230.83 | L21: =F21+I21 -> 4317 | M21: =IFERROR(K21/L21,"") -> 179.80793 | N21: 30204 | O21: 85 | P21: =IFERROR(N21/O21,"") -> 355.34118 | Q21: =29147+50798.1 -> 79945.1 | R21: =50+38+79+116+4+86+7 -> 380 | S21: =IFERROR(Q21/R21,"") -> 210.38184 | T21: =348211.25-N21-Q21-1649.25 -> 236412.9 | U21: =48+62+225+8+228+4+220+2 -> 797 | V21: =IFERROR(T21/U21,"") -> 296.62848 | W21: =SUM(N21,Q21,T21) -> 346562 | X21: =SUM(O21,R21,U21) -> 1262 | Y21: =IFERROR(W21/X21,"") -> 274.61331 | Z21: =212174.15-AC21-1104.53 -> 189125.26 | AA21: =2037-AD21 -> 1703 | AB21: =IFERROR(Z21/AA21,"") -> 111.05417 | AC21: 21944.36 | AD21: =145+189 -> 334 | AE21: =IFERROR(AC21/AD21,"") -> 65.701677 | AF21: =23111.37-107.35 -> 23004.02 | AG21: =14+10+14+43+72 -> 153 | AH21: =IFERROR(AF21/AG21,"") -> 150.35307 | AI21: =Z21+AF21+AC21 -> 234073.64 | AJ21: =AA21+AG21+AD21 -> 2190 | AK21: =IFERROR(AI21/AJ21,"") -> 106.88294 | AL21: 186396.68 | AM21: =583+660 -> 1243 | AN21: =IFERROR(AL21/AM21,"") -> 149.9571 | AO21: =811073.38-AL21-3318.8 -> 621357.9 | AP21: =4088-AM21 -> 2845 | AQ21: =IFERROR(AO21/AP21,"") -> 218.40348 | AR21: =AO21+AL21 -> 807754.58 | AS21: =AP21+AM21 -> 4088 | AT21: =IFERROR(AR21/AS21,"") -> 197.59163 | AU21: 50665.9 | AV21: =78+111+72+91+89 -> 441 | AW21: =IFERROR(AU21/AV21,0) -> 114.88866 | AX21: =392394.59-AU21-5299.1 -> 336429.59 | AY21: =2211-AV21 -> 1770 | AZ21: =IFERROR(AX21/AY21,"") -> 190.07321 | BA21: =AX21+AU21 -> 387095.49 | BB21: =AY21+AV21 -> 2211 | BC21: =IFERROR(BA21/BB21,"") -> 175.07711 | BD21: =246532.2-BG21-1171.5 -> 190216.93 | BE21: =2297-BH21 -> 1643 | BF21: =IFERROR(BD21/BE21,"") -> 115.77415 | BG21: 55143.77 | BH21: =274+380 -> 654 | BI21: =IFERROR(BG21/BH21,"") -> 84.317691 | BL21: =IFERROR(BJ21/BK21,"") | BM21: =BD21+BJ21+BG21 -> 245360.7 | BN21: =BE21+BK21+BH21 -> 2297 | BO21: =IFERROR(BM21/BN21,"") -> 106.81789 | BP21: =218157.81-BS21-376.8 -> 155598.01 | BQ21: =56+103+2+182+2+77+2 -> 424 | BR21: =IFERROR(BP21/BQ21,"") -> 366.97644 | BS21: =9668+52515 -> 62183 | BT21: =103+155+3+2+198+4+14+63 -> 542 | BU21: =IFERROR(BS21/BT21,"") -> 114.72878 | BV21: =+BP21+BS21 -> 217781.01 | BW21: =BT21+BQ21 -> 966 | BX21: =IFERROR(BV21/BW21,"") -> 225.44618 | BY21: 0 | BZ21: 0 | CA21: =IFERROR(BY21/BZ21,"") | CB21: 0 | CC21: 0 | CD21: =IFERROR(CB21/CC21,"") | CG21: =IFERROR(CE21/CF21,"") | CH21: =BY21+CE21+CB21 -> 0 | CI21: =BZ21+CF21+CC21 -> 0 | CJ21: =IFERROR(CH21/CI21,"")
A22: Week 18 | B22: P5 | C22: =VLOOKUP(A22,Dates!$B$2:$E$53,4,FALSE) -> 18 | D22: =IF(C22<='RDG Weekly Sales'!$F$1,TRUE,FALSE) -> TRUE | E22: =1094110.94-H22-12821 -> 1025559.7 | F22: =5079-I22 -> 4700 | G22: =IFERROR(E22/F22,"") -> 218.20418 | H22: 55730.28 | I22: 379 | J22: =IFERROR(H22/I22,"") -> 147.04559 | K22: =E22+H22 -> 1081289.9 | L22: =F22+I22 -> 5079 | M22: =IFERROR(K22/L22,"") -> 212.89426 | N22: 46857.8 | O22: 104 | P22: =IFERROR(N22/O22,"") -> 450.55577 | Q22: =63865+154402 -> 218267 | R22: =57+4+61+4+69+2+94+2+65+178+78+4 -> 618 | S22: =IFERROR(Q22/R22,"") -> 353.18285 | T22: =479134+54099-7521 -> 525712 | U22: =106+116+93+2+229+15+240+7+4+277+161+10 -> 1260 | V22: =IFERROR(T22/U22,"") -> 417.23175 | W22: =SUM(N22,Q22,T22) -> 790836.8 | X22: =SUM(O22,R22,U22) -> 1982 | Y22: =IFERROR(W22/X22,"") -> 399.00949 | Z22: =212174.15-AC22-134.53 -> 190874.62 | AA22: =2068-AD22 -> 1706 | AB22: =IFERROR(Z22/AA22,"") -> 111.8843 | AC22: 21165 | AD22: =151+211 -> 362 | AE22: =IFERROR(AC22/AD22,"") -> 58.466851 | AF22: =33441-678 -> 32763 | AG22: =40+19+67+8+72 -> 206 | AH22: =IFERROR(AF22/AG22,"") -> 159.04369 | AI22: =Z22+AF22+AC22 -> 244802.62 | AJ22: =AA22+AG22+AD22 -> 2274 | AK22: =IFERROR(AI22/AJ22,"") -> 107.65287 | AL22: 238619 | AM22: =462+752 -> 1214 | AN22: =IFERROR(AL22/AM22,"") -> 196.55601 | AO22: =1856610.37-AL22-5849 -> 1612142.4 | AP22: =5449-AM22 -> 4235 | AQ22: =IFERROR(AO22/AP22,"") -> 380.67116 | AR22: =AO22+AL22 -> 1850761.4 | AS22: =AP22+AM22 -> 5449 | AT22: =IFERROR(AR22/AS22,"") -> 339.65156 | AU22: 30717.92 | AV22: =74+51+68+75+78 -> 346 | AW22: =IFERROR(AU22/AV22,0) -> 88.780116 | AX22: =382648.33-2092.15-AU22 -> 349838.26 | AY22: =2406-AV22 -> 2060 | AZ22: =IFERROR(AX22/AY22,"") -> 169.8244 | BA22: =AX22+AU22 -> 380556.18 | BB22: =AY22+AV22 -> 2406 | BC22: =IFERROR(BA22/BB22,"") -> 158.16965 | BD22: =285901.58-BG22-2790.77 -> 243670.38 | BE22: =2472-BH22 -> 1901 | BF22: =IFERROR(BD22/BE22,"") -> 128.18011 | BG22: 39440.43 | BH22: =253+318 -> 571 | BI22: =IFERROR(BG22/BH22,"") -> 69.072557 | BL22: =IFERROR(BJ22/BK22,"") | BM22: =BD22+BJ22+BG22 -> 283110.81 | BN22: =BE22+BK22+BH22 -> 2472 | BO22: =IFERROR(BM22/BN22,"") -> 114.52703 | BP22: =718532.3-BS22-4072 -> 599851.3 | BQ22: =210+1+4+279+10+224+7+12+180+18 -> 945 | BR22: =IFERROR(BP22/BQ22,"") -> 634.76328 | BS22: =22579+92030 -> 114609 | BT22: =322+137+198+99 -> 756 | BU22: =IFERROR(BS22/BT22,"") -> 151.59921 | BV22: =+BP22+BS22 -> 714460.3 | BW22: =BT22+BQ22 -> 1701 | BX22: =IFERROR(BV22/BW22,"") -> 420.02369 | BY22: 0 | BZ22: 0 | CA22: =IFERROR(BY22/BZ22,"") | CB22: 0 | CC22: 0 | CD22: =IFERROR(CB22/CC22,"") | CG22: =IFERROR(CE22/CF22,"") | CH22: =BY22+CE22+CB22 -> 0 | CI22: =BZ22+CF22+CC22 -> 0 | CJ22: =IFERROR(CH22/CI22,"")
A23: Week 19 | B23: P5 | C23: =VLOOKUP(A23,Dates!$B$2:$E$53,4,FALSE) -> 19 | D23: =IF(C23<='RDG Weekly Sales'!$F$1,TRUE,FALSE) -> TRUE | E23: =916289.02-H23-12923 -> 843237.07 | F23: =5019-I23 -> 4564 | G23: =IFERROR(E23/F23,"") -> 184.75834 | H23: 60128.95 | I23: 455 | J23: =IFERROR(H23/I23,"") -> 132.15154 | K23: =E23+H23 -> 903366.02 | L23: =F23+I23 -> 5019 | M23: =IFERROR(K23/L23,"") -> 179.98924 | N23: 24121.7 | O23: 78 | P23: =IFERROR(N23/O23,"") -> 309.25256 | Q23: =73475.5+57487.7 -> 130963.2 | R23: =50+100+42+158+3+98+61+48 -> 560 | S23: =IFERROR(Q23/R23,"") -> 233.86286 | T23: =324606.73+30389-11198.12 -> 343797.61 | U23: =200+100+262+254+18+15+226+172+2 -> 1249 | V23: =IFERROR(T23/U23,"") -> 275.25829 | W23: =SUM(N23,Q23,T23) -> 498882.51 | X23: =SUM(O23,R23,U23) -> 1887 | Y23: =IFERROR(W23/X23,"") -> 264.37865 | Z23: =256827.24-AC23-344.73 -> 213980.47 | AA23: =2408-AD23 -> 1897 | AB23: =IFERROR(Z23/AA23,"") -> 112.7994 | AC23: 42502.04 | AD23: =241+270 -> 511 | AE23: =IFERROR(AC23/AD23,"") -> 83.174247 | AF23: =51412.59-891 -> 50521.59 | AG23: =40+52+29+86 -> 207 | AH23: =IFERROR(AF23/AG23,"") -> 244.06565 | AI23: =Z23+AF23+AC23 -> 307004.1 | AJ23: =AA23+AG23+AD23 -> 2615 | AK23: =IFERROR(AI23/AJ23,"") -> 117.40119 | AL23: 128682.25 | AM23: =426+809 -> 1235 | AN23: =IFERROR(AL23/AM23,"") -> 104.19615 | AO23: =631054.39-AL23-3184 -> 499188.14 | AP23: =4468-AM23 -> 3233 | AQ23: =IFERROR(AO23/AP23,"") -> 154.404 | AR23: =AO23+AL23 -> 627870.39 | AS23: =AP23+AM23 -> 4468 | AT23: =IFERROR(AR23/AS23,"") -> 140.52605 | AU23: 76214.1 | AV23: =90+55+125+89+78 -> 437 | AW23: =IFERROR(AU23/AV23,0) -> 174.40297 | AX23: =388067.51-1482-AU23 -> 310371.41 | AY23: =2945-AV23 -> 2508 | AZ23: =IFERROR(AX23/AY23,"") -> 123.75256 | BA23: =AX23+AU23 -> 386585.51 | BB23: =AY23+AV23 -> 2945 | BC23: =IFERROR(BA23/BB23,"") -> 131.26842 | BD23: =328206-BG23-2511 -> 245778.29 | BE23: =2818-BH23 -> 2008 | BF23: =IFERROR(BD23/BE23,"") -> 122.39955 | BG23: 79916.71 | BH23: =339+471 -> 810 | BI23: =IFERROR(BG23/BH23,"") -> 98.662605 | BL23: =IFERROR(BJ23/BK23,"") | BM23: =BD23+BJ23+BG23 -> 325695 | BN23: =BE23+BK23+BH23 -> 2818 | BO23: =IFERROR(BM23/BN23,"") -> 115.57665 | BP23: =137948.5-BS23 -> 95014.5 | BQ23: =6+50+86+12+177+3+14+36 -> 384 | BR23: =IFERROR(BP23/BQ23,"") -> 247.43359 | BS23: =5669+37265 -> 42934 | BT23: =52+13+44+133+99 -> 341 | BU23: =IFERROR(BS23/BT23,"") -> 125.90616 | BV23: =+BP23+BS23 -> 137948.5 | BW23: =BT23+BQ23 -> 725 | BX23: =IFERROR(BV23/BW23,"") -> 190.27379 | BY23: 0 | BZ23: 0 | CA23: =IFERROR(BY23/BZ23,"") | CB23: 0 | CC23: 0 | CD23: =IFERROR(CB23/CC23,"") | CG23: =IFERROR(CE23/CF23,"") | CH23: =BY23+CE23+CB23 -> 0 | CI23: =BZ23+CF23+CC23 -> 0 | CJ23: =IFERROR(CH23/CI23,"")
A24: Week 20 | B24: P5 | C24: =VLOOKUP(A24,Dates!$B$2:$E$53,4,FALSE) -> 20 | D24: =IF(C24<='RDG Weekly Sales'!$F$1,TRUE,FALSE) -> TRUE | E24: {=SUMPRODUCT((Dinner[Week '#]=$A24)*(INT(Dinner[yyyyMMdd]/10000)=VALUE(RIGHT($AX$2,4)))*Dinner[Net sales])-SUMPRODUCT((Non_Grat_Serv_Chrg[Week '#]=$A24)*(YEAR(Non_Grat_Serv_Chrg[Start Date])=VALUE(RIGHT($AX$2,4)))*(Non_Grat_Serv_Chrg[Sales category]="Non-Grat Svc Charges")*Non_Grat_Serv_Chrg[Net sales])} -> 669559.58 | F24: =4534-I24 -> 4118 | G24: =IFERROR(E24/F24,"") -> 162.59339 | H24: =SUMIF(Lunch[Week '#],$A24,Lunch[Net sales]) -> 42361.75 | I24: 416 | J24: =IFERROR(H24/I24,"") -> 101.83113 | K24: =E24+H24 -> 711921.33 | L24: =F24+I24 -> 4534 | M24: =IFERROR(K24/L24,"") -> 157.01838 | N24: =SUMIF(Omakase[Week '#],$A24,Omakase[Net sales]) -> 22218 | O24: 70 | P24: =IFERROR(N24/O24,"") -> 317.4 | Q24: =SUMIF(MM[Week '#],$A24,MM[Net sales]) -> 105560.35 | R24: =100+75+113+105+4 -> 397 | S24: =IFERROR(Q24/R24,"") -> 265.89509 | T24: =SUMIF(Lounge[Week '#],$A24,Lounge[Net sales])-SUMIFS(Sales_Categories[Net sales],Sales_Categories[Week '#],$A24,Sales_Categories[Sales category],"Non-Grat Svc Charges") -> 205049.24 | U24: =6+130+175+3+249+177+3 -> 743 | V24: =IFERROR(T24/U24,"") -> 275.97475 | W24: =SUM(N24,Q24,T24) -> 332827.59 | X24: =SUM(O24,R24,U24) -> 1210 | Y24: =IFERROR(W24/X24,"") -> 275.06412 | Z24: =SUMIF(_26DinnerSalesACT[Week '#],$A24,_26DinnerSalesACT[Net sales])- SUMIFS(_2026AVATotalSalesCat[Net sales],_2026AVATotalSalesCat[Week '#],$A24,_2026AVATotalSalesCat[Sales category],"Non-Grat Svc Charges") -> 190426.86 | AA24: =2032-AD24 -> 1879.853 | AB24: =IFERROR(Z24/AA24,"") -> 101.2988 | AC24: =SUMIF(_26LunchSalesACT[Week '#],$A24,_26LunchSalesACT[Net sales]) -> 18885.5 | AD24: 152.147 | AE24: =IFERROR(AC24/AD24,"") -> 124.12667 | AF24: =SUMIF(_26MMSalesACT[Week '#],$A24,_26MMSalesACT[Net sales]) -> 45974.82 | AG24: =48+5+6+63+51 -> 173 | AH24: =IFERROR(AF24/AG24,"") -> 265.7504 | AI24: =Z24+AF24+AC24 -> 255287.18 | AJ24: =AA24+AG24+AD24 -> 2205 | AK24: =IFERROR(AI24/AJ24,"") -> 115.7765 | AL24: =SUMIF(Brunch[Week '#],$A24,Brunch[Net sales]) -> 127488.5 | AM24: 306.597 | AN24: =IFERROR(AL24/AM24,"") -> 415.81783 | AO24: =SUMIF(Dinner__2[Week '#],$A24,Dinner__2[Net sales])- SUMIFS(Sales_Categories__2[Net sales],Sales_Categories__2[Week '#],$A24,Sales_Categories__2[Sales category],"Non-Grat Svc Charges") -> 601803.7 | AP24: =3828-AM24 -> 3521.403 | AQ24: =IFERROR(AO24/AP24,"") -> 170.89884 | AR24: =AO24+AL24 -> 729292.2 | AS24: =AP24+AM24 -> 3828 | AT24: =IFERROR(AR24/AS24,"") -> 190.5152 | AU24: =SUMIF(Brunch__2[Week '#],$A24,Brunch__2[Net sales]) -> 58017.71 | AV24: =63+111+45+91+71 -> 381 | AW24: =IFERROR(AU24/AV24,0) -> 152.27745 | AX24: {=SUMPRODUCT((Dinner__3[Week '#]=$A24)*(INT(Dinner__3[yyyyMMdd]/10000)=VALUE(RIGHT($AX$2,4)))*Dinner__3[Net sales])-SUMPRODUCT((Sales_Categories__3[Week '#]=$A24)*(YEAR(Sales_Categories__3[Start Date])=VALUE(RIGHT($AX$2,4)))*(Sales_Categories__3[Sales category]="Non-Grat Svc Charges")*Sales_Categories__3[Net sales])} -> 216371.04 | AY24: =2012-AV24 -> 1631 | AZ24: =IFERROR(AX24/AY24,"") -> 132.66158 | BA24: =AX24+AU24 -> 274388.75 | BB24: =AY24+AV24 -> 2012 | BC24: =IFERROR(BA24/BB24,"") -> 136.37612 | BD24: =SUMIF(_2026DinnerSales[Week '#],$A24,_2026DinnerSales[Net sales])- SUMIFS(_2026TotalSalesCat[Net sales],_2026TotalSalesCat[Week '#],$A24,_2026TotalSalesCat[Sales category],"Non-Grat Svc Charges") -> 162714.53 | BE24: =2149-BH24 -> 1521 | BF24: =IFERROR(BD24/BE24,"") -> 106.97865 | BG24: =SUMIF(_2026BrunchSales[Week '#],$A24,_2026BrunchSales[Net sales]) -> 54691.39 | BH24: =280+348 -> 628 | BI24: =IFERROR(BG24/BH24,"") -> 87.088201 | BL24: =IFERROR(BJ24/BK24,"") | BM24: =BD24+BJ24+BG24 -> 217405.92 | BN24: =BE24+BK24+BH24 -> 2149 | BO24: =IFERROR(BM24/BN24,"") -> 101.16609 | BP24: =SUMIF(Lounge__2[Week '#],$A24,Lounge__2[Net sales])- SUMIFS(Sales_Categories__4[Net sales],Sales_Categories__4[Week '#],$A24,Sales_Categories__4[Sales category],"Non-Grat Svc Charges") -> 178666.15 | BQ24: =130+1+86+2+8+215+2+18+105+3 -> 570 | BR24: =IFERROR(BP24/BQ24,"") -> 313.44939 | BS24: =SUMIF(MM__2[Week '#],$A24,MM__2[Net sales]) -> 62759.9 | BT24: =42+1+73+2+159+3 -> 280 | BU24: =IFERROR(BS24/BT24,"") -> 224.1425 | BV24: =+BP24+BS24 -> 241426.05 | BW24: =BT24+BQ24 -> 850 | BX24: =IFERROR(BV24/BW24,"") -> 284.03065 | BY24: 0 | BZ24: 0 | CA24: =IFERROR(BY24/BZ24,"") | CB24: 0 | CC24: 0 | CD24: =IFERROR(CB24/CC24,"") | CG24: =IFERROR(CE24/CF24,"") | CH24: =BY24+CE24+CB24 -> 0 | CI24: =BZ24+CF24+CC24 -> 0 | CJ24: =IFERROR(CH24/CI24,"")
A25: Week 21 | B25: P5 | C25: =VLOOKUP(A25,Dates!$B$2:$E$53,4,FALSE) -> 21 | D25: =IF(C25<='RDG Weekly Sales'!$F$1,TRUE,FALSE) -> TRUE | E25: {=SUMPRODUCT((Dinner[Week '#]=$A25)*(INT(Dinner[yyyyMMdd]/10000)=VALUE(RIGHT($AX$2,4)))*Dinner[Net sales])-SUMPRODUCT((Non_Grat_Serv_Chrg[Week '#]=$A25)*(YEAR(Non_Grat_Serv_Chrg[Start Date])=VALUE(RIGHT($AX$2,4)))*(Non_Grat_Serv_Chrg[Sales category]="Non-Grat Svc Charges")*Non_Grat_Serv_Chrg[Net sales])} -> 689359.9 | F25: =4710-I25 -> 4315 | G25: =IFERROR(E25/F25,"") -> 159.75896 | H25: =SUMIF(Lunch[Week '#],$A25,Lunch[Net sales]) -> 44255.6 | I25: 395 | J25: =IFERROR(H25/I25,"") -> 112.03949 | K25: =E25+H25 -> 733615.5 | L25: =F25+I25 -> 4710 | M25: =IFERROR(K25/L25,"") -> 155.75701 | N25: =SUMIF(Omakase[Week '#],$A25,Omakase[Net sales]) -> 20618 | O25: 66 | P25: =IFERROR(N25/O25,"") -> 312.39394 | Q25: =SUMIF(MM[Week '#],$A25,MM[Net sales]) -> 77585.61 | R25: =34+67+53+95+101+4+112 -> 466 | S25: =IFERROR(Q25/R25,"") -> 166.49273 | T25: =SUMIF(Lounge[Week '#],$A25,Lounge[Net sales])-SUMIFS(Sales_Categories[Net sales],Sales_Categories[Week '#],$A25,Sales_Categories[Sales category],"Non-Grat Svc Charges") -> 269442.41 | U25: =60+56+167+6+224+6+239+32+199 -> 989 | V25: =IFERROR(T25/U25,"") -> 272.43924 | W25: =SUM(N25,Q25,T25) -> 367646.02 | X25: =SUM(O25,R25,U25) -> 1521 | Y25: =IFERROR(W25/X25,"") -> 241.71336 | Z25: =SUMIF(_26DinnerSalesACT[Week '#],$A25,_26DinnerSalesACT[Net sales])- SUMIFS(_2026AVATotalSalesCat[Net sales],_2026AVATotalSalesCat[Week '#],$A25,_2026AVATotalSalesCat[Sales category],"Non-Grat Svc Charges") -> 206256.33 | AA25: =2072-AD25 -> 1752 | AB25: =IFERROR(Z25/AA25,"") -> 117.72622 | AC25: =SUMIF(_26LunchSalesACT[Week '#],$A25,_26LunchSalesACT[Net sales]) -> 22834.03 | AD25: =134+186 -> 320 | AE25: =IFERROR(AC25/AD25,"") -> 71.356344 | AF25: =SUMIF(_26MMSalesACT[Week '#],$A25,_26MMSalesACT[Net sales]) -> 37032.95 | AG25: =30+52+50+50 -> 182 | AH25: =IFERROR(AF25/AG25,"") -> 203.47775 | AI25: =Z25+AF25+AC25 -> 266123.31 | AJ25: =AA25+AG25+AD25 -> 2254 | AK25: =IFERROR(AI25/AJ25,"") -> 118.06713 | AL25: =SUMIF(Brunch[Week '#],$A25,Brunch[Net sales]) -> 188433.5 | AM25: =424+737 -> 1161 | AN25: =IFERROR(AL25/AM25,"") -> 162.30276 | AO25: =SUMIF(Dinner__2[Week '#],$A25,Dinner__2[Net sales])- SUMIFS(Sales_Categories__2[Net sales],Sales_Categories__2[Week '#],$A25,Sales_Categories__2[Sales category],"Non-Grat Svc Charges") -> 566349.92 | AP25: =4126-AM25 -> 2965 | AQ25: =IFERROR(AO25/AP25,"") -> 191.01178 | AR25: =AO25+AL25 -> 754783.42 | AS25: =AP25+AM25 -> 4126 | AT25: =IFERROR(AR25/AS25,"") -> 182.93345 | AU25: =SUMIF(Brunch__2[Week '#],$A25,Brunch__2[Net sales]) -> 62512.26 | AV25: =36+65+54+146+138 -> 439 | AW25: =IFERROR(AU25/AV25,0) -> 142.39695 | AX25: {=SUMPRODUCT((Dinner__3[Week '#]=$A25)*(INT(Dinner__3[yyyyMMdd]/10000)=VALUE(RIGHT($AX$2,4)))*Dinner__3[Net sales])-SUMPRODUCT((Sales_Categories__3[Week '#]=$A25)*(YEAR(Sales_Categories__3[Start Date])=VALUE(RIGHT($AX$2,4)))*(Sales_Categories__3[Sales category]="Non-Grat Svc Charges")*Sales_Categories__3[Net sales])} -> 262581.5 | AY25: =2218-AV25 -> 1779 | AZ25: =IFERROR(AX25/AY25,"") -> 147.60062 | BA25: =AX25+AU25 -> 325093.76 | BB25: =AY25+AV25 -> 2218 | BC25: =IFERROR(BA25/BB25,"") -> 146.57068 | BD25: =SUMIF(_2026DinnerSales[Week '#],$A25,_2026DinnerSales[Net sales])- SUMIFS(_2026TotalSalesCat[Net sales],_2026TotalSalesCat[Week '#],$A25,_2026TotalSalesCat[Sales category],"Non-Grat Svc Charges") -> 179449.48 | BE25: =1989-BH25 -> 1536 | BF25: =IFERROR(BD25/BE25,"") -> 116.82909 | BG25: =SUMIF(_2026BrunchSales[Week '#],$A25,_2026BrunchSales[Net sales]) -> 32852.2 | BH25: =139+314 -> 453 | BI25: =IFERROR(BG25/BH25,"") -> 72.521413 | BL25: =IFERROR(BJ25/BK25,"") | BM25: =BD25+BJ25+BG25 -> 212301.68 | BN25: =BE25+BK25+BH25 -> 1989 | BO25: =IFERROR(BM25/BN25,"") -> 106.7379 | BP25: =SUMIF(Lounge__2[Week '#],$A25,Lounge__2[Net sales])- SUMIFS(Sales_Categories__4[Net sales],Sales_Categories__4[Week '#],$A25,Sales_Categories__4[Sales category],"Non-Grat Svc Charges") -> 215040.11 | BQ25: =2+95+115+10+263+19+14+197+25 -> 740 | BR25: =IFERROR(BP25/BQ25,"") -> 290.59474 | BS25: =SUMIF(MM__2[Week '#],$A25,MM__2[Net sales]) -> 72264.91 | BT25: =133+71+2+81+145 -> 432 | BU25: =IFERROR(BS25/BT25,"") -> 167.27988 | BV25: =+BP25+BS25 -> 287305.02 | BW25: =BT25+BQ25 -> 1172 | BX25: =IFERROR(BV25/BW25,"") -> 245.1408 | BY25: 0 | BZ25: 0 | CA25: =IFERROR(BY25/BZ25,"") | CB25: 0 | CC25: 0 | CD25: =IFERROR(CB25/CC25,"") | CG25: =IFERROR(CE25/CF25,"") | CH25: =BY25+CE25+CB25 -> 0 | CI25: =BZ25+CF25+CC25 -> 0 | CJ25: =IFERROR(CH25/CI25,"")
A26: Week 22 | B26: P6 | C26: =VLOOKUP(A26,Dates!$B$2:$E$53,4,FALSE) -> 22 | D26: =IF(C26<='RDG Weekly Sales'!$F$1,TRUE,FALSE) -> TRUE | E26: {=SUMPRODUCT((Dinner[Week '#]=$A26)*(INT(Dinner[yyyyMMdd]/10000)=VALUE(RIGHT($AX$2,4)))*Dinner[Net sales])-SUMPRODUCT((Non_Grat_Serv_Chrg[Week '#]=$A26)*(YEAR(Non_Grat_Serv_Chrg[Start Date])=VALUE(RIGHT($AX$2,4)))*(Non_Grat_Serv_Chrg[Sales category]="Non-Grat Svc Charges")*Non_Grat_Serv_Chrg[Net sales])} -> 655710.44 | F26: =4807-I26 -> 4403 | G26: =IFERROR(E26/F26,"") -> 148.92356 | H26: =SUMIF(Lunch[Week '#],$A26,Lunch[Net sales]) -> 51670.2 | I26: 404 | J26: =IFERROR(H26/I26,"") -> 127.89653 | K26: =E26+H26 -> 707380.64 | L26: =F26+I26 -> 4807 | M26: =IFERROR(K26/L26,"") -> 147.15636 | N26: =SUMIF(Omakase[Week '#],$A26,Omakase[Net sales]) -> 17271 | O26: 59 | P26: =IFERROR(N26/O26,"") -> 292.72881 | Q26: =SUMIF(MM[Week '#],$A26,MM[Net sales]) -> 49181 | R26: =66+65+178+2+106 -> 417 | S26: =IFERROR(Q26/R26,"") -> 117.94005 | T26: =SUMIF(Lounge[Week '#],$A26,Lounge[Net sales])-SUMIFS(Sales_Categories[Net sales],Sales_Categories[Week '#],$A26,Sales_Categories[Sales category],"Non-Grat Svc Charges") -> 304492 | U26: =108+2+229+1+191+227+4 -> 762 | V26: =IFERROR(T26/U26,"") -> 399.5958 | W26: =SUM(N26,Q26,T26) -> 370944 | X26: =SUM(O26,R26,U26) -> 1238 | Y26: =IFERROR(W26/X26,"") -> 299.63166 | Z26: =SUMIF(_26DinnerSalesACT[Week '#],$A26,_26DinnerSalesACT[Net sales])- SUMIFS(_2026AVATotalSalesCat[Net sales],_2026AVATotalSalesCat[Week '#],$A26,_2026AVATotalSalesCat[Sales category],"Non-Grat Svc Charges") -> 158585 | AA26: =1726-AD26 -> 1464 | AB26: =IFERROR(Z26/AA26,"") -> 108.32309 | AC26: =SUMIF(_26LunchSalesACT[Week '#],$A26,_26LunchSalesACT[Net sales]) -> 17868 | AD26: 262 | AE26: =IFERROR(AC26/AD26,"") -> 68.198473 | AF26: =SUMIF(_26MMSalesACT[Week '#],$A26,_26MMSalesACT[Net sales]) -> 26732.78 | AG26: =30+22+68+80 -> 200 | AH26: =IFERROR(AF26/AG26,"") -> 133.6639 | AI26: =Z26+AF26+AC26 -> 203185.78 | AJ26: =AA26+AG26+AD26 -> 1926 | AK26: =IFERROR(AI26/AJ26,"") -> 105.49625 | AL26: =SUMIF(Brunch[Week '#],$A26,Brunch[Net sales]) -> 146762.77 | AM26: =206+524 -> 730 | AN26: =IFERROR(AL26/AM26,"") -> 201.04489 | AO26: =SUMIF(Dinner__2[Week '#],$A26,Dinner__2[Net sales])- SUMIFS(Sales_Categories__2[Net sales],Sales_Categories__2[Week '#],$A26,Sales_Categories__2[Sales category],"Non-Grat Svc Charges") -> 633283.5 | AP26: =4483-AM26 -> 3753 | AQ26: =IFERROR(AO26/AP26,"") -> 168.74061 | AR26: =AO26+AL26 -> 780046.27 | AS26: =AP26+AM26 -> 4483 | AT26: =IFERROR(AR26/AS26,"") -> 174.00095 | AU26: =SUMIF(Brunch__2[Week '#],$A26,Brunch__2[Net sales]) -> 47193.66 | AV26: 410 | AW26: =IFERROR(AU26/AV26,0) -> 115.10649 | AX26: {=SUMPRODUCT((Dinner__3[Week '#]=$A26)*(INT(Dinner__3[yyyyMMdd]/10000)=VALUE(RIGHT($AX$2,4)))*Dinner__3[Net sales])-SUMPRODUCT((Sales_Categories__3[Week '#]=$A26)*(YEAR(Sales_Categories__3[Start Date])=VALUE(RIGHT($AX$2,4)))*(Sales_Categories__3[Sales category]="Non-Grat Svc Charges")*Sales_Categories__3[Net sales])} -> 226416.99 | AY26: =1965-AV26 -> 1555 | AZ26: =IFERROR(AX26/AY26,"") -> 145.60578 | BA26: =AX26+AU26 -> 273610.65 | BB26: =AY26+AV26 -> 1965 | BC26: =IFERROR(BA26/BB26,"") -> 139.24206 | BD26: =SUMIF(_2026DinnerSales[Week '#],$A26,_2026DinnerSales[Net sales])- SUMIFS(_2026TotalSalesCat[Net sales],_2026TotalSalesCat[Week '#],$A26,_2026TotalSalesCat[Sales category],"Non-Grat Svc Charges") -> 152638.83 | BE26: =1906-BH26 -> 1374 | BF26: =IFERROR(BD26/BE26,"") -> 111.09085 | BG26: =SUMIF(_2026BrunchSales[Week '#],$A26,_2026BrunchSales[Net sales]) -> 50328.35 | BH26: =244+288 -> 532 | BI26: =IFERROR(BG26/BH26,"") -> 94.602162 | BL26: =IFERROR(BJ26/BK26,"") | BM26: =BD26+BJ26+BG26 -> 202967.18 | BN26: =BE26+BK26+BH26 -> 1906 | BO26: =IFERROR(BM26/BN26,"") -> 106.48855 | BP26: =SUMIF(Lounge__2[Week '#],$A26,Lounge__2[Net sales])- SUMIFS(Sales_Categories__4[Net sales],Sales_Categories__4[Week '#],$A26,Sales_Categories__4[Sales category],"Non-Grat Svc Charges") -> 107280.75 | BQ26: =98+89+2+177+4+14+120+3 -> 507 | BR26: =IFERROR(BP26/BQ26,"") -> 211.59911 | BS26: =SUMIF(MM__2[Week '#],$A26,MM__2[Net sales]) -> 115291.75 | BT26: =100+114+84 -> 298 | BU26: =IFERROR(BS26/BT26,"") -> 386.88507 | BV26: =+BP26+BS26 -> 222572.5 | BW26: =BT26+BQ26 -> 805 | BX26: =IFERROR(BV26/BW26,"") -> 276.48758 | BY26: 0 | BZ26: 0 | CA26: =IFERROR(BY26/BZ26,"") | CB26: 0 | CC26: 0 | CD26: =IFERROR(CB26/CC26,"") | CG26: =IFERROR(CE26/CF26,"") | CH26: =BY26+CE26+CB26 -> 0 | CI26: =BZ26+CF26+CC26 -> 0 | CJ26: =IFERROR(CH26/CI26,"")
A27: Week 23 | B27: P6 | C27: =VLOOKUP(A27,Dates!$B$2:$E$53,4,FALSE) -> 23 | D27: =IF(C27<='RDG Weekly Sales'!$F$1,TRUE,FALSE) -> TRUE | E27: {=SUMPRODUCT((Dinner[Week '#]=$A27)*(INT(Dinner[yyyyMMdd]/10000)=VALUE(RIGHT($AX$2,4)))*Dinner[Net sales])-SUMPRODUCT((Non_Grat_Serv_Chrg[Week '#]=$A27)*(YEAR(Non_Grat_Serv_Chrg[Start Date])=VALUE(RIGHT($AX$2,4)))*(Non_Grat_Serv_Chrg[Sales category]="Non-Grat Svc Charges")*Non_Grat_Serv_Chrg[Net sales])} -> 593590 | F27: =3939-I27 -> 3602 | G27: =IFERROR(E27/F27,"") -> 164.79456 | H27: =SUMIF(Lunch[Week '#],$A27,Lunch[Net sales]) -> 39216.93 | I27: 337 | J27: =IFERROR(H27/I27,"") -> 116.37071 | K27: =E27+H27 -> 632806.93 | L27: =F27+I27 -> 3939 | M27: =IFERROR(K27/L27,"") -> 160.65167 | N27: =SUMIF(Omakase[Week '#],$A27,Omakase[Net sales]) -> 18291 | O27: 72 | P27: =IFERROR(N27/O27,"") -> 254.04167 | Q27: =SUMIF(MM[Week '#],$A27,MM[Net sales]) -> 54002 | R27: =50+28+75+2+80+101+2 -> 338 | S27: =IFERROR(Q27/R27,"") -> 159.76923 | T27: =SUMIF(Lounge[Week '#],$A27,Lounge[Net sales])-SUMIFS(Sales_Categories[Net sales],Sales_Categories[Week '#],$A27,Sales_Categories[Sales category],"Non-Grat Svc Charges") -> 139156 | U27: =103+143+1+150+9+181+4+2 -> 593 | V27: =IFERROR(T27/U27,"") -> 234.66442 | W27: =SUM(N27,Q27,T27) -> 211449 | X27: =SUM(O27,R27,U27) -> 1003 | Y27: =IFERROR(W27/X27,"") -> 210.81655 | Z27: =SUMIF(_26DinnerSalesACT[Week '#],$A27,_26DinnerSalesACT[Net sales])- SUMIFS(_2026AVATotalSalesCat[Net sales],_2026AVATotalSalesCat[Week '#],$A27,_2026AVATotalSalesCat[Sales category],"Non-Grat Svc Charges") -> 161480.79 | AA27: =1773-AD27 -> 1492 | AB27: =IFERROR(Z27/AA27,"") -> 108.23109 | AC27: =SUMIF(_26LunchSalesACT[Week '#],$A27,_26LunchSalesACT[Net sales]) -> 18179.55 | AD27: 281 | AE27: =IFERROR(AC27/AD27,"") -> 64.695907 | AF27: =SUMIF(_26MMSalesACT[Week '#],$A27,_26MMSalesACT[Net sales]) -> 30796.7 | AG27: =13+48+97 -> 158 | AH27: =IFERROR(AF27/AG27,"") -> 194.91582 | AI27: =Z27+AF27+AC27 -> 210457.04 | AJ27: =AA27+AG27+AD27 -> 1931 | AK27: =IFERROR(AI27/AJ27,"") -> 108.98863 | AL27: =SUMIF(Brunch[Week '#],$A27,Brunch[Net sales]) -> 122167.5 | AM27: =191+400 -> 591 | AN27: =IFERROR(AL27/AM27,"") -> 206.7132 | AO27: =SUMIF(Dinner__2[Week '#],$A27,Dinner__2[Net sales])- SUMIFS(Sales_Categories__2[Net sales],Sales_Categories__2[Week '#],$A27,Sales_Categories__2[Sales category],"Non-Grat Svc Charges") -> 457411.87 | AP27: =3644-AM27 -> 3053 | AQ27: =IFERROR(AO27/AP27,"") -> 149.82374 | AR27: =AO27+AL27 -> 579579.37 | AS27: =AP27+AM27 -> 3644 | AT27: =IFERROR(AR27/AS27,"") -> 159.05032 | AU27: =SUMIF(Brunch__2[Week '#],$A27,Brunch__2[Net sales]) -> 30539.5 | AV27: 330 | AW27: =IFERROR(AU27/AV27,0) -> 92.543939 | AX27: {=SUMPRODUCT((Dinner__3[Week '#]=$A27)*(INT(Dinner__3[yyyyMMdd]/10000)=VALUE(RIGHT($AX$2,4)))*Dinner__3[Net sales])-SUMPRODUCT((Sales_Categories__3[Week '#]=$A27)*(YEAR(Sales_Categories__3[Start Date])=VALUE(RIGHT($AX$2,4)))*(Sales_Categories__3[Sales category]="Non-Grat Svc Charges")*Sales_Categories__3[Net sales])} -> 196591.75 | AY27: =1734-AV27 -> 1404 | AZ27: =IFERROR(AX27/AY27,"") -> 140.02261 | BA27: =AX27+AU27 -> 227131.25 | BB27: =AY27+AV27 -> 1734 | BC27: =IFERROR(BA27/BB27,"") -> 130.98688 | BD27: =SUMIF(_2026DinnerSales[Week '#],$A27,_2026DinnerSales[Net sales])- SUMIFS(_2026TotalSalesCat[Net sales],_2026TotalSalesCat[Week '#],$A27,_2026TotalSalesCat[Sales category],"Non-Grat Svc Charges") -> 147470.99 | BE27: =1706-BH27 -> 1278 | BF27: =IFERROR(BD27/BE27,"") -> 115.39201 | BG27: =SUMIF(_2026BrunchSales[Week '#],$A27,_2026BrunchSales[Net sales]) -> 37719.93 | BH27: =187+241 -> 428 | BI27: =IFERROR(BG27/BH27,"") -> 88.130678 | BL27: =IFERROR(BJ27/BK27,"") | BM27: =BD27+BJ27+BG27 -> 185190.92 | BN27: =BE27+BK27+BH27 -> 1706 | BO27: =IFERROR(BM27/BN27,"") -> 108.55271 | BP27: =SUMIF(Lounge__2[Week '#],$A27,Lounge__2[Net sales])- SUMIFS(Sales_Categories__4[Net sales],Sales_Categories__4[Week '#],$A27,Sales_Categories__4[Sales category],"Non-Grat Svc Charges") -> 168574.25 | BQ27: =156+2+130+13+149+9+18+70 -> 547 | BR27: =IFERROR(BP27/BQ27,"") -> 308.17962 | BS27: =SUMIF(MM__2[Week '#],$A27,MM__2[Net sales]) -> 37587.75 | BT27: =29+76+87+100 -> 292 | BU27: =IFERROR(BS27/BT27,"") -> 128.72517 | BV27: =+BP27+BS27 -> 206162 | BW27: =BT27+BQ27 -> 839 | BX27: =IFERROR(BV27/BW27,"") -> 245.72348 | BY27: 0 | BZ27: 0 | CA27: =IFERROR(BY27/BZ27,"") | CB27: 0 | CC27: 0 | CD27: =IFERROR(CB27/CC27,"") | CG27: =IFERROR(CE27/CF27,"") | CH27: =BY27+CE27+CB27 -> 0 | CI27: =BZ27+CF27+CC27 -> 0 | CJ27: =IFERROR(CH27/CI27,"")
A28: Week 24 | B28: P6 | C28: =VLOOKUP(A28,Dates!$B$2:$E$53,4,FALSE) -> 24 | D28: =IF(C28<='RDG Weekly Sales'!$F$1,TRUE,FALSE) -> TRUE | E28: {=SUMPRODUCT((Dinner[Week '#]=$A28)*(INT(Dinner[yyyyMMdd]/10000)=VALUE(RIGHT($AX$2,4)))*Dinner[Net sales])-SUMPRODUCT((Non_Grat_Serv_Chrg[Week '#]=$A28)*(YEAR(Non_Grat_Serv_Chrg[Start Date])=VALUE(RIGHT($AX$2,4)))*(Non_Grat_Serv_Chrg[Sales category]="Non-Grat Svc Charges")*Non_Grat_Serv_Chrg[Net sales])} -> 526690.5 | F28: =3825-I28 -> 3522 | G28: =IFERROR(E28/F28,"") -> 149.54302 | H28: {=SUMPRODUCT((Lunch[Week '#]=$A28)*(INT(Lunch[yyyyMMdd]/10000)=VALUE(RIGHT($H$2,4)))*Lunch[Net sales])} -> 35956.5 | I28: 303 | J28: =IFERROR(H28/I28,"") -> 118.66832 | K28: =E28+H28 -> 562647 | L28: =F28+I28 -> 3825 | M28: =IFERROR(K28/L28,"") -> 147.09725 | N28: {=SUMPRODUCT((Omakase[Week '#]=$A28)*(INT(Omakase[yyyyMMdd]/10000)=VALUE(RIGHT($N$2,4)))*Omakase[Net sales])} -> 17273 | O28: 47 | P28: =IFERROR(N28/O28,"") -> 367.51064 | Q28: {=SUMPRODUCT((MM[Week '#]=$A28)*(INT(MM[yyyyMMdd]/10000)=VALUE(RIGHT($Q$2,4)))*MM[Net sales])} -> 30903 | R28: =22+53+2+66+53+2 -> 198 | S28: =IFERROR(Q28/R28,"") -> 156.07576 | T28: {=SUMPRODUCT((Lounge[Week '#]=$A28)*(INT(Lounge[yyyyMMdd]/10000)=VALUE(RIGHT($Q$2,4)))*Lounge[Net sales])-SUMIFS(Sales_Categories[Net sales],Sales_Categories[Week '#],$A28,Sales_Categories[Sales category],"Non-Grat Svc Charges")} -> 138324 | U28: =58+156+10+158+172+8 -> 562 | V28: =IFERROR(T28/U28,"") -> 246.12811 | W28: =SUM(N28,Q28,T28) -> 186500 | X28: =SUM(O28,R28,U28) -> 807 | Y28: =IFERROR(W28/X28,"") -> 231.10285 | Z28: {=SUMPRODUCT((_26DinnerSalesACT[Week '#]=$A28)*(INT(_26DinnerSalesACT[yyyyMMdd]/10000)=VALUE(RIGHT($AX$2,4)))*_26DinnerSalesACT[Net sales])- SUMIFS(_2026AVATotalSalesCat[Net sales],_2026AVATotalSalesCat[Week '#],$A28,_2026AVATotalSalesCat[Sales category],"Non-Grat Svc Charges")} -> 151669.27 | AA28: =1650-AD28 -> 1370 | AB28: =IFERROR(Z28/AA28,"") -> 110.7075 | AC28: =SUMIF(_26LunchSalesACT[Week '#],$A28,_26LunchSalesACT[Net sales]) -> 16768.82 | AD28: 280 | AE28: =IFERROR(AC28/AD28,"") -> 59.888643 | AF28: =SUMIF(_26MMSalesACT[Week '#],$A28,_26MMSalesACT[Net sales]) -> 22855.4 | AG28: =34+23+62+64 -> 183 | AH28: =IFERROR(AF28/AG28,"") -> 124.8929 | AI28: =Z28+AF28+AC28 -> 191293.49 | AJ28: =AA28+AG28+AD28 -> 1833 | AK28: =IFERROR(AI28/AJ28,"") -> 104.36088 | AL28: {=SUMPRODUCT((Brunch[Week '#]=$A28)*(INT(Brunch[yyyyMMdd]/10000)=VALUE(RIGHT($AL$2,4)))*Brunch[Net sales])} -> 160575.15 | AM28: =155+449 -> 604 | AN28: =IFERROR(AL28/AM28,"") -> 265.8529 | AO28: {=SUMPRODUCT((Dinner__2[Week '#]=$A28)*(INT(Dinner__2[yyyyMMdd]/10000)=VALUE(RIGHT($AL$2,4)))*Dinner__2[Net sales])- SUMIFS(Sales_Categories__2[Net sales],Sales_Categories__2[Week '#],$A28,Sales_Categories__2[Sales category],"Non-Grat Svc Charges")} -> 403082.61 | AP28: =3090-AM28 -> 2486 | AQ28: =IFERROR(AO28/AP28,"") -> 162.14103 | AR28: =AO28+AL28 -> 563657.76 | AS28: =AP28+AM28 -> 3090 | AT28: =IFERROR(AR28/AS28,"") -> 182.41351 | AU28: {=SUMPRODUCT((Brunch__2[Week '#]=$A28)*(INT(Brunch__2[yyyyMMdd]/10000)=VALUE(RIGHT($AU$2,4)))*Brunch__2[Net sales])} -> 16610.95 | AV28: 164 | AW28: =IFERROR(AU28/AV28,0) -> 101.28628 | AX28: {=SUMPRODUCT((Dinner__3[Week '#]=$A28)*(INT(Dinner__3[yyyyMMdd]/10000)=VALUE(RIGHT($AX$2,4)))*Dinner__3[Net sales])-SUMPRODUCT((Sales_Categories__3[Week '#]=$A28)*(YEAR(Sales_Categories__3[Start Date])=VALUE(RIGHT($AX$2,4)))*(Sales_Categories__3[Sales category]="Non-Grat Svc Charges")*Sales_Categories__3[Net sales])} -> 193599.75 | AY28: =1521-AV28 -> 1357 | AZ28: =IFERROR(AX28/AY28,"") -> 142.66746 | BA28: =AX28+AU28 -> 210210.7 | BB28: =AY28+AV28 -> 1521 | BC28: =IFERROR(BA28/BB28,"") -> 138.20559 | BD28: =SUMIF(_2026DinnerSales[Week '#],$A28,_2026DinnerSales[Net sales])- SUMIFS(_2026TotalSalesCat[Net sales],_2026TotalSalesCat[Week '#],$A28,_2026TotalSalesCat[Sales category],"Non-Grat Svc Charges") -> 136044.64 | BE28: =1547-BH28 -> 1101 | BF28: =IFERROR(BD28/BE28,"") -> 123.56461 | BG28: =SUMIF(_2026BrunchSales[Week '#],$A28,_2026BrunchSales[Net sales]) -> 36384.72 | BH28: =175+271 -> 446 | BI28: =IFERROR(BG28/BH28,"") -> 81.58009 | BL28: =IFERROR(BJ28/BK28,"") | BM28: =BD28+BJ28+BG28 -> 172429.36 | BN28: =BE28+BK28+BH28 -> 1547 | BO28: =IFERROR(BM28/BN28,"") -> 111.46048 | BP28: =SUMIF(Lounge__2[Week '#],$A28,Lounge__2[Net sales])- SUMIFS(Sales_Categories__4[Net sales],Sales_Categories__4[Week '#],$A28,Sales_Categories__4[Sales category],"Non-Grat Svc Charges") -> 97436.75 | BQ28: =34+124+5+93+6+107 -> 369 | BR28: =IFERROR(BP28/BQ28,"") -> 264.05623 | BS28: =SUMIF(MM__2[Week '#],$A28,MM__2[Net sales]) -> 26800.75 | BT28: =30+67+75+74+2 -> 248 | BU28: =IFERROR(BS28/BT28,"") -> 108.06754 | BV28: =+BP28+BS28 -> 124237.5 | BW28: =BT28+BQ28 -> 617 | BX28: =IFERROR(BV28/BW28,"") -> 201.35737 | BY28: 0 | BZ28: 0 | CA28: =IFERROR(BY28/BZ28,"") | CB28: 0 | CC28: 0 | CD28: =IFERROR(CB28/CC28,"") | CG28: =IFERROR(CE28/CF28,"") | CH28: =BY28+CE28+CB28 -> 0 | CI28: =BZ28+CF28+CC28 -> 0 | CJ28: =IFERROR(CH28/CI28,"")
A29: Week 25 | B29: P6 | C29: =VLOOKUP(A29,Dates!$B$2:$E$53,4,FALSE) -> 25 | D29: =IF(C29<='RDG Weekly Sales'!$F$1,TRUE,FALSE) -> TRUE | E29: =646975.09-H29-2121.25 -> 589991.64 | F29: =4171-I29 -> 3746 | G29: =IFERROR(E29/F29,"") -> 157.4991 | H29: 54862.2 | I29: 425 | J29: =IFERROR(H29/I29,"") -> 129.08753 | K29: =E29+H29 -> 644853.84 | L29: =F29+I29 -> 4171 | M29: =IFERROR(K29/L29,"") -> 154.60413 | N29: 15028.4 | O29: 54 | P29: =IFERROR(N29/O29,"") -> 278.3037 | Q29: =35578.45+8795 -> 44373.45 | R29: =44+24+73+84 -> 225 | S29: =IFERROR(Q29/R29,"") -> 197.21533 | T29: =142711.9+17873-194.35 -> 160390.55 | U29: =42+99+10+216+193 -> 560 | V29: =IFERROR(T29/U29,"") -> 286.4117 | W29: =SUM(N29,Q29,T29) -> 219792.4 | X29: =SUM(O29,R29,U29) -> 839 | Y29: =IFERROR(W29/X29,"") -> 261.96949 | Z29: =199098.6-198.4-AC29 -> 172269.2 | AA29: =1976-AD29 -> 1626 | AB29: =IFERROR(Z29/AA29,"") -> 105.94662 | AC29: 26631 | AD29: =119+231 -> 350 | AE29: =IFERROR(AC29/AD29,"") -> 76.088571 | AF29: =26890.53-285.65 -> 26604.88 | AG29: =22+23+64+53 -> 162 | AH29: =IFERROR(AF29/AG29,"") -> 164.22765 | AI29: =Z29+AF29+AC29 -> 225505.08 | AJ29: =AA29+AG29+AD29 -> 2138 | AK29: =IFERROR(AI29/AJ29,"") -> 105.47478 | AL29: 158003.15 | AM29: =422+823 -> 1245 | AN29: =IFERROR(AL29/AM29,"") -> 126.91016 | AO29: =658336.06-AL29-4253.9 -> 496079.01 | AP29: =3622-AM29 -> 2377 | AQ29: =IFERROR(AO29/AP29,"") -> 208.69963 | AR29: =AO29+AL29 -> 654082.16 | AS29: =AP29+AM29 -> 3622 | AT29: =IFERROR(AR29/AS29,"") -> 180.58591 | AU29: 37349.05 | AV29: =8+56+73+69+57 -> 263 | AW29: =IFERROR(AU29/AV29,0) -> 142.0116 | AX29: =196016.12-AU29-504.4 -> 158162.67 | AY29: =1560-AV29 -> 1297 | AZ29: =IFERROR(AX29/AY29,"") -> 121.945 | BA29: =AX29+AU29 -> 195511.72 | BB29: =AY29+AV29 -> 1560 | BC29: =IFERROR(BA29/BB29,"") -> 125.32803 | BD29: =166501.49-BG29-224 -> 127051.99 | BE29: =1601-BH29 -> 1139 | BF29: =IFERROR(BD29/BE29,"") -> 111.54696 | BG29: 39225.5 | BH29: =156+306 -> 462 | BI29: =IFERROR(BG29/BH29,"") -> 84.90368 | BL29: =IFERROR(BJ29/BK29,"") | BM29: =BD29+BJ29+BG29 -> 166277.49 | BN29: =BE29+BK29+BH29 -> 1601 | BO29: =IFERROR(BM29/BN29,"") -> 103.85852 | BP29: =121331.23+25235-2674.35 -> 143891.88 | BQ29: =47+92+2+2+244+129+7 -> 523 | BR29: =IFERROR(BP29/BQ29,"") -> 275.12788 | BS29: =49965.15+4156 -> 54121.15 | BT29: =50+30+96+56 -> 232 | BU29: =IFERROR(BS29/BT29,"") -> 233.28082 | BV29: =+BP29+BS29 -> 198013.03 | BW29: =BT29+BQ29 -> 755 | BX29: =IFERROR(BV29/BW29,"") -> 262.26891 | BY29: 0 | BZ29: 0 | CA29: =IFERROR(BY29/BZ29,"") | CB29: 0 | CC29: 0 | CD29: =IFERROR(CB29/CC29,"") | CG29: =IFERROR(CE29/CF29,"") | CH29: =BY29+CE29+CB29 -> 0 | CI29: =BZ29+CF29+CC29 -> 0 | CJ29: =IFERROR(CH29/CI29,"")
A30: Week 26 | B30: P6 | C30: =VLOOKUP(A30,Dates!$B$2:$E$53,4,FALSE) -> 26 | D30: =IF(C30<='RDG Weekly Sales'!$F$1,TRUE,FALSE) -> TRUE | E30: {=SUMPRODUCT((Dinner[Week '#]=$A30)*(INT(Dinner[yyyyMMdd]/10000)=VALUE(RIGHT($AX$2,4)))*Dinner[Net sales])-SUMPRODUCT((Non_Grat_Serv_Chrg[Week '#]=$A30)*(YEAR(Non_Grat_Serv_Chrg[Start Date])=VALUE(RIGHT($AX$2,4)))*(Non_Grat_Serv_Chrg[Sales category]="Non-Grat Svc Charges")*Non_Grat_Serv_Chrg[Net sales])} -> 611321.75 | F30: 3797 | G30: =IFERROR(E30/F30,"") -> 161.00125 | H30: {=SUMPRODUCT((Lunch[Week '#]=$A30)*(INT(Lunch[yyyyMMdd]/10000)=VALUE(RIGHT($H$2,4)))*Lunch[Net sales])} -> 45681 | I30: 382 | J30: =IFERROR(H30/I30,"") -> 119.58377 | K30: =E30+H30 -> 657002.75 | L30: =F30+I30 -> 4179 | M30: =IFERROR(K30/L30,"") -> 157.2153 | N30: {=SUMPRODUCT((Omakase[Week '#]=$A30)*(INT(Omakase[yyyyMMdd]/10000)=VALUE(RIGHT($N$2,4)))*Omakase[Net sales])} -> 19472.1 | O30: 61 | P30: =IFERROR(N30/O30,"") -> 319.21475 | Q30: {=SUMPRODUCT((MM[Week '#]=$A30)*(INT(MM[yyyyMMdd]/10000)=VALUE(RIGHT($Q$2,4)))*MM[Net sales])} -> 57073.9 | R30: 263 | S30: =IFERROR(Q30/R30,"") -> 217.01103 | T30: {=SUMPRODUCT((Lounge[Week '#]=$A30)*(INT(Lounge[yyyyMMdd]/10000)=VALUE(RIGHT($Q$2,4)))*Lounge[Net sales])-SUMIFS(Sales_Categories[Net sales],Sales_Categories[Week '#],$A30,Sales_Categories[Sales category],"Non-Grat Svc Charges")} -> 246913.28 | U30: 781 | V30: =IFERROR(T30/U30,"") -> 316.15017 | W30: =SUM(N30,Q30,T30) -> 323459.28 | X30: =SUM(O30,R30,U30) -> 1105 | Y30: =IFERROR(W30/X30,"") -> 292.72333 | Z30: {=SUMPRODUCT((_26DinnerSalesACT[Week '#]=$A30)*(INT(_26DinnerSalesACT[yyyyMMdd]/10000)=VALUE(RIGHT($AX$2,4)))*_26DinnerSalesACT[Net sales])- SUMIFS(_2026AVATotalSalesCat[Net sales],_2026AVATotalSalesCat[Week '#],$A30,_2026AVATotalSalesCat[Sales category],"Non-Grat Svc Charges")} -> 169795.59 | AA30: 1560 | AB30: =IFERROR(Z30/AA30,"") -> 108.84333 | AC30: =SUMIF(_26LunchSalesACT[Week '#],$A30,_26LunchSalesACT[Net sales]) -> 14802.01 | AD30: 236 | AE30: =IFERROR(AC30/AD30,"") -> 62.720381 | AF30: =SUMIF(_26MMSalesACT[Week '#],$A30,_26MMSalesACT[Net sales]) -> 35790.71 | AG30: 166 | AH30: =IFERROR(AF30/AG30,"") -> 215.60669 | AI30: =Z30+AF30+AC30 -> 220388.31 | AJ30: =AA30+AG30+AD30 -> 1962 | AK30: =IFERROR(AI30/AJ30,"") -> 112.32839 | AL30: {=SUMPRODUCT((Brunch[Week '#]=$A30)*(INT(Brunch[yyyyMMdd]/10000)=VALUE(RIGHT($AL$2,4)))*Brunch[Net sales])} -> 282785.58 | AM30: 1270 | AN30: =IFERROR(AL30/AM30,"") -> 222.66581 | AO30: {=SUMPRODUCT((Dinner__2[Week '#]=$A30)*(INT(Dinner__2[yyyyMMdd]/10000)=VALUE(RIGHT($AL$2,4)))*Dinner__2[Net sales])- SUMIFS(Sales_Categories__2[Net sales],Sales_Categories__2[Week '#],$A30,Sales_Categories__2[Sales category],"Non-Grat Svc Charges")} -> 544420.23 | AP30: 2583 | AQ30: =IFERROR(AO30/AP30,"") -> 210.77051 | AR30: =AO30+AL30 -> 827205.81 | AS30: =AP30+AM30 -> 3853 | AT30: =IFERROR(AR30/AS30,"") -> 214.69136 | AU30: {=SUMPRODUCT((Brunch__2[Week '#]=$A30)*(INT(Brunch__2[yyyyMMdd]/10000)=VALUE(RIGHT($AU$2,4)))*Brunch__2[Net sales])} -> 22948.96 | AV30: 299 | AW30: =IFERROR(AU30/AV30,0) -> 76.752375 | AX30: {=SUMPRODUCT((Dinner__3[Week '#]=$A30)*(INT(Dinner__3[yyyyMMdd]/10000)=VALUE(RIGHT($AX$2,4)))*Dinner__3[Net sales])-SUMPRODUCT((Sales_Categories__3[Week '#]=$A30)*(YEAR(Sales_Categories__3[Start Date])=VALUE(RIGHT($AX$2,4)))*(Sales_Categories__3[Sales category]="Non-Grat Svc Charges")*Sales_Categories__3[Net sales])} -> 232390.55 | AY30: 1557 | AZ30: =IFERROR(AX30/AY30,"") -> 149.25533 | BA30: =AX30+AU30 -> 255339.51 | BB30: =AY30+AV30 -> 1856 | BC30: =IFERROR(BA30/BB30,"") -> 137.57517 | BD30: =SUMIF(_2026DinnerSales[Week '#],$A30,_2026DinnerSales[Net sales])- SUMIFS(_2026TotalSalesCat[Net sales],_2026TotalSalesCat[Week '#],$A30,_2026TotalSalesCat[Sales category],"Non-Grat Svc Charges") -> 124131.76 | BE30: 1081 | BF30: =IFERROR(BD30/BE30,"") -> 114.83049 | BG30: =SUMIF(_2026BrunchSales[Week '#],$A30,_2026BrunchSales[Net sales]) -> 31372.37 | BH30: 367 | BI30: =IFERROR(BG30/BH30,"") -> 85.483297 | BL30: =IFERROR(BJ30/BK30,"") | BM30: =BD30+BJ30+BG30 -> 155504.13 | BN30: =BE30+BK30+BH30 -> 1448 | BO30: =IFERROR(BM30/BN30,"") -> 107.39235 | BP30: =SUMIF(Lounge__2[Week '#],$A30,Lounge__2[Net sales])- SUMIFS(Sales_Categories__4[Net sales],Sales_Categories__4[Week '#],$A30,Sales_Categories__4[Sales category],"Non-Grat Svc Charges") -> 244637.13 | BQ30: 666 | BR30: =IFERROR(BP30/BQ30,"") -> 367.32302 | BS30: =SUMIF(MM__2[Week '#],$A30,MM__2[Net sales]) -> 26674 | BT30: 242 | BU30: =IFERROR(BS30/BT30,"") -> 110.22314 | BV30: =+BP30+BS30 -> 271311.13 | BW30: =BT30+BQ30 -> 908 | BX30: =IFERROR(BV30/BW30,"") -> 298.8008 | BY30: 0 | BZ30: 0 | CA30: =IFERROR(BY30/BZ30,"") | CB30: 0 | CC30: 0 | CD30: =IFERROR(CB30/CC30,"") | CG30: =IFERROR(CE30/CF30,"") | CH30: =BY30+CE30+CB30 -> 0 | CI30: =BZ30+CF30+CC30 -> 0 | CJ30: =IFERROR(CH30/CI30,"")
