Workbook

Sheet EBIDTA 2
D2: ='[1]Overview 2026'!B24 -> 46025
C4: ='[1]Overview 2026'!J3 -> 9 | D4: =VLOOKUP(D$2,'[1]Overview 2026'!$B$7:$AC$52,$C4,FALSE) -> CLOONEE
B5: DJ Cost | C5: ='[1]Overview 2026'!L3 -> 11 | D5: =VLOOKUP(D$2,'[1]Overview 2026'!$B$7:$AC$52,$C5,FALSE) -> 100000
B6: Dj Cost / Sales Ratio | D6: =IFERROR(D5/D8,"") -> 0.45454545
B8: Brunch Sales | C8: ='[1]Overview 2026'!F3 -> 5 | D8: =D15+D16 -> 220000
B9: Dinner Sales | C9: ='[1]Overview 2026'!H3 -> 7 | D9: =VLOOKUP(D$2,'[1]Overview 2026'!$B$7:$AC$52,$C9,FALSE) -> 101500
B10: Total Sales | D10: =SUM(D8:E9) -> 321500
B11: Budgeted Sales | C11: ='[1]Overview 2026'!D3 -> 3 | D11: =IF(VLOOKUP(D$2,'[1]Overview 2026'!$B6:$AC$52,$C11,FALSE)=0,"",VLOOKUP(D$2,'[1]Overview 2026'!$B6:$AC$52,$C11,FALSE))
B12: Holiday | C12: ='[1]Overview 2026'!C3 -> 2 | D12: =IF(VLOOKUP(D$2,'[1]Overview 2026'!$B7:$AC$52,$C12,FALSE)=0,"",VLOOKUP(D$2,'[1]Overview 2026'!$B7:$AC$52,$C12,FALSE))
B14: Brunch Sales Breakdown
B15: Dining Sales | C15: ='[1]Overview 2026'!F3 -> 5 | D15: =VLOOKUP(D$2,'[1]Overview 2026'!$B7:$AC$52,$C15,FALSE) -> 20000
B16: Bottle Service Sales | C16: ='[1]Overview 2026'!O3 -> 14 | D16: =IFERROR(D5*E16,0) -> 200000 | E16: =VLOOKUP(D$2,'[1]Overview 2026'!$B$7:$AC$52,$C16,FALSE) -> 2
B18: Table Minimum Breakdown
B19: # tables | D19: =E30 -> 28
B20: Avg. Minimum / Table | D20: =D16/D19 -> 7142.8571
C22: ='[1]Overview 2026'!R3 -> 17 | D22: =IF(VLOOKUP(D$2,'[1]Overview 2026'!$B$7:$AC$52,$C22,FALSE)=0,"Beach Club",VLOOKUP(D$2,'[1]Overview 2026'!$B$7:$AC$52,$C22,FALSE)) -> Beach Club
B23: =VLOOKUP(D$22,'[1]Floor Plan Bottle Service'!$R$29:$Y$31,2,FALSE) -> Tier 1 | C23: ='[1]Overview 2026'!W3 -> 22 | D23: =VLOOKUP(D$2,'[1]Overview 2026'!$B$7:$AC$52,$C23,FALSE) -> 11800 | E23: =IF(VLOOKUP(D$22,'[1]Floor Plan Bottle Service'!$R$33:$X$34,2,FALSE)=0,"",VLOOKUP(D$22,'[1]Floor Plan Bottle Service'!$R$33:$X$34,2,FALSE)) -> 3 | G23: =VLOOKUP(H$22,'[1]Floor Plan Bottle Service'!$R$29:$Y$31,2,FALSE) -> #N/A
B24: =VLOOKUP(D$22,'[1]Floor Plan Bottle Service'!$R$29:$Y$31,3,FALSE) -> Tier 2 | C24: ='[1]Overview 2026'!X3 -> 23 | D24: =VLOOKUP(D$2,'[1]Overview 2026'!$B$7:$AC$52,$C24,FALSE) -> 9400 | E24: =VLOOKUP(D$22,'[1]Floor Plan Bottle Service'!$R$33:$Y$34,3,FALSE) -> 2 | G24: =VLOOKUP(H$22,'[1]Floor Plan Bottle Service'!$R$29:$Y$31,3,FALSE) -> #N/A
B25: =VLOOKUP(D$22,'[1]Floor Plan Bottle Service'!$R$29:$Y$31,4,FALSE) -> Tier 3 | C25: ='[1]Overview 2026'!Y3 -> 24 | D25: =VLOOKUP(D$2,'[1]Overview 2026'!$B$7:$AC$52,$C25,FALSE) -> 8200 | E25: =VLOOKUP(D$22,'[1]Floor Plan Bottle Service'!$R$33:$Y$34,4,FALSE) -> 13 | G25: =VLOOKUP(H$22,'[1]Floor Plan Bottle Service'!$R$29:$Y$31,4,FALSE) -> #N/A
B26: =VLOOKUP(D$22,'[1]Floor Plan Bottle Service'!$R$29:$Y$31,5,FALSE) -> Tier 4 | C26: ='[1]Overview 2026'!Z3 -> 25 | D26: =VLOOKUP(D$2,'[1]Overview 2026'!$B$7:$AC$52,$C26,FALSE) -> 5800 | E26: =VLOOKUP(D$22,'[1]Floor Plan Bottle Service'!$R$33:$Y$34,5,FALSE) -> 5 | G26: =VLOOKUP(H$22,'[1]Floor Plan Bottle Service'!$R$29:$Y$31,5,FALSE) -> #N/A
B27: =IF(E27=0,"",VLOOKUP(D$22,'[1]Floor Plan Bottle Service'!$R$29:$Y$31,6,FALSE)) -> Tier 5 | C27: ='[1]Overview 2026'!AA3 -> 26 | D27: =VLOOKUP(D$2,'[1]Overview 2026'!$B$7:$AC$52,$C27,FALSE) -> 3500 | E27: =VLOOKUP(D$22,'[1]Floor Plan Bottle Service'!$R$33:$Y$34,6,FALSE) -> 5 | G27: =IF(I27=0,"",VLOOKUP(H$22,'[1]Floor Plan Bottle Service'!$R$29:$Y$31,6,FALSE))
B28: =IF(E28=0,"",VLOOKUP(D$22,'[1]Floor Plan Bottle Service'!$R$29:$Y$31,7,FALSE)) | C28: ='[1]Overview 2026'!AB3 -> 27 | D28: =VLOOKUP(D$2,'[1]Overview 2026'!$B$7:$AC$52,$C28,FALSE) -> 0 | E28: =VLOOKUP(D$22,'[1]Floor Plan Bottle Service'!$R$33:$Y$34,7,FALSE) -> 0 | G28: =IF(I28=0,"",VLOOKUP(H$22,'[1]Floor Plan Bottle Service'!$R$29:$Y$31,7,FALSE))
B29: =IF(E29=0,"",VLOOKUP(D$22,'[1]Floor Plan Bottle Service'!$R$29:$Y$31,8,FALSE)) | C29: ='[1]Overview 2026'!AC3 -> 28 | D29: =VLOOKUP(D$2,'[1]Overview 2026'!$B$7:$AC$52,$C29,FALSE) -> 0 | E29: =VLOOKUP(D$22,'[1]Floor Plan Bottle Service'!$R$33:$Y$34,8,FALSE) -> 0 | G29: =IF(I29=0,"",VLOOKUP(H$22,'[1]Floor Plan Bottle Service'!$R$29:$Y$31,8,FALSE))
D30: =(D23*E23)+(D24*E24)+(D25*E25)+(D26*E26)+(D27*E27)+(D29*E29)+(D28*E28) -> 207300 | E30: =SUM(E23:E29) -> 28
B33: LBW Sales | D33: =D$36*E33 -> 199330 | E33: 0.62
B34: Food Sales | D34: =D$36*E34 -> 109310 | E34: =E36-E33-E35 -> 0.34
B35: Beverage Sales | D35: =D$36*E35 -> 12860 | E35: 0.04
B36: Total Sales | D36: =D10 -> 321500 | E36: 1
B38: LBW Cost | D38: =E38*D33 -> 29899.5 | E38: 0.15
B39: Food Cost | D39: =E39*D34 -> 28967.15 | E39: 0.265
B40: Beverage Cost | D40: =E40*D35 -> 3600.8 | E40: 0.28
B41: COGS | D41: =SUM(D38:D40) -> 62467.45 | E41: =D41/D36 -> 0.1943
B43: Gross Profit | D43: =D36-D41 -> 259032.55 | E43: =D43/D36 -> 0.8057
B45: Payroll Expenses
B46: Management | D46: ='OPEX DATA 2'!U143 -> 4809.2312 | E46: =D46/D$36 -> 0.014958728
B47: FOH Hourly | D47: ='OPEX DATA 2'!U119 -> 2065.1092 | E47: =D47/D$36 -> 0.0064233569
B48: BOH Hourly | E48: =D48/D$36 -> 0
B49: Payroll Taxes & Other | D49: ='OPEX DATA 2'!U151 -> 2629.4965 | E49: =D49/D$36 -> 0.0081788384
B50: Total Payroll Expenses | D50: =SUM(D46:D49) -> 9503.8369 | E50: =D50/D$36 -> 0.029560924
B52: ='OPEX DATA 2'!A159 -> Direct Operating Expenses
B53: ='OPEX DATA 2'!A161 -> 6105 - Automobile | D53: ='OPEX DATA 2'!U161 -> 0.24153846 | E53: =D53/D$36 -> 7.5128604e-07
B54: ='OPEX DATA 2'!A162 -> 6110 - China | D54: ='OPEX DATA 2'!U162 -> 315.81654 | E54: =D54/D$36 -> 0.00098232205
B55: ='OPEX DATA 2'!A163 -> 6120 - Glass | D55: ='OPEX DATA 2'!U163 -> 121.49442 | E55: =D55/D$36 -> 0.00037789867
B56: ='OPEX DATA 2'!A164 -> 6130 - Silverware | D56: ='OPEX DATA 2'!U164 -> 38.287308 | E56: =D56/D$36 -> 0.0001190896
B57: ='OPEX DATA 2'!A165 -> 6200 - Bar Supplies | D57: ='OPEX DATA 2'!U165 -> 54.475385 | E57: =D57/D$36 -> 0.00016944132
B58: ='OPEX DATA 2'!A166 -> 6201 - Ice Expense | D58: ='OPEX DATA 2'!U166 -> 174.56385 | E58: =D58/D$36 -> 0.00054296686
B59: ='OPEX DATA 2'!A167 -> 6210 - Cleaning Supplies | D59: ='OPEX DATA 2'!U167 -> 147.65269 | E59: =D59/D$36 -> 0.00045926187
B60: ='OPEX DATA 2'!A168 -> 6230 - Kitchen Supplies | D60: ='OPEX DATA 2'!U168 -> 251.86308 | E60: =D60/D$36 -> 0.00078339993
B61: ='OPEX DATA 2'!A169 -> 6235 - Kitchen Equipment - Ops | D61: ='OPEX DATA 2'!U169 -> 22.196346 | E61: =D61/D$36 -> 6.9039957e-05
B62: ='OPEX DATA 2'!A170 -> 6240 - Restaurant Supplies | D62: ='OPEX DATA 2'!U170 -> 375.31942 | E62: =D62/D$36 -> 0.001167401
B63: ='OPEX DATA 2'!A171 -> 6245 - Restaurant Equipment | D63: ='OPEX DATA 2'!U171 -> 195.05365 | E63: =D63/D$36 -> 0.00060669877
B64: ='OPEX DATA 2'!A172 -> 6246 - Hotel Amenities | D64: ='OPEX DATA 2'!U172 -> 0 | E64: =D64/D$36 -> 0
... B87: ='OPEX DATA 2'!A195 -> 6610 - License & Permits | D87: ='OPEX DATA 2'!U195 -> 87.905577 | E87: =D87/D$36 -> 0.00027342326
B88: ='OPEX DATA 2'!A196 -> 6750 - Live Entertainment | D88: =D5 -> 100000 | E88: =D88/D$36 -> 0.31104199
B89: ='OPEX DATA 2'!A197 -> 6755 - Members Entertainment | D89: ='OPEX DATA 2'!U197 -> 30.485192 | E89: =D89/D$36 -> 9.4821749e-05
B90: ='OPEX DATA 2'!A198 -> 6760 - MM at Sea | D90: ='OPEX DATA 2'!U198 -> 0 | E90: =D90/D$36 -> 0
B91: ='OPEX DATA 2'!A199 -> 6761 - Docking fees expenses | D91: ='OPEX DATA 2'!U199 -> 0 | E91: =D91/D$36 -> 0
B92: ='OPEX DATA 2'!A200 -> 6762 - Operating Yachting Cost | D92: ='OPEX DATA 2'!U200 -> 0 | E92: =D92/D$36 -> 0
B93: ='OPEX DATA 2'!A201 -> 6770 - Printing Expense | D93: ='OPEX DATA 2'!U201 -> 37.785577 | E93: =D93/D$36 -> 0.00011752901
B94: ='OPEX DATA 2'!A202 -> 6780 - AVA Coconut Grove | D94: ='OPEX DATA 2'!U202 -> 0 | E94: =D94/D$36 -> 0
B95: ='OPEX DATA 2'!A203 -> 6781 - E11even | D95: ='OPEX DATA 2'!U203 -> 0 | E95: =D95/D$36 -> 0
B96: ='OPEX DATA 2'!A204 -> 6782 - Vanquish CN | D96: ='OPEX DATA 2'!U204 -> 0 | E96: =D96/D$36 -> 0
B97: ='OPEX DATA 2'!A205 -> 6783 - Mila Cannes | D97: ='OPEX DATA 2'!U205 -> 0 | E97: =D97/D$36 -> 0
B98: ='OPEX DATA 2'!A206 -> 6784 - GP (Casa Neos) | D98: ='OPEX DATA 2'!U206 -> 0 | E98: =D98/D$36 -> 0
B99: ='OPEX DATA 2'!A207 -> 6785 - AVA research and Development | D99: ='OPEX DATA 2'!U207 -> 0 | E99: =D99/D$36 -> 0
B100: ='OPEX DATA 2'!A208 -> 6800 - COVID Expenses | D100: ='OPEX DATA 2'!U208 -> 0 | E100: =D100/D$36 -> 0
B101: ='OPEX DATA 2'!A209 -> Total Direct Operating Expenses | D101: =SUM(D53:D100) -> 105124.52 | E101: =D101/D$36 -> 0.3269814
B103: ='OPEX DATA 2'!A213 -> General and Administrative
B104: ='OPEX DATA 2'!A215 -> 7010 - Credit Card Fees | D104: =E104*D10 -> 9645 | E104: 0.03
B105: ='OPEX DATA 2'!A216 -> 7015 - Open Table Fees | D105: ='OPEX DATA 2'!U216 -> 136.86538 | E105: =D105/D$36 -> 0.00042570882
B106: ='OPEX DATA 2'!A217 -> 7020 - Dues and Subscriptions | D106: ='OPEX DATA 2'!U217 -> 566.11923 | E106: =D106/D$36 -> 0.0017608685
B107: ='OPEX DATA 2'!A218 -> 7040 - Payroll Processing Fees | D107: ='OPEX DATA 2'!U218 -> 56.692308 | E107: =D107/D$36 -> 0.00017633688
B108: ='OPEX DATA 2'!A219 -> 7050 - Fire & Security | D108: ='OPEX DATA 2'!U219 -> 859.605 | E108: =D108/D$36 -> 0.0026737325
B109: ='OPEX DATA 2'!A220 -> 7060 - Postage & Delivery | D109: ='OPEX DATA 2'!U220 -> 33.871154 | E109: =D109/D$36 -> 0.00010535351
B110: ='OPEX DATA 2'!A221 -> 7070 - Storage facility | D110: ='OPEX DATA 2'!U221 -> 160.44846 | E110: =D110/D$36 -> 0.00049906209
B111: ='OPEX DATA 2'!A222 -> 7080 - Office Supplies | D111: ='OPEX DATA 2'!U222 -> 4.1528846 | E111: =D111/D$36 -> 1.2917215e-05
B112: ='OPEX DATA 2'!A223 -> 7090 - Computer Supplies | D112: ='OPEX DATA 2'!U223 -> 14.536154 | E112: =D112/D$36 -> 4.5213542e-05
B113: ='OPEX DATA 2'!A224 -> 7091 - IT Support | D113: ='OPEX DATA 2'!U224 -> 7.265 | E113: =D113/D$36 -> 2.2597201e-05
B114: ='OPEX DATA 2'!A225 -> 7092 - IT AI solutions | D114: ='OPEX DATA 2'!U225 -> 12.499423 | E114: =D114/D$36 -> 3.8878454e-05
B115: ='OPEX DATA 2'!A226 -> 7100 - Cash Short (Over) | D115: ='OPEX DATA 2'!U226 -> 3.9086538 | E115: =D115/D$36 -> 1.2157555e-05
B116: ='OPEX DATA 2'!A227 -> 7110 - Bank Fees | D116: ='OPEX DATA 2'!U227 -> 53.207115 | E116: =D116/D$36 -> 0.00016549647
... B129: ='OPEX DATA 2'!A240 -> 7180 - Commissary General Administrative | D129: ='OPEX DATA 2'!U240 -> 0 | E129: =D129/D$36 -> 0
B130: ='OPEX DATA 2'!A241 -> Total General and Administrative | D130: =SUM(D104:D129) -> 14144.821 | E130: =D130/D$36 -> 0.043996331
B132: ='OPEX DATA 2'!A242 -> Utilities
B133: ='OPEX DATA 2'!A244 -> 7510 - Telephone | D133: ='OPEX DATA 2'!U244 -> 41.0875 | E133: =D133/D$36 -> 0.00012779938
B134: ='OPEX DATA 2'!A245 -> 7520 - Internet | D134: ='OPEX DATA 2'!U245 -> 56.722308 | E134: =D134/D$36 -> 0.00017643019
B135: ='OPEX DATA 2'!A246 -> 7530 - Cable & Music | D135: ='OPEX DATA 2'!U246 -> 0 | E135: =D135/D$36 -> 0
B136: ='OPEX DATA 2'!A247 -> 7540 - Electricity | D136: ='OPEX DATA 2'!U247 -> 238.67615 | E136: =D136/D$36 -> 0.00074238306
B137: ='OPEX DATA 2'!A248 -> 7550 - Gas | D137: ='OPEX DATA 2'!U248 -> 46.737308 | E137: =D137/D$36 -> 0.00014537265
B138: ='OPEX DATA 2'!A249 -> 7570 - Garbage/Recycle | D138: ='OPEX DATA 2'!U249 -> 206.64577 | E138: =D138/D$36 -> 0.00064275511
B139: ='OPEX DATA 2'!A250 -> 7580 - Water & Sewer | D139: ='OPEX DATA 2'!U250 -> 42.426154 | E139: =D139/D$36 -> 0.00013196315
B140: ='OPEX DATA 2'!A251 -> 7700 - Commissary Utilities | D140: ='OPEX DATA 2'!U251 -> 0 | E140: =D140/D$36 -> 0
B141: ='OPEX DATA 2'!A252 -> Total Utilities | D141: =SUM(D133:D140) -> 632.29519 | E141: =D141/D$36 -> 0.0019667036
B143: ='OPEX DATA 2'!A253 -> Occupancy
B144: ='OPEX DATA 2'!A255 -> 7910 - Rent | D144: ='OPEX DATA 2'!U255 -> 0 | E144: =D144/D$36 -> 0
B145: ='OPEX DATA 2'!A256 -> 7911 - Percentage Rent | D145: ='OPEX DATA 2'!U256 -> 1801.5821 | E145: =D145/D$36 -> 0.0056036769
B146: ='OPEX DATA 2'!A257 -> 7912 - Prior Year Rent Exp | D146: ='OPEX DATA 2'!U257 -> 0 | E146: =D146/D$36 -> 0
B147: ='OPEX DATA 2'!A258 -> 7920 - CAM Charges | D147: ='OPEX DATA 2'!U258 -> 533.03462 | E147: =D147/D$36 -> 0.0016579615
B148: ='OPEX DATA 2'!A259 -> 7930 - Commissary Occupancy | D148: ='OPEX DATA 2'!U259 -> 0 | E148: =D148/D$36 -> 0
B149: ='OPEX DATA 2'!A260 -> 7940 - Property Tax | D149: ='OPEX DATA 2'!U260 -> 0 | E149: =D149/D$36 -> 0
...

Sheet OPEX DATA 2
A1: ` | U1: # Weeks: | V1: =4+4+5 -> 13
K5: Period 4, 2026 | N5: Period 5, 2026 | Q5: PTD 6, 2026 | T5: YTD | U5: Daily Costs
A6: Sales
A7: Food Sales
A8: 4010 - Food Sales | K8: 185418.37 | L8: =IFERROR(K8/K327, "NA") -> 0.20328162 | N8: 273267.01 | O8: =IFERROR(N8/N327, "NA") -> 0.18961866 | Q8: 212103 | R8: =IFERROR(Q8/Q327, "NA") -> 0.19209179 | T8: =IFERROR(B8+E8+H8+K8+N8+Q8, "NA") -> 670788.38 | U8: =(T8/$V$1)/4 -> 12899.777
A9: 4015 - Commissary sales | K9: 0 | L9: =IFERROR(K9/K327, "NA") -> 0 | N9: 0 | O9: =IFERROR(N9/N327, "NA") -> 0 | Q9: 0 | R9: =IFERROR(Q9/Q327, "NA") -> 0 | T9: =IFERROR(B9+E9+H9+K9+N9+Q9, "NA") -> 0 | U9: =(T9/$V$1)/4 -> 0
A10: Total Food Sales | K10: =IFERROR(K8+K9, "NA") -> 185418.37 | L10: =IFERROR(K10/K327, "NA") -> 0.20328162 | N10: =IFERROR(N8+N9, "NA") -> 273267.01 | O10: =IFERROR(N10/N327, "NA") -> 0.18961866 | Q10: =IFERROR(Q8+Q9, "NA") -> 212103 | R10: =IFERROR(Q10/Q327, "NA") -> 0.19209179 | T10: =IFERROR(B10+E10+H10+K10+N10+Q10, "NA") -> 670788.38 | U10: =(T10/$V$1)/4 -> 12899.777
A11: 4020 - N/A Beverage Sales | K11: 33711 | L11: =IFERROR(K11/K327, "NA") -> 0.036958727 | N11: 40376 | O11: =IFERROR(N11/N327, "NA") -> 0.028016711 | Q11: 39938 | R11: =IFERROR(Q11/Q327, "NA") -> 0.036169984 | T11: =IFERROR(B11+E11+H11+K11+N11+Q11, "NA") -> 114025 | U11: =(T11/$V$1)/4 -> 2192.7885
A12: LBW Sales | T12: =IFERROR(B12+E12+H12+K12+N12+Q12, "NA") -> 0 | U12: =(T12/$V$1)/4 -> 0
A13: 4100 - LBW Sales | K13: 0 | L13: =IFERROR(K13/K327, "NA") -> 0 | N13: 0 | O13: =IFERROR(N13/N327, "NA") -> 0 | Q13: 0 | R13: =IFERROR(Q13/Q327, "NA") -> 0 | T13: =IFERROR(B13+E13+H13+K13+N13+Q13, "NA") -> 0 | U13: =(T13/$V$1)/4 -> 0
A14: 4105 - Liquor Sales | K14: 590693 | L14: =IFERROR(K14/K327, "NA") -> 0.64760052 | N14: 816948.21 | O14: =IFERROR(N14/N327, "NA") -> 0.56687642 | Q14: 640884.52 | R14: =IFERROR(Q14/Q327, "NA") -> 0.58041921 | T14: =IFERROR(B14+E14+H14+K14+N14+Q14, "NA") -> 2048525.7 | U14: =(T14/$V$1)/4 -> 39394.726
A15: 4165 - Beer Sales | K15: 5016 | L15: =IFERROR(K15/K327, "NA") -> 0.0054992428 | N15: 6128 | O15: =IFERROR(N15/N327, "NA") -> 0.0042521896 | Q15: 5940 | R15: =IFERROR(Q15/Q327, "NA") -> 0.0053795809 | T15: =IFERROR(B15+E15+H15+K15+N15+Q15, "NA") -> 17084 | U15: =(T15/$V$1)/4 -> 328.53846
A16: 4180 - Wine Sales | K16: 124735 | L16: =IFERROR(K16/K327, "NA") -> 0.136752 | N16: 248408 | O16: =IFERROR(N16/N327, "NA") -> 0.17236911 | Q16: 123330 | R16: =IFERROR(Q16/Q327, "NA") -> 0.11169423 | T16: =IFERROR(B16+E16+H16+K16+N16+Q16, "NA") -> 496473 | U16: =(T16/$V$1)/4 -> 9547.5577
A17: 4181 - Wine BTG Sales | K17: 20799 | L17: =IFERROR(K17/K327, "NA") -> 0.022802781 | N17: 19808 | O17: =IFERROR(N17/N327, "NA") -> 0.013744675 | Q17: 22299 | R17: =IFERROR(Q17/Q327, "NA") -> 0.020195164 | T17: =IFERROR(B17+E17+H17+K17+N17+Q17, "NA") -> 62906 | U17: =(T17/$V$1)/4 -> 1209.7308
A18: 4182 - Wine Reserve Sales | K18: 0 | L18: =IFERROR(K18/K327, "NA") -> 0 | N18: 0 | O18: =IFERROR(N18/N327, "NA") -> 0 | Q18: 0 | R18: =IFERROR(Q18/Q327, "NA") -> 0 | T18: =IFERROR(B18+E18+H18+K18+N18+Q18, "NA") -> 0 | U18: =(T18/$V$1)/4 -> 0
A19: Total LBW Sales | K19: =IFERROR(K13+K14+K15+K16+K17+K18, "NA") -> 741243 | L19: =IFERROR(K19/K327, "NA") -> 0.81265455 | N19: =IFERROR(N13+N14+N15+N16+N17+N18, "NA") -> 1091292.2 | O19: =IFERROR(N19/N327, "NA") -> 0.75724239 | Q19: =IFERROR(Q13+Q14+Q15+Q16+Q17+Q18, "NA") -> 792453.52 | R19: =IFERROR(Q19/Q327, "NA") -> 0.71768819 | T19: =IFERROR(B19+E19+H19+K19+N19+Q19, "NA") -> 2624988.7 | U19: =(T19/$V$1)/4 -> 50480.552
A20: Other Sales | T20: =IFERROR(B20+E20+H20+K20+N20+Q20, "NA") -> 0 | U20: =(T20/$V$1)/4 -> 0
A21: 4209 - Other Sales | K21: 0 | L21: =IFERROR(K21/K327, "NA") -> 0 | N21: 0 | O21: =IFERROR(N21/N327, "NA") -> 0 | Q21: 0 | R21: =IFERROR(Q21/Q327, "NA") -> 0 | T21: =IFERROR(B21+E21+H21+K21+N21+Q21, "NA") -> 0 | U21: =(T21/$V$1)/4 -> 0
A22: 4210 - Retail Sales | K22: 15485.86 | L22: =IFERROR(K22/K327, "NA") -> 0.016977772 | N22: 30095.36 | O22: =IFERROR(N22/N327, "NA") -> 0.020883025 | Q22: 33235.43 | R22: =IFERROR(Q22/Q327, "NA") -> 0.030099779 | T22: =IFERROR(B22+E22+H22+K22+N22+Q22, "NA") -> 78816.65 | U22: =(T22/$V$1)/4 -> 1515.7048
A23: 4211 - No show / Min not met | K23: 412 | L23: =IFERROR(K23/K327, "NA") -> 0.00045169219 | N23: 0 | O23: =IFERROR(N23/N327, "NA") -> 0 | Q23: 886.11 | R23: =IFERROR(Q23/Q327, "NA") -> 0.00080250849 | T23: =IFERROR(B23+E23+H23+K23+N23+Q23, "NA") -> 1298.11 | U23: =(T23/$V$1)/4 -> 24.963654
A24: 4215 - Yacht sales | K24: 0 | L24: =IFERROR(K24/K327, "NA") -> 0 | N24: 0 | O24: =IFERROR(N24/N327, "NA") -> 0 | Q24: 0 | R24: =IFERROR(Q24/Q327, "NA") -> 0 | T24: =IFERROR(B24+E24+H24+K24+N24+Q24, "NA") -> 0 | U24: =(T24/$V$1)/4 -> 0
A25: 4216 - Docking fees Revenue | K25: 0 | L25: =IFERROR(K25/K327, "NA") -> 0 | N25: 0 | O25: =IFERROR(N25/N327, "NA") -> 0 | Q25: 0 | R25: =IFERROR(Q25/Q327, "NA") -> 0 | T25: =IFERROR(B25+E25+H25+K25+N25+Q25, "NA") -> 0 | U25: =(T25/$V$1)/4 -> 0
A26: 4220 - Membership Revenue | K26: 0 | L26: =IFERROR(K26/K327, "NA") -> 0 | N26: 62421.3 | O26: =IFERROR(N26/N327, "NA") -> 0.043313838 | Q26: 81567.48 | R26: =IFERROR(Q26/Q327, "NA") -> 0.073871862 | T26: =IFERROR(B26+E26+H26+K26+N26+Q26, "NA") -> 143988.78 | U26: =(T26/$V$1)/4 -> 2769.015
A27: 4221 - Application Fee Revenue | K27: 0 | L27: =IFERROR(K27/K327, "NA") -> 0 | N27: 0 | O27: =IFERROR(N27/N327, "NA") -> 0 | Q27: 0 | R27: =IFERROR(Q27/Q327, "NA") -> 0 | T27: =IFERROR(B27+E27+H27+K27+N27+Q27, "NA") -> 0 | U27: =(T27/$V$1)/4 -> 0
A28: 4230 - Retained Service Charge | K28: 0 | L28: =IFERROR(K28/K327, "NA") -> 0 | N28: 0 | O28: =IFERROR(N28/N327, "NA") -> 0 | Q28: 0 | R28: =IFERROR(Q28/Q327, "NA") -> 0 | T28: =IFERROR(B28+E28+H28+K28+N28+Q28, "NA") -> 0 | U28: =(T28/$V$1)/4 -> 0
A29: 4250 - Service Sales | K29: 0 | L29: =IFERROR(K29/K327, "NA") -> 0 | N29: 0 | O29: =IFERROR(N29/N327, "NA") -> 0 | Q29: 0 | R29: =IFERROR(Q29/Q327, "NA") -> 0 | T29: =IFERROR(B29+E29+H29+K29+N29+Q29, "NA") -> 0 | U29: =(T29/$V$1)/4 -> 0
A30: Total Other Sales | K30: =IFERROR(K21+K22+K23+K24+K25+K26+K27+K28+K29, "NA") -> 15897.86 | L30: =IFERROR(K30/K327, "NA") -> 0.017429464 | N30: =IFERROR(N21+N22+N23+N24+N25+N26+N27+N28+N29, "NA") -> 92516.66 | O30: =IFERROR(N30/N327, "NA") -> 0.064196863 | Q30: =IFERROR(Q21+Q22+Q23+Q24+Q25+Q26+Q27+Q28+Q29, "NA") -> 115689.02 | R30: =IFERROR(Q30/Q327, "NA") -> 0.10477415 | T30: =IFERROR(B30+E30+H30+K30+N30+Q30, "NA") -> 224103.54 | U30: =(T30/$V$1)/4 -> 4309.6835
A31: Hotel Sales | T31: =IFERROR(B31+E31+H31+K31+N31+Q31, "NA") -> 0 | U31: =(T31/$V$1)/4 -> 0
A32: 4399 - Hotel Sales | K32: 0 | L32: =IFERROR(K32/K327, "NA") -> 0 | N32: 0 | O32: =IFERROR(N32/N327, "NA") -> 0 | Q32: 0 | R32: =IFERROR(Q32/Q327, "NA") -> 0 | T32: =IFERROR(B32+E32+H32+K32+N32+Q32, "NA") -> 0 | U32: =(T32/$V$1)/4 -> 0
A33: 4301 - Accommodation | K33: 0 | L33: =IFERROR(K33/K327, "NA") -> 0 | N33: 0 | O33: =IFERROR(N33/N327, "NA") -> 0 | Q33: 0 | R33: =IFERROR(Q33/Q327, "NA") -> 0 | T33: =IFERROR(B33+E33+H33+K33+N33+Q33, "NA") -> 0 | U33: =(T33/$V$1)/4 -> 0
A34: 4310 - Mini Bar | K34: 0 | L34: =IFERROR(K34/K327, "NA") -> 0 | N34: 0 | O34: =IFERROR(N34/N327, "NA") -> 0 | Q34: 0 | R34: =IFERROR(Q34/Q327, "NA") -> 0 | T34: =IFERROR(B34+E34+H34+K34+N34+Q34, "NA") -> 0 | U34: =(T34/$V$1)/4 -> 0
A35: 4320 - Destination Fee | K35: 0 | L35: =IFERROR(K35/K327, "NA") -> 0 | N35: 0 | O35: =IFERROR(N35/N327, "NA") -> 0 | Q35: 0 | R35: =IFERROR(Q35/Q327, "NA") -> 0 | T35: =IFERROR(B35+E35+H35+K35+N35+Q35, "NA") -> 0 | U35: =(T35/$V$1)/4 -> 0
A36: 4340 - Other Accommodation | K36: 0 | L36: =IFERROR(K36/K327, "NA") -> 0 | N36: 0 | O36: =IFERROR(N36/N327, "NA") -> 0 | Q36: 0 | R36: =IFERROR(Q36/Q327, "NA") -> 0 | T36: =IFERROR(B36+E36+H36+K36+N36+Q36, "NA") -> 0 | U36: =(T36/$V$1)/4 -> 0
A37: Total Hotel Sales | K37: =IFERROR(K32+K33+K34+K35+K36, "NA") -> 0 | L37: =IFERROR(K37/K327, "NA") -> 0 | N37: =IFERROR(N32+N33+N34+N35+N36, "NA") -> 0 | O37: =IFERROR(N37/N327, "NA") -> 0 | Q37: =IFERROR(Q32+Q33+Q34+Q35+Q36, "NA") -> 0 | R37: =IFERROR(Q37/Q327, "NA") -> 0 | T37: =IFERROR(B37+E37+H37+K37+N37+Q37, "NA") -> 0 | U37: =(T37/$V$1)/4 -> 0
A38: Comps & Promotions | T38: =IFERROR(B38+E38+H38+K38+N38+Q38, "NA") -> 0 | U38: =(T38/$V$1)/4 -> 0
A39: 4900 - Comps & Promotions | K39: 0 | L39: =IFERROR(K39/K327, "NA") -> 0 | N39: 0 | O39: =IFERROR(N39/N327, "NA") -> 0 | Q39: 0 | R39: =IFERROR(Q39/Q327, "NA") -> 0 | T39: =IFERROR(B39+E39+H39+K39+N39+Q39, "NA") -> 0 | U39: =(T39/$V$1)/4 -> 0
A40: 4910 - Employee Discount | K40: -88.25 | L40: =IFERROR(K40/K327, "NA") -> -9.6752028e-05 | N40: -132.75 | O40: =IFERROR(N40/N327, "NA") -> -9.2114584e-05 | Q40: -148.5 | R40: =IFERROR(Q40/Q327, "NA") -> -0.00013448952 | T40: =IFERROR(B40+E40+H40+K40+N40+Q40, "NA") -> -369.5 | U40: =(T40/$V$1)/4 -> -7.1057692
A41: 4915 - Manager Meal | K41: -1187 | L41: =IFERROR(K41/K327, "NA") -> -0.0013013559 | N41: -929 | O41: =IFERROR(N41/N327, "NA") -> -0.00064462861 | Q41: -1884 | R41: =IFERROR(Q41/Q327, "NA") -> -0.0017062509 | T41: =IFERROR(B41+E41+H41+K41+N41+Q41, "NA") -> -4000 | U41: =(T41/$V$1)/4 -> -76.923077
A42: 4920 - Positive Comp | K42: -3451 | L42: =IFERROR(K42/K327, "NA") -> -0.0037834703 | N42: -3002 | O42: =IFERROR(N42/N327, "NA") -> -0.0020830733 | Q42: -4067 | R42: =IFERROR(Q42/Q327, "NA") -> -0.0036832922 | T42: =IFERROR(B42+E42+H42+K42+N42+Q42, "NA") -> -10520 | U42: =(T42/$V$1)/4 -> -202.30769
A43: 4924 - Marketing/Promotions | K43: -12703 | L43: =IFERROR(K43/K327, "NA") -> -0.01392681 | N43: -18620.04 | O43: =IFERROR(N43/N327, "NA") -> -0.012920356 | Q43: -24439.41 | R43: =IFERROR(Q43/Q327, "NA") -> -0.022133634 | T43: =IFERROR(B43+E43+H43+K43+N43+Q43, "NA") -> -55762.45 | U43: =(T43/$V$1)/4 -> -1072.3548
A44: 4925 - Customer Discounts | K44: -1498.4 | L44: =IFERROR(K44/K327, "NA") -> -0.0016427563 | N44: -1603.2 | O44: =IFERROR(N44/N327, "NA") -> -0.0011124527 | Q44: -1696.4 | R44: =IFERROR(Q44/Q327, "NA") -> -0.0015363503 | T44: =IFERROR(B44+E44+H44+K44+N44+Q44, "NA") -> -4798 | U44: =(T44/$V$1)/4 -> -92.269231
A45: 4926 - Promo G/C | K45: 0 | L45: =IFERROR(K45/K327, "NA") -> 0 | N45: 0 | O45: =IFERROR(N45/N327, "NA") -> 0 | Q45: 0 | R45: =IFERROR(Q45/Q327, "NA") -> 0 | T45: =IFERROR(B45+E45+H45+K45+N45+Q45, "NA") -> 0 | U45: =(T45/$V$1)/4 -> 0
A46: 4927 - Entertainment staff meal | K46: -31827 | L46: =IFERROR(K46/K327, "NA") -> -0.034893222 | N46: -22410.01 | O46: =IFERROR(N46/N327, "NA") -> -0.015550198 | Q46: -14593 | R46: =IFERROR(Q46/Q327, "NA") -> -0.013216199 | T46: =IFERROR(B46+E46+H46+K46+N46+Q46, "NA") -> -68830.01 | U46: =(T46/$V$1)/4 -> -1323.654
A47: 4930 - Negative Comp | K47: -6605 | L47: =IFERROR(K47/K327, "NA") -> -0.0072413274 | N47: -5894 | O47: =IFERROR(N47/N327, "NA") -> -0.0040898181 | Q47: -4607 | R47: =IFERROR(Q47/Q327, "NA") -> -0.004172345 | T47: =IFERROR(B47+E47+H47+K47+N47+Q47, "NA") -> -17106 | U47: =(T47/$V$1)/4 -> -328.96154
A48: 4933 - Training & Tasting | K48: -2021 | L48: =IFERROR(K48/K327, "NA") -> -0.0022157037 | N48: -2254 | O48: =IFERROR(N48/N327, "NA") -> -0.0015640397 | Q48: -2397 | R48: =IFERROR(Q48/Q327, "NA") -> -0.0021708511 | T48: =IFERROR(B48+E48+H48+K48+N48+Q48, "NA") -> -6672 | U48: =(T48/$V$1)/4 -> -128.30769
A49: 4934 - Corporate Comp | K49: 0 | L49: =IFERROR(K49/K327, "NA") -> 0 | N49: 0 | O49: =IFERROR(N49/N327, "NA") -> 0 | Q49: 0 | R49: =IFERROR(Q49/Q327, "NA") -> 0 | T49: =IFERROR(B49+E49+H49+K49+N49+Q49, "NA") -> 0 | U49: =(T49/$V$1)/4 -> 0
A50: 4935 - Exec Comp | K50: -4764 | L50: =IFERROR(K50/K327, "NA") -> -0.005222965 | N50: -1467 | O50: =IFERROR(N50/N327, "NA") -> -0.0010179442 | Q50: -2176 | R50: =IFERROR(Q50/Q327, "NA") -> -0.0019707017 | T50: =IFERROR(B50+E50+H50+K50+N50+Q50, "NA") -> -8407 | U50: =(T50/$V$1)/4 -> -161.67308
A51: Total Comps & Promotions | K51: =IFERROR(K39+K40+K41+K42+K43+K44+K45+K46+K47+K48+K49+K50, "NA") -> -64144.65 | L51: =IFERROR(K51/K327, "NA") -> -0.070324363 | N51: =IFERROR(N39+N40+N41+N42+N43+N44+N45+N46+N47+N48+N49+N50, "NA") -> -56312 | O51: =IFERROR(N51/N327, "NA") -> -0.039074625 | Q51: =IFERROR(Q39+Q40+Q41+Q42+Q43+Q44+Q45+Q46+Q47+Q48+Q49+Q50, "NA") -> -56008.31 | R51: =IFERROR(Q51/Q327, "NA") -> -0.050724114 | T51: =IFERROR(B51+E51+H51+K51+N51+Q51, "NA") -> -176464.96 | U51: =(T51/$V$1)/4 -> -3393.5569
A52: Total Sales | K52: =IFERROR(K8+K9+K11+K13+K14+K15+K16+K17+K18+K21+K22+K23+K24+K25+K26+K27+K28+K29+K32+K33+K34+K35+K36+K39+K40+K41+K42+K43+K44+K45+K46+K47+K48+K49+K50, "NA") -> 912125.58 | L52: =IFERROR(K52/K327, "NA") -> 1 | N52: =IFERROR(N8+N9+N11+N13+N14+N15+N16+N17+N18+N21+N22+N23+N24+N25+N26+N27+N28+N29+N32+N33+N34+N35+N36+N39+N40+N41+N42+N43+N44+N45+N46+N47+N48+N49+N50, "NA") -> 1441139.9 | O52: =IFERROR(N52/N327, "NA") -> 1 | Q52: =IFERROR(Q8+Q9+Q11+Q13+Q14+Q15+Q16+Q17+Q18+Q21+Q22+Q23+Q24+Q25+Q26+Q27+Q28+Q29+Q32+Q33+Q34+Q35+Q36+Q39+Q40+Q41+Q42+Q43+Q44+Q45+Q46+Q47+Q48+Q49+Q50, "NA") -> 1104175.2 | R52: =IFERROR(Q52/Q327, "NA") -> 1 | T52: =IFERROR(B52+E52+H52+K52+N52+Q52, "NA") -> 3457440.7 | U52: =(T52/$V$1)/4 -> 66489.244
A53: Prime Cost | T53: =IFERROR(B53+E53+H53+K53+N53+Q53, "NA") -> 0 | U53: =(T53/$V$1)/4 -> 0
A54: Food Cost | T54: =IFERROR(B54+E54+H54+K54+N54+Q54, "NA") -> 0 | U54: =(T54/$V$1)/4 -> 0
A55: 5009 - Food Cost | K55: 0 | L55: =IFERROR(K55/K327, "NA") -> 0 | N55: 0 | O55: =IFERROR(N55/N327, "NA") -> 0 | Q55: 0 | R55: =IFERROR(Q55/Q327, "NA") -> 0 | T55: =IFERROR(B55+E55+H55+K55+N55+Q55, "NA") -> 0 | U55: =(T55/$V$1)/4 -> 0
A56: 5010 - Purchase Produce | K56: 8321.14 | L56: =IFERROR(K56/K327, "NA") -> 0.0091228008 | N56: 9549.65 | O56: =IFERROR(N56/N327, "NA") -> 0.006626456 | Q56: 8437.28 | R56: =IFERROR(Q56/Q327, "NA") -> 0.0076412509 | T56: =IFERROR(B56+E56+H56+K56+N56+Q56, "NA") -> 26308.07 | U56: =(T56/$V$1)/4 -> 505.92442
A57: 5020 - Purchase Dairy | K57: 3203.14 | L57: =IFERROR(K57/K327, "NA") -> 0.0035117314 | N57: 3738.59 | O57: =IFERROR(N57/N327, "NA") -> 0.0025941895 | Q57: 3491.79 | R57: =IFERROR(Q57/Q327, "NA") -> 0.0031623513 | T57: =IFERROR(B57+E57+H57+K57+N57+Q57, "NA") -> 10433.52 | U57: =(T57/$V$1)/4 -> 200.64462
A58: 5030 - Purchase Meat | K58: 10248.71 | L58: =IFERROR(K58/K327, "NA") -> 0.011236073 | N58: 15031.22 | O58: =IFERROR(N58/N327, "NA") -> 0.010430091 | Q58: 11160.62 | R58: =IFERROR(Q58/Q327, "NA") -> 0.010107653 | T58: =IFERROR(B58+E58+H58+K58+N58+Q58, "NA") -> 36440.55 | U58: =(T58/$V$1)/4 -> 700.77981
A59: 5033 - Purchase Poultry | K59: 840.16 | L59: =IFERROR(K59/K327, "NA") -> 0.00092110124 | N59: 1193.64 | O59: =IFERROR(N59/N327, "NA") -> 0.00082826103 | Q59: 925.38 | R59: =IFERROR(Q59/Q327, "NA") -> 0.0008380735 | T59: =IFERROR(B59+E59+H59+K59+N59+Q59, "NA") -> 2959.18 | U59: =(T59/$V$1)/4 -> 56.907308
A60: 5040 - Purchase Seafood | K60: 19139.29 | L60: =IFERROR(K60/K327, "NA") -> 0.020983174 | N60: 23556.63 | O60: =IFERROR(N60/N327, "NA") -> 0.016345832 | Q60: 22822.31 | R60: =IFERROR(Q60/Q327, "NA") -> 0.020669102 | T60: =IFERROR(B60+E60+H60+K60+N60+Q60, "NA") -> 65518.23 | U60: =(T60/$V$1)/4 -> 1259.966
A61: 5050 - Purchase Dry Goods | K61: 7298.08 | L61: =IFERROR(K61/K327, "NA") -> 0.008001179 | N61: 8870.78 | O61: =IFERROR(N61/N327, "NA") -> 0.0061553914 | Q61: 6838.47 | R61: =IFERROR(Q61/Q327, "NA") -> 0.0061932833 | T61: =IFERROR(B61+E61+H61+K61+N61+Q61, "NA") -> 23007.33 | U61: =(T61/$V$1)/4 -> 442.44865
A62: 5060 - Purchase Bread | K62: 1299.95 | L62: =IFERROR(K62/K327, "NA") -> 0.0014251875 | N62: 999.33 | O62: =IFERROR(N62/N327, "NA") -> 0.00069343026 | Q62: 2383.49 | R62: =IFERROR(Q62/Q327, "NA") -> 0.0021586157 | T62: =IFERROR(B62+E62+H62+K62+N62+Q62, "NA") -> 4682.77 | U62: =(T62/$V$1)/4 -> 90.053269
A63: 5070 - Purchase Food Commissary | K63: 1840.5 | L63: =IFERROR(K63/K327, "NA") -> 0.0020178143 | N63: 2476.18 | O63: =IFERROR(N63/N327, "NA") -> 0.0017182093 | Q63: 1676.06 | R63: =IFERROR(Q63/Q327, "NA") -> 0.0015179294 | T63: =IFERROR(B63+E63+H63+K63+N63+Q63, "NA") -> 5992.74 | U63: =(T63/$V$1)/4 -> 115.245
A64: 5090 - Purchase Family Meal DNU old | K64: 0 | L64: =IFERROR(K64/K327, "NA") -> 0 | N64: 0 | O64: =IFERROR(N64/N327, "NA") -> 0 | Q64: 0 | R64: =IFERROR(Q64/Q327, "NA") -> 0 | T64: =IFERROR(B64+E64+H64+K64+N64+Q64, "NA") -> 0 | U64: =(T64/$V$1)/4 -> 0
A65: Total Food Cost | K65: =IFERROR(K55+K56+K57+K58+K59+K60+K61+K62+K63+K64, "NA") -> 52190.97 | L65: =IFERROR(K65/K327, "NA") -> 0.057219062 | N65: =IFERROR(N55+N56+N57+N58+N59+N60+N61+N62+N63+N64, "NA") -> 65416.02 | O65: =IFERROR(N65/N327, "NA") -> 0.04539186 | Q65: =IFERROR(Q55+Q56+Q57+Q58+Q59+Q60+Q61+Q62+Q63+Q64, "NA") -> 57735.4 | R65: =IFERROR(Q65/Q327, "NA") -> 0.052288259 | T65: =IFERROR(B65+E65+H65+K65+N65+Q65, "NA") -> 175342.39 | U65: =(T65/$V$1)/4 -> 3371.969
A66: 5080 - Purchase N/A Beverages | K66: 7626.2 | L66: =IFERROR(K66/K327, "NA") -> 0.0083609101 | N66: 8085.89 | O66: =IFERROR(N66/N327, "NA") -> 0.00561076 | Q66: 7989.18 | R66: =IFERROR(Q66/Q327, "NA") -> 0.0072354277 | T66: =IFERROR(B66+E66+H66+K66+N66+Q66, "NA") -> 23701.27 | U66: =(T66/$V$1)/4 -> 455.79365
A67: LBW Cost | T67: =IFERROR(B67+E67+H67+K67+N67+Q67, "NA") -> 0 | U67: =(T67/$V$1)/4 -> 0
A68: 5110 - LBW Cost | K68: 0 | L68: =IFERROR(K68/K327, "NA") -> 0 | N68: 0 | O68: =IFERROR(N68/N327, "NA") -> 0 | Q68: 0 | R68: =IFERROR(Q68/Q327, "NA") -> 0 | T68: =IFERROR(B68+E68+H68+K68+N68+Q68, "NA") -> 0 | U68: =(T68/$V$1)/4 -> 0
A69: 5120 - Purchase Beer | K69: 648.12 | L69: =IFERROR(K69/K327, "NA") -> 0.00071056005 | N69: 941.44 | O69: =IFERROR(N69/N327, "NA") -> 0.00065326067 | Q69: 707.82 | R69: =IFERROR(Q69/Q327, "NA") -> 0.00064103956 | T69: =IFERROR(B69+E69+H69+K69+N69+Q69, "NA") -> 2297.38 | U69: =(T69/$V$1)/4 -> 44.180385
A70: 5130 - Purchase Wine BTG | K70: 0 | L70: =IFERROR(K70/K327, "NA") -> 0 | N70: 0 | O70: =IFERROR(N70/N327, "NA") -> 0 | Q70: 0 | R70: =IFERROR(Q70/Q327, "NA") -> 0 | T70: =IFERROR(B70+E70+H70+K70+N70+Q70, "NA") -> 0 | U70: =(T70/$V$1)/4 -> 0
A71: 5131 - Purchase Wine | K71: 23652.02 | L71: =IFERROR(K71/K327, "NA") -> 0.025930662 | N71: 49068.54 | O71: =IFERROR(N71/N327, "NA") -> 0.034048423 | Q71: 23501.09 | R71: =IFERROR(Q71/Q327, "NA") -> 0.021283841 | T71: =IFERROR(B71+E71+H71+K71+N71+Q71, "NA") -> 96221.65 | U71: =(T71/$V$1)/4 -> 1850.4163
A72: 5132 - Purchase Wine Reserve | K72: 0 | L72: =IFERROR(K72/K327, "NA") -> 0 | N72: 0 | O72: =IFERROR(N72/N327, "NA") -> 0 | Q72: 90 | R72: =IFERROR(Q72/Q327, "NA") -> 8.1508802e-05 | T72: =IFERROR(B72+E72+H72+K72+N72+Q72, "NA") -> 90 | U72: =(T72/$V$1)/4 -> 1.7307692
A73: 5170 - Purchase Liquor | K73: 48088.1 | L73: =IFERROR(K73/K327, "NA") -> 0.05272092 | N73: 83799.05 | O73: =IFERROR(N73/N327, "NA") -> 0.058147756 | Q73: 56573.1 | R73: =IFERROR(Q73/Q327, "NA") -> 0.051235618 | T73: =IFERROR(B73+E73+H73+K73+N73+Q73, "NA") -> 188460.25 | U73: =(T73/$V$1)/4 -> 3624.2356
A74: 5174 - Purchase Beverage Commissary | K74: 0 | L74: =IFERROR(K74/K327, "NA") -> 0 | N74: 0 | O74: =IFERROR(N74/N327, "NA") -> 0 | Q74: 0 | R74: =IFERROR(Q74/Q327, "NA") -> 0 | T74: =IFERROR(B74+E74+H74+K74+N74+Q74, "NA") -> 0 | U74: =(T74/$V$1)/4 -> 0
A75: 5175 - Purchase Bar Consumables | K75: 4712.2 | L75: =IFERROR(K75/K327, "NA") -> 0.0051661746 | N75: 5216.41 | O75: =IFERROR(N75/N327, "NA") -> 0.0036196417 | Q75: 6625.24 | R75: =IFERROR(Q75/Q327, "NA") -> 0.0060001708 | T75: =IFERROR(B75+E75+H75+K75+N75+Q75, "NA") -> 16553.85 | U75: =(T75/$V$1)/4 -> 318.34327
A76: Total LBW Cost | K76: =IFERROR(K68+K69+K70+K71+K72+K73+K74+K75, "NA") -> 77100.44 | L76: =IFERROR(K76/K327, "NA") -> 0.084528317 | N76: =IFERROR(N68+N69+N70+N71+N72+N73+N74+N75, "NA") -> 139025.44 | O76: =IFERROR(N76/N327, "NA") -> 0.096469081 | Q76: =IFERROR(Q68+Q69+Q70+Q71+Q72+Q73+Q74+Q75, "NA") -> 87497.25 | R76: =IFERROR(Q76/Q327, "NA") -> 0.079242178 | T76: =IFERROR(B76+E76+H76+K76+N76+Q76, "NA") -> 303623.13 | U76: =(T76/$V$1)/4 -> 5838.9063
A77: Purchase Retail | T77: =IFERROR(B77+E77+H77+K77+N77+Q77, "NA") -> 0 | U77: =(T77/$V$1)/4 -> 0
A78: 5200 - Purchase Retail | K78: 0 | L78: =IFERROR(K78/K327, "NA") -> 0 | N78: 0 | O78: =IFERROR(N78/N327, "NA") -> 0 | Q78: 0 | R78: =IFERROR(Q78/Q327, "NA") -> 0 | T78: =IFERROR(B78+E78+H78+K78+N78+Q78, "NA") -> 0 | U78: =(T78/$V$1)/4 -> 0
A79: 5210 - Purchase Mini Bar | K79: 0 | L79: =IFERROR(K79/K327, "NA") -> 0 | N79: 0 | O79: =IFERROR(N79/N327, "NA") -> 0 | Q79: 0 | R79: =IFERROR(Q79/Q327, "NA") -> 0 | T79: =IFERROR(B79+E79+H79+K79+N79+Q79, "NA") -> 0 | U79: =(T79/$V$1)/4 -> 0
A80: Total Purchase Retail | K80: =IFERROR(K78+K79, "NA") -> 0 | L80: =IFERROR(K80/K327, "NA") -> 0 | N80: =IFERROR(N78+N79, "NA") -> 0 | O80: =IFERROR(N80/N327, "NA") -> 0 | Q80: =IFERROR(Q78+Q79, "NA") -> 0 | R80: =IFERROR(Q80/Q327, "NA") -> 0 | T80: =IFERROR(B80+E80+H80+K80+N80+Q80, "NA") -> 0 | U80: =(T80/$V$1)/4 -> 0
A81: Payroll Expenses | T81: =IFERROR(B81+E81+H81+K81+N81+Q81, "NA") -> 0 | U81: =(T81/$V$1)/4 -> 0
A82: 5400 - Payroll Expenses | K82: 0 | L82: =IFERROR(K82/K327, "NA") -> 0 | N82: 0 | O82: =IFERROR(N82/N327, "NA") -> 0 | Q82: 0 | R82: =IFERROR(Q82/Q327, "NA") -> 0 | T82: =IFERROR(B82+E82+H82+K82+N82+Q82, "NA") -> 0 | U82: =(T82/$V$1)/4 -> 0
A83: Houlry Labor | T83: =IFERROR(B83+E83+H83+K83+N83+Q83, "NA") -> 0 | U83: =(T83/$V$1)/4 -> 0
A84: 5445 - Houlry Labor | K84: 0 | L84: =IFERROR(K84/K327, "NA") -> 0 | N84: 0 | O84: =IFERROR(N84/N327, "NA") -> 0 | Q84: 0 | R84: =IFERROR(Q84/Q327, "NA") -> 0 | T84: =IFERROR(B84+E84+H84+K84+N84+Q84, "NA") -> 0 | U84: =(T84/$V$1)/4 -> 0
A85: 5430 - Line Cook | K85: 0 | L85: =IFERROR(K85/K327, "NA") -> 0 | N85: 0 | O85: =IFERROR(N85/N327, "NA") -> 0 | Q85: 0 | R85: =IFERROR(Q85/Q327, "NA") -> 0 | T85: =IFERROR(B85+E85+H85+K85+N85+Q85, "NA") -> 0 | U85: =(T85/$V$1)/4 -> 0
A86: 5431 - Prep Cook | K86: 0 | L86: =IFERROR(K86/K327, "NA") -> 0 | N86: 0 | O86: =IFERROR(N86/N327, "NA") -> 0 | Q86: 0 | R86: =IFERROR(Q86/Q327, "NA") -> 0 | T86: =IFERROR(B86+E86+H86+K86+N86+Q86, "NA") -> 0 | U86: =(T86/$V$1)/4 -> 0
A87: 5432 - Pastry Cook | K87: 0 | L87: =IFERROR(K87/K327, "NA") -> 0 | N87: 0 | O87: =IFERROR(N87/N327, "NA") -> 0 | Q87: 0 | R87: =IFERROR(Q87/Q327, "NA") -> 0 | T87: =IFERROR(B87+E87+H87+K87+N87+Q87, "NA") -> 0 | U87: =(T87/$V$1)/4 -> 0
A88: 5433 - Sushi Cook | K88: 0 | L88: =IFERROR(K88/K327, "NA") -> 0 | N88: 0 | O88: =IFERROR(N88/N327, "NA") -> 0 | Q88: 0 | R88: =IFERROR(Q88/Q327, "NA") -> 0 | T88: =IFERROR(B88+E88+H88+K88+N88+Q88, "NA") -> 0 | U88: =(T88/$V$1)/4 -> 0
A89: 5435 - Chef de Partie | K89: 0 | L89: =IFERROR(K89/K327, "NA") -> 0 | N89: 0 | O89: =IFERROR(N89/N327, "NA") -> 0 | Q89: 0 | R89: =IFERROR(Q89/Q327, "NA") -> 0 | T89: =IFERROR(B89+E89+H89+K89+N89+Q89, "NA") -> 0 | U89: =(T89/$V$1)/4 -> 0
A90: 5436 - Butcher | K90: 0 | L90: =IFERROR(K90/K327, "NA") -> 0 | N90: 0 | O90: =IFERROR(N90/N327, "NA") -> 0 | Q90: 0 | R90: =IFERROR(Q90/Q327, "NA") -> 0 | T90: =IFERROR(B90+E90+H90+K90+N90+Q90, "NA") -> 0 | U90: =(T90/$V$1)/4 -> 0
A91: 5439 - Food EXPO BOH | K91: 0 | L91: =IFERROR(K91/K327, "NA") -> 0 | N91: 0 | O91: =IFERROR(N91/N327, "NA") -> 0 | Q91: 0 | R91: =IFERROR(Q91/Q327, "NA") -> 0 | T91: =IFERROR(B91+E91+H91+K91+N91+Q91, "NA") -> 0 | U91: =(T91/$V$1)/4 -> 0
A92: 5440 - Dishwashers | K92: 0 | L92: =IFERROR(K92/K327, "NA") -> 0 | N92: 0 | O92: =IFERROR(N92/N327, "NA") -> 0 | Q92: 0 | R92: =IFERROR(Q92/Q327, "NA") -> 0 | T92: =IFERROR(B92+E92+H92+K92+N92+Q92, "NA") -> 0 | U92: =(T92/$V$1)/4 -> 0
A93: 5447 - Receiver | K93: 0 | L93: =IFERROR(K93/K327, "NA") -> 0 | N93: 0 | O93: =IFERROR(N93/N327, "NA") -> 0 | Q93: 0 | R93: =IFERROR(Q93/Q327, "NA") -> 0 | T93: =IFERROR(B93+E93+H93+K93+N93+Q93, "NA") -> 0 | U93: =(T93/$V$1)/4 -> 0
A94: 5449 - BOH Contract Labor | K94: 0 | L94: =IFERROR(K94/K327, "NA") -> 0 | N94: 0 | O94: =IFERROR(N94/N327, "NA") -> 0 | Q94: 0 | R94: =IFERROR(Q94/Q327, "NA") -> 0 | T94: =IFERROR(B94+E94+H94+K94+N94+Q94, "NA") -> 0 | U94: =(T94/$V$1)/4 -> 0
A95: 5450 - Bonus BOH Hourly | K95: 0 | L95: =IFERROR(K95/K327, "NA") -> 0 | N95: 0 | O95: =IFERROR(N95/N327, "NA") -> 0 | Q95: 0 | R95: =IFERROR(Q95/Q327, "NA") -> 0 | T95: =IFERROR(B95+E95+H95+K95+N95+Q95, "NA") -> 0 | U95: =(T95/$V$1)/4 -> 0
A96: 5451 - Vacation BOH | K96: 0 | L96: =IFERROR(K96/K327, "NA") -> 0 | N96: 0 | O96: =IFERROR(N96/N327, "NA") -> 0 | Q96: 0 | R96: =IFERROR(Q96/Q327, "NA") -> 0 | T96: =IFERROR(B96+E96+H96+K96+N96+Q96, "NA") -> 0 | U96: =(T96/$V$1)/4 -> 0
A97: 5455 - Host | K97: 17323.34 | L97: =IFERROR(K97/K327, "NA") -> 0.018992275 | N97: 18020.2 | O97: =IFERROR(N97/N327, "NA") -> 0.01250413 | Q97: 17851.78 | R97: =IFERROR(Q97/Q327, "NA") -> 0.016167524 | T97: =IFERROR(B97+E97+H97+K97+N97+Q97, "NA") -> 53195.32 | U97: =(T97/$V$1)/4 -> 1022.9869
A98: 5456 - Reservationist | K98: 3674 | L98: =IFERROR(K98/K327, "NA") -> 0.0040279541 | N98: 4942.72 | O98: =IFERROR(N98/N327, "NA") -> 0.0034297295 | Q98: 4618 | R98: =IFERROR(Q98/Q327, "NA") -> 0.0041823072 | T98: =IFERROR(B98+E98+H98+K98+N98+Q98, "NA") -> 13234.72 | U98: =(T98/$V$1)/4 -> 254.51385
A99: 5457 - Receptionnist | K99: 0 | L99: =IFERROR(K99/K327, "NA") -> 0 | N99: 0 | O99: =IFERROR(N99/N327, "NA") -> 0 | Q99: 0 | R99: =IFERROR(Q99/Q327, "NA") -> 0 | T99: =IFERROR(B99+E99+H99+K99+N99+Q99, "NA") -> 0 | U99: =(T99/$V$1)/4 -> 0
A100: 5460 - Servers | K100: 0 | L100: =IFERROR(K100/K327, "NA") -> 0 | N100: 0 | O100: =IFERROR(N100/N327, "NA") -> 0 | Q100: 0 | R100: =IFERROR(Q100/Q327, "NA") -> 0 | T100: =IFERROR(B100+E100+H100+K100+N100+Q100, "NA") -> 0 | U100: =(T100/$V$1)/4 -> 0
A101: 5463 - Captain | K101: 0 | L101: =IFERROR(K101/K327, "NA") -> 0 | N101: 0 | O101: =IFERROR(N101/N327, "NA") -> 0 | Q101: 0 | R101: =IFERROR(Q101/Q327, "NA") -> 0 | T101: =IFERROR(B101+E101+H101+K101+N101+Q101, "NA") -> 0 | U101: =(T101/$V$1)/4 -> 0
A102: 5464 - Sommelier | K102: 0 | L102: =IFERROR(K102/K327, "NA") -> 0 | N102: 0 | O102: =IFERROR(N102/N327, "NA") -> 0 | Q102: 0 | R102: =IFERROR(Q102/Q327, "NA") -> 0 | T102: =IFERROR(B102+E102+H102+K102+N102+Q102, "NA") -> 0 | U102: =(T102/$V$1)/4 -> 0
A103: 5480 - Server Assistant | K103: 0 | L103: =IFERROR(K103/K327, "NA") -> 0 | N103: 0 | O103: =IFERROR(N103/N327, "NA") -> 0 | Q103: 0 | R103: =IFERROR(Q103/Q327, "NA") -> 0 | T103: =IFERROR(B103+E103+H103+K103+N103+Q103, "NA") -> 0 | U103: =(T103/$V$1)/4 -> 0
...
