Workbook

Sheet EBIDTA 2
D2: ='[1]Overview 2026'!B24 -> 46025
C4: ='[1]Overview 2026'!J3 -> 9 | D4: =VLOOKUP(D$2,'[1]Overview 2026'!$B$7:$AC$52,$C4,FALSE) -> CLOONEE
B5: DJ Cost | C5: ='[1]Overview 2026'!L3 -> 11 | D5: 4000
B6: Dj Cost / Sales Ratio | D6: =IFERROR(D5/D8,"") -> 0.14285714
B8: Brunch Sales | C8: ='[1]Overview 2026'!F3 -> 5 | D8: =D15+D16 -> 28000 | T8: =IFERROR(B8+E8+H8+K8+N8+Q8, "NA") -> NA
B9: Dinner Sales | C9: ='[1]Overview 2026'!H3 -> 7 | D9: =VLOOKUP(D$2,'[1]Overview 2026'!$B$7:$AC$52,$C9,FALSE) -> 101500 | W9: =4+4+5 -> 13
B10: Total Sales | D10: 61500 | W10: =W9*2 -> 26
B11: Budgeted Sales | C11: ='[1]Overview 2026'!D3 -> 3 | D11: =IF(VLOOKUP(D$2,'[1]Overview 2026'!$B6:$AC$52,$C11,FALSE)=0,"",VLOOKUP(D$2,'[1]Overview 2026'!$B6:$AC$52,$C11,FALSE))
B12: Holiday | C12: ='[1]Overview 2026'!C3 -> 2 | D12: =IF(VLOOKUP(D$2,'[1]Overview 2026'!$B7:$AC$52,$C12,FALSE)=0,"",VLOOKUP(D$2,'[1]Overview 2026'!$B7:$AC$52,$C12,FALSE))
B14: Brunch Sales Breakdown
B15: Dining Sales | C15: ='[1]Overview 2026'!F3 -> 5 | D15: =VLOOKUP(D$2,'[1]Overview 2026'!$B7:$AC$52,$C15,FALSE) -> 20000
B16: Bottle Service Sales | C16: ='[1]Overview 2026'!O3 -> 14 | D16: =IFERROR(D5*E16,0) -> 8000 | E16: =VLOOKUP(D$2,'[1]Overview 2026'!$B$7:$AC$52,$C16,FALSE) -> 2
B18: Table Minimum Breakdown
B19: # tables | D19: =E30 -> 28
B20: Avg. Minimum / Table | D20: =D16/D19 -> 285.71429
C22: ='[1]Overview 2026'!R3 -> 17 | D22: =IF(VLOOKUP(D$2,'[1]Overview 2026'!$B$7:$AC$52,$C22,FALSE)=0,"Beach Club",VLOOKUP(D$2,'[1]Overview 2026'!$B$7:$AC$52,$C22,FALSE)) -> Beach Club
B23: =VLOOKUP(D$22,'[1]Floor Plan Bottle Service'!$R$29:$Y$31,2,FALSE) -> Tier 1 | C23: ='[1]Overview 2026'!W3 -> 22 | D23: =VLOOKUP(D$2,'[1]Overview 2026'!$B$7:$AC$52,$C23,FALSE) -> 11800 | E23: =IF(VLOOKUP(D$22,'[1]Floor Plan Bottle Service'!$R$33:$X$34,2,FALSE)=0,"",VLOOKUP(D$22,'[1]Floor Plan Bottle Service'!$R$33:$X$34,2,FALSE)) -> 3 | G23: =VLOOKUP(H$22,'[1]Floor Plan Bottle Service'!$R$29:$Y$31,2,FALSE) -> #N/A
B24: =VLOOKUP(D$22,'[1]Floor Plan Bottle Service'!$R$29:$Y$31,3,FALSE) -> Tier 2 | C24: ='[1]Overview 2026'!X3 -> 23 | D24: =VLOOKUP(D$2,'[1]Overview 2026'!$B$7:$AC$52,$C24,FALSE) -> 9400 | E24: =VLOOKUP(D$22,'[1]Floor Plan Bottle Service'!$R$33:$Y$34,3,FALSE) -> 2 | G24: =VLOOKUP(H$22,'[1]Floor Plan Bottle Service'!$R$29:$Y$31,3,FALSE) -> #N/A
B25: =VLOOKUP(D$22,'[1]Floor Plan Bottle Service'!$R$29:$Y$31,4,FALSE) -> Tier 3 | C25: ='[1]Overview 2026'!Y3 -> 24 | D25: =VLOOKUP(D$2,'[1]Overview 2026'!$B$7:$AC$52,$C25,FALSE) -> 8200 | E25: =VLOOKUP(D$22,'[1]Floor Plan Bottle Service'!$R$33:$Y$34,4,FALSE) -> 13 | G25: =VLOOKUP(H$22,'[1]Floor Plan Bottle Service'!$R$29:$Y$31,4,FALSE) -> #N/A
B26: =VLOOKUP(D$22,'[1]Floor Plan Bottle Service'!$R$29:$Y$31,5,FALSE) -> Tier 4 | C26: ='[1]Overview 2026'!Z3 -> 25 | D26: =VLOOKUP(D$2,'[1]Overview 2026'!$B$7:$AC$52,$C26,FALSE) -> 5800 | E26: =VLOOKUP(D$22,'[1]Floor Plan Bottle Service'!$R$33:$Y$34,5,FALSE) -> 5 | G26: =VLOOKUP(H$22,'[1]Floor Plan Bottle Service'!$R$29:$Y$31,5,FALSE) -> #N/A
B27: =IF(E27=0,"",VLOOKUP(D$22,'[1]Floor Plan Bottle Service'!$R$29:$Y$31,6,FALSE)) -> Tier 5 | C27: ='[1]Overview 2026'!AA3 -> 26 | D27: =VLOOKUP(D$2,'[1]Overview 2026'!$B$7:$AC$52,$C27,FALSE) -> 3500 | E27: =VLOOKUP(D$22,'[1]Floor Plan Bottle Service'!$R$33:$Y$34,6,FALSE) -> 5 | G27: =IF(I27=0,"",VLOOKUP(H$22,'[1]Floor Plan Bottle Service'!$R$29:$Y$31,6,FALSE))
B28: =IF(E28=0,"",VLOOKUP(D$22,'[1]Floor Plan Bottle Service'!$R$29:$Y$31,7,FALSE)) | C28: ='[1]Overview 2026'!AB3 -> 27 | D28: =VLOOKUP(D$2,'[1]Overview 2026'!$B$7:$AC$52,$C28,FALSE) -> 0 | E28: =VLOOKUP(D$22,'[1]Floor Plan Bottle Service'!$R$33:$Y$34,7,FALSE) -> 0 | G28: =IF(I28=0,"",VLOOKUP(H$22,'[1]Floor Plan Bottle Service'!$R$29:$Y$31,7,FALSE))
B29: =IF(E29=0,"",VLOOKUP(D$22,'[1]Floor Plan Bottle Service'!$R$29:$Y$31,8,FALSE)) | C29: ='[1]Overview 2026'!AC3 -> 28 | D29: =VLOOKUP(D$2,'[1]Overview 2026'!$B$7:$AC$52,$C29,FALSE) -> 0 | E29: =VLOOKUP(D$22,'[1]Floor Plan Bottle Service'!$R$33:$Y$34,8,FALSE) -> 0 | G29: =IF(I29=0,"",VLOOKUP(H$22,'[1]Floor Plan Bottle Service'!$R$29:$Y$31,8,FALSE))
D30: =(D23*E23)+(D24*E24)+(D25*E25)+(D26*E26)+(D27*E27)+(D29*E29)+(D28*E28) -> 207300 | E30: =SUM(E23:E29) -> 28
B33: LBW Sales | D33: =D$36*E33 -> 38130 | E33: 0.62
B34: Food Sales | D34: =D$36*E34 -> 20910 | E34: =E36-E33-E35 -> 0.34
B35: Beverage Sales | D35: =D$36*E35 -> 2460 | E35: 0.04
B36: Total Sales | D36: =D10 -> 61500 | E36: 1
B38: LBW Cost | D38: =E38*D33 -> 5719.5 | E38: 0.15
B39: Food Cost | D39: =E39*D34 -> 5541.15 | E39: 0.265
B40: Beverage Cost | D40: =E40*D35 -> 688.8 | E40: 0.28
B41: COGS | D41: =SUM(D38:D40) -> 11949.45 | E41: =D41/D36 -> 0.1943
B43: Gross Profit | D43: =D36-D41 -> 49550.55 | E43: =D43/D36 -> 0.8057
B45: Payroll Expenses
B46: Management | D46: ='OPEX DATA 2'!U139+'OPEX DATA 2'!U141+'OPEX DATA 2'!U142 -> 4344.7518 | E46: =D46/D$36 -> 0.070646371
B47: FOH Hourly | D47: ='OPEX DATA 2'!U123+'OPEX DATA 2'!U97+'OPEX DATA 2'!U98+'OPEX DATA 2'!U110+'OPEX DATA 2'!U112 -> 1423.4991 | E47: =D47/D$36 -> 0.023146327
B48: BOH Hourly | D48: ='OPEX DATA 2'!U85+'OPEX DATA 2'!U86+'OPEX DATA 2'!U87+'OPEX DATA 2'!U88+'OPEX DATA 2'!U92+'OPEX DATA 2'!U124 -> 3049.3579 | E48: =D48/D$36 -> 0.049583055
B49: Payroll Taxes & Other | D49: ='OPEX DATA 2'!U151+'OPEX DATA 2'!U153+'OPEX DATA 2'!U154 -> 2499.9872 | E49: =D49/D$36 -> 0.040650198
B50: Total Payroll Expenses | D50: =SUM(D46:D49) -> 11317.596 | E50: =D50/D$36 -> 0.18402595
B52: ='OPEX DATA 2'!A159 -> Direct Operating Expenses
B53: ='OPEX DATA 2'!A161 -> 6105 - Automobile | D53: ='OPEX DATA 2'!U161 -> 0.15428571 | E53: =D53/D$36 -> 2.5087108e-06
B54: ='OPEX DATA 2'!A162 -> 6110 - China | D54: ='OPEX DATA 2'!U162 -> 87.15011 | E54: =D54/D$36 -> 0.001417075
B55: ='OPEX DATA 2'!A163 -> 6120 - Glass | D55: ='OPEX DATA 2'!U163 -> 140.36489 | E55: =D55/D$36 -> 0.0022823559
B56: ='OPEX DATA 2'!A164 -> 6130 - Silverware | D56: ='OPEX DATA 2'!U164 -> 21.980879 | E56: =D56/D$36 -> 0.00035741267
B57: ='OPEX DATA 2'!A165 -> 6200 - Bar Supplies | D57: ='OPEX DATA 2'!U165 -> 23.528022 | E57: =D57/D$36 -> 0.00038256946
B58: ='OPEX DATA 2'!A166 -> 6201 - Ice Expense | D58: ='OPEX DATA 2'!U166 -> 131.82385 | E58: =D58/D$36 -> 0.0021434772
B59: ='OPEX DATA 2'!A167 -> 6210 - Cleaning Supplies | D59: ='OPEX DATA 2'!U167 -> 98.866648 | E59: =D59/D$36 -> 0.0016075878
B60: ='OPEX DATA 2'!A168 -> 6230 - Kitchen Supplies | D60: ='OPEX DATA 2'!U168 -> 404.94473 | E60: =D60/D$36 -> 0.0065844671
B61: ='OPEX DATA 2'!A169 -> 6235 - Kitchen Equipment - Ops | D61: ='OPEX DATA 2'!U169 -> 20.565275 | E61: =D61/D$36 -> 0.00033439471
B62: ='OPEX DATA 2'!A170 -> 6240 - Restaurant Supplies | D62: ='OPEX DATA 2'!U170 -> 144.35527 | E62: =D62/D$36 -> 0.0023472402
B63: ='OPEX DATA 2'!A171 -> 6245 - Restaurant Equipment | D63: ='OPEX DATA 2'!U171 -> 159.63819 | E63: =D63/D$36 -> 0.0025957429
B64: ='OPEX DATA 2'!A172 -> 6246 - Hotel Amenities | D64: ='OPEX DATA 2'!U172 -> 0 | E64: =D64/D$36 -> 0
... B87: ='OPEX DATA 2'!A195 -> 6610 - License & Permits | D87: ='OPEX DATA 2'!U195 -> 42.526264 | E87: =D87/D$36 -> 0.00069148396
B88: ='OPEX DATA 2'!A196 -> 6750 - Live Entertainment | D88: =D5 -> 4000 | E88: =D88/D$36 -> 0.06504065
B89: ='OPEX DATA 2'!A197 -> 6755 - Members Entertainment | D89: ='OPEX DATA 2'!U197 -> 16.457582 | E89: =D89/D$36 -> 0.00026760297
B90: ='OPEX DATA 2'!A198 -> 6760 - MM at Sea | D90: ='OPEX DATA 2'!U198 -> 0 | E90: =D90/D$36 -> 0
B91: ='OPEX DATA 2'!A199 -> 6761 - Docking fees expenses | D91: ='OPEX DATA 2'!U199 -> 0 | E91: =D91/D$36 -> 0
B92: ='OPEX DATA 2'!A200 -> 6762 - Operating Yachting Cost | D92: ='OPEX DATA 2'!U200 -> 0 | E92: =D92/D$36 -> 0
B93: ='OPEX DATA 2'!A201 -> 6770 - Printing Expense | D93: ='OPEX DATA 2'!U201 -> 15.443187 | E93: =D93/D$36 -> 0.00025110873
B94: ='OPEX DATA 2'!A202 -> 6780 - AVA Coconut Grove | D94: ='OPEX DATA 2'!U202 -> 0 | E94: =D94/D$36 -> 0
B95: ='OPEX DATA 2'!A203 -> 6781 - E11even | D95: ='OPEX DATA 2'!U203 -> 0 | E95: =D95/D$36 -> 0
B96: ='OPEX DATA 2'!A204 -> 6782 - Vanquish CN | D96: ='OPEX DATA 2'!U204 -> 0 | E96: =D96/D$36 -> 0
B97: ='OPEX DATA 2'!A205 -> 6783 - Mila Cannes | D97: ='OPEX DATA 2'!U205 -> 0 | E97: =D97/D$36 -> 0
B98: ='OPEX DATA 2'!A206 -> 6784 - GP (Casa Neos) | D98: ='OPEX DATA 2'!U206 -> 0 | E98: =D98/D$36 -> 0
B99: ='OPEX DATA 2'!A207 -> 6785 - AVA research and Development | D99: ='OPEX DATA 2'!U207 -> 0 | E99: =D99/D$36 -> 0
B100: ='OPEX DATA 2'!A208 -> 6800 - COVID Expenses | D100: ='OPEX DATA 2'!U208 -> 0 | E100: =D100/D$36 -> 0
B101: ='OPEX DATA 2'!A209 -> Total Direct Operating Expenses | D101: =SUM(D53:D100) -> 7809.9299 | E101: =D101/D$36 -> 0.12699073
B103: ='OPEX DATA 2'!A213 -> General and Administrative
B104: ='OPEX DATA 2'!A215 -> 7010 - Credit Card Fees | D104: ='OPEX DATA 2'!U215 -> 1942.827 | E104: =D104/D$36 -> 0.031590683
B105: ='OPEX DATA 2'!A216 -> 7015 - Open Table Fees | D105: ='OPEX DATA 2'!U216 -> 28.043956 | E105: =D105/D$36 -> 0.00045599929
B106: ='OPEX DATA 2'!A217 -> 7020 - Dues and Subscriptions | D106: ='OPEX DATA 2'!U217 -> 426.59027 | E106: =D106/D$36 -> 0.0069364272
B107: ='OPEX DATA 2'!A218 -> 7040 - Payroll Processing Fees | D107: ='OPEX DATA 2'!U218 -> 34.257363 | E107: =D107/D$36 -> 0.00055703029
B108: ='OPEX DATA 2'!A219 -> 7050 - Fire & Security | D108: ='OPEX DATA 2'!U219 -> 794.67242 | E108: =D108/D$36 -> 0.012921503
B109: ='OPEX DATA 2'!A220 -> 7060 - Postage & Delivery | D109: ='OPEX DATA 2'!U220 -> 18.373187 | E109: =D109/D$36 -> 0.00029875101
B110: ='OPEX DATA 2'!A221 -> 7070 - Storage facility | D110: ='OPEX DATA 2'!U221 -> 0 | E110: =D110/D$36 -> 0
B111: ='OPEX DATA 2'!A222 -> 7080 - Office Supplies | D111: ='OPEX DATA 2'!U222 -> 8.7974176 | E111: =D111/D$36 -> 0.00014304744
B112: ='OPEX DATA 2'!A223 -> 7090 - Computer Supplies | D112: ='OPEX DATA 2'!U223 -> 0.040824176 | E112: =D112/D$36 -> 6.6380774e-07
B113: ='OPEX DATA 2'!A224 -> 7091 - IT Support | D113: ='OPEX DATA 2'!U224 -> 3.8060989 | E113: =D113/D$36 -> 6.1887787e-05
B114: ='OPEX DATA 2'!A225 -> 7092 - IT AI solutions | D114: ='OPEX DATA 2'!U225 -> 0 | E114: =D114/D$36 -> 0
B115: ='OPEX DATA 2'!A226 -> 7100 - Cash Short (Over) | D115: ='OPEX DATA 2'!U226 -> -0.74967033 | E115: =D115/D$36 -> -1.2189761e-05
... B129: ='OPEX DATA 2'!A240 -> 7180 - Commissary General Administrative | D129: ='OPEX DATA 2'!U240 -> 0 | E129: =D129/D$36 -> 0
B130: ='OPEX DATA 2'!A241 -> Total General and Administrative | D130: =SUM(D104:D129) -> 4743.9819 | E130: =D130/D$36 -> 0.077137917
B132: ='OPEX DATA 2'!A242 -> Utilities
B133: ='OPEX DATA 2'!A244 -> 7510 - Telephone | D133: ='OPEX DATA 2'!U244 -> 20.959286 | E133: =D133/D$36 -> 0.00034080139
B134: ='OPEX DATA 2'!A245 -> 7520 - Internet | D134: ='OPEX DATA 2'!U245 -> 15.02511 | E134: =D134/D$36 -> 0.00024431073
B135: ='OPEX DATA 2'!A246 -> 7530 - Cable & Music | D135: ='OPEX DATA 2'!U246 -> 0 | E135: =D135/D$36 -> 0
B136: ='OPEX DATA 2'!A247 -> 7540 - Electricity | D136: ='OPEX DATA 2'!U247 -> 144.80396 | E136: =D136/D$36 -> 0.0023545359
B137: ='OPEX DATA 2'!A248 -> 7550 - Gas | D137: ='OPEX DATA 2'!U248 -> 24.86044 | E137: =D137/D$36 -> 0.00040423479
B138: ='OPEX DATA 2'!A249 -> 7570 - Garbage/Recycle | D138: ='OPEX DATA 2'!U249 -> 155.47115 | E138: =D138/D$36 -> 0.0025279862
B139: ='OPEX DATA 2'!A250 -> 7580 - Water & Sewer | D139: ='OPEX DATA 2'!U250 -> 0 | E139: =D139/D$36 -> 0
B140: ='OPEX DATA 2'!A251 -> 7700 - Commissary Utilities | D140: ='OPEX DATA 2'!U251 -> 0 | E140: =D140/D$36 -> 0
B141: ='OPEX DATA 2'!A252 -> Total Utilities | D141: =SUM(D133:D140) -> 361.11995 | E141: =D141/D$36 -> 0.005871869
B143: ='OPEX DATA 2'!A253 -> Occupancy
B144: ='OPEX DATA 2'!A255 -> 7910 - Rent | D144: ='OPEX DATA 2'!U255 -> 0 | E144: =D144/D$36 -> 0
B145: ='OPEX DATA 2'!A256 -> 7911 - Percentage Rent | D145: ='OPEX DATA 2'!U256 -> 2508.187 | E145: =D145/D$36 -> 0.040783529
B146: ='OPEX DATA 2'!A257 -> 7912 - Prior Year Rent Exp | D146: ='OPEX DATA 2'!U257 -> 0 | E146: =D146/D$36 -> 0
B147: ='OPEX DATA 2'!A258 -> 7920 - CAM Charges | D147: ='OPEX DATA 2'!U258 -> 126.06516 | E147: =D147/D$36 -> 0.0020498401
B148: ='OPEX DATA 2'!A259 -> 7930 - Commissary Occupancy | D148: ='OPEX DATA 2'!U259 -> 0 | E148: =D148/D$36 -> 0
B149: ='OPEX DATA 2'!A260 -> 7940 - Property Tax | D149: ='OPEX DATA 2'!U260 -> 0 | E149: =D149/D$36 -> 0
B150: ='OPEX DATA 2'!A261 -> 9212 - Depreciation ROU | D150: ='OPEX DATA 2'!U261 -> 831.80676 | E150: =D150/D$36 -> 0.013525313
...

Sheet OPEX DATA 2
A1: ` | U1: # Weeks: | V1: 26
B5: Period 1, 2026 | E5: Period 2, 2026 | H5: Period 3, 2026 | K5: Period 4, 2026 | N5: Period 5, 2026 | Q5: Period 6, 2026 | T5: YTD | U5: Daily Costs
A6: Sales
A7: Food Sales
A8: 4010 - Food Sales | B8: 572516.55 | C8: =IFERROR(B8/B327, "NA") -> 0.2583052 | E8: 470187 | F8: =IFERROR(E8/E327, "NA") -> 0.26723839 | H8: 697656.3 | I8: =IFERROR(H8/H327, "NA") -> 0.28507415 | K8: 395561 | L8: =IFERROR(K8/K327, "NA") -> 0.26112304 | N8: 596937.21 | O8: =IFERROR(N8/N327, "NA") -> 0.28237076 | Q8: 385651 | R8: =IFERROR(Q8/Q327, "NA") -> 0.27800031 | T8: =IFERROR(B8+E8+H8+K8+N8+Q8, "NA") -> 3118509.1 | U8: =(T8/$V$1)/7 -> 17134.665
A9: 4015 - Commissary sales | B9: 0 | C9: =IFERROR(B9/B327, "NA") -> 0 | E9: 0 | F9: =IFERROR(E9/E327, "NA") -> 0 | H9: 0 | I9: =IFERROR(H9/H327, "NA") -> 0 | K9: 0 | L9: =IFERROR(K9/K327, "NA") -> 0 | N9: 0 | O9: =IFERROR(N9/N327, "NA") -> 0 | Q9: 0 | R9: =IFERROR(Q9/Q327, "NA") -> 0 | T9: =IFERROR(B9+E9+H9+K9+N9+Q9, "NA") -> 0 | U9: =(T9/$V$1)/7 -> 0 | W9: =4+4+5 -> 13
A10: Total Food Sales | B10: =IFERROR(B8+B9, "NA") -> 572516.55 | C10: =IFERROR(B10/B327, "NA") -> 0.2583052 | E10: =IFERROR(E8+E9, "NA") -> 470187 | F10: =IFERROR(E10/E327, "NA") -> 0.26723839 | H10: =IFERROR(H8+H9, "NA") -> 697656.3 | I10: =IFERROR(H10/H327, "NA") -> 0.28507415 | K10: =IFERROR(K8+K9, "NA") -> 395561 | L10: =IFERROR(K10/K327, "NA") -> 0.26112304 | N10: =IFERROR(N8+N9, "NA") -> 596937.21 | O10: =IFERROR(N10/N327, "NA") -> 0.28237076 | Q10: =IFERROR(Q8+Q9, "NA") -> 385651 | R10: =IFERROR(Q10/Q327, "NA") -> 0.27800031 | T10: =IFERROR(B10+E10+H10+K10+N10+Q10, "NA") -> 3118509.1 | U10: =(T10/$V$1)/7 -> 17134.665 | W10: =W9*2 -> 26
A11: 4020 - N/A Beverage Sales | B11: 70391 | C11: =IFERROR(B11/B327, "NA") -> 0.031758665 | E11: 53929 | F11: =IFERROR(E11/E327, "NA") -> 0.03065142 | H11: 75086.53 | I11: =IFERROR(H11/H327, "NA") -> 0.030681625 | K11: 52783.51 | L11: =IFERROR(K11/K327, "NA") -> 0.03484416 | N11: 65238 | O11: =IFERROR(N11/N327, "NA") -> 0.030859701 | Q11: 51065 | R11: =IFERROR(Q11/Q327, "NA") -> 0.036810707 | T11: =IFERROR(B11+E11+H11+K11+N11+Q11, "NA") -> 368493.04 | U11: =(T11/$V$1)/7 -> 2024.687
A12: LBW Sales | T12: =IFERROR(B12+E12+H12+K12+N12+Q12, "NA") -> 0 | U12: =(T12/$V$1)/7 -> 0
A13: 4100 - LBW Sales | B13: 0 | C13: =IFERROR(B13/B327, "NA") -> 0 | E13: 0 | F13: =IFERROR(E13/E327, "NA") -> 0 | H13: 0 | I13: =IFERROR(H13/H327, "NA") -> 0 | K13: 0 | L13: =IFERROR(K13/K327, "NA") -> 0 | N13: 0 | O13: =IFERROR(N13/N327, "NA") -> 0 | Q13: 0 | R13: =IFERROR(Q13/Q327, "NA") -> 0 | T13: =IFERROR(B13+E13+H13+K13+N13+Q13, "NA") -> 0 | U13: =(T13/$V$1)/7 -> 0
A14: 4105 - Liquor Sales | B14: 1090650 | C14: =IFERROR(B14/B327, "NA") -> 0.4920741 | E14: 830839 | F14: =IFERROR(E14/E327, "NA") -> 0.4722208 | H14: 1166419 | I14: =IFERROR(H14/H327, "NA") -> 0.47661852 | K14: 722390 | L14: =IFERROR(K14/K327, "NA") -> 0.4768738 | N14: 940974.71 | O14: =IFERROR(N14/N327, "NA") -> 0.44511171 | Q14: 677135 | R14: =IFERROR(Q14/Q327, "NA") -> 0.48811941 | T14: =IFERROR(B14+E14+H14+K14+N14+Q14, "NA") -> 5428407.7 | U14: =(T14/$V$1)/7 -> 29826.416
A15: 4165 - Beer Sales | B15: 10518 | C15: =IFERROR(B15/B327, "NA") -> 0.0047454595 | E15: 8634 | F15: =IFERROR(E15/E327, "NA") -> 0.0049072737 | H15: 13368 | I15: =IFERROR(H15/H327, "NA") -> 0.0054623907 | K15: 7233 | L15: =IFERROR(K15/K327, "NA") -> 0.0047747452 | N15: 8969 | O15: =IFERROR(N15/N327, "NA") -> 0.0042426294 | Q15: 5467 | R15: =IFERROR(Q15/Q327, "NA") -> 0.0039409406 | T15: =IFERROR(B15+E15+H15+K15+N15+Q15, "NA") -> 54189 | U15: =(T15/$V$1)/7 -> 297.74176
A16: 4180 - Wine Sales | B16: 197139 | C16: =IFERROR(B16/B327, "NA") -> 0.088944204 | E16: 175759 | F16: =IFERROR(E16/E327, "NA") -> 0.099895473 | H16: 256346 | I16: =IFERROR(H16/H327, "NA") -> 0.10474731 | K16: 166595 | L16: =IFERROR(K16/K327, "NA") -> 0.10997493 | N16: 303542 | O16: =IFERROR(N16/N327, "NA") -> 0.14358526 | Q16: 145189 | R16: =IFERROR(Q16/Q327, "NA") -> 0.10466092 | T16: =IFERROR(B16+E16+H16+K16+N16+Q16, "NA") -> 1244570 | U16: =(T16/$V$1)/7 -> 6838.2967
A17: 4181 - Wine BTG Sales | B17: 45936 | C17: =IFERROR(B17/B327, "NA") -> 0.020725178 | E17: 53549 | F17: =IFERROR(E17/E327, "NA") -> 0.030435441 | H17: 51850 | I17: =IFERROR(H17/H327, "NA") -> 0.021186786 | K17: 34556 | L17: =IFERROR(K17/K327, "NA") -> 0.022811571 | N17: 41151 | O17: =IFERROR(N17/N327, "NA") -> 0.019465764 | Q17: 28108 | R17: =IFERROR(Q17/Q327, "NA") -> 0.020261928 | T17: =IFERROR(B17+E17+H17+K17+N17+Q17, "NA") -> 255150 | U17: =(T17/$V$1)/7 -> 1401.9231
A18: 4182 - Wine Reserve Sales | B18: 135005 | C18: =IFERROR(B18/B327, "NA") -> 0.060910891 | E18: 88110 | F18: =IFERROR(E18/E327, "NA") -> 0.050078745 | H18: 127530 | I18: =IFERROR(H18/H327, "NA") -> 0.052110913 | K18: 79700 | L18: =IFERROR(K18/K327, "NA") -> 0.052612635 | N18: 61455 | O18: =IFERROR(N18/N327, "NA") -> 0.029070218 | Q18: 71370 | R18: =IFERROR(Q18/Q327, "NA") -> 0.051447765 | T18: =IFERROR(B18+E18+H18+K18+N18+Q18, "NA") -> 563170 | U18: =(T18/$V$1)/7 -> 3094.3407
A19: Total LBW Sales | B19: =IFERROR(B13+B14+B15+B16+B17+B18, "NA") -> 1479248 | C19: =IFERROR(B19/B327, "NA") -> 0.66739983 | E19: =IFERROR(E13+E14+E15+E16+E17+E18, "NA") -> 1156891 | F19: =IFERROR(E19/E327, "NA") -> 0.65753773 | H19: =IFERROR(H13+H14+H15+H16+H17+H18, "NA") -> 1615513 | I19: =IFERROR(H19/H327, "NA") -> 0.66012591 | K19: =IFERROR(K13+K14+K15+K16+K17+K18, "NA") -> 1010474 | L19: =IFERROR(K19/K327, "NA") -> 0.66704768 | N19: =IFERROR(N13+N14+N15+N16+N17+N18, "NA") -> 1356091.7 | O19: =IFERROR(N19/N327, "NA") -> 0.64147559 | Q19: =IFERROR(Q13+Q14+Q15+Q16+Q17+Q18, "NA") -> 927269 | R19: =IFERROR(Q19/Q327, "NA") -> 0.66843096 | T19: =IFERROR(B19+E19+H19+K19+N19+Q19, "NA") -> 7545486.7 | U19: =(T19/$V$1)/7 -> 41458.718
A20: Other Sales | T20: =IFERROR(B20+E20+H20+K20+N20+Q20, "NA") -> 0 | U20: =(T20/$V$1)/7 -> 0
A21: 4209 - Other Sales | B21: 0 | C21: =IFERROR(B21/B327, "NA") -> 0 | E21: 0 | F21: =IFERROR(E21/E327, "NA") -> 0 | H21: 0 | I21: =IFERROR(H21/H327, "NA") -> 0 | K21: 0 | L21: =IFERROR(K21/K327, "NA") -> 0 | N21: 0 | O21: =IFERROR(N21/N327, "NA") -> 0 | Q21: 0 | R21: =IFERROR(Q21/Q327, "NA") -> 0 | T21: =IFERROR(B21+E21+H21+K21+N21+Q21, "NA") -> 0 | U21: =(T21/$V$1)/7 -> 0
A22: 4210 - Retail Sales | B22: 50476.5 | C22: =IFERROR(B22/B327, "NA") -> 0.022773739 | E22: 37420.46 | F22: =IFERROR(E22/E327, "NA") -> 0.021268524 | H22: 51519.72 | I22: =IFERROR(H22/H327, "NA") -> 0.021051828 | K22: 20531.92 | L22: =IFERROR(K22/K327, "NA") -> 0.013553807 | N22: 44399.59 | O22: =IFERROR(N22/N327, "NA") -> 0.021002453 | Q22: 9221.53 | R22: =IFERROR(Q22/Q327, "NA") -> 0.0066474304 | T22: =IFERROR(B22+E22+H22+K22+N22+Q22, "NA") -> 213569.72 | U22: =(T22/$V$1)/7 -> 1173.46
A23: 4211 - No show / Min not met | B23: 0 | C23: =IFERROR(B23/B327, "NA") -> 0 | E23: 0 | F23: =IFERROR(E23/E327, "NA") -> 0 | H23: 0 | I23: =IFERROR(H23/H327, "NA") -> 0 | K23: -216 | L23: =IFERROR(K23/K327, "NA") -> -0.00014258882 | N23: 0 | O23: =IFERROR(N23/N327, "NA") -> 0 | Q23: 0 | R23: =IFERROR(Q23/Q327, "NA") -> 0 | T23: =IFERROR(B23+E23+H23+K23+N23+Q23, "NA") -> -216 | U23: =(T23/$V$1)/7 -> -1.1868132
A24: 4215 - Yacht sales | B24: 0 | C24: =IFERROR(B24/B327, "NA") -> 0 | E24: 0 | F24: =IFERROR(E24/E327, "NA") -> 0 | H24: 0 | I24: =IFERROR(H24/H327, "NA") -> 0 | K24: 0 | L24: =IFERROR(K24/K327, "NA") -> 0 | N24: 0 | O24: =IFERROR(N24/N327, "NA") -> 0 | Q24: 0 | R24: =IFERROR(Q24/Q327, "NA") -> 0 | T24: =IFERROR(B24+E24+H24+K24+N24+Q24, "NA") -> 0 | U24: =(T24/$V$1)/7 -> 0
A25: 4216 - Docking fees Revenue | B25: 0 | C25: =IFERROR(B25/B327, "NA") -> 0 | E25: 0 | F25: =IFERROR(E25/E327, "NA") -> 0 | H25: 0 | I25: =IFERROR(H25/H327, "NA") -> 0 | K25: 0 | L25: =IFERROR(K25/K327, "NA") -> 0 | N25: 0 | O25: =IFERROR(N25/N327, "NA") -> 0 | Q25: 0 | R25: =IFERROR(Q25/Q327, "NA") -> 0 | T25: =IFERROR(B25+E25+H25+K25+N25+Q25, "NA") -> 0 | U25: =(T25/$V$1)/7 -> 0
A26: 4220 - Membership Revenue | B26: 95724.78 | C26: =IFERROR(B26/B327, "NA") -> 0.043188635 | E26: 102708.41 | F26: =IFERROR(E26/E327, "NA") -> 0.058375988 | H26: 99171.36 | I26: =IFERROR(H26/H327, "NA") -> 0.040523094 | K26: 89854.81 | L26: =IFERROR(K26/K327, "NA") -> 0.059316165 | N26: 109882.7 | O26: =IFERROR(N26/N327, "NA") -> 0.051978099 | Q26: 75533.59 | R26: =IFERROR(Q26/Q327, "NA") -> 0.05444913 | T26: =IFERROR(B26+E26+H26+K26+N26+Q26, "NA") -> 572875.65 | U26: =(T26/$V$1)/7 -> 3147.6684
A27: 4221 - Application Fee Revenue | B27: 0 | C27: =IFERROR(B27/B327, "NA") -> 0 | E27: 0 | F27: =IFERROR(E27/E327, "NA") -> 0 | H27: 0 | I27: =IFERROR(H27/H327, "NA") -> 0 | K27: 0 | L27: =IFERROR(K27/K327, "NA") -> 0 | N27: 0 | O27: =IFERROR(N27/N327, "NA") -> 0 | Q27: 0 | R27: =IFERROR(Q27/Q327, "NA") -> 0 | T27: =IFERROR(B27+E27+H27+K27+N27+Q27, "NA") -> 0 | U27: =(T27/$V$1)/7 -> 0
A28: 4230 - Retained Service Charge | B28: 0 | C28: =IFERROR(B28/B327, "NA") -> 0 | E28: 0 | F28: =IFERROR(E28/E327, "NA") -> 0 | H28: 0 | I28: =IFERROR(H28/H327, "NA") -> 0 | K28: 0 | L28: =IFERROR(K28/K327, "NA") -> 0 | N28: 0 | O28: =IFERROR(N28/N327, "NA") -> 0 | Q28: 0 | R28: =IFERROR(Q28/Q327, "NA") -> 0 | T28: =IFERROR(B28+E28+H28+K28+N28+Q28, "NA") -> 0 | U28: =(T28/$V$1)/7 -> 0
A29: 4250 - Service Sales | B29: 0 | C29: =IFERROR(B29/B327, "NA") -> 0 | E29: 0 | F29: =IFERROR(E29/E327, "NA") -> 0 | H29: 0 | I29: =IFERROR(H29/H327, "NA") -> 0 | K29: 0 | L29: =IFERROR(K29/K327, "NA") -> 0 | N29: 0 | O29: =IFERROR(N29/N327, "NA") -> 0 | Q29: 0 | R29: =IFERROR(Q29/Q327, "NA") -> 0 | T29: =IFERROR(B29+E29+H29+K29+N29+Q29, "NA") -> 0 | U29: =(T29/$V$1)/7 -> 0
A30: Total Other Sales | B30: =IFERROR(B21+B22+B23+B24+B25+B26+B27+B28+B29, "NA") -> 146201.28 | C30: =IFERROR(B30/B327, "NA") -> 0.065962374 | E30: =IFERROR(E21+E22+E23+E24+E25+E26+E27+E28+E29, "NA") -> 140128.87 | F30: =IFERROR(E30/E327, "NA") -> 0.079644512 | H30: =IFERROR(H21+H22+H23+H24+H25+H26+H27+H28+H29, "NA") -> 150691.08 | I30: =IFERROR(H30/H327, "NA") -> 0.061574922 | K30: =IFERROR(K21+K22+K23+K24+K25+K26+K27+K28+K29, "NA") -> 110170.73 | L30: =IFERROR(K30/K327, "NA") -> 0.072727383 | N30: =IFERROR(N21+N22+N23+N24+N25+N26+N27+N28+N29, "NA") -> 154282.29 | O30: =IFERROR(N30/N327, "NA") -> 0.072980553 | Q30: =IFERROR(Q21+Q22+Q23+Q24+Q25+Q26+Q27+Q28+Q29, "NA") -> 84755.12 | R30: =IFERROR(Q30/Q327, "NA") -> 0.06109656 | T30: =IFERROR(B30+E30+H30+K30+N30+Q30, "NA") -> 786229.37 | U30: =(T30/$V$1)/7 -> 4319.9416
A31: Hotel Sales | T31: =IFERROR(B31+E31+H31+K31+N31+Q31, "NA") -> 0 | U31: =(T31/$V$1)/7 -> 0
A32: 4399 - Hotel Sales | B32: 0 | C32: =IFERROR(B32/B327, "NA") -> 0 | E32: 0 | F32: =IFERROR(E32/E327, "NA") -> 0 | H32: 0 | I32: =IFERROR(H32/H327, "NA") -> 0 | K32: 0 | L32: =IFERROR(K32/K327, "NA") -> 0 | N32: 0 | O32: =IFERROR(N32/N327, "NA") -> 0 | Q32: 0 | R32: =IFERROR(Q32/Q327, "NA") -> 0 | T32: =IFERROR(B32+E32+H32+K32+N32+Q32, "NA") -> 0 | U32: =(T32/$V$1)/7 -> 0
A33: 4301 - Accommodation | B33: 0 | C33: =IFERROR(B33/B327, "NA") -> 0 | E33: 0 | F33: =IFERROR(E33/E327, "NA") -> 0 | H33: 0 | I33: =IFERROR(H33/H327, "NA") -> 0 | K33: 0 | L33: =IFERROR(K33/K327, "NA") -> 0 | N33: 0 | O33: =IFERROR(N33/N327, "NA") -> 0 | Q33: 0 | R33: =IFERROR(Q33/Q327, "NA") -> 0 | T33: =IFERROR(B33+E33+H33+K33+N33+Q33, "NA") -> 0 | U33: =(T33/$V$1)/7 -> 0
A34: 4310 - Mini Bar | B34: 0 | C34: =IFERROR(B34/B327, "NA") -> 0 | E34: 0 | F34: =IFERROR(E34/E327, "NA") -> 0 | H34: 0 | I34: =IFERROR(H34/H327, "NA") -> 0 | K34: 0 | L34: =IFERROR(K34/K327, "NA") -> 0 | N34: 0 | O34: =IFERROR(N34/N327, "NA") -> 0 | Q34: 0 | R34: =IFERROR(Q34/Q327, "NA") -> 0 | T34: =IFERROR(B34+E34+H34+K34+N34+Q34, "NA") -> 0 | U34: =(T34/$V$1)/7 -> 0
A35: 4320 - Destination Fee | B35: 0 | C35: =IFERROR(B35/B327, "NA") -> 0 | E35: 0 | F35: =IFERROR(E35/E327, "NA") -> 0 | H35: 0 | I35: =IFERROR(H35/H327, "NA") -> 0 | K35: 0 | L35: =IFERROR(K35/K327, "NA") -> 0 | N35: 0 | O35: =IFERROR(N35/N327, "NA") -> 0 | Q35: 0 | R35: =IFERROR(Q35/Q327, "NA") -> 0 | T35: =IFERROR(B35+E35+H35+K35+N35+Q35, "NA") -> 0 | U35: =(T35/$V$1)/7 -> 0
A36: 4340 - Other Accommodation | B36: 0 | C36: =IFERROR(B36/B327, "NA") -> 0 | E36: 0 | F36: =IFERROR(E36/E327, "NA") -> 0 | H36: 0 | I36: =IFERROR(H36/H327, "NA") -> 0 | K36: 0 | L36: =IFERROR(K36/K327, "NA") -> 0 | N36: 0 | O36: =IFERROR(N36/N327, "NA") -> 0 | Q36: 0 | R36: =IFERROR(Q36/Q327, "NA") -> 0 | T36: =IFERROR(B36+E36+H36+K36+N36+Q36, "NA") -> 0 | U36: =(T36/$V$1)/7 -> 0
A37: Total Hotel Sales | B37: =IFERROR(B32+B33+B34+B35+B36, "NA") -> 0 | C37: =IFERROR(B37/B327, "NA") -> 0 | E37: =IFERROR(E32+E33+E34+E35+E36, "NA") -> 0 | F37: =IFERROR(E37/E327, "NA") -> 0 | H37: =IFERROR(H32+H33+H34+H35+H36, "NA") -> 0 | I37: =IFERROR(H37/H327, "NA") -> 0 | K37: =IFERROR(K32+K33+K34+K35+K36, "NA") -> 0 | L37: =IFERROR(K37/K327, "NA") -> 0 | N37: =IFERROR(N32+N33+N34+N35+N36, "NA") -> 0 | O37: =IFERROR(N37/N327, "NA") -> 0 | Q37: =IFERROR(Q32+Q33+Q34+Q35+Q36, "NA") -> 0 | R37: =IFERROR(Q37/Q327, "NA") -> 0 | T37: =IFERROR(B37+E37+H37+K37+N37+Q37, "NA") -> 0 | U37: =(T37/$V$1)/7 -> 0
A38: Comps & Promotions | T38: =IFERROR(B38+E38+H38+K38+N38+Q38, "NA") -> 0 | U38: =(T38/$V$1)/7 -> 0
A39: 4900 - Comps & Promotions | B39: 0 | C39: =IFERROR(B39/B327, "NA") -> 0 | E39: 0 | F39: =IFERROR(E39/E327, "NA") -> 0 | H39: 0 | I39: =IFERROR(H39/H327, "NA") -> 0 | K39: 0 | L39: =IFERROR(K39/K327, "NA") -> 0 | N39: 0 | O39: =IFERROR(N39/N327, "NA") -> 0 | Q39: 0 | R39: =IFERROR(Q39/Q327, "NA") -> 0 | T39: =IFERROR(B39+E39+H39+K39+N39+Q39, "NA") -> 0 | U39: =(T39/$V$1)/7 -> 0
A40: 4910 - Employee Discount | B40: -100.25 | C40: =IFERROR(B40/B327, "NA") -> -4.5230302e-05 | E40: 0 | F40: =IFERROR(E40/E327, "NA") -> 0 | H40: 0 | I40: =IFERROR(H40/H327, "NA") -> 0 | K40: 0 | L40: =IFERROR(K40/K327, "NA") -> 0 | N40: 0 | O40: =IFERROR(N40/N327, "NA") -> 0 | Q40: -221.25 | R40: =IFERROR(Q40/Q327, "NA") -> -0.00015949023 | T40: =IFERROR(B40+E40+H40+K40+N40+Q40, "NA") -> -321.5 | U40: =(T40/$V$1)/7 -> -1.7664835
A41: 4915 - Manager Meal | B41: -2319 | C41: =IFERROR(B41/B327, "NA") -> -0.001046275 | E41: -2352 | F41: =IFERROR(E41/E327, "NA") -> -0.0013367973 | H41: -3429.8 | I41: =IFERROR(H41/H327, "NA") -> -0.0014014742 | K41: -1147 | L41: =IFERROR(K41/K327, "NA") -> -0.00075717306 | N41: -1310 | O41: =IFERROR(N41/N327, "NA") -> -0.0006196727 | Q41: -1565 | R41: =IFERROR(Q41/Q327, "NA") -> -0.0011281456 | T41: =IFERROR(B41+E41+H41+K41+N41+Q41, "NA") -> -12122.8 | U41: =(T41/$V$1)/7 -> -66.608791
A42: 4920 - Positive Comp | B42: -3672 | C42: =IFERROR(B42/B327, "NA") -> -0.0016567149 | E42: -4399 | F42: =IFERROR(E42/E327, "NA") -> -0.0025002429 | H42: -10877 | I42: =IFERROR(H42/H327, "NA") -> -0.004444526 | K42: -8407 | L42: =IFERROR(K42/K327, "NA") -> -0.0055497418 | N42: -3132 | O42: =IFERROR(N42/N327, "NA") -> -0.0014815381 | Q42: -2673.6 | R42: =IFERROR(Q42/Q327, "NA") -> -0.0019272908 | T42: =IFERROR(B42+E42+H42+K42+N42+Q42, "NA") -> -33160.6 | U42: =(T42/$V$1)/7 -> -182.2011
A43: 4924 - Marketing/Promotions | B43: -10163 | C43: =IFERROR(B43/B327, "NA") -> -0.0045852923 | E43: -20965 | F43: =IFERROR(E43/E327, "NA") -> -0.011915797 | H43: -33183 | I43: =IFERROR(H43/H327, "NA") -> -0.013559135 | K43: -23229 | L43: =IFERROR(K43/K327, "NA") -> -0.01533424 | N43: -17162 | O43: =IFERROR(N43/N327, "NA") -> -0.0081181855 | Q43: -24608 | R43: =IFERROR(Q43/Q327, "NA") -> -0.017738918 | T43: =IFERROR(B43+E43+H43+K43+N43+Q43, "NA") -> -129310 | U43: =(T43/$V$1)/7 -> -710.49451
A44: 4925 - Customer Discounts | B44: 0 | C44: =IFERROR(B44/B327, "NA") -> 0 | E44: 0 | F44: =IFERROR(E44/E327, "NA") -> 0 | H44: 0 | I44: =IFERROR(H44/H327, "NA") -> 0 | K44: -122 | L44: =IFERROR(K44/K327, "NA") -> -8.053628e-05 | N44: -2204 | O44: =IFERROR(N44/N327, "NA") -> -0.0010425638 | Q44: -375 | R44: =IFERROR(Q44/Q327, "NA") -> -0.00027032243 | T44: =IFERROR(B44+E44+H44+K44+N44+Q44, "NA") -> -2701 | U44: =(T44/$V$1)/7 -> -14.840659
A45: 4926 - Promo G/C | B45: 0 | C45: =IFERROR(B45/B327, "NA") -> 0 | E45: 0 | F45: =IFERROR(E45/E327, "NA") -> 0 | H45: 0 | I45: =IFERROR(H45/H327, "NA") -> 0 | K45: 0 | L45: =IFERROR(K45/K327, "NA") -> 0 | N45: 0 | O45: =IFERROR(N45/N327, "NA") -> 0 | Q45: 0 | R45: =IFERROR(Q45/Q327, "NA") -> 0 | T45: =IFERROR(B45+E45+H45+K45+N45+Q45, "NA") -> 0 | U45: =(T45/$V$1)/7 -> 0
A46: 4927 - Entertainment staff meal | B46: -24166 | C46: =IFERROR(B46/B327, "NA") -> -0.010903097 | D46: =(11977+7579+3952)/7 -> 3358.2857 | E46: -19531 | F46: =IFERROR(E46/E327, "NA") -> -0.01110076 | H46: -26546.03 | I46: =IFERROR(H46/H327, "NA") -> -0.010847156 | K46: -14558 | L46: =IFERROR(K46/K327, "NA") -> -0.0096102226 | N46: -21956 | O46: =IFERROR(N46/N327, "NA") -> -0.010385904 | Q46: -22676 | R46: =IFERROR(Q46/Q327, "NA") -> -0.016346217 | T46: =IFERROR(B46+E46+H46+K46+N46+Q46, "NA") -> -129433.03 | U46: =(T46/$V$1)/7 -> -711.17049
A47: 4930 - Negative Comp | B47: -4409.5 | C47: =IFERROR(B47/B327, "NA") -> -0.0019894565 | E47: -6615 | F47: =IFERROR(E47/E327, "NA") -> -0.0037597424 | H47: -7014 | I47: =IFERROR(H47/H327, "NA") -> -0.0028660389 | K47: -2834 | L47: =IFERROR(K47/K327, "NA") -> -0.0018708182 | N47: -3689 | O47: =IFERROR(N47/N327, "NA") -> -0.0017450173 | Q47: -3845 | R47: =IFERROR(Q47/Q327, "NA") -> -0.002771706 | T47: =IFERROR(B47+E47+H47+K47+N47+Q47, "NA") -> -28406.5 | U47: =(T47/$V$1)/7 -> -156.07967
A48: 4933 - Training & Tasting | B48: -2432 | C48: =IFERROR(B48/B327, "NA") -> -0.0010972578 | E48: -4320 | F48: =IFERROR(E48/E327, "NA") -> -0.0024553419 | H48: -5904 | I48: =IFERROR(H48/H327, "NA") -> -0.0024124742 | K48: -2032 | L48: =IFERROR(K48/K327, "NA") -> -0.0013413912 | N48: -3622 | O48: =IFERROR(N48/N327, "NA") -> -0.0017133241 | Q48: -4828 | R48: =IFERROR(Q48/Q327, "NA") -> -0.0034803112 | T48: =IFERROR(B48+E48+H48+K48+N48+Q48, "NA") -> -23138 | U48: =(T48/$V$1)/7 -> -127.13187
A49: 4934 - Corporate Comp | B49: -172 | C49: =IFERROR(B49/B327, "NA") -> -7.7602113e-05 | E49: -98 | F49: =IFERROR(E49/E327, "NA") -> -5.5699887e-05 | H49: -1600 | I49: =IFERROR(H49/H327, "NA") -> -0.00065378704 | K49: -748 | L49: =IFERROR(K49/K327, "NA") -> -0.00049377981 | N49: 0 | O49: =IFERROR(N49/N327, "NA") -> 0 | Q49: -42 | R49: =IFERROR(Q49/Q327, "NA") -> -3.0276112e-05 | T49: =IFERROR(B49+E49+H49+K49+N49+Q49, "NA") -> -2660 | U49: =(T49/$V$1)/7 -> -14.615385
A50: 4935 - Exec Comp | B50: -4488.6 | C50: =IFERROR(B50/B327, "NA") -> -0.0020251445 | D50: =SUM(D46:D49) -> 3358.2857 | E50: -3426.8 | F50: =IFERROR(E50/E327, "NA") -> -0.0019476773 | H50: -3113 | I50: =IFERROR(H50/H327, "NA") -> -0.0012720244 | K50: -1067 | L50: =IFERROR(K50/K327, "NA") -> -0.00070436238 | N50: -5455 | O50: =IFERROR(N50/N327, "NA") -> -0.0025803928 | Q50: -674 | R50: =IFERROR(Q50/Q327, "NA") -> -0.00048585952 | T50: =IFERROR(B50+E50+H50+K50+N50+Q50, "NA") -> -18224.4 | U50: =(T50/$V$1)/7 -> -100.13407
A51: Total Comps & Promotions | B51: =IFERROR(B39+B40+B41+B42+B43+B44+B45+B46+B47+B48+B49+B50, "NA") -> -51922.35 | C51: =IFERROR(B51/B327, "NA") -> -0.02342607 | E51: =IFERROR(E39+E40+E41+E42+E43+E44+E45+E46+E47+E48+E49+E50, "NA") -> -61706.8 | F51: =IFERROR(E51/E327, "NA") -> -0.035072059 | H51: =IFERROR(H39+H40+H41+H42+H43+H44+H45+H46+H47+H48+H49+H50, "NA") -> -91666.83 | I51: =IFERROR(H51/H327, "NA") -> -0.037456616 | K51: =IFERROR(K39+K40+K41+K42+K43+K44+K45+K46+K47+K48+K49+K50, "NA") -> -54144 | L51: =IFERROR(K51/K327, "NA") -> -0.035742265 | N51: =IFERROR(N39+N40+N41+N42+N43+N44+N45+N46+N47+N48+N49+N50, "NA") -> -58530 | O51: =IFERROR(N51/N327, "NA") -> -0.027686598 | Q51: =IFERROR(Q39+Q40+Q41+Q42+Q43+Q44+Q45+Q46+Q47+Q48+Q49+Q50, "NA") -> -61507.85 | R51: =IFERROR(Q51/Q327, "NA") -> -0.044338537 | T51: =IFERROR(B51+E51+H51+K51+N51+Q51, "NA") -> -379477.83 | U51: =(T51/$V$1)/7 -> -2085.043
A52: Total Sales | B52: =IFERROR(B8+B9+B11+B13+B14+B15+B16+B17+B18+B21+B22+B23+B24+B25+B26+B27+B28+B29+B32+B33+B34+B35+B36+B39+B40+B41+B42+B43+B44+B45+B46+B47+B48+B49+B50, "NA") -> 2216434.5 | C52: =IFERROR(B52/B327, "NA") -> 1 | E52: =IFERROR(E8+E9+E11+E13+E14+E15+E16+E17+E18+E21+E22+E23+E24+E25+E26+E27+E28+E29+E32+E33+E34+E35+E36+E39+E40+E41+E42+E43+E44+E45+E46+E47+E48+E49+E50, "NA") -> 1759429.1 | F52: =IFERROR(E52/E327, "NA") -> 1 | H52: =IFERROR(H8+H9+H11+H13+H14+H15+H16+H17+H18+H21+H22+H23+H24+H25+H26+H27+H28+H29+H32+H33+H34+H35+H36+H39+H40+H41+H42+H43+H44+H45+H46+H47+H48+H49+H50, "NA") -> 2447280.1 | I52: =IFERROR(H52/H327, "NA") -> 1 | K52: =IFERROR(K8+K9+K11+K13+K14+K15+K16+K17+K18+K21+K22+K23+K24+K25+K26+K27+K28+K29+K32+K33+K34+K35+K36+K39+K40+K41+K42+K43+K44+K45+K46+K47+K48+K49+K50, "NA") -> 1514845.2 | L52: =IFERROR(K52/K327, "NA") -> 1 | N52: =IFERROR(N8+N9+N11+N13+N14+N15+N16+N17+N18+N21+N22+N23+N24+N25+N26+N27+N28+N29+N32+N33+N34+N35+N36+N39+N40+N41+N42+N43+N44+N45+N46+N47+N48+N49+N50, "NA") -> 2114019.2 | O52: =IFERROR(N52/N327, "NA") -> 1 | Q52: =IFERROR(Q8+Q9+Q11+Q13+Q14+Q15+Q16+Q17+Q18+Q21+Q22+Q23+Q24+Q25+Q26+Q27+Q28+Q29+Q32+Q33+Q34+Q35+Q36+Q39+Q40+Q41+Q42+Q43+Q44+Q45+Q46+Q47+Q48+Q49+Q50, "NA") -> 1387232.3 | R52: =IFERROR(Q52/Q327, "NA") -> 1 | T52: =IFERROR(B52+E52+H52+K52+N52+Q52, "NA") -> 11439240 | U52: =(T52/$V$1)/7 -> 62852.969
A53: Prime Cost | T53: =IFERROR(B53+E53+H53+K53+N53+Q53, "NA") -> 0 | U53: =(T53/$V$1)/7 -> 0
A54: Food Cost | T54: =IFERROR(B54+E54+H54+K54+N54+Q54, "NA") -> 0 | U54: =(T54/$V$1)/7 -> 0
A55: 5009 - Food Cost | B55: 0 | C55: =IFERROR(B55/B327, "NA") -> 0 | E55: 0 | F55: =IFERROR(E55/E327, "NA") -> 0 | H55: 0 | I55: =IFERROR(H55/H327, "NA") -> 0 | K55: 0 | L55: =IFERROR(K55/K327, "NA") -> 0 | N55: 0 | O55: =IFERROR(N55/N327, "NA") -> 0 | Q55: 0 | R55: =IFERROR(Q55/Q327, "NA") -> 0 | T55: =IFERROR(B55+E55+H55+K55+N55+Q55, "NA") -> 0 | U55: =(T55/$V$1)/7 -> 0
A56: 5010 - Purchase Produce | B56: 2275.68 | C56: =IFERROR(B56/B327, "NA") -> 0.0010267301 | E56: 2660.63 | F56: =IFERROR(E56/E327, "NA") -> 0.0015122121 | H56: 2609.05 | I56: =IFERROR(H56/H327, "NA") -> 0.0010661019 | K56: 17260.19 | L56: =IFERROR(K56/K327, "NA") -> 0.011394029 | N56: 27597.66 | O56: =IFERROR(N56/N327, "NA") -> 0.013054593 | Q56: 15626.09 | R56: =IFERROR(Q56/Q327, "NA") -> 0.01126422 | T56: =IFERROR(B56+E56+H56+K56+N56+Q56, "NA") -> 68029.3 | U56: =(T56/$V$1)/7 -> 373.78736
A57: 5020 - Purchase Dairy | B57: 6580.99 | C57: =IFERROR(B57/B327, "NA") -> 0.0029691787 | E57: 2775.22 | F57: =IFERROR(E57/E327, "NA") -> 0.0015773412 | H57: 2669.86 | I57: =IFERROR(H57/H327, "NA") -> 0.0010909499 | K57: 2383.78 | L57: =IFERROR(K57/K327, "NA") -> 0.0015736129 | N57: 1965.67 | O57: =IFERROR(N57/N327, "NA") -> 0.00092982599 | Q57: 664.8 | R57: =IFERROR(Q57/Q327, "NA") -> 0.00047922761 | T57: =IFERROR(B57+E57+H57+K57+N57+Q57, "NA") -> 17040.32 | U57: =(T57/$V$1)/7 -> 93.628132
A58: 5030 - Purchase Meat | B58: 40142.94 | C58: =IFERROR(B58/B327, "NA") -> 0.018111494 | E58: 23110.39 | F58: =IFERROR(E58/E327, "NA") -> 0.013135164 | H58: 75978.12 | I58: =IFERROR(H58/H327, "NA") -> 0.031045944 | K58: 21530.8 | L58: =IFERROR(K58/K327, "NA") -> 0.014213201 | N58: 30414.96 | O58: =IFERROR(N58/N327, "NA") -> 0.014387268 | Q58: 23216.01 | R58: =IFERROR(Q58/Q327, "NA") -> 0.016735489 | T58: =IFERROR(B58+E58+H58+K58+N58+Q58, "NA") -> 214393.22 | U58: =(T58/$V$1)/7 -> 1177.9847
A59: 5033 - Purchase Poultry | B59: 3290.03 | C59: =IFERROR(B59/B327, "NA") -> 0.0014843795 | E59: 1966.97 | F59: =IFERROR(E59/E327, "NA") -> 0.0011179592 | H59: 2602.77 | I59: =IFERROR(H59/H327, "NA") -> 0.0010635358 | K59: 1537.55 | L59: =IFERROR(K59/K327, "NA") -> 0.0010149882 | N59: 2101.32 | O59: =IFERROR(N59/N327, "NA") -> 0.00099399286 | Q59: 1262.63 | R59: =IFERROR(Q59/Q327, "NA") -> 0.00091017923 | T59: =IFERROR(B59+E59+H59+K59+N59+Q59, "NA") -> 12761.27 | U59: =(T59/$V$1)/7 -> 70.116868
A60: 5040 - Purchase Seafood | B60: 64532.78 | C60: =IFERROR(B60/B327, "NA") -> 0.029115582 | E60: 72971.28 | F60: =IFERROR(E60/E327, "NA") -> 0.041474409 | H60: 72507.52 | I60: =IFERROR(H60/H327, "NA") -> 0.029627798 | K60: 38008.32 | L60: =IFERROR(K60/K327, "NA") -> 0.025090563 | N60: 50014.59 | O60: =IFERROR(N60/N327, "NA") -> 0.023658531 | Q60: 29980.21 | R60: =IFERROR(Q60/Q327, "NA") -> 0.021611529 | T60: =IFERROR(B60+E60+H60+K60+N60+Q60, "NA") -> 328014.7 | U60: =(T60/$V$1)/7 -> 1802.2786
A61: 5050 - Purchase Dry Goods | B61: 3810.54 | C61: =IFERROR(B61/B327, "NA") -> 0.0017192207 | E61: 3878.87 | F61: =IFERROR(E61/E327, "NA") -> 0.0022046186 | H61: 3925.55 | I61: =IFERROR(H61/H327, "NA") -> 0.0016040461 | K61: 13294.96 | L61: =IFERROR(K61/K327, "NA") -> 0.0087764477 | N61: 17402.94 | O61: =IFERROR(N61/N327, "NA") -> 0.0082321579 | Q61: 14013.12 | R61: =IFERROR(Q61/Q327, "NA") -> 0.010101495 | T61: =IFERROR(B61+E61+H61+K61+N61+Q61, "NA") -> 56325.98 | U61: =(T61/$V$1)/7 -> 309.48341
A62: 5060 - Purchase Bread | B62: 150.56 | C62: =IFERROR(B62/B327, "NA") -> 6.792892e-05 | E62: 130.95 | F62: =IFERROR(E62/E327, "NA") -> 7.4427553e-05 | H62: 116.61 | I62: =IFERROR(H62/H327, "NA") -> 4.7648817e-05 | K62: 175.84 | L62: =IFERROR(K62/K327, "NA") -> 0.00011607786 | N62: 150.47 | O62: =IFERROR(N62/N327, "NA") -> 7.1177215e-05 | Q62: 99.2 | R62: =IFERROR(Q62/Q327, "NA") -> 7.1509294e-05 | T62: =IFERROR(B62+E62+H62+K62+N62+Q62, "NA") -> 823.63 | U62: =(T62/$V$1)/7 -> 4.5254396
A63: 5070 - Purchase Food Commissary | B63: 6887.67 | C63: =IFERROR(B63/B327, "NA") -> 0.0031075451 | E63: 4069.12 | F63: =IFERROR(E63/E327, "NA") -> 0.0023127502 | H63: 4730.1 | I63: =IFERROR(H63/H327, "NA") -> 0.0019327988 | K63: 3802.73 | L63: =IFERROR(K63/K327, "NA") -> 0.0025103092 | N63: 3958.27 | O63: =IFERROR(N63/N327, "NA") -> 0.0018723907 | Q63: 3833.79 | R63: =IFERROR(Q63/Q327, "NA") -> 0.0027636252 | T63: =IFERROR(B63+E63+H63+K63+N63+Q63, "NA") -> 27281.68 | U63: =(T63/$V$1)/7 -> 149.89934
A64: 5090 - Purchase Family Meal DNU old | B64: 0 | C64: =IFERROR(B64/B327, "NA") -> 0 | E64: 0 | F64: =IFERROR(E64/E327, "NA") -> 0 | H64: 0 | I64: =IFERROR(H64/H327, "NA") -> 0 | K64: 0 | L64: =IFERROR(K64/K327, "NA") -> 0 | N64: 0 | O64: =IFERROR(N64/N327, "NA") -> 0 | Q64: 0 | R64: =IFERROR(Q64/Q327, "NA") -> 0 | T64: =IFERROR(B64+E64+H64+K64+N64+Q64, "NA") -> 0 | U64: =(T64/$V$1)/7 -> 0
A65: Total Food Cost | B65: =IFERROR(B55+B56+B57+B58+B59+B60+B61+B62+B63+B64, "NA") -> 127671.19 | C65: =IFERROR(B65/B327, "NA") -> 0.057602059 | E65: =IFERROR(E55+E56+E57+E58+E59+E60+E61+E62+E63+E64, "NA") -> 111563.43 | F65: =IFERROR(E65/E327, "NA") -> 0.063408882 | H65: =IFERROR(H55+H56+H57+H58+H59+H60+H61+H62+H63+H64, "NA") -> 165139.58 | I65: =IFERROR(H65/H327, "NA") -> 0.067478823 | K65: =IFERROR(K55+K56+K57+K58+K59+K60+K61+K62+K63+K64, "NA") -> 97994.17 | L65: =IFERROR(K65/K327, "NA") -> 0.064689229 | N65: =IFERROR(N55+N56+N57+N58+N59+N60+N61+N62+N63+N64, "NA") -> 133605.88 | O65: =IFERROR(N65/N327, "NA") -> 0.063199937 | Q65: =IFERROR(Q55+Q56+Q57+Q58+Q59+Q60+Q61+Q62+Q63+Q64, "NA") -> 88695.85 | R65: =IFERROR(Q65/Q327, "NA") -> 0.063937274 | T65: =IFERROR(B65+E65+H65+K65+N65+Q65, "NA") -> 724670.1 | U65: =(T65/$V$1)/7 -> 3981.7038
A66: 5080 - Purchase N/A Beverages | B66: 14852.5 | C66: =IFERROR(B66/B327, "NA") -> 0.0067010779 | E66: 20783.56 | F66: =IFERROR(E66/E327, "NA") -> 0.011812673 | H66: 12180.9 | I66: =IFERROR(H66/H327, "NA") -> 0.0049773216 | K66: 12162.36 | L66: =IFERROR(K66/K327, "NA") -> 0.0080287806 | N66: 14063.41 | O66: =IFERROR(N66/N327, "NA") -> 0.0066524514 | Q66: 10591.9 | R66: =IFERROR(Q66/Q327, "NA") -> 0.0076352751 | T66: =IFERROR(B66+E66+H66+K66+N66+Q66, "NA") -> 84634.63 | U66: =(T66/$V$1)/7 -> 465.02544
A67: LBW Cost | T67: =IFERROR(B67+E67+H67+K67+N67+Q67, "NA") -> 0 | U67: =(T67/$V$1)/7 -> 0
A68: 5110 - LBW Cost | B68: 0 | C68: =IFERROR(B68/B327, "NA") -> 0 | E68: 0 | F68: =IFERROR(E68/E327, "NA") -> 0 | H68: 0 | I68: =IFERROR(H68/H327, "NA") -> 0 | K68: 0 | L68: =IFERROR(K68/K327, "NA") -> 0 | N68: 0 | O68: =IFERROR(N68/N327, "NA") -> 0 | Q68: 0 | R68: =IFERROR(Q68/Q327, "NA") -> 0 | T68: =IFERROR(B68+E68+H68+K68+N68+Q68, "NA") -> 0 | U68: =(T68/$V$1)/7 -> 0
A69: 5120 - Purchase Beer | B69: 1546.15 | C69: =IFERROR(B69/B327, "NA") -> 0.00069758435 | E69: 2024.46 | F69: =IFERROR(E69/E327, "NA") -> 0.0011506346 | H69: 1998.25 | I69: =IFERROR(H69/H327, "NA") -> 0.00081651872 | K69: 1171.29 | L69: =IFERROR(K69/K327, "NA") -> 0.0007732077 | N69: 1229.06 | O69: =IFERROR(N69/N327, "NA") -> 0.00058138545 | Q69: 413.38 | R69: =IFERROR(Q69/Q327, "NA") -> 0.00029798903 | T69: =IFERROR(B69+E69+H69+K69+N69+Q69, "NA") -> 8382.59 | U69: =(T69/$V$1)/7 -> 46.058187
A70: 5130 - Purchase Wine BTG | B70: 0 | C70: =IFERROR(B70/B327, "NA") -> 0 | E70: 0 | F70: =IFERROR(E70/E327, "NA") -> 0 | H70: 35843.97 | I70: =IFERROR(H70/H327, "NA") -> 0.014646452 | K70: 0 | L70: =IFERROR(K70/K327, "NA") -> 0 | N70: 0 | O70: =IFERROR(N70/N327, "NA") -> 0 | Q70: 0 | R70: =IFERROR(Q70/Q327, "NA") -> 0 | T70: =IFERROR(B70+E70+H70+K70+N70+Q70, "NA") -> 35843.97 | U70: =(T70/$V$1)/7 -> 196.94489
A71: 5131 - Purchase Wine | B71: 90739.2 | C71: =IFERROR(B71/B327, "NA") -> 0.040939266 | E71: 79260.8 | F71: =IFERROR(E71/E327, "NA") -> 0.045049159 | H71: 100217 | I71: =IFERROR(H71/H327, "NA") -> 0.04095036 | K71: 73979.43 | L71: =IFERROR(K71/K327, "NA") -> 0.048836296 | N71: 93337.94 | O71: =IFERROR(N71/N327, "NA") -> 0.044151888 | Q71: 61009.89 | R71: =IFERROR(Q71/Q327, "NA") -> 0.043979578 | T71: =IFERROR(B71+E71+H71+K71+N71+Q71, "NA") -> 498544.26 | U71: =(T71/$V$1)/7 -> 2739.2542
A72: 5132 - Purchase Wine Reserve | B72: 0 | C72: =IFERROR(B72/B327, "NA") -> 0 | E72: 0 | F72: =IFERROR(E72/E327, "NA") -> 0 | H72: 0 | I72: =IFERROR(H72/H327, "NA") -> 0 | K72: 0 | L72: =IFERROR(K72/K327, "NA") -> 0 | N72: 0 | O72: =IFERROR(N72/N327, "NA") -> 0 | Q72: 0 | R72: =IFERROR(Q72/Q327, "NA") -> 0 | T72: =IFERROR(B72+E72+H72+K72+N72+Q72, "NA") -> 0 | U72: =(T72/$V$1)/7 -> 0
A73: 5170 - Purchase Liquor | B73: 112542.95 | C73: =IFERROR(B73/B327, "NA") -> 0.050776574 | E73: 95799.89 | F73: =IFERROR(E73/E327, "NA") -> 0.054449419 | H73: 142250.77 | I73: =IFERROR(H73/H327, "NA") -> 0.058126069 | K73: 68314.36 | L73: =IFERROR(K73/K327, "NA") -> 0.045096593 | N73: 65976.12 | O73: =IFERROR(N73/N327, "NA") -> 0.031208855 | Q73: 41414.64 | R73: =IFERROR(Q73/Q327, "NA") -> 0.02985415 | T73: =IFERROR(B73+E73+H73+K73+N73+Q73, "NA") -> 526298.73 | U73: =(T73/$V$1)/7 -> 2891.7513
A74: 5174 - Purchase Beverage Commissary | B74: 0 | C74: =IFERROR(B74/B327, "NA") -> 0 | E74: 0 | F74: =IFERROR(E74/E327, "NA") -> 0 | H74: 0 | I74: =IFERROR(H74/H327, "NA") -> 0 | K74: 0 | L74: =IFERROR(K74/K327, "NA") -> 0 | N74: 0 | O74: =IFERROR(N74/N327, "NA") -> 0 | Q74: 0 | R74: =IFERROR(Q74/Q327, "NA") -> 0 | T74: =IFERROR(B74+E74+H74+K74+N74+Q74, "NA") -> 0 | U74: =(T74/$V$1)/7 -> 0
A75: 5175 - Purchase Bar Consumables | B75: 41.7 | C75: =IFERROR(B75/B327, "NA") -> 1.8814001e-05 | E75: 62.24 | F75: =IFERROR(E75/E327, "NA") -> 3.5375112e-05 | H75: 51.98 | I75: =IFERROR(H75/H327, "NA") -> 2.1239906e-05 | K75: 10516.2 | L75: =IFERROR(K75/K327, "NA") -> 0.0069420953 | N75: 14850.01 | O75: =IFERROR(N75/N327, "NA") -> 0.0070245388 | Q75: 13947.37 | R75: =IFERROR(Q75/Q327, "NA") -> 0.010054099 | T75: =IFERROR(B75+E75+H75+K75+N75+Q75, "NA") -> 39469.5 | U75: =(T75/$V$1)/7 -> 216.86538
A76: Total LBW Cost | B76: =IFERROR(B68+B69+B70+B71+B72+B73+B74+B75, "NA") -> 204870 | C76: =IFERROR(B76/B327, "NA") -> 0.092432238 | E76: =IFERROR(E68+E69+E70+E71+E72+E73+E74+E75, "NA") -> 177147.39 | F76: =IFERROR(E76/E327, "NA") -> 0.10068459 | H76: =IFERROR(H68+H69+H70+H71+H72+H73+H74+H75, "NA") -> 280361.97 | I76: =IFERROR(H76/H327, "NA") -> 0.11456064 | K76: =IFERROR(K68+K69+K70+K71+K72+K73+K74+K75, "NA") -> 153981.28 | L76: =IFERROR(K76/K327, "NA") -> 0.10164819 | N76: =IFERROR(N68+N69+N70+N71+N72+N73+N74+N75, "NA") -> 175393.13 | O76: =IFERROR(N76/N327, "NA") -> 0.082966668 | Q76: =IFERROR(Q68+Q69+Q70+Q71+Q72+Q73+Q74+Q75, "NA") -> 116785.28 | R76: =IFERROR(Q76/Q327, "NA") -> 0.084185816 | T76: =IFERROR(B76+E76+H76+K76+N76+Q76, "NA") -> 1108539.1 | U76: =(T76/$V$1)/7 -> 6090.8739
A77: Purchase Retail | T77: =IFERROR(B77+E77+H77+K77+N77+Q77, "NA") -> 0 | U77: =(T77/$V$1)/7 -> 0
A78: 5200 - Purchase Retail | B78: 0 | C78: =IFERROR(B78/B327, "NA") -> 0 | E78: 0 | F78: =IFERROR(E78/E327, "NA") -> 0 | H78: 0 | I78: =IFERROR(H78/H327, "NA") -> 0 | K78: 0 | L78: =IFERROR(K78/K327, "NA") -> 0 | N78: 0 | O78: =IFERROR(N78/N327, "NA") -> 0 | Q78: 0 | R78: =IFERROR(Q78/Q327, "NA") -> 0 | T78: =IFERROR(B78+E78+H78+K78+N78+Q78, "NA") -> 0 | U78: =(T78/$V$1)/7 -> 0
A79: 5210 - Purchase Mini Bar | B79: 0 | C79: =IFERROR(B79/B327, "NA") -> 0 | E79: 0 | F79: =IFERROR(E79/E327, "NA") -> 0 | H79: 0 | I79: =IFERROR(H79/H327, "NA") -> 0 | K79: 0 | L79: =IFERROR(K79/K327, "NA") -> 0 | N79: 0 | O79: =IFERROR(N79/N327, "NA") -> 0 | Q79: 0 | R79: =IFERROR(Q79/Q327, "NA") -> 0 | T79: =IFERROR(B79+E79+H79+K79+N79+Q79, "NA") -> 0 | U79: =(T79/$V$1)/7 -> 0
A80: Total Purchase Retail | B80: =IFERROR(B78+B79, "NA") -> 0 | C80: =IFERROR(B80/B327, "NA") -> 0 | E80: =IFERROR(E78+E79, "NA") -> 0 | F80: =IFERROR(E80/E327, "NA") -> 0 | H80: =IFERROR(H78+H79, "NA") -> 0 | I80: =IFERROR(H80/H327, "NA") -> 0 | K80: =IFERROR(K78+K79, "NA") -> 0 | L80: =IFERROR(K80/K327, "NA") -> 0 | N80: =IFERROR(N78+N79, "NA") -> 0 | O80: =IFERROR(N80/N327, "NA") -> 0 | Q80: =IFERROR(Q78+Q79, "NA") -> 0 | R80: =IFERROR(Q80/Q327, "NA") -> 0 | T80: =IFERROR(B80+E80+H80+K80+N80+Q80, "NA") -> 0 | U80: =(T80/$V$1)/7 -> 0
A81: Payroll Expenses | T81: =IFERROR(B81+E81+H81+K81+N81+Q81, "NA") -> 0 | U81: =(T81/$V$1)/7 -> 0
A82: 5400 - Payroll Expenses | B82: 0 | C82: =IFERROR(B82/B327, "NA") -> 0 | E82: 0 | F82: =IFERROR(E82/E327, "NA") -> 0 | H82: 0 | I82: =IFERROR(H82/H327, "NA") -> 0 | K82: 0 | L82: =IFERROR(K82/K327, "NA") -> 0 | N82: 0 | O82: =IFERROR(N82/N327, "NA") -> 0 | Q82: 0 | R82: =IFERROR(Q82/Q327, "NA") -> 0 | T82: =IFERROR(B82+E82+H82+K82+N82+Q82, "NA") -> 0 | U82: =(T82/$V$1)/7 -> 0
A83: Houlry Labor | T83: =IFERROR(B83+E83+H83+K83+N83+Q83, "NA") -> 0 | U83: =(T83/$V$1)/7 -> 0
A84: 5445 - Houlry Labor | B84: 0 | C84: =IFERROR(B84/B327, "NA") -> 0 | E84: 0 | F84: =IFERROR(E84/E327, "NA") -> 0 | H84: 0 | I84: =IFERROR(H84/H327, "NA") -> 0 | K84: 0 | L84: =IFERROR(K84/K327, "NA") -> 0 | N84: 0 | O84: =IFERROR(N84/N327, "NA") -> 0 | Q84: 0 | R84: =IFERROR(Q84/Q327, "NA") -> 0 | T84: =IFERROR(B84+E84+H84+K84+N84+Q84, "NA") -> 0 | U84: =(T84/$V$1)/7 -> 0
A85: 5430 - Line Cook | B85: 19409.6 | C85: =IFERROR(B85/B327, "NA") -> 0.0087571278 | E85: 25372.51 | F85: =IFERROR(E85/E327, "NA") -> 0.014420877 | H85: 31406.26 | I85: =IFERROR(H85/H327, "NA") -> 0.012833129 | K85: 22006.53 | L85: =IFERROR(K85/K327, "NA") -> 0.014527246 | N85: 24971.7 | O85: =IFERROR(N85/N327, "NA") -> 0.011812428 | Q85: 23130.87 | R85: =IFERROR(Q85/Q327, "NA") -> 0.016674115 | T85: =IFERROR(B85+E85+H85+K85+N85+Q85, "NA") -> 146297.47 | U85: =(T85/$V$1)/7 -> 803.83225
A86: 5431 - Prep Cook | B86: 8333.33 | C86: =IFERROR(B86/B327, "NA") -> 0.0037597908 | E86: 4784.29 | F86: =IFERROR(E86/E327, "NA") -> 0.0027192287 | H86: 8427.23 | I86: =IFERROR(H86/H327, "NA") -> 0.0034435086 | K86: 5755.11 | L86: =IFERROR(K86/K327, "NA") -> 0.0037991406 | N86: 5615.18 | O86: =IFERROR(N86/N327, "NA") -> 0.0026561632 | Q86: 5076.23 | R86: =IFERROR(Q86/Q327, "NA") -> 0.0036592502 | T86: =IFERROR(B86+E86+H86+K86+N86+Q86, "NA") -> 37991.37 | U86: =(T86/$V$1)/7 -> 208.74379
A87: 5432 - Pastry Cook | B87: 0 | C87: =IFERROR(B87/B327, "NA") -> 0 | E87: 988.11 | F87: =IFERROR(E87/E327, "NA") -> 0.00056160832 | H87: 6464.25 | I87: =IFERROR(H87/H327, "NA") -> 0.0026414018 | K87: 3611.69 | L87: =IFERROR(K87/K327, "NA") -> 0.0023841973 | N87: 4586.32 | O87: =IFERROR(N87/N327, "NA") -> 0.0021694789 | Q87: 3742.73 | R87: =IFERROR(Q87/Q327, "NA") -> 0.0026979837 | T87: =IFERROR(B87+E87+H87+K87+N87+Q87, "NA") -> 19393.1 | U87: =(T87/$V$1)/7 -> 106.55549
A88: 5433 - Sushi Cook | B88: 25552.83 | C88: =IFERROR(B88/B327, "NA") -> 0.0115288 | E88: 25736.2 | F88: =IFERROR(E88/E327, "NA") -> 0.014627586 | H88: 36580 | I88: =IFERROR(H88/H327, "NA") -> 0.014947206 | K88: 19826.38 | L88: =IFERROR(K88/K327, "NA") -> 0.013088056 | N88: 20226.52 | O88: =IFERROR(N88/N327, "NA") -> 0.0095678033 | Q88: 14246.29 | R88: =IFERROR(Q88/Q327, "NA") -> 0.010269578 | T88: =IFERROR(B88+E88+H88+K88+N88+Q88, "NA") -> 142168.22 | U88: =(T88/$V$1)/7 -> 781.14407
A89: 5435 - Chef de Partie | B89: 0 | C89: =IFERROR(B89/B327, "NA") -> 0 | E89: 216.59 | F89: =IFERROR(E89/E327, "NA") -> 0.00012310243 | H89: 749.17 | I89: =IFERROR(H89/H327, "NA") -> 0.00030612352 | K89: 138.56 | L89: =IFERROR(K89/K327, "NA") -> 9.146809e-05 | N89: 0 | O89: =IFERROR(N89/N327, "NA") -> 0 | Q89: 0 | R89: =IFERROR(Q89/Q327, "NA") -> 0 | T89: =IFERROR(B89+E89+H89+K89+N89+Q89, "NA") -> 1104.32 | U89: =(T89/$V$1)/7 -> 6.0676923
A90: 5436 - Butcher | B90: 0 | C90: =IFERROR(B90/B327, "NA") -> 0 | E90: 0 | F90: =IFERROR(E90/E327, "NA") -> 0 | H90: 0 | I90: =IFERROR(H90/H327, "NA") -> 0 | K90: 0 | L90: =IFERROR(K90/K327, "NA") -> 0 | N90: 0 | O90: =IFERROR(N90/N327, "NA") -> 0 | Q90: 0 | R90: =IFERROR(Q90/Q327, "NA") -> 0 | T90: =IFERROR(B90+E90+H90+K90+N90+Q90, "NA") -> 0 | U90: =(T90/$V$1)/7 -> 0
A91: 5439 - Food EXPO BOH | B91: 0 | C91: =IFERROR(B91/B327, "NA") -> 0 | E91: 0 | F91: =IFERROR(E91/E327, "NA") -> 0 | H91: 0 | I91: =IFERROR(H91/H327, "NA") -> 0 | K91: 0 | L91: =IFERROR(K91/K327, "NA") -> 0 | N91: 0 | O91: =IFERROR(N91/N327, "NA") -> 0 | Q91: 0 | R91: =IFERROR(Q91/Q327, "NA") -> 0 | T91: =IFERROR(B91+E91+H91+K91+N91+Q91, "NA") -> 0 | U91: =(T91/$V$1)/7 -> 0
A92: 5440 - Dishwashers | B92: 8148.4 | C92: =IFERROR(B92/B327, "NA") -> 0.003676355 | E92: 11032.89 | F92: =IFERROR(E92/E327, "NA") -> 0.0062707217 | H92: 17992.9 | I92: =IFERROR(H92/H327, "NA") -> 0.007352203 | K92: 10607.35 | L92: =IFERROR(K92/K327, "NA") -> 0.0070022664 | N92: 10322.76 | O92: =IFERROR(N92/N327, "NA") -> 0.004883002 | Q92: 8951.79 | R92: =IFERROR(Q92/Q327, "NA") -> 0.0064529857 | T92: =IFERROR(B92+E92+H92+K92+N92+Q92, "NA") -> 67056.09 | U92: =(T92/$V$1)/7 -> 368.44005
A93: 5447 - Receiver | B93: 0 | C93: =IFERROR(B93/B327, "NA") -> 0 | E93: 0 | F93: =IFERROR(E93/E327, "NA") -> 0 | H93: 0 | I93: =IFERROR(H93/H327, "NA") -> 0 | K93: 0 | L93: =IFERROR(K93/K327, "NA") -> 0 | N93: 0 | O93: =IFERROR(N93/N327, "NA") -> 0 | Q93: 0 | R93: =IFERROR(Q93/Q327, "NA") -> 0 | T93: =IFERROR(B93+E93+H93+K93+N93+Q93, "NA") -> 0 | U93: =(T93/$V$1)/7 -> 0
A94: 5449 - BOH Contract Labor | B94: 0 | C94: =IFERROR(B94/B327, "NA") -> 0 | E94: 0 | F94: =IFERROR(E94/E327, "NA") -> 0 | H94: 0 | I94: =IFERROR(H94/H327, "NA") -> 0 | K94: 0 | L94: =IFERROR(K94/K327, "NA") -> 0 | N94: 0 | O94: =IFERROR(N94/N327, "NA") -> 0 | Q94: 0 | R94: =IFERROR(Q94/Q327, "NA") -> 0 | T94: =IFERROR(B94+E94+H94+K94+N94+Q94, "NA") -> 0 | U94: =(T94/$V$1)/7 -> 0
A95: 5450 - Bonus BOH Hourly | B95: 0 | C95: =IFERROR(B95/B327, "NA") -> 0 | E95: 0 | F95: =IFERROR(E95/E327, "NA") -> 0 | H95: 0 | I95: =IFERROR(H95/H327, "NA") -> 0 | K95: 0 | L95: =IFERROR(K95/K327, "NA") -> 0 | N95: 0 | O95: =IFERROR(N95/N327, "NA") -> 0 | Q95: 0 | R95: =IFERROR(Q95/Q327, "NA") -> 0 | T95: =IFERROR(B95+E95+H95+K95+N95+Q95, "NA") -> 0 | U95: =(T95/$V$1)/7 -> 0
A96: 5451 - Vacation BOH | B96: 1120 | C96: =IFERROR(B96/B327, "NA") -> 0.00050531609 | E96: 1120 | F96: =IFERROR(E96/E327, "NA") -> 0.00063657013 | H96: 1400 | I96: =IFERROR(H96/H327, "NA") -> 0.00057206366 | K96: 1120 | L96: =IFERROR(K96/K327, "NA") -> 0.00073934945 | N96: 1120 | O96: =IFERROR(N96/N327, "NA") -> 0.00052979651 | Q96: 1120 | R96: =IFERROR(Q96/Q327, "NA") -> 0.00080736299 | T96: =IFERROR(B96+E96+H96+K96+N96+Q96, "NA") -> 7000 | U96: =(T96/$V$1)/7 -> 38.461538
A97: 5455 - Host | B97: 7926.28 | C97: =IFERROR(B97/B327, "NA") -> 0.00357614 | E97: 5338.55 | F97: =IFERROR(E97/E327, "NA") -> 0.0030342513 | H97: 15061.37 | I97: =IFERROR(H97/H327, "NA") -> 0.0061543303 | K97: 8566.87 | L97: =IFERROR(K97/K327, "NA") -> 0.0056552774 | N97: 11020.32 | O97: =IFERROR(N97/N327, "NA") -> 0.0052129706 | Q97: 3501.89 | R97: =IFERROR(Q97/Q327, "NA") -> 0.0025243718 | T97: =IFERROR(B97+E97+H97+K97+N97+Q97, "NA") -> 51415.28 | U97: =(T97/$V$1)/7 -> 282.50154
A98: 5456 - Reservationist | B98: 8279.12 | C98: =IFERROR(B98/B327, "NA") -> 0.0037353326 | E98: 9646.2 | F98: =IFERROR(E98/E327, "NA") -> 0.005482574 | H98: 7995.24 | I98: =IFERROR(H98/H327, "NA") -> 0.0032669902 | K98: 4733.68 | L98: =IFERROR(K98/K327, "NA") -> 0.0031248605 | N98: 6009 | O98: =IFERROR(N98/N327, "NA") -> 0.0028424529 | Q98: 5833 | R98: =IFERROR(Q98/Q327, "NA") -> 0.0042047753 | T98: =IFERROR(B98+E98+H98+K98+N98+Q98, "NA") -> 42496.24 | U98: =(T98/$V$1)/7 -> 233.49582
A99: 5457 - Receptionnist | B99: 0 | C99: =IFERROR(B99/B327, "NA") -> 0 | E99: 0 | F99: =IFERROR(E99/E327, "NA") -> 0 | H99: 0 | I99: =IFERROR(H99/H327, "NA") -> 0 | K99: 0 | L99: =IFERROR(K99/K327, "NA") -> 0 | N99: 0 | O99: =IFERROR(N99/N327, "NA") -> 0 | Q99: 0 | R99: =IFERROR(Q99/Q327, "NA") -> 0 | T99: =IFERROR(B99+E99+H99+K99+N99+Q99, "NA") -> 0 | U99: =(T99/$V$1)/7 -> 0
A100: 5460 - Servers | B100: 0 | C100: =IFERROR(B100/B327, "NA") -> 0 | E100: 0 | F100: =IFERROR(E100/E327, "NA") -> 0 | H100: 0 | I100: =IFERROR(H100/H327, "NA") -> 0 | K100: 0 | L100: =IFERROR(K100/K327, "NA") -> 0 | N100: 0 | O100: =IFERROR(N100/N327, "NA") -> 0 | Q100: 0 | R100: =IFERROR(Q100/Q327, "NA") -> 0 | T100: =IFERROR(B100+E100+H100+K100+N100+Q100, "NA") -> 0 | U100: =(T100/$V$1)/7 -> 0
A101: 5463 - Captain | B101: 0 | C101: =IFERROR(B101/B327, "NA") -> 0 | E101: 0 | F101: =IFERROR(E101/E327, "NA") -> 0 | H101: 0 | I101: =IFERROR(H101/H327, "NA") -> 0 | K101: 0 | L101: =IFERROR(K101/K327, "NA") -> 0 | N101: 0 | O101: =IFERROR(N101/N327, "NA") -> 0 | Q101: 0 | R101: =IFERROR(Q101/Q327, "NA") -> 0 | T101: =IFERROR(B101+E101+H101+K101+N101+Q101, "NA") -> 0 | U101: =(T101/$V$1)/7 -> 0
A102: 5464 - Sommelier | B102: 0 | C102: =IFERROR(B102/B327, "NA") -> 0 | E102: 0 | F102: =IFERROR(E102/E327, "NA") -> 0 | H102: 0 | I102: =IFERROR(H102/H327, "NA") -> 0 | K102: 0 | L102: =IFERROR(K102/K327, "NA") -> 0 | N102: 0 | O102: =IFERROR(N102/N327, "NA") -> 0 | Q102: 0 | R102: =IFERROR(Q102/Q327, "NA") -> 0 | T102: =IFERROR(B102+E102+H102+K102+N102+Q102, "NA") -> 0 | U102: =(T102/$V$1)/7 -> 0
A103: 5480 - Server Assistant | B103: 0 | C103: =IFERROR(B103/B327, "NA") -> 0 | E103: 0 | F103: =IFERROR(E103/E327, "NA") -> 0 | H103: 0 | I103: =IFERROR(H103/H327, "NA") -> 0 | K103: 0 | L103: =IFERROR(K103/K327, "NA") -> 0 | N103: 0 | O103: =IFERROR(N103/N327, "NA") -> 0 | Q103: 0 | R103: =IFERROR(Q103/Q327, "NA") -> 0 | T103: =IFERROR(B103+E103+H103+K103+N103+Q103, "NA") -> 0 | U103: =(T103/$V$1)/7 -> 0
...
